Workbook

Sheet Daily Model
A1: HYPERLIQUID (HYPE) — DAILY MODEL. Volumes -> Gross Fees -> Fee→Revenue bridge (−HLP, −Unit, −HIP-3 deployer; builder is on-top) -> Revenue per segment (sum = HyperCore = hyperscreener) -> + HyperEVM + Auction = Total Revenue. Then AF/supply & OTS. Daily 2024-11-30 → 2026-06-04. Hover headers for source. blue=source · black=formula · green=cross-check
B2: VOLUME ($) | F2: HIP-3 VOLUME BY CATEGORY ($) | M2: GROSS FEES ($) [user-paid] | R2: FEE → REVENUE BRIDGE [deductions, $] | Z2: REVENUE TO HYPERCORE ($) | AG2: IMPLIED TAKE-RATE (bps) | AJ2: OTHER REVENUE ($) | AM2: ASSISTANCE FUND & SUPPLY | AV2: OTS (Hyperliquid Strategies basis)
A3: Date | B3: Core Crypto Perp Vol ($) | C3: HIP-3 Perp Vol ($) | D3: Spot Vol ($) | E3: HIP-4 Vol ($) | F3: HIP-3 Commodities ($) | G3: HIP-3 Crypto ($) | H3: HIP-3 FX ($) | I3: HIP-3 Indices ($) | J3: HIP-3 Pre-IPO ($) | K3: HIP-3 Stocks ($) | L3: HIP-3 Cat Total ($) | M3: Core Crypto Perp Fees ($) | N3: HIP-3 Gross Fees ($) | O3: Spot Fees incl Unit ($) | P3: HIP-4 Fees ($) | Q3: Total Gross Fees ($) | R3: HLP Rate | S3: (-) HLP on Core Perp ($) | T3: (-) HLP on HIP-3 ($) | U3: (-) HLP on Spot ($) | V3: (-) Unit Protocol Fees ($) | W3: (-) HIP-3 Deployer Fees ($) | X3: Total Deductions ($) | Y3: Builder Code Fees [on-top, not deducted] ($) | Z3: Core Crypto Perp Revenue ($) | AA3: HIP-3 Revenue ($) | AB3: Spot Revenue ($) | AC3: HIP-4 Revenue ($) | AD3: =HyperCore Revenue (model) ($) | AE3: HyperCore Revenue [hyperscreener] ($) | AF3: Check: model - hyperscreener ($) | AG3: Core Perp Take-Rate (bps) | AH3: HIP-3 Take-Rate (bps) | AI3: Spot Take-Rate (bps) | AJ3: HyperEVM Burn ($) | AK3: Auction Burn ($) | AL3: Total Revenue ($) | AM3: Revenue -> AF ($) | AN3: Buyback HYPE | AO3: Buyback Avg Price ($) | AP3: AF HYPE Balance | AQ3: Staking Emissions (HYPE) | AR3: Fee Burn (HYPE) | AS3: Team Tokens Unlocked (HYPE) | AT3: HYPE Staked (M) | AU3: Implied Staking Yield | AV3: (-) Future Emissions & CR (HYPE) | AW3: (-) Hyper Foundation (HYPE) | AX3: (-) Assistance Fund (HYPE) | AY3: (-) Community Grants (HYPE) | AZ3: (-) HC&EVM Fee Burns (HYPE) | BA3: =OTS (HYPE) | BB3: Core Contributors Locked (M) | BC3: Circulating Token Supply (M) | BD3: OTS Value ($)
A4: 45626 | B4: 1.9278396e+09 | D4: 460835741 | R4: 0.03 | AG4: =IF(OR(B4="",B4=0,M4=""),"",M4/B4*10000) | AH4: =IF(OR(C4="",C4=0),"",N4/C4*10000) | AI4: =IF(OR(D4="",D4=0),"",O4/D4*10000) | AP4: 8714980.2 | AQ4: 0 | AR4: 32364.464 | AV4: 0 | AW4: 60100000 | AX4: 8714980.2 | AY4: 3100000 | AZ4: =1000000000-999967635.536 | BA4: =1000000000-AV4-AW4-AX4-AY4-AZ4 | BB4: 244.9 | BC4: =BA4/1000000-BB4 | BD4: =BA4*8.64
A5: 45627 | B5: 2.2309523e+09 | D5: 382137710 | R5: 0.03 | AG5: =IF(OR(B5="",B5=0,M5=""),"",M5/B5*10000) | AH5: =IF(OR(C5="",C5=0),"",N5/C5*10000) | AI5: =IF(OR(D5="",D5=0),"",O5/D5*10000) | AP5: 9336088.4 | AQ5: 0 | AR5: 10604.896 | AV5: 0 | AW5: 60100000 | AX5: 9336088.4 | AY5: 3100000 | AZ5: =1000000000-999957030.64 | BA5: =1000000000-AV5-AW5-AX5-AY5-AZ5 | BB5: 244.9 | BC5: =BA5/1000000-BB5 | BD5: =BA5*8.9
A6: 45628 | B6: 5.3331258e+09 | D6: 320571512 | R6: 0.03 | AG6: =IF(OR(B6="",B6=0,M6=""),"",M6/B6*10000) | AH6: =IF(OR(C6="",C6=0),"",N6/C6*10000) | AI6: =IF(OR(D6="",D6=0),"",O6/D6*10000) | AP6: 9336088.4 | AQ6: 0 | AR6: 2916.6523 | AV6: 0 | AW6: 60100000 | AX6: 9336088.4 | AY6: 3100000 | AZ6: =1000000000-999954113.9877 | BA6: =1000000000-AV6-AW6-AX6-AY6-AZ6 | BB6: 244.9 | BC6: =BA6/1000000-BB6 | BD6: =BA6*8.66
A7: 45629 | B7: 4.8819819e+09 | D7: 302890343 | R7: 0.03 | AG7: =IF(OR(B7="",B7=0,M7=""),"",M7/B7*10000) | AH7: =IF(OR(C7="",C7=0),"",N7/C7*10000) | AI7: =IF(OR(D7="",D7=0),"",O7/D7*10000) | AP7: 9933598.1 | AQ7: 0 | AR7: 3632.1998 | AV7: 0 | AW7: 60100000 | AX7: 9933598.1 | AY7: 3100000 | AZ7: =1000000000-999950481.7879 | BA7: =1000000000-AV7-AW7-AX7-AY7-AZ7 | BB7: 244.9 | BC7: =BA7/1000000-BB7 | BD7: =BA7*8.96
A8: 45630 | B8: 6.2259185e+09 | D8: 318696984 | R8: 0.03 | AG8: =IF(OR(B8="",B8=0,M8=""),"",M8/B8*10000) | AH8: =IF(OR(C8="",C8=0),"",N8/C8*10000) | AI8: =IF(OR(D8="",D8=0),"",O8/D8*10000) | AP8: 10009960 | AQ8: 0 | AR8: 3743.7999 | AV8: 0 | AW8: 60100000 | AX8: 10009960 | AY8: 3100000 | AZ8: =1000000000-999946737.988 | BA8: =1000000000-AV8-AW8-AX8-AY8-AZ8 | BB8: 244.9 | BC8: =BA8/1000000-BB8 | BD8: =BA8*11.08
A9: 45631 | B9: 9.7895628e+09 | D9: 323114172 | R9: 0.03 | AG9: =IF(OR(B9="",B9=0,M9=""),"",M9/B9*10000) | AH9: =IF(OR(C9="",C9=0),"",N9/C9*10000) | AI9: =IF(OR(D9="",D9=0),"",O9/D9*10000) | AP9: 10009960 | AQ9: 0 | AR9: 4041.2964 | AV9: 0 | AW9: 60100000 | AX9: 10009960 | AY9: 3100000 | AZ9: =1000000000-999942696.6916 | BA9: =1000000000-AV9-AW9-AX9-AY9-AZ9 | BB9: 244.9 | BC9: =BA9/1000000-BB9 | BD9: =BA9*11.4
A10: 45632 | B10: 7.8114744e+09 | D10: 218646771 | R10: 0.03 | AG10: =IF(OR(B10="",B10=0,M10=""),"",M10/B10*10000) | AH10: =IF(OR(C10="",C10=0),"",N10/C10*10000) | AI10: =IF(OR(D10="",D10=0),"",O10/D10*10000) | AP10: 10428491 | AQ10: 0 | AR10: 3472.5047 | AV10: 0 | AW10: 60100000 | AX10: 10428491 | AY10: 3100000 | AZ10: =1000000000-999939224.1869 | BA10: =1000000000-AV10-AW10-AX10-AY10-AZ10 | BB10: 244.9 | BC10: =BA10/1000000-BB10 | BD10: =BA10*12.69
A11: 45633 | B11: 2.8624379e+09 | D11: 182104753 | R11: 0.03 | AG11: =IF(OR(B11="",B11=0,M11=""),"",M11/B11*10000) | AH11: =IF(OR(C11="",C11=0),"",N11/C11*10000) | AI11: =IF(OR(D11="",D11=0),"",O11/D11*10000) | AP11: 10428491 | AQ11: 0 | AR11: 2255.2254 | AV11: 0 | AW11: 60100000 | AX11: 10428491 | AY11: 3100000 | AZ11: =1000000000-999936968.9615 | BA11: =1000000000-AV11-AW11-AX11-AY11-AZ11 | BB11: 244.9 | BC11: =BA11/1000000-BB11 | BD11: =BA11*13.83
A12: 45634 | B12: 3.2527988e+09 | D12: 136064768 | R12: 0.03 | AG12: =IF(OR(B12="",B12=0,M12=""),"",M12/B12*10000) | AH12: =IF(OR(C12="",C12=0),"",N12/C12*10000) | AI12: =IF(OR(D12="",D12=0),"",O12/D12*10000) | AP12: 10428491 | AQ12: 0 | AR12: 1897.8347 | AV12: 0 | AW12: 60100000 | AX12: 10428491 | AY12: 3100000 | AZ12: =1000000000-999935071.1268 | BA12: =1000000000-AV12-AW12-AX12-AY12-AZ12 | BB12: 244.9 | BC12: =BA12/1000000-BB12 | BD12: =BA12*14.12
A13: 45635 | B13: 5.3063589e+09 | D13: 270676721 | R13: 0.03 | AG13: =IF(OR(B13="",B13=0,M13=""),"",M13/B13*10000) | AH13: =IF(OR(C13="",C13=0),"",N13/C13*10000) | AI13: =IF(OR(D13="",D13=0),"",O13/D13*10000) | AP13: 10654299 | AQ13: 0 | AR13: 1284.1908 | AV13: 0 | AW13: 60100000 | AX13: 10654299 | AY13: 3100000 | AZ13: =1000000000-999933786.9361 | BA13: =1000000000-AV13-AW13-AX13-AY13-AZ13 | BB13: 244.9 | BC13: =BA13/1000000-BB13 | BD13: =BA13*14.02
A14: 45636 | B14: 1.0009954e+10 | D14: 208129108 | R14: 0.03 | AG14: =IF(OR(B14="",B14=0,M14=""),"",M14/B14*10000) | AH14: =IF(OR(C14="",C14=0),"",N14/C14*10000) | AI14: =IF(OR(D14="",D14=0),"",O14/D14*10000) | AP14: 10654299 | AQ14: 0 | AR14: 2527.2104 | AV14: 0 | AW14: 60100000 | AX14: 10654299 | AY14: 3100000 | AZ14: =1000000000-999931259.7256 | BA14: =1000000000-AV14-AW14-AX14-AY14-AZ14 | BB14: 244.9 | BC14: =BA14/1000000-BB14 | BD14: =BA14*13.54
A15: 45637 | B15: 3.9793992e+09 | D15: 211797447 | R15: 0.03 | AG15: =IF(OR(B15="",B15=0,M15=""),"",M15/B15*10000) | AH15: =IF(OR(C15="",C15=0),"",N15/C15*10000) | AI15: =IF(OR(D15="",D15=0),"",O15/D15*10000) | AP15: 10654299 | AQ15: 0 | AR15: 2003.998 | AV15: 0 | AW15: 60100000 | AX15: 10654299 | AY15: 3100000 | AZ15: =1000000000-999929255.7277 | BA15: =1000000000-AV15-AW15-AX15-AY15-AZ15 | BB15: 244.9 | BC15: =BA15/1000000-BB15 | BD15: =BA15*13.56
A16: 45638 | B16: 4.8390459e+09 | D16: 324908474 | R16: 0.03 | AG16: =IF(OR(B16="",B16=0,M16=""),"",M16/B16*10000) | AH16: =IF(OR(C16="",C16=0),"",N16/C16*10000) | AI16: =IF(OR(D16="",D16=0),"",O16/D16*10000) | AP16: 10654299 | AQ16: 0 | AR16: 1932.7073 | AV16: 0 | AW16: 60100000 | AX16: 10654299 | AY16: 3100000 | AZ16: =1000000000-999927323.0204 | BA16: =1000000000-AV16-AW16-AX16-AY16-AZ16 | BB16: 244.9 | BC16: =BA16/1000000-BB16 | BD16: =BA16*16.11
A17: 45639 | B17: 4.2533193e+09 | D17: 334237923 | R17: 0.03 | AG17: =IF(OR(B17="",B17=0,M17=""),"",M17/B17*10000) | AH17: =IF(OR(C17="",C17=0),"",N17/C17*10000) | AI17: =IF(OR(D17="",D17=0),"",O17/D17*10000) | AP17: 10662922 | AQ17: 0 | AR17: 2435.2699 | AV17: 0 | AW17: 60100000 | AX17: 10662922 | AY17: 3100000 | AZ17: =1000000000-999924887.7505 | BA17: =1000000000-AV17-AW17-AX17-AY17-AZ17 | BB17: 244.9 | BC17: =BA17/1000000-BB17 | BD17: =BA17*18.04
A18: 45640 | B18: 3.1705221e+09 | D18: 546075604 | R18: 0.03 | AG18: =IF(OR(B18="",B18=0,M18=""),"",M18/B18*10000) | AH18: =IF(OR(C18="",C18=0),"",N18/C18*10000) | AI18: =IF(OR(D18="",D18=0),"",O18/D18*10000) | AP18: 10761181 | AQ18: 0 | AR18: 1602.2514 | AV18: 0 | AW18: 60100000 | AX18: 10761181 | AY18: 3100000 | AZ18: =1000000000-999923285.4991 | BA18: =1000000000-AV18-AW18-AX18-AY18-AZ18 | BB18: 244.9 | BC18: =BA18/1000000-BB18 | BD18: =BA18*19.49
A19: 45641 | B19: 3.786629e+09 | D19: 517821521 | R19: 0.03 | AG19: =IF(OR(B19="",B19=0,M19=""),"",M19/B19*10000) | AH19: =IF(OR(C19="",C19=0),"",N19/C19*10000) | AI19: =IF(OR(D19="",D19=0),"",O19/D19*10000) | AP19: 10761181 | AQ19: 0 | AR19: 2857.882 | AV19: 0 | AW19: 60100000 | AX19: 10761181 | AY19: 3100000 | AZ19: =1000000000-999920427.6171 | BA19: =1000000000-AV19-AW19-AX19-AY19-AZ19 | BB19: 244.9 | BC19: =BA19/1000000-BB19 | BD19: =BA19*24.15
A20: 45642 | B20: 6.2672948e+09 | D20: 552491542 | R20: 0.03 | AG20: =IF(OR(B20="",B20=0,M20=""),"",M20/B20*10000) | AH20: =IF(OR(C20="",C20=0),"",N20/C20*10000) | AI20: =IF(OR(D20="",D20=0),"",O20/D20*10000) | AP20: 10761181 | AQ20: 0 | AR20: 2419.5935 | AV20: 0 | AW20: 60100000 | AX20: 10761181 | AY20: 3100000 | AZ20: =1000000000-999918008.0235 | BA20: =1000000000-AV20-AW20-AX20-AY20-AZ20 | BB20: 244.9 | BC20: =BA20/1000000-BB20 | BD20: =BA20*23.88
A21: 45643 | B21: 5.5938649e+09 | D21: 533018011 | R21: 0.03 | AG21: =IF(OR(B21="",B21=0,M21=""),"",M21/B21*10000) | AH21: =IF(OR(C21="",C21=0),"",N21/C21*10000) | AI21: =IF(OR(D21="",D21=0),"",O21/D21*10000) | AP21: 10789059 | AQ21: 0 | AR21: 2278.9176 | AV21: 0 | AW21: 60100000 | AX21: 10789059 | AY21: 3100000 | AZ21: =1000000000-999915729.1059 | BA21: =1000000000-AV21-AW21-AX21-AY21-AZ21 | BB21: 244.9 | BC21: =BA21/1000000-BB21 | BD21: =BA21*27.24
A22: 45644 | B22: 8.540539e+09 | D22: 472394527 | R22: 0.03 | AG22: =IF(OR(B22="",B22=0,M22=""),"",M22/B22*10000) | AH22: =IF(OR(C22="",C22=0),"",N22/C22*10000) | AI22: =IF(OR(D22="",D22=0),"",O22/D22*10000) | AP22: 10927485 | AQ22: 0 | AR22: 2263.4293 | AV22: 0 | AW22: 60100000 | AX22: 10927485 | AY22: 3100000 | AZ22: =1000000000-999913465.6766 | BA22: =1000000000-AV22-AW22-AX22-AY22-AZ22 | BB22: 244.9 | BC22: =BA22/1000000-BB22 | BD22: =BA22*25.57
A23: 45645 | B23: 1.1512982e+10 | D23: 564194362 | R23: 0.03 | AG23: =IF(OR(B23="",B23=0,M23=""),"",M23/B23*10000) | AH23: =IF(OR(C23="",C23=0),"",N23/C23*10000) | AI23: =IF(OR(D23="",D23=0),"",O23/D23*10000) | AP23: 11039806 | AQ23: 0 | AR23: 2427.0823 | AV23: 0 | AW23: 60100000 | AX23: 11039806 | AY23: 3100000 | AZ23: =1000000000-999911038.5943 | BA23: =1000000000-AV23-AW23-AX23-AY23-AZ23 | BB23: 244.9 | BC23: =BA23/1000000-BB23 | BD23: =BA23*23.22
A24: 45646 | B24: 9.8785211e+09 | D24: 703781781 | R24: 0.03 | AG24: =IF(OR(B24="",B24=0,M24=""),"",M24/B24*10000) | AH24: =IF(OR(C24="",C24=0),"",N24/C24*10000) | AI24: =IF(OR(D24="",D24=0),"",O24/D24*10000) | AP24: 11180484 | AQ24: 0 | AR24: 2863.6836 | AV24: 0 | AW24: 60100000 | AX24: 11180484 | AY24: 3100000 | AZ24: =1000000000-999908174.9107 | BA24: =1000000000-AV24-AW24-AX24-AY24-AZ24 | BB24: 244.9 | BC24: =BA24/1000000-BB24 | BD24: =BA24*24.92
A25: 45647 | B25: 5.2030282e+09 | D25: 527191283 | R25: 0.03 | AG25: =IF(OR(B25="",B25=0,M25=""),"",M25/B25*10000) | AH25: =IF(OR(C25="",C25=0),"",N25/C25*10000) | AI25: =IF(OR(D25="",D25=0),"",O25/D25*10000) | AP25: 11244814 | AQ25: 0 | AR25: 3033.9608 | AV25: 0 | AW25: 60100000 | AX25: 11244814 | AY25: 3100000 | AZ25: =1000000000-999905140.9499 | BA25: =1000000000-AV25-AW25-AX25-AY25-AZ25 | BB25: 244.9 | BC25: =BA25/1000000-BB25 | BD25: =BA25*29.74
A26: 45648 | B26: 4.6867317e+09 | D26: 471634786 | R26: 0.03 | AG26: =IF(OR(B26="",B26=0,M26=""),"",M26/B26*10000) | AH26: =IF(OR(C26="",C26=0),"",N26/C26*10000) | AI26: =IF(OR(D26="",D26=0),"",O26/D26*10000) | AP26: 11290999 | AQ26: 0 | AR26: 2044.5791 | AV26: 0 | AW26: 60100000 | AX26: 11290999 | AY26: 3100000 | AZ26: =1000000000-999903096.3708 | BA26: =1000000000-AV26-AW26-AX26-AY26-AZ26 | BB26: 244.9 | BC26: =BA26/1000000-BB26 | BD26: =BA26*32.02
A27: 45649 | B27: 6.1684635e+09 | D27: 375034673 | O27: 96254 | R27: 0.03 | AG27: =IF(OR(B27="",B27=0,M27=""),"",M27/B27*10000) | AH27: =IF(OR(C27="",C27=0),"",N27/C27*10000) | AI27: =IF(OR(D27="",D27=0),"",O27/D27*10000) | AP27: 11346521 | AQ27: 0 | AR27: 2041.5641 | AV27: 0 | AW27: 60100000 | AX27: 11346521 | AY27: 3100000 | AZ27: =1000000000-999901054.8066 | BA27: =1000000000-AV27-AW27-AX27-AY27-AZ27 | BB27: 244.9 | BC27: =BA27/1000000-BB27 | BD27: =BA27*28.47
A28: 45650 | B28: 4.4015652e+09 | D28: 319403848 | O28: 47315 | R28: 0.03 | AG28: =IF(OR(B28="",B28=0,M28=""),"",M28/B28*10000) | AH28: =IF(OR(C28="",C28=0),"",N28/C28*10000) | AI28: =IF(OR(D28="",D28=0),"",O28/D28*10000) | AP28: 11396463 | AQ28: 0 | AR28: 3190.5125 | AV28: 0 | AW28: 60100000 | AX28: 11396463 | AY28: 3100000 | AZ28: =1000000000-999897864.2941 | BA28: =1000000000-AV28-AW28-AX28-AY28-AZ28 | BB28: 244.9 | BC28: =BA28/1000000-BB28 | BD28: =BA28*28.6
A29: 45651 | B29: 3.0900267e+09 | D29: 310480616 | O29: 43561 | R29: 0.03 | AG29: =IF(OR(B29="",B29=0,M29=""),"",M29/B29*10000) | AH29: =IF(OR(C29="",C29=0),"",N29/C29*10000) | AI29: =IF(OR(D29="",D29=0),"",O29/D29*10000) | AP29: 11439370 | AQ29: 0 | AR29: 1832.8323 | AV29: 0 | AW29: 60100000 | AX29: 11439370 | AY29: 3100000 | AZ29: =1000000000-999896031.4618 | BA29: =1000000000-AV29-AW29-AX29-AY29-AZ29 | BB29: 244.9 | BC29: =BA29/1000000-BB29 | BD29: =BA29*29.78
A30: 45652 | B30: 3.8974652e+09 | D30: 214091088 | O30: 44254 | R30: 0.03 | AG30: =IF(OR(B30="",B30=0,M30=""),"",M30/B30*10000) | AH30: =IF(OR(C30="",C30=0),"",N30/C30*10000) | AI30: =IF(OR(D30="",D30=0),"",O30/D30*10000) | AP30: 11468143 | AQ30: 0 | AR30: 1373.0965 | AV30: 0 | AW30: 60100000 | AX30: 11468143 | AY30: 3100000 | AZ30: =1000000000-999894658.3653 | BA30: =1000000000-AV30-AW30-AX30-AY30-AZ30 | BB30: 244.9 | BC30: =BA30/1000000-BB30 | BD30: =BA30*26.55
A31: 45653 | B31: 3.8894731e+09 | D31: 216391282 | O31: 28523 | R31: 0.03 | AG31: =IF(OR(B31="",B31=0,M31=""),"",M31/B31*10000) | AH31: =IF(OR(C31="",C31=0),"",N31/C31*10000) | AI31: =IF(OR(D31="",D31=0),"",O31/D31*10000) | AP31: 11513537 | AQ31: 0 | AR31: 1476.4802 | AV31: 0 | AW31: 60100000 | AX31: 11513537 | AY31: 3100000 | AZ31: =1000000000-999893181.8852 | BA31: =1000000000-AV31-AW31-AX31-AY31-AZ31 | BB31: 244.9 | BC31: =BA31/1000000-BB31 | BD31: =BA31*27.22
A32: 45654 | B32: 2.0771914e+09 | D32: 212391739 | O32: 28430 | R32: 0.03 | AG32: =IF(OR(B32="",B32=0,M32=""),"",M32/B32*10000) | AH32: =IF(OR(C32="",C32=0),"",N32/C32*10000) | AI32: =IF(OR(D32="",D32=0),"",O32/D32*10000) | AP32: 11560234 | AQ32: 0 | AR32: 1019.7076 | AT32: 301.00122 | AV32: 0 | AW32: 60100000 | AX32: 11560234 | AY32: 3100000 | AZ32: =1000000000-999892162.1776 | BA32: =1000000000-AV32-AW32-AX32-AY32-AZ32 | BB32: 244.9 | BC32: =BA32/1000000-BB32 | BD32: =BA32*27.11
A33: 45655 | B33: 1.9659316e+09 | D33: 342862746 | O33: 31496 | R33: 0.03 | AG33: =IF(OR(B33="",B33=0,M33=""),"",M33/B33*10000) | AH33: =IF(OR(C33="",C33=0),"",N33/C33*10000) | AI33: =IF(OR(D33="",D33=0),"",O33/D33*10000) | AP33: 11594187 | AQ33: 0 | AR33: 774.4857 | AT33: 301.02439 | AV33: 4.2805004e+08 | AW33: 60100000 | AX33: 11594187 | AY33: 3100000 | AZ33: =1000000000-999891387.692 | BA33: =1000000000-AV33-AW33-AX33-AY33-AZ33 | BB33: 244.9 | BC33: =BA33/1000000-BB33 | BD33: =BA33*29.26
A34: 45656 | B34: 4.6971711e+09 | D34: 267028183 | O34: 49113 | R34: 0.03 | AG34: =IF(OR(B34="",B34=0,M34=""),"",M34/B34*10000) | AH34: =IF(OR(C34="",C34=0),"",N34/C34*10000) | AI34: =IF(OR(D34="",D34=0),"",O34/D34*10000) | AP34: 11626219 | AQ34: 22225.362 | AR34: 611.8805 | AT34: 301.10728 | AU34: 0.02518994 | AV34: 4.2802781e+08 | AW34: 60100000 | AX34: 11626219 | AY34: 3100000 | AZ34: =1000000000-999890775.8115 | BA34: =1000000000-AV34-AW34-AX34-AY34-AZ34 | BB34: 244.9 | BC34: =BA34/1000000-BB34 | BD34: =BA34*27.44
A35: 45657 | B35: 3.4505145e+09 | D35: 225503235 | O35: 42962 | R35: 0.03 | AG35: =IF(OR(B35="",B35=0,M35=""),"",M35/B35*10000) | AH35: =IF(OR(C35="",C35=0),"",N35/C35*10000) | AI35: =IF(OR(D35="",D35=0),"",O35/D35*10000) | AP35: 11670797 | AQ35: 23028.588 | AR35: 870.4787 | AT35: 352.79856 | AU35: 0.02334773 | AV35: 4.2800478e+08 | AW35: 60100000 | AX35: 11670797 | AY35: 3100000 | AZ35: =1000000000-999889905.3328 | BA35: =1000000000-AV35-AW35-AX35-AY35-AZ35 | BB35: 244.9 | BC35: =BA35/1000000-BB35 | BD35: =BA35*26.95
A36: 45658 | B36: 2.1572568e+09 | D36: 256438336 | O36: 30141 | R36: 0.03 | AG36: =IF(OR(B36="",B36=0,M36=""),"",M36/B36*10000) | AH36: =IF(OR(C36="",C36=0),"",N36/C36*10000) | AI36: =IF(OR(D36="",D36=0),"",O36/D36*10000) | AP36: 11719551 | AQ36: 24499.354 | AR36: 941.1022 | AT36: 372.98553 | AU36: 0.02271528 | AV36: 4.2798028e+08 | AW36: 60100000 | AX36: 11719551 | AY36: 3100000 | AZ36: =1000000000-999888964.2307 | BA36: =1000000000-AV36-AW36-AX36-AY36-AZ36 | BB36: 244.9 | BC36: =BA36/1000000-BB36 | BD36: =BA36*24
A37: 45659 | B37: 3.6458162e+09 | D37: 267239456 | O37: 41666 | R37: 0.03 | AG37: =IF(OR(B37="",B37=0,M37=""),"",M37/B37*10000) | AH37: =IF(OR(C37="",C37=0),"",N37/C37*10000) | AI37: =IF(OR(D37="",D37=0),"",O37/D37*10000) | AP37: 11756781 | AQ37: 24851.902 | AR37: 920.9016 | AT37: 380.75278 | AU37: 0.02249743 | AV37: 4.2795543e+08 | AW37: 60100000 | AX37: 11756781 | AY37: 3100000 | AZ37: =1000000000-999888043.3291 | BA37: =1000000000-AV37-AW37-AX37-AY37-AZ37 | BB37: 244.9 | BC37: =BA37/1000000-BB37 | BD37: =BA37*26.31
A38: 45660 | B38: 3.5731603e+09 | D38: 176550030 | O38: 37005 | R38: 0.03 | AG38: =IF(OR(B38="",B38=0,M38=""),"",M38/B38*10000) | AH38: =IF(OR(C38="",C38=0),"",N38/C38*10000) | AI38: =IF(OR(D38="",D38=0),"",O38/D38*10000) | AP38: 11812513 | AQ38: 25219.868 | AR38: 905.5316 | AT38: 390.38936 | AU38: 0.02223263 | AV38: 4.2793021e+08 | AW38: 60100000 | AX38: 11812513 | AY38: 3100000 | AZ38: =1000000000-999887137.7975 | BA38: =1000000000-AV38-AW38-AX38-AY38-AZ38 | BB38: 244.9 | BC38: =BA38/1000000-BB38 | BD38: =BA38*23.15
A39: 45661 | B39: 2.5062676e+09 | D39: 119410641 | O39: 25377 | R39: 0.03 | AG39: =IF(OR(B39="",B39=0,M39=""),"",M39/B39*10000) | AH39: =IF(OR(C39="",C39=0),"",N39/C39*10000) | AI39: =IF(OR(D39="",D39=0),"",O39/D39*10000) | AP39: 11846794 | AQ39: 25452.778 | AR39: 1232.8801 | AT39: 395.40416 | AU39: 0.02224488 | AV39: 4.2790476e+08 | AW39: 60100000 | AX39: 11846794 | AY39: 3100000 | AZ39: =1000000000-999885904.9174 | BA39: =1000000000-AV39-AW39-AX39-AY39-AZ39 | BB39: 244.9 | BC39: =BA39/1000000-BB39 | BD39: =BA39*24.43
A40: 45662 | B40: 2.149149e+09 | D40: 174388254 | O40: 19262 | R40: 0.03 | AG40: =IF(OR(B40="",B40=0,M40=""),"",M40/B40*10000) | AH40: =IF(OR(C40="",C40=0),"",N40/C40*10000) | AI40: =IF(OR(D40="",D40=0),"",O40/D40*10000) | AP40: 11889348 | AQ40: 25665.111 | AR40: 617.3145 | AT40: 401.89251 | AU40: 0.02206674 | AV40: 4.2787909e+08 | AW40: 60100000 | AX40: 11889348 | AY40: 3100000 | AZ40: =1000000000-999885287.603 | BA40: =1000000000-AV40-AW40-AX40-AY40-AZ40 | BB40: 244.9 | BC40: =BA40/1000000-BB40 | BD40: =BA40*25.02
A41: 45663 | B41: 4.4049187e+09 | D41: 194364069 | O41: 23453 | R41: 0.03 | AG41: =IF(OR(B41="",B41=0,M41=""),"",M41/B41*10000) | AH41: =IF(OR(C41="",C41=0),"",N41/C41*10000) | AI41: =IF(OR(D41="",D41=0),"",O41/D41*10000) | AP41: 11933135 | AQ41: 25789.885 | AR41: 447.5855 | AT41: 404.49525 | AU41: 0.02199648 | AV41: 4.278533e+08 | AW41: 60100000 | AX41: 11933135 | AY41: 3100000 | AZ41: =1000000000-999884840.0175 | BA41: =1000000000-AV41-AW41-AX41-AY41-AZ41 | BB41: 244.9 | BC41: =BA41/1000000-BB41 | BD41: =BA41*24.4
A42: 45664 | B42: 7.0045455e+09 | D42: 298520602 | O42: 30214 | R42: 0.03 | AG42: =IF(OR(B42="",B42=0,M42=""),"",M42/B42*10000) | AH42: =IF(OR(C42="",C42=0),"",N42/C42*10000) | AI42: =IF(OR(D42="",D42=0),"",O42/D42*10000) | AP42: 11991787 | AQ42: 25854.611 | AR42: 718.7295 | AT42: 407.40015 | AU42: 0.02191885 | AV42: 4.2782745e+08 | AW42: 60100000 | AX42: 11991787 | AY42: 3100000 | AZ42: =1000000000-999884121.288 | BA42: =1000000000-AV42-AW42-AX42-AY42-AZ42 | BB42: 244.9 | BC42: =BA42/1000000-BB42 | BD42: =BA42*25.23
A43: 45665 | B43: 6.0197847e+09 | D43: 325463853 | O43: 45273 | R43: 0.03 | AG43: =IF(OR(B43="",B43=0,M43=""),"",M43/B43*10000) | AH43: =IF(OR(C43="",C43=0),"",N43/C43*10000) | AI43: =IF(OR(D43="",D43=0),"",O43/D43*10000) | AP43: 12076330 | AQ43: 25924.42 | AR43: 744.9065 | AT43: 409.06593 | AU43: 0.02187471 | AV43: 4.2780152e+08 | AW43: 60100000 | AX43: 12076330 | AY43: 3100000 | AZ43: =1000000000-999883376.3815 | BA43: =1000000000-AV43-AW43-AX43-AY43-AZ43 | BB43: 244.9 | BC43: =BA43/1000000-BB43 | BD43: =BA43*23.5
A44: 45666 | B44: 7.1233273e+09 | D44: 194078337 | O44: 47391 | R44: 0.03 | AG44: =IF(OR(B44="",B44=0,M44=""),"",M44/B44*10000) | AH44: =IF(OR(C44="",C44=0),"",N44/C44*10000) | AI44: =IF(OR(D44="",D44=0),"",O44/D44*10000) | AP44: 12156975 | AQ44: 25984.345 | AR44: 1579.5356 | AT44: 410.2463 | AU44: 0.02184359 | AV44: 4.2777554e+08 | AW44: 60100000 | AX44: 12156975 | AY44: 3100000 | AZ44: =1000000000-999881796.8459 | BA44: =1000000000-AV44-AW44-AX44-AY44-AZ44 | BB44: 244.9 | BC44: =BA44/1000000-BB44 | BD44: =BA44*22.51
A45: 45667 | B45: 5.1100061e+09 | D45: 104484914 | O45: 27771 | R45: 0.03 | AG45: =IF(OR(B45="",B45=0,M45=""),"",M45/B45*10000) | AH45: =IF(OR(C45="",C45=0),"",N45/C45*10000) | AI45: =IF(OR(D45="",D45=0),"",O45/D45*10000) | AP45: 12241033 | AQ45: 26008.903 | AR45: 1664.9046 | AT45: 410.55517 | AU45: 0.0218538 | AV45: 4.2774953e+08 | AW45: 60100000 | AX45: 12241033 | AY45: 3100000 | AZ45: =1000000000-999880131.9413 | BA45: =1000000000-AV45-AW45-AX45-AY45-AZ45 | BB45: 244.9 | BC45: =BA45/1000000-BB45 | BD45: =BA45*20.28
A46: 45668 | B46: 1.9752201e+09 | D46: 104729289 | O46: 14961 | R46: 0.03 | AG46: =IF(OR(B46="",B46=0,M46=""),"",M46/B46*10000) | AH46: =IF(OR(C46="",C46=0),"",N46/C46*10000) | AI46: =IF(OR(D46="",D46=0),"",O46/D46*10000) | AP46: 12305409 | AQ46: 26032.719 | AR46: 984.8383 | AT46: 411.89327 | AU46: 0.0218187 | AV46: 4.277235e+08 | AW46: 60100000 | AX46: 12305409 | AY46: 3100000 | AZ46: =1000000000-999879147.103 | BA46: =1000000000-AV46-AW46-AX46-AY46-AZ46 | BB46: 244.9 | BC46: =BA46/1000000-BB46 | BD46: =BA46*20.65
A47: 45669 | B47: 1.8688233e+09 | D47: 230154418 | R47: 0.03 | AG47: =IF(OR(B47="",B47=0,M47=""),"",M47/B47*10000) | AH47: =IF(OR(C47="",C47=0),"",N47/C47*10000) | AI47: =IF(OR(D47="",D47=0),"",O47/D47*10000) | AP47: 12323093 | AQ47: 26062.989 | AR47: 555.3528 | AT47: 412.63036 | AU47: 0.02179943 | AV47: 4.2769743e+08 | AW47: 60100000 | AX47: 12323093 | AY47: 3100000 | AZ47: =1000000000-999878591.7502 | BA47: =1000000000-AV47-AW47-AX47-AY47-AZ47 | BB47: 244.9 | BC47: =BA47/1000000-BB47 | BD47: =BA47*20.88
A48: 45670 | B48: 7.6148894e+09 | D48: 195123318 | R48: 0.03 | AG48: =IF(OR(B48="",B48=0,M48=""),"",M48/B48*10000) | AH48: =IF(OR(C48="",C48=0),"",N48/C48*10000) | AI48: =IF(OR(D48="",D48=0),"",O48/D48*10000) | AP48: 12366458 | AQ48: 26085.585 | AR48: 490.8274 | AT48: 414.40353 | AU48: 0.02175025 | AV48: 4.2767135e+08 | AW48: 60100000 | AX48: 12366458 | AY48: 3100000 | AZ48: =1000000000-999878100.9228 | BA48: =1000000000-AV48-AW48-AX48-AY48-AZ48 | BB48: 244.9 | BC48: =BA48/1000000-BB48 | BD48: =BA48*21.12
A49: 45671 | B49: 4.1645346e+09 | D49: 186174573 | O49: 24324 | R49: 0.03 | AG49: =IF(OR(B49="",B49=0,M49=""),"",M49/B49*10000) | AH49: =IF(OR(C49="",C49=0),"",N49/C49*10000) | AI49: =IF(OR(D49="",D49=0),"",O49/D49*10000) | AP49: 12467821 | AQ49: 26275.62 | AR49: 1292.8946 | AT49: 422.39819 | AU49: 0.02154585 | AV49: 4.2764507e+08 | AW49: 60100000 | AX49: 12467821 | AY49: 3100000 | AZ49: =1000000000-999876808.0282 | BA49: =1000000000-AV49-AW49-AX49-AY49-AZ49 | BB49: 244.9 | BC49: =BA49/1000000-BB49 | BD49: =BA49*21.63
A50: 45672 | B50: 5.3154076e+09 | D50: 125668891 | O50: 23915 | R50: 0.03 | AG50: =IF(OR(B50="",B50=0,M50=""),"",M50/B50*10000) | AH50: =IF(OR(C50="",C50=0),"",N50/C50*10000) | AI50: =IF(OR(D50="",D50=0),"",O50/D50*10000) | AP50: 12522774 | AQ50: 26404.186 | AR50: 1035.8599 | AT50: 425.11787 | AU50: 0.02147762 | AV50: 4.2761867e+08 | AW50: 60100000 | AX50: 12522774 | AY50: 3100000 | AZ50: =1000000000-999875772.1684 | BA50: =1000000000-AV50-AW50-AX50-AY50-AZ50 | BB50: 244.9 | BC50: =BA50/1000000-BB50 | BD50: =BA50*23
A51: 45673 | B51: 5.7136112e+09 | D51: 148144621 | O51: 18602 | R51: 0.03 | AG51: =IF(OR(B51="",B51=0,M51=""),"",M51/B51*10000) | AH51: =IF(OR(C51="",C51=0),"",N51/C51*10000) | AI51: =IF(OR(D51="",D51=0),"",O51/D51*10000) | AP51: 12591917 | AQ51: 26508.232 | AR51: 883.4029 | AT51: 427.00147 | AU51: 0.02143075 | AV51: 4.2759216e+08 | AW51: 60100000 | AX51: 12591917 | AY51: 3100000 | AZ51: =1000000000-999874888.7655 | BA51: =1000000000-AV51-AW51-AX51-AY51-AZ51 | BB51: 244.9 | BC51: =BA51/1000000-BB51 | BD51: =BA51*24.38
A52: 45674 | B52: 5.4612772e+09 | D52: 342126938 | O52: 20485 | R52: 0.03 | AG52: =IF(OR(B52="",B52=0,M52=""),"",M52/B52*10000) | AH52: =IF(OR(C52="",C52=0),"",N52/C52*10000) | AI52: =IF(OR(D52="",D52=0),"",O52/D52*10000) | AP52: 12657482 | AQ52: 26562.754 | AR52: 560.1256 | AT52: 429.33507 | AU52: 0.0213731 | AV52: 4.275656e+08 | AW52: 60100000 | AX52: 12657482 | AY52: 3100000 | AZ52: =1000000000-999874328.6399 | BA52: =1000000000-AV52-AW52-AX52-AY52-AZ52 | BB52: 244.9 | BC52: =BA52/1000000-BB52 | BD52: =BA52*23.47
A53: 45675 | B53: 9.6789601e+09 | D53: 452915269 | O53: 52413 | R53: 0.03 | AG53: =IF(OR(B53="",B53=0,M53=""),"",M53/B53*10000) | AH53: =IF(OR(C53="",C53=0),"",N53/C53*10000) | AI53: =IF(OR(D53="",D53=0),"",O53/D53*10000) | AP53: 12746262 | AQ53: 26584.013 | AR53: 614.0791 | AT53: 430.01937 | AU53: 0.02137321 | AV53: 4.2753901e+08 | AW53: 60100000 | AX53: 12746262 | AY53: 3100000 | AZ53: =1000000000-999873714.5608 | BA53: =1000000000-AV53-AW53-AX53-AY53-AZ53 | BB53: 244.9 | BC53: =BA53/1000000-BB53 | BD53: =BA53*23.09
A54: 45676 | B54: 1.775022e+10 | D54: 234451715 | O54: 61521 | R54: 0.03 | AG54: =IF(OR(B54="",B54=0,M54=""),"",M54/B54*10000) | AH54: =IF(OR(C54="",C54=0),"",N54/C54*10000) | AI54: =IF(OR(D54="",D54=0),"",O54/D54*10000) | AP54: 12889603 | AQ54: 26576.453 | AR54: 1549.2138 | AT54: 428.25571 | AU54: 0.02141667 | AV54: 4.2751244e+08 | AW54: 60100000 | AX54: 12889603 | AY54: 3100000 | AZ54: =1000000000-999872165.347 | BA54: =1000000000-AV54-AW54-AX54-AY54-AZ54 | BB54: 244.9 | BC54: =BA54/1000000-BB54 | BD54: =BA54*21.94
A55: 45677 | B55: 1.6339005e+10 | D55: 255573062 | O55: 34279 | R55: 0.03 | AG55: =IF(OR(B55="",B55=0,M55=""),"",M55/B55*10000) | AH55: =IF(OR(C55="",C55=0),"",N55/C55*10000) | AI55: =IF(OR(D55="",D55=0),"",O55/D55*10000) | AP55: 13118130 | AQ55: 26541.273 | AR55: 2127.3129 | AT55: 426.49034 | AU55: 0.02146043 | AV55: 4.274859e+08 | AW55: 60100000 | AX55: 13118130 | AY55: 3100000 | AZ55: =1000000000-999870038.0341 | BA55: =1000000000-AV55-AW55-AX55-AY55-AZ55 | BB55: 244.9 | BC55: =BA55/1000000-BB55 | BD55: =BA55*20.19
A56: 45678 | B56: 8.3419449e+09 | D56: 217426990 | O56: 34069 | R56: 0.03 | AG56: =IF(OR(B56="",B56=0,M56=""),"",M56/B56*10000) | AH56: =IF(OR(C56="",C56=0),"",N56/C56*10000) | AI56: =IF(OR(D56="",D56=0),"",O56/D56*10000) | AP56: 13251259 | AQ56: 26530.748 | AR56: 1392.5278 | AT56: 428.3282 | AU56: 0.02141488 | AV56: 4.2745937e+08 | AW56: 60100000 | AX56: 13251259 | AY56: 3100000 | AZ56: =1000000000-999868645.5063 | BA56: =1000000000-AV56-AW56-AX56-AY56-AZ56 | BB56: 244.9 | BC56: =BA56/1000000-BB56 | BD56: =BA56*20.55
A57: 45679 | B57: 5.2815512e+09 | D57: 268190024 | O57: 30418 | R57: 0.03 | AG57: =IF(OR(B57="",B57=0,M57=""),"",M57/B57*10000) | AH57: =IF(OR(C57="",C57=0),"",N57/C57*10000) | AI57: =IF(OR(D57="",D57=0),"",O57/D57*10000) | AP57: 13322389 | AQ57: 26567.346 | AR57: 1404.8497 | AT57: 428.48155 | AU57: 0.02141109 | AV57: 4.274328e+08 | AW57: 60100000 | AX57: 13322389 | AY57: 3100000 | AZ57: =1000000000-999867240.6567 | BA57: =1000000000-AV57-AW57-AX57-AY57-AZ57 | BB57: 244.9 | BC57: =BA57/1000000-BB57 | BD57: =BA57*23.18
A58: 45680 | B58: 1.1321581e+10 | D58: 178140305 | O58: 38159 | R58: 0.03 | AG58: =IF(OR(B58="",B58=0,M58=""),"",M58/B58*10000) | AH58: =IF(OR(C58="",C58=0),"",N58/C58*10000) | AI58: =IF(OR(D58="",D58=0),"",O58/D58*10000) | AP58: 13384449 | AQ58: 26581.533 | AR58: 923.5959 | AT58: 428.62572 | AU58: 0.02140753 | AV58: 4.2740622e+08 | AW58: 60100000 | AX58: 13384449 | AY58: 3100000 | AZ58: =1000000000-999866317.0608 | BA58: =1000000000-AV58-AW58-AX58-AY58-AZ58 | BB58: 244.9 | BC58: =BA58/1000000-BB58 | BD58: =BA58*24.31
A59: 45681 | B59: 5.7847318e+09 | D59: 93192677 | O59: 23999 | R59: 0.03 | AG59: =IF(OR(B59="",B59=0,M59=""),"",M59/B59*10000) | AH59: =IF(OR(C59="",C59=0),"",N59/C59*10000) | AI59: =IF(OR(D59="",D59=0),"",O59/D59*10000) | AP59: 13500446 | AQ59: 26552.402 | AR59: 1425.0715 | AT59: 427.50931 | AU59: 0.02143514 | AV59: 4.2737966e+08 | AW59: 60100000 | AX59: 13500446 | AY59: 3100000 | AZ59: =1000000000-999864891.9893 | BA59: =1000000000-AV59-AW59-AX59-AY59-AZ59 | BB59: 244.9 | BC59: =BA59/1000000-BB59 | BD59: =BA59*21.97
A60: 45682 | B60: 3.5167284e+09 | D60: 138875526 | O60: 14317 | R60: 0.03 | AG60: =IF(OR(B60="",B60=0,M60=""),"",M60/B60*10000) | AH60: =IF(OR(C60="",C60=0),"",N60/C60*10000) | AI60: =IF(OR(D60="",D60=0),"",O60/D60*10000) | AP60: 13559681 | AQ60: 26530.811 | AR60: 909.6107 | AT60: 427.32622 | AU60: 0.02143968 | AV60: 4.2735313e+08 | AW60: 60100000 | AX60: 13559681 | AY60: 3100000 | AZ60: =1000000000-999863982.3786 | BA60: =1000000000-AV60-AW60-AX60-AY60-AZ60 | BB60: 244.9 | BC60: =BA60/1000000-BB60 | BD60: =BA60*23.06
A61: 45683 | B61: 3.5973869e+09 | D61: 229716868 | O61: 16865 | R61: 0.03 | AG61: =IF(OR(B61="",B61=0,M61=""),"",M61/B61*10000) | AH61: =IF(OR(C61="",C61=0),"",N61/C61*10000) | AI61: =IF(OR(D61="",D61=0),"",O61/D61*10000) | AP61: 13589448 | AQ61: 26541.029 | AR61: 462.2589 | AT61: 427.62726 | AU61: 0.02143222 | AV61: 4.2732659e+08 | AW61: 60100000 | AX61: 13589448 | AY61: 3100000 | AZ61: =1000000000-999863520.1197 | BA61: =1000000000-AV61-AW61-AX61-AY61-AZ61 | BB61: 244.9 | BC61: =BA61/1000000-BB61 | BD61: =BA61*23.15
A62: 45684 | B62: 1.0972896e+10 | D62: 185620600 | O62: 37573 | R62: 0.03 | AG62: =IF(OR(B62="",B62=0,M62=""),"",M62/B62*10000) | AH62: =IF(OR(C62="",C62=0),"",N62/C62*10000) | AI62: =IF(OR(D62="",D62=0),"",O62/D62*10000) | AP62: 13665774 | AQ62: 26557.334 | AR62: 515.1838 | AT62: 428.24228 | AU62: 0.021417 | AV62: 4.2730004e+08 | AW62: 60100000 | AX62: 13665774 | AY62: 3100000 | AZ62: =1000000000-999863004.9359 | BA62: =1000000000-AV62-AW62-AX62-AY62-AZ62 | BB62: 244.9 | BC62: =BA62/1000000-BB62 | BD62: =BA62*22.08
A63: 45685 | B63: 6.6891424e+09 | D63: 170638730 | O63: 26779 | R63: 0.03 | AG63: =IF(OR(B63="",B63=0,M63=""),"",M63/B63*10000) | AH63: =IF(OR(C63="",C63=0),"",N63/C63*10000) | AI63: =IF(OR(D63="",D63=0),"",O63/D63*10000) | AP63: 13764322 | AQ63: 26537.844 | AR63: 1494.8576 | AT63: 427.08438 | AU63: 0.02152959 | AV63: 4.272735e+08 | AW63: 60100000 | AX63: 13764322 | AY63: 3100000 | AZ63: =1000000000-999861510.0783 | BA63: =1000000000-AV63-AW63-AX63-AY63-AZ63 | BB63: 244.9 | BC63: =BA63/1000000-BB63 | BD63: =BA63*23.38
A64: 45686 | B64: 7.4872889e+09 | D64: 283645800 | O64: 20016 | R64: 0.03 | AG64: =IF(OR(B64="",B64=0,M64=""),"",M64/B64*10000) | AH64: =IF(OR(C64="",C64=0),"",N64/C64*10000) | AI64: =IF(OR(D64="",D64=0),"",O64/D64*10000) | AP64: 13830231 | AQ64: 26534.291 | AR64: 925.2888 | AT64: 427.49321 | AU64: 0.02156435 | AV64: 4.2724696e+08 | AW64: 60100000 | AX64: 13830231 | AY64: 3100000 | AZ64: =1000000000-999860584.7895 | BA64: =1000000000-AV64-AW64-AX64-AY64-AZ64 | BB64: 244.9 | BC64: =BA64/1000000-BB64 | BD64: =BA64*22.28
A65: 45687 | B65: 5.3196267e+09 | D65: 212136745 | O65: 38508 | R65: 0.03 | AG65: =IF(OR(B65="",B65=0,M65=""),"",M65/B65*10000) | AH65: =IF(OR(C65="",C65=0),"",N65/C65*10000) | AI65: =IF(OR(D65="",D65=0),"",O65/D65*10000) | AP65: 13916941 | AQ65: 26544.879 | AR65: 730.3546 | AT65: 427.68581 | AU65: 0.02155955 | AV65: 4.2722042e+08 | AW65: 60100000 | AX65: 13916941 | AY65: 3100000 | AZ65: =1000000000-999859854.4349 | BA65: =1000000000-AV65-AW65-AX65-AY65-AZ65 | BB65: 244.9 | BC65: =BA65/1000000-BB65 | BD65: =BA65*23.75
A66: 45688 | B66: 7.0891165e+09 | D66: 263781612 | O66: 30778 | R66: 0.03 | AG66: =IF(OR(B66="",B66=0,M66=""),"",M66/B66*10000) | AH66: =IF(OR(C66="",C66=0),"",N66/C66*10000) | AI66: =IF(OR(D66="",D66=0),"",O66/D66*10000) | AP66: 13956055 | AQ66: 32252.715 | AR66: 1669.5925 | AT66: 427.82029 | AU66: 0.0215562 | AV66: 4.2718817e+08 | AW66: 60100000 | AX66: 13956055 | AY66: 3100000 | AZ66: =1000000000-999858184.8425 | BA66: =1000000000-AV66-AW66-AX66-AY66-AZ66 | BB66: 244.9 | BC66: =BA66/1000000-BB66 | BD66: =BA66*26.19
A67: 45689 | B67: 5.3354864e+09 | D67: 305083845 | O67: 40422 | R67: 0.03 | AG67: =IF(OR(B67="",B67=0,M67=""),"",M67/B67*10000) | AH67: =IF(OR(C67="",C67=0),"",N67/C67*10000) | AI67: =IF(OR(D67="",D67=0),"",O67/D67*10000) | AP67: 14024319 | AQ67: 20850.625 | AR67: 797.4358 | AT67: 427.55556 | AU67: 0.02156279 | AV67: 4.2716732e+08 | AW67: 60100000 | AX67: 14024319 | AY67: 3100000 | AZ67: =1000000000-999857387.4067 | BA67: =1000000000-AV67-AW67-AX67-AY67-AZ67 | BB67: 244.9 | BC67: =BA67/1000000-BB67 | BD67: =BA67*26.92
A68: 45690 | B68: 9.0448218e+09 | D68: 443687078 | O68: 44496 | R68: 0.03 | AG68: =IF(OR(B68="",B68=0,M68=""),"",M68/B68*10000) | AH68: =IF(OR(C68="",C68=0),"",N68/C68*10000) | AI68: =IF(OR(D68="",D68=0),"",O68/D68*10000) | AP68: 14089848 | AQ68: 26556.909 | AR68: 1144.1562 | AT68: 428.02669 | AU68: 0.02155106 | AV68: 4.2714076e+08 | AW68: 60100000 | AX68: 14089848 | AY68: 3100000 | AZ68: =1000000000-999856243.2505 | BA68: =1000000000-AV68-AW68-AX68-AY68-AZ68 | BB68: 244.9 | BC68: =BA68/1000000-BB68 | BD68: =BA68*23.17
A69: 45691 | B69: 1.8072547e+10 | D69: 263016289 | O69: 63480 | R69: 0.03 | AG69: =IF(OR(B69="",B69=0,M69=""),"",M69/B69*10000) | AH69: =IF(OR(C69="",C69=0),"",N69/C69*10000) | AI69: =IF(OR(D69="",D69=0),"",O69/D69*10000) | AP69: 14260320 | AQ69: 26546.419 | AR69: 1529.404 | AT69: 427.38822 | AU69: 0.02156696 | AV69: 4.2711421e+08 | AW69: 60100000 | AX69: 14260320 | AY69: 3100000 | AZ69: =1000000000-999854713.8465 | BA69: =1000000000-AV69-AW69-AX69-AY69-AZ69 | BB69: 244.9 | BC69: =BA69/1000000-BB69 | BD69: =BA69*22.32
A70: 45692 | B70: 1.0231406e+10 | D70: 208560749 | O70: 37612 | R70: 0.03 | AG70: =IF(OR(B70="",B70=0,M70=""),"",M70/B70*10000) | AH70: =IF(OR(C70="",C70=0),"",N70/C70*10000) | AI70: =IF(OR(D70="",D70=0),"",O70/D70*10000) | AP70: 14367347 | AQ70: 26535.168 | AR70: 2737.9562 | AT70: 427.17774 | AU70: 0.02157222 | AV70: 4.2708768e+08 | AW70: 60100000 | AX70: 14367347 | AY70: 3100000 | AZ70: =1000000000-999851975.8903 | BA70: =1000000000-AV70-AW70-AX70-AY70-AZ70 | BB70: 244.9 | BC70: =BA70/1000000-BB70 | BD70: =BA70*25.19
A71: 45693 | B71: 5.6946084e+09 | D71: 168626713 | O71: 28216 | R71: 0.03 | AG71: =IF(OR(B71="",B71=0,M71=""),"",M71/B71*10000) | AH71: =IF(OR(C71="",C71=0),"",N71/C71*10000) | AI71: =IF(OR(D71="",D71=0),"",O71/D71*10000) | AP71: 14446985 | AQ71: 26543.473 | AR71: 1264.3163 | AT71: 427.62767 | AU71: 0.021561 | AV71: 4.2706113e+08 | AW71: 60100000 | AX71: 14446985 | AY71: 3100000 | AZ71: =1000000000-999850711.5739 | BA71: =1000000000-AV71-AW71-AX71-AY71-AZ71 | BB71: 244.9 | BC71: =BA71/1000000-BB71 | BD71: =BA71*25.14
A72: 45694 | B72: 5.9046597e+09 | D72: 178176120 | O72: 24592 | R72: 0.03 | AG72: =IF(OR(B72="",B72=0,M72=""),"",M72/B72*10000) | AH72: =IF(OR(C72="",C72=0),"",N72/C72*10000) | AI72: =IF(OR(D72="",D72=0),"",O72/D72*10000) | AP72: 14496741 | AQ72: 26548.785 | AR72: 989.8233 | AT72: 427.57185 | AU72: 0.02156239 | AV72: 4.2703458e+08 | AW72: 60100000 | AX72: 14496741 | AY72: 3100000 | AZ72: =1000000000-999849721.7506 | BA72: =1000000000-AV72-AW72-AX72-AY72-AZ72 | BB72: 244.9 | BC72: =BA72/1000000-BB72 | BD72: =BA72*24.75
A73: 45695 | B73: 6.1893943e+09 | D73: 86858735 | O73: 26352 | R73: 0.03 | AG73: =IF(OR(B73="",B73=0,M73=""),"",M73/B73*10000) | AH73: =IF(OR(C73="",C73=0),"",N73/C73*10000) | AI73: =IF(OR(D73="",D73=0),"",O73/D73*10000) | AP73: 14557024 | AQ73: 26612.271 | AR73: 827.2076 | AT73: 429.46034 | AU73: 0.02151548 | AV73: 4.2700797e+08 | AW73: 60100000 | AX73: 14557024 | AY73: 3100000 | AZ73: =1000000000-999848894.5431 | BA73: =1000000000-AV73-AW73-AX73-AY73-AZ73 | BB73: 244.9 | BC73: =BA73/1000000-BB73 | BD73: =BA73*23.83
A74: 45696 | B74: 3.0067196e+09 | D74: 75118825 | O74: 12064 | R74: 0.03 | AG74: =IF(OR(B74="",B74=0,M74=""),"",M74/B74*10000) | AH74: =IF(OR(C74="",C74=0),"",N74/C74*10000) | AI74: =IF(OR(D74="",D74=0),"",O74/D74*10000) | AP74: 14613413 | AQ74: 26577.922 | AR74: 996.1893 | AT74: 428.28436 | AU74: 0.02154465 | AV74: 4.2698139e+08 | AW74: 60100000 | AX74: 14613413 | AY74: 3100000 | AZ74: =1000000000-999847898.3538 | BA74: =1000000000-AV74-AW74-AX74-AY74-AZ74 | BB74: 244.9 | BC74: =BA74/1000000-BB74 | BD74: =BA74*22.83
A75: 45697 | B75: 3.7546019e+09 | D75: 91079022 | O75: 10683 | R75: 0.03 | AG75: =IF(OR(B75="",B75=0,M75=""),"",M75/B75*10000) | AH75: =IF(OR(C75="",C75=0),"",N75/C75*10000) | AI75: =IF(OR(D75="",D75=0),"",O75/D75*10000) | AP75: 14643949 | AQ75: 26528.153 | AR75: 470.7789 | AT75: 426.85498 | AU75: 0.02158028 | AV75: 4.2695487e+08 | AW75: 60100000 | AX75: 14643949 | AY75: 3100000 | AZ75: =1000000000-999847427.5749 | BA75: =1000000000-AV75-AW75-AX75-AY75-AZ75 | BB75: 244.9 | BC75: =BA75/1000000-BB75 | BD75: =BA75*23.4
A76: 45698 | B76: 5.1786321e+09 | D76: 107918816 | O76: 11999 | R76: 0.03 | AG76: =IF(OR(B76="",B76=0,M76=""),"",M76/B76*10000) | AH76: =IF(OR(C76="",C76=0),"",N76/C76*10000) | AI76: =IF(OR(D76="",D76=0),"",O76/D76*10000) | AP76: 14699099 | AQ76: 26525.199 | AR76: 358.1593 | AT76: 426.91151 | AU76: 0.02157886 | AV76: 4.2692834e+08 | AW76: 60100000 | AX76: 14699099 | AY76: 3100000 | AZ76: =1000000000-999847069.4156 | BA76: =1000000000-AV76-AW76-AX76-AY76-AZ76 | BB76: 244.9 | BC76: =BA76/1000000-BB76 | BD76: =BA76*22.98
A77: 45699 | B77: 6.5938638e+09 | D77: 142810624 | O77: 15656 | R77: 0.03 | AG77: =IF(OR(B77="",B77=0,M77=""),"",M77/B77*10000) | AH77: =IF(OR(C77="",C77=0),"",N77/C77*10000) | AI77: =IF(OR(D77="",D77=0),"",O77/D77*10000) | AP77: 14742922 | AQ77: 26523.32 | AR77: 521.8924 | AT77: 426.80892 | AU77: 0.02158143 | AV77: 4.2690182e+08 | AW77: 60100000 | AX77: 14742922 | AY77: 3100000 | AZ77: =1000000000-999846547.5232 | BA77: =1000000000-AV77-AW77-AX77-AY77-AZ77 | BB77: 244.9 | BC77: =BA77/1000000-BB77 | BD77: =BA77*23.32
A78: 45700 | B78: 7.5755804e+09 | D78: 122695803 | O78: 18209 | R78: 0.03 | AG78: =IF(OR(B78="",B78=0,M78=""),"",M78/B78*10000) | AH78: =IF(OR(C78="",C78=0),"",N78/C78*10000) | AI78: =IF(OR(D78="",D78=0),"",O78/D78*10000) | AP78: 14806912 | AQ78: 26541.339 | AR78: 579.0042 | AT78: 427.89424 | AU78: 0.02155735 | AV78: 4.2687528e+08 | AW78: 60100000 | AX78: 14806912 | AY78: 3100000 | AZ78: =1000000000-999845968.519 | BA78: =1000000000-AV78-AW78-AX78-AY78-AZ78 | BB78: 244.9 | BC78: =BA78/1000000-BB78 | BD78: =BA78*23.49
A79: 45701 | B79: 5.121162e+09 | D79: 199613305 | O79: 18585 | R79: 0.03 | AG79: =IF(OR(B79="",B79=0,M79=""),"",M79/B79*10000) | AH79: =IF(OR(C79="",C79=0),"",N79/C79*10000) | AI79: =IF(OR(D79="",D79=0),"",O79/D79*10000) | AP79: 14867924 | AQ79: 26562.25 | AR79: 792.7335 | AT79: 428.77533 | AU79: 0.02153545 | AV79: 4.2684871e+08 | AW79: 60100000 | AX79: 14867924 | AY79: 3100000 | AZ79: =1000000000-999845175.7854 | BA79: =1000000000-AV79-AW79-AX79-AY79-AZ79 | BB79: 244.9 | BC79: =BA79/1000000-BB79 | BD79: =BA79*25.84
A80: 45702 | B80: 5.0712944e+09 | D80: 103410352 | O80: 25753 | R80: 0.03 | AG80: =IF(OR(B80="",B80=0,M80=""),"",M80/B80*10000) | AH80: =IF(OR(C80="",C80=0),"",N80/C80*10000) | AI80: =IF(OR(D80="",D80=0),"",O80/D80*10000) | AP80: 14914741 | AQ80: 26581.329 | AR80: 591.6068 | AT80: 428.77106 | AU80: 0.02153555 | AV80: 4.2682213e+08 | AW80: 60100000 | AX80: 14914741 | AY80: 3100000 | AZ80: =1000000000-999844584.1786 | BA80: =1000000000-AV80-AW80-AX80-AY80-AZ80 | BB80: 244.9 | BC80: =BA80/1000000-BB80 | BD80: =BA80*26.26
A81: 45703 | B81: 2.5695663e+09 | D81: 78021652 | O81: 17622 | R81: 0.03 | AG81: =IF(OR(B81="",B81=0,M81=""),"",M81/B81*10000) | AH81: =IF(OR(C81="",C81=0),"",N81/C81*10000) | AI81: =IF(OR(D81="",D81=0),"",O81/D81*10000) | AP81: 14965063 | AQ81: 26587.268 | AR81: 978.1297 | AT81: 429.01678 | AU81: 0.02152946 | AV81: 4.2679555e+08 | AW81: 60100000 | AX81: 14965063 | AY81: 3100000 | AZ81: =1000000000-999843606.0489 | BA81: =1000000000-AV81-AW81-AX81-AY81-AZ81 | BB81: 244.9 | BC81: =BA81/1000000-BB81 | BD81: =BA81*26.2
A82: 45704 | B82: 2.5764633e+09 | D82: 120737014 | O82: 8856 | R82: 0.03 | AG82: =IF(OR(B82="",B82=0,M82=""),"",M82/B82*10000) | AH82: =IF(OR(C82="",C82=0),"",N82/C82*10000) | AI82: =IF(OR(D82="",D82=0),"",O82/D82*10000) | AP82: 14987424 | AQ82: 26607.02 | AR82: 420.737 | AT82: 430.11068 | AU82: 0.02150238 | AV82: 4.2676894e+08 | AW82: 60100000 | AX82: 14987424 | AY82: 3100000 | AZ82: =1000000000-999843185.3119 | BA82: =1000000000-AV82-AW82-AX82-AY82-AZ82 | BB82: 244.9 | BC82: =BA82/1000000-BB82 | BD82: =BA82*25.72
A83: 45705 | B83: 5.0493661e+09 | D83: 360271474 | O83: 18954 | R83: 0.03 | AG83: =IF(OR(B83="",B83=0,M83=""),"",M83/B83*10000) | AH83: =IF(OR(C83="",C83=0),"",N83/C83*10000) | AI83: =IF(OR(D83="",D83=0),"",O83/D83*10000) | AP83: 15018355 | AQ83: 26613.699 | AR83: 311.4459 | AT83: 429.38031 | AU83: 0.02152045 | AV83: 4.2674232e+08 | AW83: 60100000 | AX83: 15018355 | AY83: 3100000 | AZ83: =1000000000-999842873.8661 | BA83: =1000000000-AV83-AW83-AX83-AY83-AZ83 | BB83: 244.9 | BC83: =BA83/1000000-BB83 | BD83: =BA83*26.8
A84: 45706 | B84: 6.7872459e+09 | D84: 146705782 | O84: 55805 | R84: 0.03 | AG84: =IF(OR(B84="",B84=0,M84=""),"",M84/B84*10000) | AH84: =IF(OR(C84="",C84=0),"",N84/C84*10000) | AI84: =IF(OR(D84="",D84=0),"",O84/D84*10000) | AP84: 15074930 | AQ84: 26591.793 | AR84: 491.1939 | AT84: 429.55342 | AU84: 0.02151616 | AV84: 4.2671573e+08 | AW84: 60100000 | AX84: 15074930 | AY84: 3100000 | AZ84: =1000000000-999842382.6722 | BA84: =1000000000-AV84-AW84-AX84-AY84-AZ84 | BB84: 244.9 | BC84: =BA84/1000000-BB84 | BD84: =BA84*25.38
A85: 45707 | B85: 3.9018598e+09 | D85: 136622361 | O85: 22056 | R85: 0.03 | AG85: =IF(OR(B85="",B85=0,M85=""),"",M85/B85*10000) | AH85: =IF(OR(C85="",C85=0),"",N85/C85*10000) | AI85: =IF(OR(D85="",D85=0),"",O85/D85*10000) | AP85: 15130595 | AQ85: 26568.731 | AR85: 1766.3576 | AT85: 428.44817 | AU85: 0.02154357 | AV85: 4.2668916e+08 | AW85: 60100000 | AX85: 15130595 | AY85: 3100000 | AZ85: =1000000000-999840616.3146 | BA85: =1000000000-AV85-AW85-AX85-AY85-AZ85 | BB85: 244.9 | BC85: =BA85/1000000-BB85 | BD85: =BA85*24.08
A86: 45708 | B86: 5.0373787e+09 | D86: 206747279 | O86: 20113 | R86: 0.03 | AG86: =IF(OR(B86="",B86=0,M86=""),"",M86/B86*10000) | AH86: =IF(OR(C86="",C86=0),"",N86/C86*10000) | AI86: =IF(OR(D86="",D86=0),"",O86/D86*10000) | AP86: 15173205 | AQ86: 26580.86 | AR86: 672.5468 | AT86: 427.90059 | AU86: 0.02155719 | AV86: 4.2666258e+08 | AW86: 60100000 | AX86: 15173205 | AY86: 3100000 | AZ86: =1000000000-999839943.7678 | BA86: =1000000000-AV86-AW86-AX86-AY86-AZ86 | BB86: 244.9 | BC86: =BA86/1000000-BB86 | BD86: =BA86*24.06
A87: 45709 | B87: 1.0385529e+10 | D87: 71766053 | O87: 27835 | R87: 0.03 | AG87: =IF(OR(B87="",B87=0,M87=""),"",M87/B87*10000) | AH87: =IF(OR(C87="",C87=0),"",N87/C87*10000) | AI87: =IF(OR(D87="",D87=0),"",O87/D87*10000) | AP87: 15227193 | AQ87: 26551.304 | AR87: 563.1262 | AT87: 427.61213 | AU87: 0.02156438 | AV87: 4.2663603e+08 | AW87: 60100000 | AX87: 15227193 | AY87: 3100000 | AZ87: =1000000000-999839380.6415 | BA87: =1000000000-AV87-AW87-AX87-AY87-AZ87 | BB87: 244.9 | BC87: =BA87/1000000-BB87 | BD87: =BA87*24.45
A88: 45710 | B88: 3.0222128e+09 | D88: 87664629 | O88: 12423 | R88: 0.03 | AG88: =IF(OR(B88="",B88=0,M88=""),"",M88/B88*10000) | AH88: =IF(OR(C88="",C88=0),"",N88/C88*10000) | AI88: =IF(OR(D88="",D88=0),"",O88/D88*10000) | AP88: 15315067 | AQ88: 26531.537 | AR88: 957.8834 | AT88: 426.77454 | AU88: 0.02158528 | AV88: 4.266095e+08 | AW88: 60100000 | AX88: 15315067 | AY88: 3100000 | AZ88: =1000000000-999838422.7581 | BA88: =1000000000-AV88-AW88-AX88-AY88-AZ88 | BB88: 244.9 | BC88: =BA88/1000000-BB88 | BD88: =BA88*24.99
A89: 45711 | B89: 3.3579305e+09 | D89: 313527932 | O89: 13884 | R89: 0.03 | AG89: =IF(OR(B89="",B89=0,M89=""),"",M89/B89*10000) | AH89: =IF(OR(C89="",C89=0),"",N89/C89*10000) | AI89: =IF(OR(D89="",D89=0),"",O89/D89*10000) | AP89: 15345748 | AQ89: 26510.007 | AR89: 272.4934 | AT89: 426.16778 | AU89: 0.02160047 | AV89: 4.2658299e+08 | AW89: 60100000 | AX89: 15345748 | AY89: 3100000 | AZ89: =1000000000-999838150.2647 | BA89: =1000000000-AV89-AW89-AX89-AY89-AZ89 | BB89: 244.9 | BC89: =BA89/1000000-BB89 | BD89: =BA89*24.79
A90: 45712 | B90: 9.4427579e+09 | D90: 403523120 | O90: 36499 | R90: 0.03 | AG90: =IF(OR(B90="",B90=0,M90=""),"",M90/B90*10000) | AH90: =IF(OR(C90="",C90=0),"",N90/C90*10000) | AI90: =IF(OR(D90="",D90=0),"",O90/D90*10000) | AP90: 15395297 | AQ90: 26495.592 | AR90: 359.0801 | AT90: 425.75838 | AU90: 0.021610727 | AV90: 4.2655649e+08 | AW90: 60100000 | AX90: 15395297 | AY90: 3100000 | AZ90: =1000000000-999837791.1845 | BA90: =1000000000-AV90-AW90-AX90-AY90-AZ90 | BB90: 244.9 | BC90: =BA90/1000000-BB90 | BD90: =BA90*23.15
A91: 45713 | B91: 1.3212927e+10 | D91: 252882738 | O91: 76421 | R91: 0.03 | AG91: =IF(OR(B91="",B91=0,M91=""),"",M91/B91*10000) | AH91: =IF(OR(C91="",C91=0),"",N91/C91*10000) | AI91: =IF(OR(D91="",D91=0),"",O91/D91*10000) | AP91: 15434587 | AQ91: 26462.362 | AR91: 1448.4853 | AT91: 424.00807 | AU91: 0.021654767 | AV91: 4.2653003e+08 | AW91: 60100000 | AX91: 15434587 | AY91: 3100000 | AZ91: =1000000000-999836342.6993 | BA91: =1000000000-AV91-AW91-AX91-AY91-AZ91 | BB91: 244.9 | BC91: =BA91/1000000-BB91 | BD91: =BA91*19.88
A92: 45714 | B92: 9.3616944e+09 | D92: 163029559 | O92: 36925 | R92: 0.03 | AG92: =IF(OR(B92="",B92=0,M92=""),"",M92/B92*10000) | AH92: =IF(OR(C92="",C92=0),"",N92/C92*10000) | AI92: =IF(OR(D92="",D92=0),"",O92/D92*10000) | AP92: 15640861 | AQ92: 26402.54 | AR92: 2533.9117 | AT92: 422.61334 | AU92: 0.021690054 | AV92: 4.2650363e+08 | AW92: 60100000 | AX92: 15640861 | AY92: 3100000 | AZ92: =1000000000-999833808.7876 | BA92: =1000000000-AV92-AW92-AX92-AY92-AZ92 | BB92: 244.9 | BC92: =BA92/1000000-BB92 | BD92: =BA92*20.19
A93: 45715 | B93: 6.7969396e+09 | D93: 214669060 | O93: 21492 | R93: 0.03 | AG93: =IF(OR(B93="",B93=0,M93=""),"",M93/B93*10000) | AH93: =IF(OR(C93="",C93=0),"",N93/C93*10000) | AI93: =IF(OR(D93="",D93=0),"",O93/D93*10000) | AP93: 15754076 | AQ93: 26370.782 | AR93: 1291.9301 | AT93: 422.10103 | AU93: 0.021703059 | AV93: 4.2647726e+08 | AW93: 60100000 | AX93: 15754076 | AY93: 3100000 | AZ93: =1000000000-999832516.8574 | BA93: =1000000000-AV93-AW93-AX93-AY93-AZ93 | BB93: 244.9 | BC93: =BA93/1000000-BB93 | BD93: =BA93*19.56
A94: 45716 | B94: 1.1157923e+10 | D94: 87391052 | O94: 33048 | R94: 0.03 | AG94: =IF(OR(B94="",B94=0,M94=""),"",M94/B94*10000) | AH94: =IF(OR(C94="",C94=0),"",N94/C94*10000) | AI94: =IF(OR(D94="",D94=0),"",O94/D94*10000) | AP94: 15863736 | AQ94: 26389.878 | AR94: 800.0369 | AT94: 421.8219 | AU94: 0.021710154 | AV94: 4.2645087e+08 | AW94: 60100000 | AX94: 15863736 | AY94: 3100000 | AZ94: =1000000000-999831716.8206 | BA94: =1000000000-AV94-AW94-AX94-AY94-AZ94 | BB94: 244.9 | BC94: =BA94/1000000-BB94 | BD94: =BA94*20.87
A95: 45717 | B95: 4.3004895e+09 | D95: 230865213 | O95: 12337 | R95: 0.03 | AG95: =IF(OR(B95="",B95=0,M95=""),"",M95/B95*10000) | AH95: =IF(OR(C95="",C95=0),"",N95/C95*10000) | AI95: =IF(OR(D95="",D95=0),"",O95/D95*10000) | AP95: 15955801 | AQ95: 26354.432 | AR95: 1113.9076 | AT95: 421.27242 | AU95: 0.021724143 | AV95: 4.2642451e+08 | AW95: 60100000 | AX95: 15955801 | AY95: 3100000 | AZ95: =1000000000-999830602.913 | BA95: =1000000000-AV95-AW95-AX95-AY95-AZ95 | BB95: 244.9 | BC95: =BA95/1000000-BB95 | BD95: =BA95*19.95
A96: 45718 | B96: 1.1125716e+10 | D96: 260215664 | O96: 31229 | R96: 0.03 | AG96: =IF(OR(B96="",B96=0,M96=""),"",M96/B96*10000) | AH96: =IF(OR(C96="",C96=0),"",N96/C96*10000) | AI96: =IF(OR(D96="",D96=0),"",O96/D96*10000) | AP96: 15998308 | AQ96: 26347.556 | AR96: 456.8228 | AT96: 421.32777 | AU96: 0.021722733 | AV96: 4.2639817e+08 | AW96: 60100000 | AX96: 15998308 | AY96: 3100000 | AZ96: =1000000000-999830146.0902 | BA96: =1000000000-AV96-AW96-AX96-AY96-AZ96 | BB96: 244.9 | BC96: =BA96/1000000-BB96 | BD96: =BA96*19.6
A97: 45719 | B97: 1.1687297e+10 | D97: 277747349 | O97: 31999 | R97: 0.03 | AG97: =IF(OR(B97="",B97=0,M97=""),"",M97/B97*10000) | AH97: =IF(OR(C97="",C97=0),"",N97/C97*10000) | AI97: =IF(OR(D97="",D97=0),"",O97/D97*10000) | AP97: 16155015 | AQ97: 26343.694 | AR97: 1076.7938 | AT97: 420.61561 | AU97: 0.0217409 | AV97: 4.2637182e+08 | AW97: 60100000 | AX97: 16155015 | AY97: 3100000 | AZ97: =1000000000-999829069.2964 | BA97: =1000000000-AV97-AW97-AX97-AY97-AZ97 | BB97: 244.9 | BC97: =BA97/1000000-BB97 | BD97: =BA97*20.53
A98: 45720 | B98: 1.0923024e+10 | D98: 143679985 | O98: 47916 | R98: 0.03 | AG98: =IF(OR(B98="",B98=0,M98=""),"",M98/B98*10000) | AH98: =IF(OR(C98="",C98=0),"",N98/C98*10000) | AI98: =IF(OR(D98="",D98=0),"",O98/D98*10000) | AP98: 16312097 | AQ98: 26300.191 | AR98: 1191.9757 | AT98: 419.72848 | AU98: 0.021763594 | AV98: 4.2634552e+08 | AW98: 60100000 | AX98: 16312097 | AY98: 3100000 | AZ98: =1000000000-999827877.3207 | BA98: =1000000000-AV98-AW98-AX98-AY98-AZ98 | BB98: 244.9 | BC98: =BA98/1000000-BB98 | BD98: =BA98*17.88
A99: 45721 | B99: 6.3931022e+09 | D99: 171189803 | O99: 20047 | R99: 0.03 | AG99: =IF(OR(B99="",B99=0,M99=""),"",M99/B99*10000) | AH99: =IF(OR(C99="",C99=0),"",N99/C99*10000) | AI99: =IF(OR(D99="",D99=0),"",O99/D99*10000) | AP99: 16429515 | AQ99: 26023.156 | AR99: 2036.1675 | AT99: 418.28364 | AU99: 0.021800709 | AV99: 4.263195e+08 | AW99: 60100000 | AX99: 16429515 | AY99: 3100000 | AZ99: =1000000000-999825841.1532 | BA99: =1000000000-AV99-AW99-AX99-AY99-AZ99 | BB99: 244.9 | BC99: =BA99/1000000-BB99 | BD99: =BA99*17.09
A100: 45722 | B100: 6.8989258e+09 | D100: 199378699 | O100: 24157 | R100: 0.03 | AG100: =IF(OR(B100="",B100=0,M100=""),"",M100/B100*10000) | AH100: =IF(OR(C100="",C100=0),"",N100/C100*10000) | AI100: =IF(OR(D100="",D100=0),"",O100/D100*10000) | AP100: 16512215 | AQ100: 26246.193 | AR100: 835.7671 | AT100: 418.42368 | AU100: 0.021797104 | AV100: 4.2629325e+08 | AW100: 60100000 | AX100: 16512215 | AY100: 3100000 | AZ100: =1000000000-999825005.3861 | BA100: =1000000000-AV100-AW100-AX100-AY100-AZ100 | BB100: 244.9 | BC100: =BA100/1000000-BB100 | BD100: =BA100*17.18
...

Sheet Quarterly Model
A1: HYPERLIQUID (HYPE) — QUARTERLY MODEL. Same columns as Daily. Flows summed (SUMIFS); stocks/rates at period-end; OTS at quarter-end.
D2: VOLUME ($) | H2: HIP-3 VOLUME BY CATEGORY ($) | O2: GROSS FEES ($) [user-paid] | T2: FEE → REVENUE BRIDGE [deductions, $] | AB2: REVENUE TO HYPERCORE ($) | AI2: IMPLIED TAKE-RATE (bps) | AL2: OTHER REVENUE ($) | AO2: ASSISTANCE FUND & SUPPLY | AX2: OTS (Hyperliquid Strategies basis)
A3: Quarter | B3: Start | C3: End | D3: Core Crypto Perp Vol ($) | E3: HIP-3 Perp Vol ($) | F3: Spot Vol ($) | G3: HIP-4 Vol ($) | H3: HIP-3 Commodities ($) | I3: HIP-3 Crypto ($) | J3: HIP-3 FX ($) | K3: HIP-3 Indices ($) | L3: HIP-3 Pre-IPO ($) | M3: HIP-3 Stocks ($) | N3: HIP-3 Cat Total ($) | O3: Core Crypto Perp Fees ($) | P3: HIP-3 Gross Fees ($) | Q3: Spot Fees incl Unit ($) | R3: HIP-4 Fees ($) | S3: Total Gross Fees ($) | T3: HLP Rate | U3: (-) HLP on Core Perp ($) | V3: (-) HLP on HIP-3 ($) | W3: (-) HLP on Spot ($) | X3: (-) Unit Protocol Fees ($) | Y3: (-) HIP-3 Deployer Fees ($) | Z3: Total Deductions ($) | AA3: Builder Code Fees [on-top, not deducted] ($) | AB3: Core Crypto Perp Revenue ($) | AC3: HIP-3 Revenue ($) | AD3: Spot Revenue ($) | AE3: HIP-4 Revenue ($) | AF3: =HyperCore Revenue (model) ($) | AG3: HyperCore Revenue [hyperscreener] ($) | AH3: Check: model - hyperscreener ($) | AI3: Core Perp Take-Rate (bps) | AJ3: HIP-3 Take-Rate (bps) | AK3: Spot Take-Rate (bps) | AL3: HyperEVM Burn ($) | AM3: Auction Burn ($) | AN3: Total Revenue ($) | AO3: Revenue -> AF ($) | AP3: Buyback HYPE | AQ3: Buyback Avg Price ($) | AR3: AF HYPE Balance | AS3: Staking Emissions (HYPE) | AT3: Fee Burn (HYPE) | AU3: Team Tokens Unlocked (HYPE) | AV3: HYPE Staked (M) | AW3: Implied Staking Yield | AX3: (-) Future Emissions & CR (HYPE) | AY3: (-) Hyper Foundation (HYPE) | AZ3: (-) Assistance Fund (HYPE) | BA3: (-) Community Grants (HYPE) | BB3: (-) HC&EVM Fee Burns (HYPE) | BC3: =OTS (HYPE) | BD3: Core Contributors Locked (M) | BE3: Circulating Token Supply (M) | BF3: OTS Value ($)
A4: Q4 2024 (Nov-Dec) | B4: 45626 | C4: 45657 | D4: =SUMIFS('Daily Model'!$B$4:$B$555,'Daily Model'!$A$4:$A$555,">="&$B4,'Daily Model'!$A$4:$A$555,"<="&$C4) | E4: =SUMIFS('Daily Model'!$C$4:$C$555,'Daily Model'!$A$4:$A$555,">="&$B4,'Daily Model'!$A$4:$A$555,"<="&$C4) | F4: =SUMIFS('Daily Model'!$D$4:$D$555,'Daily Model'!$A$4:$A$555,">="&$B4,'Daily Model'!$A$4:$A$555,"<="&$C4) | G4: =SUMIFS('Daily Model'!$E$4:$E$555,'Daily Model'!$A$4:$A$555,">="&$B4,'Daily Model'!$A$4:$A$555,"<="&$C4) | H4: =SUMIFS('Daily Model'!$F$4:$F$555,'Daily Model'!$A$4:$A$555,">="&$B4,'Daily Model'!$A$4:$A$555,"<="&$C4) | I4: =SUMIFS('Daily Model'!$G$4:$G$555,'Daily Model'!$A$4:$A$555,">="&$B4,'Daily Model'!$A$4:$A$555,"<="&$C4) | J4: =SUMIFS('Daily Model'!$H$4:$H$555,'Daily Model'!$A$4:$A$555,">="&$B4,'Daily Model'!$A$4:$A$555,"<="&$C4) | K4: =SUMIFS('Daily Model'!$I$4:$I$555,'Daily Model'!$A$4:$A$555,">="&$B4,'Daily Model'!$A$4:$A$555,"<="&$C4) | L4: =SUMIFS('Daily Model'!$J$4:$J$555,'Daily Model'!$A$4:$A$555,">="&$B4,'Daily Model'!$A$4:$A$555,"<="&$C4) | M4: =SUMIFS('Daily Model'!$K$4:$K$555,'Daily Model'!$A$4:$A$555,">="&$B4,'Daily Model'!$A$4:$A$555,"<="&$C4) | N4: =SUMIFS('Daily Model'!$L$4:$L$555,'Daily Model'!$A$4:$A$555,">="&$B4,'Daily Model'!$A$4:$A$555,"<="&$C4) | O4: =SUMIFS('Daily Model'!$M$4:$M$555,'Daily Model'!$A$4:$A$555,">="&$B4,'Daily Model'!$A$4:$A$555,"<="&$C4) | P4: =SUMIFS('Daily Model'!$N$4:$N$555,'Daily Model'!$A$4:$A$555,">="&$B4,'Daily Model'!$A$4:$A$555,"<="&$C4) | Q4: =SUMIFS('Daily Model'!$O$4:$O$555,'Daily Model'!$A$4:$A$555,">="&$B4,'Daily Model'!$A$4:$A$555,"<="&$C4) | R4: =SUMIFS('Daily Model'!$P$4:$P$555,'Daily Model'!$A$4:$A$555,">="&$B4,'Daily Model'!$A$4:$A$555,"<="&$C4) | S4: =SUMIFS('Daily Model'!$Q$4:$Q$555,'Daily Model'!$A$4:$A$555,">="&$B4,'Daily Model'!$A$4:$A$555,"<="&$C4) | U4: =SUMIFS('Daily Model'!$S$4:$S$555,'Daily Model'!$A$4:$A$555,">="&$B4,'Daily Model'!$A$4:$A$555,"<="&$C4) | V4: =SUMIFS('Daily Model'!$T$4:$T$555,'Daily Model'!$A$4:$A$555,">="&$B4,'Daily Model'!$A$4:$A$555,"<="&$C4) | W4: =SUMIFS('Daily Model'!$U$4:$U$555,'Daily Model'!$A$4:$A$555,">="&$B4,'Daily Model'!$A$4:$A$555,"<="&$C4) | X4: =SUMIFS('Daily Model'!$V$4:$V$555,'Daily Model'!$A$4:$A$555,">="&$B4,'Daily Model'!$A$4:$A$555,"<="&$C4) | Y4: =SUMIFS('Daily Model'!$W$4:$W$555,'Daily Model'!$A$4:$A$555,">="&$B4,'Daily Model'!$A$4:$A$555,"<="&$C4) | Z4: =SUMIFS('Daily Model'!$X$4:$X$555,'Daily Model'!$A$4:$A$555,">="&$B4,'Daily Model'!$A$4:$A$555,"<="&$C4) | AA4: =SUMIFS('Daily Model'!$Y$4:$Y$555,'Daily Model'!$A$4:$A$555,">="&$B4,'Daily Model'!$A$4:$A$555,"<="&$C4) | AB4: =SUMIFS('Daily Model'!$Z$4:$Z$555,'Daily Model'!$A$4:$A$555,">="&$B4,'Daily Model'!$A$4:$A$555,"<="&$C4) | AC4: =SUMIFS('Daily Model'!$AA$4:$AA$555,'Daily Model'!$A$4:$A$555,">="&$B4,'Daily Model'!$A$4:$A$555,"<="&$C4) | AD4: =SUMIFS('Daily Model'!$AB$4:$AB$555,'Daily Model'!$A$4:$A$555,">="&$B4,'Daily Model'!$A$4:$A$555,"<="&$C4) | AE4: =SUMIFS('Daily Model'!$AC$4:$AC$555,'Daily Model'!$A$4:$A$555,">="&$B4,'Daily Model'!$A$4:$A$555,"<="&$C4) | AF4: =SUMIFS('Daily Model'!$AD$4:$AD$555,'Daily Model'!$A$4:$A$555,">="&$B4,'Daily Model'!$A$4:$A$555,"<="&$C4) | AG4: =SUMIFS('Daily Model'!$AE$4:$AE$555,'Daily Model'!$A$4:$A$555,">="&$B4,'Daily Model'!$A$4:$A$555,"<="&$C4) | AH4: =AF4-AG4 | AI4: =IF(D4=0,"",O4/D4*10000) | AJ4: =IF(E4=0,"",P4/E4*10000) | AK4: =IF(F4=0,"",Q4/F4*10000) | AL4: =SUMIFS('Daily Model'!$AJ$4:$AJ$555,'Daily Model'!$A$4:$A$555,">="&$B4,'Daily Model'!$A$4:$A$555,"<="&$C4) | AM4: =SUMIFS('Daily Model'!$AK$4:$AK$555,'Daily Model'!$A$4:$A$555,">="&$B4,'Daily Model'!$A$4:$A$555,"<="&$C4) | AN4: =SUMIFS('Daily Model'!$AL$4:$AL$555,'Daily Model'!$A$4:$A$555,">="&$B4,'Daily Model'!$A$4:$A$555,"<="&$C4) | AO4: =SUMIFS('Daily Model'!$AM$4:$AM$555,'Daily Model'!$A$4:$A$555,">="&$B4,'Daily Model'!$A$4:$A$555,"<="&$C4) | AP4: =SUMIFS('Daily Model'!$AN$4:$AN$555,'Daily Model'!$A$4:$A$555,">="&$B4,'Daily Model'!$A$4:$A$555,"<="&$C4) | AQ4: =IF(AP4=0,"",AO4/AP4) | AR4: 11670797 | AS4: =SUMIFS('Daily Model'!$AQ$4:$AQ$555,'Daily Model'!$A$4:$A$555,">="&$B4,'Daily Model'!$A$4:$A$555,"<="&$C4) | AT4: =SUMIFS('Daily Model'!$AR$4:$AR$555,'Daily Model'!$A$4:$A$555,">="&$B4,'Daily Model'!$A$4:$A$555,"<="&$C4) | AU4: =SUMIFS('Daily Model'!$AS$4:$AS$555,'Daily Model'!$A$4:$A$555,">="&$B4,'Daily Model'!$A$4:$A$555,"<="&$C4) | AV4: 352.7986 | AW4: 0.0233 | AX4: 4.2800478e+08 | AY4: 60100000 | AZ4: 11670797 | BA4: 3100000 | BB4: 110094.67 | BC4: 4.9701433e+08 | BD4: 244.9 | BE4: 252.1143 | BF4: 1.3394536e+10
A5: Q1 2025 | B5: 45658 | C5: 45747 | D5: =SUMIFS('Daily Model'!$B$4:$B$555,'Daily Model'!$A$4:$A$555,">="&$B5,'Daily Model'!$A$4:$A$555,"<="&$C5) | E5: =SUMIFS('Daily Model'!$C$4:$C$555,'Daily Model'!$A$4:$A$555,">="&$B5,'Daily Model'!$A$4:$A$555,"<="&$C5) | F5: =SUMIFS('Daily Model'!$D$4:$D$555,'Daily Model'!$A$4:$A$555,">="&$B5,'Daily Model'!$A$4:$A$555,"<="&$C5) | G5: =SUMIFS('Daily Model'!$E$4:$E$555,'Daily Model'!$A$4:$A$555,">="&$B5,'Daily Model'!$A$4:$A$555,"<="&$C5) | H5: =SUMIFS('Daily Model'!$F$4:$F$555,'Daily Model'!$A$4:$A$555,">="&$B5,'Daily Model'!$A$4:$A$555,"<="&$C5) | I5: =SUMIFS('Daily Model'!$G$4:$G$555,'Daily Model'!$A$4:$A$555,">="&$B5,'Daily Model'!$A$4:$A$555,"<="&$C5) | J5: =SUMIFS('Daily Model'!$H$4:$H$555,'Daily Model'!$A$4:$A$555,">="&$B5,'Daily Model'!$A$4:$A$555,"<="&$C5) | K5: =SUMIFS('Daily Model'!$I$4:$I$555,'Daily Model'!$A$4:$A$555,">="&$B5,'Daily Model'!$A$4:$A$555,"<="&$C5) | L5: =SUMIFS('Daily Model'!$J$4:$J$555,'Daily Model'!$A$4:$A$555,">="&$B5,'Daily Model'!$A$4:$A$555,"<="&$C5) | M5: =SUMIFS('Daily Model'!$K$4:$K$555,'Daily Model'!$A$4:$A$555,">="&$B5,'Daily Model'!$A$4:$A$555,"<="&$C5) | N5: =SUMIFS('Daily Model'!$L$4:$L$555,'Daily Model'!$A$4:$A$555,">="&$B5,'Daily Model'!$A$4:$A$555,"<="&$C5) | O5: =SUMIFS('Daily Model'!$M$4:$M$555,'Daily Model'!$A$4:$A$555,">="&$B5,'Daily Model'!$A$4:$A$555,"<="&$C5) | P5: =SUMIFS('Daily Model'!$N$4:$N$555,'Daily Model'!$A$4:$A$555,">="&$B5,'Daily Model'!$A$4:$A$555,"<="&$C5) | Q5: =SUMIFS('Daily Model'!$O$4:$O$555,'Daily Model'!$A$4:$A$555,">="&$B5,'Daily Model'!$A$4:$A$555,"<="&$C5) | R5: =SUMIFS('Daily Model'!$P$4:$P$555,'Daily Model'!$A$4:$A$555,">="&$B5,'Daily Model'!$A$4:$A$555,"<="&$C5) | S5: =SUMIFS('Daily Model'!$Q$4:$Q$555,'Daily Model'!$A$4:$A$555,">="&$B5,'Daily Model'!$A$4:$A$555,"<="&$C5) | U5: =SUMIFS('Daily Model'!$S$4:$S$555,'Daily Model'!$A$4:$A$555,">="&$B5,'Daily Model'!$A$4:$A$555,"<="&$C5) | V5: =SUMIFS('Daily Model'!$T$4:$T$555,'Daily Model'!$A$4:$A$555,">="&$B5,'Daily Model'!$A$4:$A$555,"<="&$C5) | W5: =SUMIFS('Daily Model'!$U$4:$U$555,'Daily Model'!$A$4:$A$555,">="&$B5,'Daily Model'!$A$4:$A$555,"<="&$C5) | X5: =SUMIFS('Daily Model'!$V$4:$V$555,'Daily Model'!$A$4:$A$555,">="&$B5,'Daily Model'!$A$4:$A$555,"<="&$C5) | Y5: =SUMIFS('Daily Model'!$W$4:$W$555,'Daily Model'!$A$4:$A$555,">="&$B5,'Daily Model'!$A$4:$A$555,"<="&$C5) | Z5: =SUMIFS('Daily Model'!$X$4:$X$555,'Daily Model'!$A$4:$A$555,">="&$B5,'Daily Model'!$A$4:$A$555,"<="&$C5) | AA5: =SUMIFS('Daily Model'!$Y$4:$Y$555,'Daily Model'!$A$4:$A$555,">="&$B5,'Daily Model'!$A$4:$A$555,"<="&$C5) | AB5: =SUMIFS('Daily Model'!$Z$4:$Z$555,'Daily Model'!$A$4:$A$555,">="&$B5,'Daily Model'!$A$4:$A$555,"<="&$C5) | AC5: =SUMIFS('Daily Model'!$AA$4:$AA$555,'Daily Model'!$A$4:$A$555,">="&$B5,'Daily Model'!$A$4:$A$555,"<="&$C5) | AD5: =SUMIFS('Daily Model'!$AB$4:$AB$555,'Daily Model'!$A$4:$A$555,">="&$B5,'Daily Model'!$A$4:$A$555,"<="&$C5) | AE5: =SUMIFS('Daily Model'!$AC$4:$AC$555,'Daily Model'!$A$4:$A$555,">="&$B5,'Daily Model'!$A$4:$A$555,"<="&$C5) | AF5: =SUMIFS('Daily Model'!$AD$4:$AD$555,'Daily Model'!$A$4:$A$555,">="&$B5,'Daily Model'!$A$4:$A$555,"<="&$C5) | AG5: =SUMIFS('Daily Model'!$AE$4:$AE$555,'Daily Model'!$A$4:$A$555,">="&$B5,'Daily Model'!$A$4:$A$555,"<="&$C5) | AH5: =AF5-AG5 | AI5: =IF(D5=0,"",O5/D5*10000) | AJ5: =IF(E5=0,"",P5/E5*10000) | AK5: =IF(F5=0,"",Q5/F5*10000) | AL5: =SUMIFS('Daily Model'!$AJ$4:$AJ$555,'Daily Model'!$A$4:$A$555,">="&$B5,'Daily Model'!$A$4:$A$555,"<="&$C5) | AM5: =SUMIFS('Daily Model'!$AK$4:$AK$555,'Daily Model'!$A$4:$A$555,">="&$B5,'Daily Model'!$A$4:$A$555,"<="&$C5) | AN5: =SUMIFS('Daily Model'!$AL$4:$AL$555,'Daily Model'!$A$4:$A$555,">="&$B5,'Daily Model'!$A$4:$A$555,"<="&$C5) | AO5: =SUMIFS('Daily Model'!$AM$4:$AM$555,'Daily Model'!$A$4:$A$555,">="&$B5,'Daily Model'!$A$4:$A$555,"<="&$C5) | AP5: =SUMIFS('Daily Model'!$AN$4:$AN$555,'Daily Model'!$A$4:$A$555,">="&$B5,'Daily Model'!$A$4:$A$555,"<="&$C5) | AQ5: =IF(AP5=0,"",AO5/AP5) | AR5: 18407964 | AS5: =SUMIFS('Daily Model'!$AQ$4:$AQ$555,'Daily Model'!$A$4:$A$555,">="&$B5,'Daily Model'!$A$4:$A$555,"<="&$C5) | AT5: =SUMIFS('Daily Model'!$AR$4:$AR$555,'Daily Model'!$A$4:$A$555,">="&$B5,'Daily Model'!$A$4:$A$555,"<="&$C5) | AU5: =SUMIFS('Daily Model'!$AS$4:$AS$555,'Daily Model'!$A$4:$A$555,">="&$B5,'Daily Model'!$A$4:$A$555,"<="&$C5) | AV5: 421.3321 | AW5: 0.0217 | AX5: 4.2563427e+08 | AY5: 60100000 | AZ5: 18407964 | BA5: 3100000 | BB5: 195016.42 | BC5: 4.9256275e+08 | BD5: 244.9 | BE5: 247.6628 | BF5: 6.1471832e+09
A6: Q2 2025 | B6: 45748 | C6: 45838 | D6: =SUMIFS('Daily Model'!$B$4:$B$555,'Daily Model'!$A$4:$A$555,">="&$B6,'Daily Model'!$A$4:$A$555,"<="&$C6) | E6: =SUMIFS('Daily Model'!$C$4:$C$555,'Daily Model'!$A$4:$A$555,">="&$B6,'Daily Model'!$A$4:$A$555,"<="&$C6) | F6: =SUMIFS('Daily Model'!$D$4:$D$555,'Daily Model'!$A$4:$A$555,">="&$B6,'Daily Model'!$A$4:$A$555,"<="&$C6) | G6: =SUMIFS('Daily Model'!$E$4:$E$555,'Daily Model'!$A$4:$A$555,">="&$B6,'Daily Model'!$A$4:$A$555,"<="&$C6) | H6: =SUMIFS('Daily Model'!$F$4:$F$555,'Daily Model'!$A$4:$A$555,">="&$B6,'Daily Model'!$A$4:$A$555,"<="&$C6) | I6: =SUMIFS('Daily Model'!$G$4:$G$555,'Daily Model'!$A$4:$A$555,">="&$B6,'Daily Model'!$A$4:$A$555,"<="&$C6) | J6: =SUMIFS('Daily Model'!$H$4:$H$555,'Daily Model'!$A$4:$A$555,">="&$B6,'Daily Model'!$A$4:$A$555,"<="&$C6) | K6: =SUMIFS('Daily Model'!$I$4:$I$555,'Daily Model'!$A$4:$A$555,">="&$B6,'Daily Model'!$A$4:$A$555,"<="&$C6) | L6: =SUMIFS('Daily Model'!$J$4:$J$555,'Daily Model'!$A$4:$A$555,">="&$B6,'Daily Model'!$A$4:$A$555,"<="&$C6) | M6: =SUMIFS('Daily Model'!$K$4:$K$555,'Daily Model'!$A$4:$A$555,">="&$B6,'Daily Model'!$A$4:$A$555,"<="&$C6) | N6: =SUMIFS('Daily Model'!$L$4:$L$555,'Daily Model'!$A$4:$A$555,">="&$B6,'Daily Model'!$A$4:$A$555,"<="&$C6) | O6: =SUMIFS('Daily Model'!$M$4:$M$555,'Daily Model'!$A$4:$A$555,">="&$B6,'Daily Model'!$A$4:$A$555,"<="&$C6) | P6: =SUMIFS('Daily Model'!$N$4:$N$555,'Daily Model'!$A$4:$A$555,">="&$B6,'Daily Model'!$A$4:$A$555,"<="&$C6) | Q6: =SUMIFS('Daily Model'!$O$4:$O$555,'Daily Model'!$A$4:$A$555,">="&$B6,'Daily Model'!$A$4:$A$555,"<="&$C6) | R6: =SUMIFS('Daily Model'!$P$4:$P$555,'Daily Model'!$A$4:$A$555,">="&$B6,'Daily Model'!$A$4:$A$555,"<="&$C6) | S6: =SUMIFS('Daily Model'!$Q$4:$Q$555,'Daily Model'!$A$4:$A$555,">="&$B6,'Daily Model'!$A$4:$A$555,"<="&$C6) | U6: =SUMIFS('Daily Model'!$S$4:$S$555,'Daily Model'!$A$4:$A$555,">="&$B6,'Daily Model'!$A$4:$A$555,"<="&$C6) | V6: =SUMIFS('Daily Model'!$T$4:$T$555,'Daily Model'!$A$4:$A$555,">="&$B6,'Daily Model'!$A$4:$A$555,"<="&$C6) | W6: =SUMIFS('Daily Model'!$U$4:$U$555,'Daily Model'!$A$4:$A$555,">="&$B6,'Daily Model'!$A$4:$A$555,"<="&$C6) | X6: =SUMIFS('Daily Model'!$V$4:$V$555,'Daily Model'!$A$4:$A$555,">="&$B6,'Daily Model'!$A$4:$A$555,"<="&$C6) | Y6: =SUMIFS('Daily Model'!$W$4:$W$555,'Daily Model'!$A$4:$A$555,">="&$B6,'Daily Model'!$A$4:$A$555,"<="&$C6) | Z6: =SUMIFS('Daily Model'!$X$4:$X$555,'Daily Model'!$A$4:$A$555,">="&$B6,'Daily Model'!$A$4:$A$555,"<="&$C6) | AA6: =SUMIFS('Daily Model'!$Y$4:$Y$555,'Daily Model'!$A$4:$A$555,">="&$B6,'Daily Model'!$A$4:$A$555,"<="&$C6) | AB6: =SUMIFS('Daily Model'!$Z$4:$Z$555,'Daily Model'!$A$4:$A$555,">="&$B6,'Daily Model'!$A$4:$A$555,"<="&$C6) | AC6: =SUMIFS('Daily Model'!$AA$4:$AA$555,'Daily Model'!$A$4:$A$555,">="&$B6,'Daily Model'!$A$4:$A$555,"<="&$C6) | AD6: =SUMIFS('Daily Model'!$AB$4:$AB$555,'Daily Model'!$A$4:$A$555,">="&$B6,'Daily Model'!$A$4:$A$555,"<="&$C6) | AE6: =SUMIFS('Daily Model'!$AC$4:$AC$555,'Daily Model'!$A$4:$A$555,">="&$B6,'Daily Model'!$A$4:$A$555,"<="&$C6) | AF6: =SUMIFS('Daily Model'!$AD$4:$AD$555,'Daily Model'!$A$4:$A$555,">="&$B6,'Daily Model'!$A$4:$A$555,"<="&$C6) | AG6: =SUMIFS('Daily Model'!$AE$4:$AE$555,'Daily Model'!$A$4:$A$555,">="&$B6,'Daily Model'!$A$4:$A$555,"<="&$C6) | AH6: =AF6-AG6 | AI6: =IF(D6=0,"",O6/D6*10000) | AJ6: =IF(E6=0,"",P6/E6*10000) | AK6: =IF(F6=0,"",Q6/F6*10000) | AL6: =SUMIFS('Daily Model'!$AJ$4:$AJ$555,'Daily Model'!$A$4:$A$555,">="&$B6,'Daily Model'!$A$4:$A$555,"<="&$C6) | AM6: =SUMIFS('Daily Model'!$AK$4:$AK$555,'Daily Model'!$A$4:$A$555,">="&$B6,'Daily Model'!$A$4:$A$555,"<="&$C6) | AN6: =SUMIFS('Daily Model'!$AL$4:$AL$555,'Daily Model'!$A$4:$A$555,">="&$B6,'Daily Model'!$A$4:$A$555,"<="&$C6) | AO6: =SUMIFS('Daily Model'!$AM$4:$AM$555,'Daily Model'!$A$4:$A$555,">="&$B6,'Daily Model'!$A$4:$A$555,"<="&$C6) | AP6: =SUMIFS('Daily Model'!$AN$4:$AN$555,'Daily Model'!$A$4:$A$555,">="&$B6,'Daily Model'!$A$4:$A$555,"<="&$C6) | AQ6: =IF(AP6=0,"",AO6/AP6) | AR6: 25508876 | AS6: =SUMIFS('Daily Model'!$AQ$4:$AQ$555,'Daily Model'!$A$4:$A$555,">="&$B6,'Daily Model'!$A$4:$A$555,"<="&$C6) | AT6: =SUMIFS('Daily Model'!$AR$4:$AR$555,'Daily Model'!$A$4:$A$555,">="&$B6,'Daily Model'!$A$4:$A$555,"<="&$C6) | AU6: =SUMIFS('Daily Model'!$AS$4:$AS$555,'Daily Model'!$A$4:$A$555,">="&$B6,'Daily Model'!$A$4:$A$555,"<="&$C6) | AV6: 422.0714 | AW6: 0.0217 | AX6: 4.2324595e+08 | AY6: 60100000 | AZ6: 25508876 | BA6: 3100000 | BB6: 309088.56 | BC6: 4.8773608e+08 | BD6: 244.9 | BE6: 242.8361 | BF6: 1.9280207e+10
A7: Q3 2025 | B7: 45839 | C7: 45930 | D7: =SUMIFS('Daily Model'!$B$4:$B$555,'Daily Model'!$A$4:$A$555,">="&$B7,'Daily Model'!$A$4:$A$555,"<="&$C7) | E7: =SUMIFS('Daily Model'!$C$4:$C$555,'Daily Model'!$A$4:$A$555,">="&$B7,'Daily Model'!$A$4:$A$555,"<="&$C7) | F7: =SUMIFS('Daily Model'!$D$4:$D$555,'Daily Model'!$A$4:$A$555,">="&$B7,'Daily Model'!$A$4:$A$555,"<="&$C7) | G7: =SUMIFS('Daily Model'!$E$4:$E$555,'Daily Model'!$A$4:$A$555,">="&$B7,'Daily Model'!$A$4:$A$555,"<="&$C7) | H7: =SUMIFS('Daily Model'!$F$4:$F$555,'Daily Model'!$A$4:$A$555,">="&$B7,'Daily Model'!$A$4:$A$555,"<="&$C7) | I7: =SUMIFS('Daily Model'!$G$4:$G$555,'Daily Model'!$A$4:$A$555,">="&$B7,'Daily Model'!$A$4:$A$555,"<="&$C7) | J7: =SUMIFS('Daily Model'!$H$4:$H$555,'Daily Model'!$A$4:$A$555,">="&$B7,'Daily Model'!$A$4:$A$555,"<="&$C7) | K7: =SUMIFS('Daily Model'!$I$4:$I$555,'Daily Model'!$A$4:$A$555,">="&$B7,'Daily Model'!$A$4:$A$555,"<="&$C7) | L7: =SUMIFS('Daily Model'!$J$4:$J$555,'Daily Model'!$A$4:$A$555,">="&$B7,'Daily Model'!$A$4:$A$555,"<="&$C7) | M7: =SUMIFS('Daily Model'!$K$4:$K$555,'Daily Model'!$A$4:$A$555,">="&$B7,'Daily Model'!$A$4:$A$555,"<="&$C7) | N7: =SUMIFS('Daily Model'!$L$4:$L$555,'Daily Model'!$A$4:$A$555,">="&$B7,'Daily Model'!$A$4:$A$555,"<="&$C7) | O7: =SUMIFS('Daily Model'!$M$4:$M$555,'Daily Model'!$A$4:$A$555,">="&$B7,'Daily Model'!$A$4:$A$555,"<="&$C7) | P7: =SUMIFS('Daily Model'!$N$4:$N$555,'Daily Model'!$A$4:$A$555,">="&$B7,'Daily Model'!$A$4:$A$555,"<="&$C7) | Q7: =SUMIFS('Daily Model'!$O$4:$O$555,'Daily Model'!$A$4:$A$555,">="&$B7,'Daily Model'!$A$4:$A$555,"<="&$C7) | R7: =SUMIFS('Daily Model'!$P$4:$P$555,'Daily Model'!$A$4:$A$555,">="&$B7,'Daily Model'!$A$4:$A$555,"<="&$C7) | S7: =SUMIFS('Daily Model'!$Q$4:$Q$555,'Daily Model'!$A$4:$A$555,">="&$B7,'Daily Model'!$A$4:$A$555,"<="&$C7) | U7: =SUMIFS('Daily Model'!$S$4:$S$555,'Daily Model'!$A$4:$A$555,">="&$B7,'Daily Model'!$A$4:$A$555,"<="&$C7) | V7: =SUMIFS('Daily Model'!$T$4:$T$555,'Daily Model'!$A$4:$A$555,">="&$B7,'Daily Model'!$A$4:$A$555,"<="&$C7) | W7: =SUMIFS('Daily Model'!$U$4:$U$555,'Daily Model'!$A$4:$A$555,">="&$B7,'Daily Model'!$A$4:$A$555,"<="&$C7) | X7: =SUMIFS('Daily Model'!$V$4:$V$555,'Daily Model'!$A$4:$A$555,">="&$B7,'Daily Model'!$A$4:$A$555,"<="&$C7) | Y7: =SUMIFS('Daily Model'!$W$4:$W$555,'Daily Model'!$A$4:$A$555,">="&$B7,'Daily Model'!$A$4:$A$555,"<="&$C7) | Z7: =SUMIFS('Daily Model'!$X$4:$X$555,'Daily Model'!$A$4:$A$555,">="&$B7,'Daily Model'!$A$4:$A$555,"<="&$C7) | AA7: =SUMIFS('Daily Model'!$Y$4:$Y$555,'Daily Model'!$A$4:$A$555,">="&$B7,'Daily Model'!$A$4:$A$555,"<="&$C7) | AB7: =SUMIFS('Daily Model'!$Z$4:$Z$555,'Daily Model'!$A$4:$A$555,">="&$B7,'Daily Model'!$A$4:$A$555,"<="&$C7) | AC7: =SUMIFS('Daily Model'!$AA$4:$AA$555,'Daily Model'!$A$4:$A$555,">="&$B7,'Daily Model'!$A$4:$A$555,"<="&$C7) | AD7: =SUMIFS('Daily Model'!$AB$4:$AB$555,'Daily Model'!$A$4:$A$555,">="&$B7,'Daily Model'!$A$4:$A$555,"<="&$C7) | AE7: =SUMIFS('Daily Model'!$AC$4:$AC$555,'Daily Model'!$A$4:$A$555,">="&$B7,'Daily Model'!$A$4:$A$555,"<="&$C7) | AF7: =SUMIFS('Daily Model'!$AD$4:$AD$555,'Daily Model'!$A$4:$A$555,">="&$B7,'Daily Model'!$A$4:$A$555,"<="&$C7) | AG7: =SUMIFS('Daily Model'!$AE$4:$AE$555,'Daily Model'!$A$4:$A$555,">="&$B7,'Daily Model'!$A$4:$A$555,"<="&$C7) | AH7: =AF7-AG7 | AI7: =IF(D7=0,"",O7/D7*10000) | AJ7: =IF(E7=0,"",P7/E7*10000) | AK7: =IF(F7=0,"",Q7/F7*10000) | AL7: =SUMIFS('Daily Model'!$AJ$4:$AJ$555,'Daily Model'!$A$4:$A$555,">="&$B7,'Daily Model'!$A$4:$A$555,"<="&$C7) | AM7: =SUMIFS('Daily Model'!$AK$4:$AK$555,'Daily Model'!$A$4:$A$555,">="&$B7,'Daily Model'!$A$4:$A$555,"<="&$C7) | AN7: =SUMIFS('Daily Model'!$AL$4:$AL$555,'Daily Model'!$A$4:$A$555,">="&$B7,'Daily Model'!$A$4:$A$555,"<="&$C7) | AO7: =SUMIFS('Daily Model'!$AM$4:$AM$555,'Daily Model'!$A$4:$A$555,">="&$B7,'Daily Model'!$A$4:$A$555,"<="&$C7) | AP7: =SUMIFS('Daily Model'!$AN$4:$AN$555,'Daily Model'!$A$4:$A$555,">="&$B7,'Daily Model'!$A$4:$A$555,"<="&$C7) | AQ7: =IF(AP7=0,"",AO7/AP7) | AR7: 31785059 | AS7: =SUMIFS('Daily Model'!$AQ$4:$AQ$555,'Daily Model'!$A$4:$A$555,">="&$B7,'Daily Model'!$A$4:$A$555,"<="&$C7) | AT7: =SUMIFS('Daily Model'!$AR$4:$AR$555,'Daily Model'!$A$4:$A$555,">="&$B7,'Daily Model'!$A$4:$A$555,"<="&$C7) | AU7: =SUMIFS('Daily Model'!$AS$4:$AS$555,'Daily Model'!$A$4:$A$555,">="&$B7,'Daily Model'!$A$4:$A$555,"<="&$C7) | AV7: 425.4931 | AW7: 0.0216 | AX7: 4.2082436e+08 | AY7: 60100000 | AZ7: 31785059 | BA7: 3100000 | BB7: 424925.91 | BC7: 4.8376566e+08 | BD7: 244.9 | BE7: 238.8657 | BF7: 2.2306435e+10
A8: Q4 2025 | B8: 45931 | C8: 46022 | D8: =SUMIFS('Daily Model'!$B$4:$B$555,'Daily Model'!$A$4:$A$555,">="&$B8,'Daily Model'!$A$4:$A$555,"<="&$C8) | E8: =SUMIFS('Daily Model'!$C$4:$C$555,'Daily Model'!$A$4:$A$555,">="&$B8,'Daily Model'!$A$4:$A$555,"<="&$C8) | F8: =SUMIFS('Daily Model'!$D$4:$D$555,'Daily Model'!$A$4:$A$555,">="&$B8,'Daily Model'!$A$4:$A$555,"<="&$C8) | G8: =SUMIFS('Daily Model'!$E$4:$E$555,'Daily Model'!$A$4:$A$555,">="&$B8,'Daily Model'!$A$4:$A$555,"<="&$C8) | H8: =SUMIFS('Daily Model'!$F$4:$F$555,'Daily Model'!$A$4:$A$555,">="&$B8,'Daily Model'!$A$4:$A$555,"<="&$C8) | I8: =SUMIFS('Daily Model'!$G$4:$G$555,'Daily Model'!$A$4:$A$555,">="&$B8,'Daily Model'!$A$4:$A$555,"<="&$C8) | J8: =SUMIFS('Daily Model'!$H$4:$H$555,'Daily Model'!$A$4:$A$555,">="&$B8,'Daily Model'!$A$4:$A$555,"<="&$C8) | K8: =SUMIFS('Daily Model'!$I$4:$I$555,'Daily Model'!$A$4:$A$555,">="&$B8,'Daily Model'!$A$4:$A$555,"<="&$C8) | L8: =SUMIFS('Daily Model'!$J$4:$J$555,'Daily Model'!$A$4:$A$555,">="&$B8,'Daily Model'!$A$4:$A$555,"<="&$C8) | M8: =SUMIFS('Daily Model'!$K$4:$K$555,'Daily Model'!$A$4:$A$555,">="&$B8,'Daily Model'!$A$4:$A$555,"<="&$C8) | N8: =SUMIFS('Daily Model'!$L$4:$L$555,'Daily Model'!$A$4:$A$555,">="&$B8,'Daily Model'!$A$4:$A$555,"<="&$C8) | O8: =SUMIFS('Daily Model'!$M$4:$M$555,'Daily Model'!$A$4:$A$555,">="&$B8,'Daily Model'!$A$4:$A$555,"<="&$C8) | P8: =SUMIFS('Daily Model'!$N$4:$N$555,'Daily Model'!$A$4:$A$555,">="&$B8,'Daily Model'!$A$4:$A$555,"<="&$C8) | Q8: =SUMIFS('Daily Model'!$O$4:$O$555,'Daily Model'!$A$4:$A$555,">="&$B8,'Daily Model'!$A$4:$A$555,"<="&$C8) | R8: =SUMIFS('Daily Model'!$P$4:$P$555,'Daily Model'!$A$4:$A$555,">="&$B8,'Daily Model'!$A$4:$A$555,"<="&$C8) | S8: =SUMIFS('Daily Model'!$Q$4:$Q$555,'Daily Model'!$A$4:$A$555,">="&$B8,'Daily Model'!$A$4:$A$555,"<="&$C8) | U8: =SUMIFS('Daily Model'!$S$4:$S$555,'Daily Model'!$A$4:$A$555,">="&$B8,'Daily Model'!$A$4:$A$555,"<="&$C8) | V8: =SUMIFS('Daily Model'!$T$4:$T$555,'Daily Model'!$A$4:$A$555,">="&$B8,'Daily Model'!$A$4:$A$555,"<="&$C8) | W8: =SUMIFS('Daily Model'!$U$4:$U$555,'Daily Model'!$A$4:$A$555,">="&$B8,'Daily Model'!$A$4:$A$555,"<="&$C8) | X8: =SUMIFS('Daily Model'!$V$4:$V$555,'Daily Model'!$A$4:$A$555,">="&$B8,'Daily Model'!$A$4:$A$555,"<="&$C8) | Y8: =SUMIFS('Daily Model'!$W$4:$W$555,'Daily Model'!$A$4:$A$555,">="&$B8,'Daily Model'!$A$4:$A$555,"<="&$C8) | Z8: =SUMIFS('Daily Model'!$X$4:$X$555,'Daily Model'!$A$4:$A$555,">="&$B8,'Daily Model'!$A$4:$A$555,"<="&$C8) | AA8: =SUMIFS('Daily Model'!$Y$4:$Y$555,'Daily Model'!$A$4:$A$555,">="&$B8,'Daily Model'!$A$4:$A$555,"<="&$C8) | AB8: =SUMIFS('Daily Model'!$Z$4:$Z$555,'Daily Model'!$A$4:$A$555,">="&$B8,'Daily Model'!$A$4:$A$555,"<="&$C8) | AC8: =SUMIFS('Daily Model'!$AA$4:$AA$555,'Daily Model'!$A$4:$A$555,">="&$B8,'Daily Model'!$A$4:$A$555,"<="&$C8) | AD8: =SUMIFS('Daily Model'!$AB$4:$AB$555,'Daily Model'!$A$4:$A$555,">="&$B8,'Daily Model'!$A$4:$A$555,"<="&$C8) | AE8: =SUMIFS('Daily Model'!$AC$4:$AC$555,'Daily Model'!$A$4:$A$555,">="&$B8,'Daily Model'!$A$4:$A$555,"<="&$C8) | AF8: =SUMIFS('Daily Model'!$AD$4:$AD$555,'Daily Model'!$A$4:$A$555,">="&$B8,'Daily Model'!$A$4:$A$555,"<="&$C8) | AG8: =SUMIFS('Daily Model'!$AE$4:$AE$555,'Daily Model'!$A$4:$A$555,">="&$B8,'Daily Model'!$A$4:$A$555,"<="&$C8) | AH8: =AF8-AG8 | AI8: =IF(D8=0,"",O8/D8*10000) | AJ8: =IF(E8=0,"",P8/E8*10000) | AK8: =IF(F8=0,"",Q8/F8*10000) | AL8: =SUMIFS('Daily Model'!$AJ$4:$AJ$555,'Daily Model'!$A$4:$A$555,">="&$B8,'Daily Model'!$A$4:$A$555,"<="&$C8) | AM8: =SUMIFS('Daily Model'!$AK$4:$AK$555,'Daily Model'!$A$4:$A$555,">="&$B8,'Daily Model'!$A$4:$A$555,"<="&$C8) | AN8: =SUMIFS('Daily Model'!$AL$4:$AL$555,'Daily Model'!$A$4:$A$555,">="&$B8,'Daily Model'!$A$4:$A$555,"<="&$C8) | AO8: =SUMIFS('Daily Model'!$AM$4:$AM$555,'Daily Model'!$A$4:$A$555,">="&$B8,'Daily Model'!$A$4:$A$555,"<="&$C8) | AP8: =SUMIFS('Daily Model'!$AN$4:$AN$555,'Daily Model'!$A$4:$A$555,">="&$B8,'Daily Model'!$A$4:$A$555,"<="&$C8) | AQ8: =IF(AP8=0,"",AO8/AP8) | AR8: 37855112 | AS8: =SUMIFS('Daily Model'!$AQ$4:$AQ$555,'Daily Model'!$A$4:$A$555,">="&$B8,'Daily Model'!$A$4:$A$555,"<="&$C8) | AT8: =SUMIFS('Daily Model'!$AR$4:$AR$555,'Daily Model'!$A$4:$A$555,">="&$B8,'Daily Model'!$A$4:$A$555,"<="&$C8) | AU8: =SUMIFS('Daily Model'!$AS$4:$AS$555,'Daily Model'!$A$4:$A$555,">="&$B8,'Daily Model'!$A$4:$A$555,"<="&$C8) | AV8: 432.3217 | AW8: 0.0214 | AX8: 4.1841903e+08 | AY8: 60100000 | AZ8: 37855112 | BA8: 3100000 | BB8: 552936.25 | BC8: 4.7997292e+08 | BD8: 243.1543 | BE8: 236.8187 | BF8: 1.24121e+10
A9: Q1 2026 | B9: 46023 | C9: 46112 | D9: =SUMIFS('Daily Model'!$B$4:$B$555,'Daily Model'!$A$4:$A$555,">="&$B9,'Daily Model'!$A$4:$A$555,"<="&$C9) | E9: =SUMIFS('Daily Model'!$C$4:$C$555,'Daily Model'!$A$4:$A$555,">="&$B9,'Daily Model'!$A$4:$A$555,"<="&$C9) | F9: =SUMIFS('Daily Model'!$D$4:$D$555,'Daily Model'!$A$4:$A$555,">="&$B9,'Daily Model'!$A$4:$A$555,"<="&$C9) | G9: =SUMIFS('Daily Model'!$E$4:$E$555,'Daily Model'!$A$4:$A$555,">="&$B9,'Daily Model'!$A$4:$A$555,"<="&$C9) | H9: =SUMIFS('Daily Model'!$F$4:$F$555,'Daily Model'!$A$4:$A$555,">="&$B9,'Daily Model'!$A$4:$A$555,"<="&$C9) | I9: =SUMIFS('Daily Model'!$G$4:$G$555,'Daily Model'!$A$4:$A$555,">="&$B9,'Daily Model'!$A$4:$A$555,"<="&$C9) | J9: =SUMIFS('Daily Model'!$H$4:$H$555,'Daily Model'!$A$4:$A$555,">="&$B9,'Daily Model'!$A$4:$A$555,"<="&$C9) | K9: =SUMIFS('Daily Model'!$I$4:$I$555,'Daily Model'!$A$4:$A$555,">="&$B9,'Daily Model'!$A$4:$A$555,"<="&$C9) | L9: =SUMIFS('Daily Model'!$J$4:$J$555,'Daily Model'!$A$4:$A$555,">="&$B9,'Daily Model'!$A$4:$A$555,"<="&$C9) | M9: =SUMIFS('Daily Model'!$K$4:$K$555,'Daily Model'!$A$4:$A$555,">="&$B9,'Daily Model'!$A$4:$A$555,"<="&$C9) | N9: =SUMIFS('Daily Model'!$L$4:$L$555,'Daily Model'!$A$4:$A$555,">="&$B9,'Daily Model'!$A$4:$A$555,"<="&$C9) | O9: =SUMIFS('Daily Model'!$M$4:$M$555,'Daily Model'!$A$4:$A$555,">="&$B9,'Daily Model'!$A$4:$A$555,"<="&$C9) | P9: =SUMIFS('Daily Model'!$N$4:$N$555,'Daily Model'!$A$4:$A$555,">="&$B9,'Daily Model'!$A$4:$A$555,"<="&$C9) | Q9: =SUMIFS('Daily Model'!$O$4:$O$555,'Daily Model'!$A$4:$A$555,">="&$B9,'Daily Model'!$A$4:$A$555,"<="&$C9) | R9: =SUMIFS('Daily Model'!$P$4:$P$555,'Daily Model'!$A$4:$A$555,">="&$B9,'Daily Model'!$A$4:$A$555,"<="&$C9) | S9: =SUMIFS('Daily Model'!$Q$4:$Q$555,'Daily Model'!$A$4:$A$555,">="&$B9,'Daily Model'!$A$4:$A$555,"<="&$C9) | U9: =SUMIFS('Daily Model'!$S$4:$S$555,'Daily Model'!$A$4:$A$555,">="&$B9,'Daily Model'!$A$4:$A$555,"<="&$C9) | V9: =SUMIFS('Daily Model'!$T$4:$T$555,'Daily Model'!$A$4:$A$555,">="&$B9,'Daily Model'!$A$4:$A$555,"<="&$C9) | W9: =SUMIFS('Daily Model'!$U$4:$U$555,'Daily Model'!$A$4:$A$555,">="&$B9,'Daily Model'!$A$4:$A$555,"<="&$C9) | X9: =SUMIFS('Daily Model'!$V$4:$V$555,'Daily Model'!$A$4:$A$555,">="&$B9,'Daily Model'!$A$4:$A$555,"<="&$C9) | Y9: =SUMIFS('Daily Model'!$W$4:$W$555,'Daily Model'!$A$4:$A$555,">="&$B9,'Daily Model'!$A$4:$A$555,"<="&$C9) | Z9: =SUMIFS('Daily Model'!$X$4:$X$555,'Daily Model'!$A$4:$A$555,">="&$B9,'Daily Model'!$A$4:$A$555,"<="&$C9) | AA9: =SUMIFS('Daily Model'!$Y$4:$Y$555,'Daily Model'!$A$4:$A$555,">="&$B9,'Daily Model'!$A$4:$A$555,"<="&$C9) | AB9: =SUMIFS('Daily Model'!$Z$4:$Z$555,'Daily Model'!$A$4:$A$555,">="&$B9,'Daily Model'!$A$4:$A$555,"<="&$C9) | AC9: =SUMIFS('Daily Model'!$AA$4:$AA$555,'Daily Model'!$A$4:$A$555,">="&$B9,'Daily Model'!$A$4:$A$555,"<="&$C9) | AD9: =SUMIFS('Daily Model'!$AB$4:$AB$555,'Daily Model'!$A$4:$A$555,">="&$B9,'Daily Model'!$A$4:$A$555,"<="&$C9) | AE9: =SUMIFS('Daily Model'!$AC$4:$AC$555,'Daily Model'!$A$4:$A$555,">="&$B9,'Daily Model'!$A$4:$A$555,"<="&$C9) | AF9: =SUMIFS('Daily Model'!$AD$4:$AD$555,'Daily Model'!$A$4:$A$555,">="&$B9,'Daily Model'!$A$4:$A$555,"<="&$C9) | AG9: =SUMIFS('Daily Model'!$AE$4:$AE$555,'Daily Model'!$A$4:$A$555,">="&$B9,'Daily Model'!$A$4:$A$555,"<="&$C9) | AH9: =AF9-AG9 | AI9: =IF(D9=0,"",O9/D9*10000) | AJ9: =IF(E9=0,"",P9/E9*10000) | AK9: =IF(F9=0,"",Q9/F9*10000) | AL9: =SUMIFS('Daily Model'!$AJ$4:$AJ$555,'Daily Model'!$A$4:$A$555,">="&$B9,'Daily Model'!$A$4:$A$555,"<="&$C9) | AM9: =SUMIFS('Daily Model'!$AK$4:$AK$555,'Daily Model'!$A$4:$A$555,">="&$B9,'Daily Model'!$A$4:$A$555,"<="&$C9) | AN9: =SUMIFS('Daily Model'!$AL$4:$AL$555,'Daily Model'!$A$4:$A$555,">="&$B9,'Daily Model'!$A$4:$A$555,"<="&$C9) | AO9: =SUMIFS('Daily Model'!$AM$4:$AM$555,'Daily Model'!$A$4:$A$555,">="&$B9,'Daily Model'!$A$4:$A$555,"<="&$C9) | AP9: =SUMIFS('Daily Model'!$AN$4:$AN$555,'Daily Model'!$A$4:$A$555,">="&$B9,'Daily Model'!$A$4:$A$555,"<="&$C9) | AQ9: =IF(AP9=0,"",AO9/AP9) | AR9: 42797055 | AS9: =SUMIFS('Daily Model'!$AQ$4:$AQ$555,'Daily Model'!$A$4:$A$555,">="&$B9,'Daily Model'!$A$4:$A$555,"<="&$C9) | AT9: =SUMIFS('Daily Model'!$AR$4:$AR$555,'Daily Model'!$A$4:$A$555,">="&$B9,'Daily Model'!$A$4:$A$555,"<="&$C9) | AU9: =SUMIFS('Daily Model'!$AS$4:$AS$555,'Daily Model'!$A$4:$A$555,">="&$B9,'Daily Model'!$A$4:$A$555,"<="&$C9) | AV9: 434.6766 | AW9: 0.0214 | AX9: 4.1603739e+08 | AY9: 60100000 | AZ9: 42797055 | BA9: 3100000 | BB9: 731922.87 | BC9: 4.7723363e+08 | BD9: 241.7149 | BE9: 235.5187 | BF9: 1.7586059e+10
A10: Q2 2026 (to 06-04) | B10: 46113 | C10: 46177 | D10: =SUMIFS('Daily Model'!$B$4:$B$555,'Daily Model'!$A$4:$A$555,">="&$B10,'Daily Model'!$A$4:$A$555,"<="&$C10) | E10: =SUMIFS('Daily Model'!$C$4:$C$555,'Daily Model'!$A$4:$A$555,">="&$B10,'Daily Model'!$A$4:$A$555,"<="&$C10) | F10: =SUMIFS('Daily Model'!$D$4:$D$555,'Daily Model'!$A$4:$A$555,">="&$B10,'Daily Model'!$A$4:$A$555,"<="&$C10) | G10: =SUMIFS('Daily Model'!$E$4:$E$555,'Daily Model'!$A$4:$A$555,">="&$B10,'Daily Model'!$A$4:$A$555,"<="&$C10) | H10: =SUMIFS('Daily Model'!$F$4:$F$555,'Daily Model'!$A$4:$A$555,">="&$B10,'Daily Model'!$A$4:$A$555,"<="&$C10) | I10: =SUMIFS('Daily Model'!$G$4:$G$555,'Daily Model'!$A$4:$A$555,">="&$B10,'Daily Model'!$A$4:$A$555,"<="&$C10) | J10: =SUMIFS('Daily Model'!$H$4:$H$555,'Daily Model'!$A$4:$A$555,">="&$B10,'Daily Model'!$A$4:$A$555,"<="&$C10) | K10: =SUMIFS('Daily Model'!$I$4:$I$555,'Daily Model'!$A$4:$A$555,">="&$B10,'Daily Model'!$A$4:$A$555,"<="&$C10) | L10: =SUMIFS('Daily Model'!$J$4:$J$555,'Daily Model'!$A$4:$A$555,">="&$B10,'Daily Model'!$A$4:$A$555,"<="&$C10) | M10: =SUMIFS('Daily Model'!$K$4:$K$555,'Daily Model'!$A$4:$A$555,">="&$B10,'Daily Model'!$A$4:$A$555,"<="&$C10) | N10: =SUMIFS('Daily Model'!$L$4:$L$555,'Daily Model'!$A$4:$A$555,">="&$B10,'Daily Model'!$A$4:$A$555,"<="&$C10) | O10: =SUMIFS('Daily Model'!$M$4:$M$555,'Daily Model'!$A$4:$A$555,">="&$B10,'Daily Model'!$A$4:$A$555,"<="&$C10) | P10: =SUMIFS('Daily Model'!$N$4:$N$555,'Daily Model'!$A$4:$A$555,">="&$B10,'Daily Model'!$A$4:$A$555,"<="&$C10) | Q10: =SUMIFS('Daily Model'!$O$4:$O$555,'Daily Model'!$A$4:$A$555,">="&$B10,'Daily Model'!$A$4:$A$555,"<="&$C10) | R10: =SUMIFS('Daily Model'!$P$4:$P$555,'Daily Model'!$A$4:$A$555,">="&$B10,'Daily Model'!$A$4:$A$555,"<="&$C10) | S10: =SUMIFS('Daily Model'!$Q$4:$Q$555,'Daily Model'!$A$4:$A$555,">="&$B10,'Daily Model'!$A$4:$A$555,"<="&$C10) | U10: =SUMIFS('Daily Model'!$S$4:$S$555,'Daily Model'!$A$4:$A$555,">="&$B10,'Daily Model'!$A$4:$A$555,"<="&$C10) | V10: =SUMIFS('Daily Model'!$T$4:$T$555,'Daily Model'!$A$4:$A$555,">="&$B10,'Daily Model'!$A$4:$A$555,"<="&$C10) | W10: =SUMIFS('Daily Model'!$U$4:$U$555,'Daily Model'!$A$4:$A$555,">="&$B10,'Daily Model'!$A$4:$A$555,"<="&$C10) | X10: =SUMIFS('Daily Model'!$V$4:$V$555,'Daily Model'!$A$4:$A$555,">="&$B10,'Daily Model'!$A$4:$A$555,"<="&$C10) | Y10: =SUMIFS('Daily Model'!$W$4:$W$555,'Daily Model'!$A$4:$A$555,">="&$B10,'Daily Model'!$A$4:$A$555,"<="&$C10) | Z10: =SUMIFS('Daily Model'!$X$4:$X$555,'Daily Model'!$A$4:$A$555,">="&$B10,'Daily Model'!$A$4:$A$555,"<="&$C10) | AA10: =SUMIFS('Daily Model'!$Y$4:$Y$555,'Daily Model'!$A$4:$A$555,">="&$B10,'Daily Model'!$A$4:$A$555,"<="&$C10) | AB10: =SUMIFS('Daily Model'!$Z$4:$Z$555,'Daily Model'!$A$4:$A$555,">="&$B10,'Daily Model'!$A$4:$A$555,"<="&$C10) | AC10: =SUMIFS('Daily Model'!$AA$4:$AA$555,'Daily Model'!$A$4:$A$555,">="&$B10,'Daily Model'!$A$4:$A$555,"<="&$C10) | AD10: =SUMIFS('Daily Model'!$AB$4:$AB$555,'Daily Model'!$A$4:$A$555,">="&$B10,'Daily Model'!$A$4:$A$555,"<="&$C10) | AE10: =SUMIFS('Daily Model'!$AC$4:$AC$555,'Daily Model'!$A$4:$A$555,">="&$B10,'Daily Model'!$A$4:$A$555,"<="&$C10) | AF10: =SUMIFS('Daily Model'!$AD$4:$AD$555,'Daily Model'!$A$4:$A$555,">="&$B10,'Daily Model'!$A$4:$A$555,"<="&$C10) | AG10: =SUMIFS('Daily Model'!$AE$4:$AE$555,'Daily Model'!$A$4:$A$555,">="&$B10,'Daily Model'!$A$4:$A$555,"<="&$C10) | AH10: =AF10-AG10 | AI10: =IF(D10=0,"",O10/D10*10000) | AJ10: =IF(E10=0,"",P10/E10*10000) | AK10: =IF(F10=0,"",Q10/F10*10000) | AL10: =SUMIFS('Daily Model'!$AJ$4:$AJ$555,'Daily Model'!$A$4:$A$555,">="&$B10,'Daily Model'!$A$4:$A$555,"<="&$C10) | AM10: =SUMIFS('Daily Model'!$AK$4:$AK$555,'Daily Model'!$A$4:$A$555,">="&$B10,'Daily Model'!$A$4:$A$555,"<="&$C10) | AN10: =SUMIFS('Daily Model'!$AL$4:$AL$555,'Daily Model'!$A$4:$A$555,">="&$B10,'Daily Model'!$A$4:$A$555,"<="&$C10) | AO10: =SUMIFS('Daily Model'!$AM$4:$AM$555,'Daily Model'!$A$4:$A$555,">="&$B10,'Daily Model'!$A$4:$A$555,"<="&$C10) | AP10: =SUMIFS('Daily Model'!$AN$4:$AN$555,'Daily Model'!$A$4:$A$555,">="&$B10,'Daily Model'!$A$4:$A$555,"<="&$C10) | AQ10: =IF(AP10=0,"",AO10/AP10) | AR10: 44818417 | AS10: =SUMIFS('Daily Model'!$AQ$4:$AQ$555,'Daily Model'!$A$4:$A$555,">="&$B10,'Daily Model'!$A$4:$A$555,"<="&$C10) | AT10: =SUMIFS('Daily Model'!$AR$4:$AR$555,'Daily Model'!$A$4:$A$555,">="&$B10,'Daily Model'!$A$4:$A$555,"<="&$C10) | AU10: =SUMIFS('Daily Model'!$AS$4:$AS$555,'Daily Model'!$A$4:$A$555,">="&$B10,'Daily Model'!$A$4:$A$555,"<="&$C10) | AV10: 430.5641 | AW10: 0.0215 | AX10: 4.1434815e+08 | AY10: 60100000 | AZ10: 44818417 | BA10: 3100000 | BB10: 803572.8 | BC10: 4.7682986e+08 | BD10: 241.3849 | BE10: 235.4449 | BF10: 3.3559286e+10

Sheet Sources
A1: SOURCES & METHODOLOGY
A2: • BRIDGE (per segment): Gross Fees − HLP − (Unit on spot) − (deployer on HIP-3) = Revenue to HyperCore. Builder code fees are ON-TOP (paid by users to front-ends) and are NOT deducted. Sum of segment revenues = HyperCore Revenue = hyperscreener "HyperCore Buybacks" (north star). + HyperEVM + Auction burn = Total Revenue.
A3: • Core crypto perp is the residual segment: Core Revenue = HyperCore − Spot − HIP-3 − HIP-4; Core Fees = Core Revenue / (1 − HLP). This makes the bridge tie exactly to the north star (Check column ≈ 0).
A4: • HLP share: 1% of perp+spot fees from 2025-08-30 (3% before); on spot it applies to (fees − Unit). HIP-3 & Spot revenue use clean computed HLP; any accrual-vs-buyback timing difference is absorbed by the core-perp residual.
A5: • HIP-3 volume AND fees are both from Loris (single source) so the take-rate is internally consistent. The asset-category split (commodities/crypto/fx/indices/pre-IPO/stocks) is the hyperscreener category mix allocated to the Loris HIP-3 total, so the categories sum exactly to HIP-3 volume.
A6: • HIP-4 (outcome / prediction markets) launched 2026-05-02, zero-fee. Hyperscreener only publishes the current day for HIP-4 (no daily history endpoint), so the column is sparse; immaterial to revenue.
A7: • OTS (Hyperliquid Strategies basis) = 1,000M − Future Emissions&CR − Hyper Foundation − Assistance Fund − Community Grants − HyperCore&HyperEVM fee burns. Validated to HL Strategies 29-Apr-2026 (477.0M vs 476.7M). Split into Core Contributors (locked) + Circulating; team vesting moves tokens Core→Circulating, OTS unchanged.
A9: Data | B9: Source | C9: Endpoint / URL | D9: Notes
A10: Core / total perp volume | B10: hyperscreener (ASXN) | C10: https://api-hyperliquid.asxn.xyz/api/cloudfront/total_volume | D10: Daily $ by coin, summed. Core = total − HIP-3.
A11: HIP-3 volume, gross fees, deployer fees | B11: Loris | C11: https://loris.tools/hip3 (api.loris.tools; HL perpDexs-derived) | D11: timeseries: volume, total_fees, total_deployer_fees. Single source for HIP-3 vol & fees.
A12: HIP-3 category mix | B12: hyperscreener (ASXN) | C12: https://api-hyperliquid.asxn.xyz/api/categories/hip3-categories/historical | D12: Asset-category proportions; allocated to the Loris HIP-3 total.
A13: Spot volume / fees / revenue | B13: DefiLlama | C13: https://api.llama.fi/summary/fees/hyperliquid-spot-orderbook · /dexs/hyperliquid-spot-orderbook | D13: dailyVolume, dailyFees (incl Unit).
A14: Unit protocol fees | B14: DefiLlama | C14: https://api.llama.fi/summary/fees/unit | D14: Hyperunit deployer cut on spot tokens it deploys.
A15: HIP-4 (outcome) volume/fees | B15: hyperscreener (ASXN) | C15: https://api-hyperliquid.asxn.xyz/api/outcome-coins/analytics/daily | D15: Current day only; live 2026-05-02, zero-fee.
A16: HyperCore revenue / buyback / AF | B16: hyperscreener (ASXN) | C16: https://api-hyperliquid.asxn.xyz/api/buyback/revenues · /hl-buybacks · /assistance-fund-holdings | D16: HyperCore Buybacks (north star), HyperEVM & auction burn, buyback HYPE/price, AF balance.
A17: Emissions / supply / fee burns | B17: hyperscreener (ASXN) | C17: https://api-hyperliquid.asxn.xyz/api/validators/daily-emissions · buyback/daily-burn | D17: dailyEmission, future-emission, total supply, dailyBurn.
A18: HYPE staked + implied yield | B18: hyperscreener (ASXN) | C18: https://api-hyperliquid.asxn.xyz/api/validators/hype-staking/metrics | D18: Daily totalStake + ASXN-computed yield.
A19: Builder code fees (on-top) | B19: hyperscreener (ASXN) | C19: https://api-hyperliquid.asxn.xyz/api/node/builders/stacked-fees-chart | D19: Pass-through to front-ends; not in the bridge.
A20: HLP share (1%/3%) | B20: DefiLlama methodology | C20: hyperliquid-perps & -spot-orderbook methodology | D20: 1% from 2025-08-30, 3% before.
... A23: Perp revenue (cross-check only) | B23: DefiLlama | C23: https://api.llama.fi/summary/fees/hyperliquid-perps | D23: Accrual basis; ~7.5% above hyperscreener buyback cumulatively (timing).
