Workbook
Name HLP_Current: Assumptions!$C$4
Name HLP_Legacy: Assumptions!$C$5
Name HLP_ChangeDate: Assumptions!$C$6
Name Team_Genesis: Assumptions!$C$17
Name Pre_Cliff_Vested: Assumptions!$C$18
Name Cliff_Date: Assumptions!$C$19
Name Vest_Months: Assumptions!$C$20
Name Monthly_Vest: Assumptions!$C$21
Name Daily_Vest: Assumptions!$C$22
Name Vest_End_Date: Assumptions!$C$23

Sheet Read Me
B1: Hyperliquid — Fee → Revenue DAILY Decomposition
B2: Splits the actual HyperCore revenue into core-perp / HIP-3 / spot, every day, by top-down subtraction.
B3: Generated 2026-05-26. Daily, 2025-01-01 → 2026-05-20.
B5: THE METHOD (everything daily — no monthly aggregation)
B6: • NORTH STAR: the actual HyperCore revenue reported by hyperscreener.asxn.xyz (the $ that funds HYPE buybacks). The model never overrides it — it decomposes it.
B7: • STEP 1 — HIP-3: HIP-3 gross fees and deployer fees come from Loris (loris.tools), daily. HIP-3 protocol revenue = gross fees − deployer fees.
B8: • STEP 2 — Spot: spot revenue comes from DefiLlama (hyperliquid-spot-orderbook), daily.
B9: • STEP 3 — Core perp (the plug): Core perp revenue = HyperCore revenue − HIP-3 protocol revenue − spot revenue. Because it is a residual, the three pieces ALWAYS sum back to the north star exactly.
B10: • STEP 4 — Fees & HLP: revenue is grossed up to protocol fees by adding back the HLP provider share — 1% of perp+spot fees, and 3% before 2025-08-30 (DefiLlama methodology). Protocol fee = revenue ÷ (1 − HLP%).
B11: • CROSS-CHECKS: each segment's implied take-rate (fees ÷ volume, in bps) is shown so you can sanity-check it against the Hyperliquid fee schedule.
B13: WHAT THE NUMBERS SAY (read these before using the model)
B14: • HIP-3 is in GROWTH MODE: gross fees are ~0.7 bps of HIP-3 volume — roughly 4x lower than core perp. HIP-3 deployer fees are zero until 2026-03-21 (deployers took 0% in growth mode), so before that the protocol kept 100% of the (small) HIP-3 fees. HIP-3 is huge in volume but tiny in revenue today.
... B22: TABS
B23: Assumptions | D23: HLP share (1% from 2025-08-30, 3% before). Yellow = editable.
B24: Quarterly Model | D24: Segment-by-segment quarterly view: volumes ($Bn), gross fees ($Mn), take-rates, HyperCore deduction bridge (HLP / Unit / HIP-3 Deployer / Builder), revenue, burns, buyback, supply movements and ending OTS — plus an OTS cross-check vs PURR / CoinGecko at 2026-04-29.
B25: Daily Model | D25: The daily revenue decomposition — volumes → revenue split → implied fees → take-rates. Spot Gross Fees = DefiLlama actual; Unit Protocol Fees = balancing item (Spot Fees − Spot Revenue).
B26: OTS Breakdown | D26: Historical Outstanding Token Supply: supply flows (buyback, emissions, burns, vesting) and the OTS calc per day — the valuation base.
B27: Daily Data | D27: Raw daily inputs from every source, plus the supply reconciliation.
B28: Sources | D28: Each column → its exact source.
B30: Colour legend: | C30: yellow = input | E30: blue = source value | G30: black = formula | I30: green = cross-tab link

Sheet Assumptions
A1: ASSUMPTIONS — yellow cells are inputs you control
B3: Parameter | C3: Value | E3: Basis / notes
B4: HLP provider share — current | C4: 0.01 | D4: =C4 | E4: Share of perp+spot protocol fees paid to HLP liquidity providers, from 2025-08-30. Source: DefiLlama methodology.
B5: HLP provider share — legacy (pre-changeover) | C5: 0.03 | D5: =C5 | E5: HLP share before 2025-08-30 (it was 3%, cut to 1%). Source: DefiLlama methodology.
B6: HLP rate changeover date | C6: 45899 | E6: Date the HLP share dropped from legacy to current.
B9: • Decomposition identity: HyperCore revenue = core perp revenue + HIP-3 protocol revenue + spot revenue (exact, every day).
B10: • HIP-3 (Hyperliquid docs + Loris): users pay ~2x a normal perp fee, but HIP-3 markets run in growth mode — realised HIP-3 fees are very low and the deployer share was 0% until 2026-03-21.
B11: • Hyperliquid fee schedule (reference): perps 0.045%/0.015% taker/maker; spot 0.07%/0.04%; realised rates are far lower due to volume tiers and discounts.
B13: Total HYPE Staked — latest snapshot (HYPE) | C13: 431410000 | E13: May-2026 Total Stake = 431.41M HYPE. Source: ASXN dashboard Total HYPE Staked chart (Active + Inactive). Cross-checks vs HL /info validatorSummaries (431.43M).
B14: Avg Implied APR (observed, validator-network) | C14: 0.0225 | D14: =C14 | E14: Daily Emission × 365 ÷ Total Stake. Hovers in 2.20–2.34% across the full period (averaging ~2.25%) — consistent with HL's published formula yield = 2.37% × √(400M / stake).
B15: Staking data snapshot date | C15: 46143 | E15: Date the ASXN staking chart was read. Monthly granularity (held flat within each month). For audit only.
B17: Core Contributor allocation (genesis, HYPE) | C17: 238000000 | E17: Genesis allocation to core contributors / team: 23.80% × 1B = 238M HYPE. Source: HL tokenomics. Subject to vesting (cliff + linear, staggered per-contributor).
B18: Pre-cliff already vested (HYPE) | C18: 3515062 | E18: Cumulative team-contributor distributions Nov-2025 → Apr-2026 (discretionary early unlocks). Source: insights.unlocks.app + tokenomist.ai unlock-events page. Sum of all monthly events on the 6th: 1.746M + 0 + 1.126M + 0.140M + 0.173M + 0.330M.
B19: Team vesting cliff date | C19: 46179 | E19: Per Tokenomist.ai: next major unlock = 2026-06-06. The main linear-vest period starts here.
B20: Vest duration (months) post-cliff | C20: 24 | E20: 24 months. Stretches the post-cliff schedule to May 2028 (cliff date + 24 months). Reflects most sources saying vesting completes 2027-2028.
B21: Monthly vest post-cliff (HYPE) — DERIVED | C21: =(Team_Genesis-Pre_Cliff_Vested)/Vest_Months | D21: =C21 | E21: FORMULA: (Team_Genesis − Pre_Cliff_Vested) ÷ Vest_Months. Computes ~9.77M HYPE/month (vs Tokenomist's nominal 9.92M — slightly lower because we credit the 3.5M already distributed).
B22: Daily vest post-cliff (HYPE) — DERIVED | C22: =Monthly_Vest/30.4375 | D22: =C22 | E22: FORMULA: Monthly_Vest ÷ 30.4375 days/month (avg). ≈ 321K HYPE/day. For projection rows on OTS Breakdown, put this in col G (Team Tokens Unlocked) for EVERY day between Cliff_Date (2026-06-06) and Vest_End_Date (Cliff_Date + Vest_Months × 30.4375 days ≈ 2028-06-05). Daily-granularity vesting matches the smooth per-contributor vesting nature better than monthly chunks.
B23: Vest end date — DERIVED | C23: =Cliff_Date+Vest_Months*30.4375 | E23: FORMULA: Cliff_Date + Vest_Months × 30.4375. = 2028-06-05. After this date, projection rows should set Team Tokens Unlocked = 0 (all 238M is vested by then).

Sheet Quarterly Model
A1: QUARTERLY MODEL — segment fees, HyperCore deduction bridge, capital deployment & supply movements. Volumes in $Bn, fees in $Mn, HYPE in millions. Every figure is a live SUMIFS from Daily Model / Daily Data / OTS Breakdown — changes upstream flow through. BRIDGE: Total Fees − HLP − Unit − HIP-3 Deployer = HyperCore Revenue (north star, ties to hyperscreener buyback). Recon Δ ≈ 0. Builder/Core is an ON-TOP pass-through fee paid by users directly to front-ends — shown for transparency but NOT in the bridge (it never enters HL's revenue).
D2: CORE PERPS — CRYPTO | G2: HIP-3 | J2: SPOT | M2: HYPERCORE DEDUCTIONS (Gross Fees → HyperCore Revenue) | R2: HYPERCORE | V2: OTHER REVENUE (Burns) | X2: CAPITAL DEPLOYMENT | AA2: SUPPLY MOVEMENTS (HYPE, M) | AE2: OTS COMPOSITION (OTS = Circulating + Core Contributors)
A3: Quarter | B3: Start Date | C3: End Date | D3: Volume ($Bn) | E3: Fees ($Mn) | F3: Take-Rate (bps) | G3: Volume ($Bn) | H3: Fees ($Mn) | I3: Take-Rate (bps) | J3: Volume ($Bn) | K3: Fees ($Mn) | L3: Take-Rate (bps) | M3: HLP ($Mn) | N3: HLP Eff. Rate | O3: Unit / Spot ($Mn) | P3: HIP-3 Deployer ($Mn) | Q3: Builder / Core ($Mn) — on-top | R3: Total Fees ($Mn) | S3: Revenue ($Mn) | T3: Revenue / Fees (%) | U3: Recon Δ ($Mn) | V3: HyperEVM Fees ($Mn) | W3: Auction Burn ($Mn) | X3: Revenue → AF ($Mn) | Y3: HYPE Bought (M) | Z3: Avg HYPE Price ($) | AA3: Staking Emissions | AB3: Team / Vesting | AC3: Fees Burned | AD3: Ending OTS (M HYPE) | AE3: Ending Core Locked (M HYPE) | AF3: Ending Circulating (M HYPE) | AG3: Split Check ≈ 0
A4: Q1 2025 | B4: 45658 | C4: 45747 | D4: =SUMIFS('Daily Data'!$B$4:$B$508,'Daily Data'!$A$4:$A$508,">="&B4,'Daily Data'!$A$4:$A$508,"<="&C4)/1000000000 | E4: =SUMIFS('Daily Model'!$L$4:$L$508,'Daily Model'!$A$4:$A$508,">="&B4,'Daily Model'!$A$4:$A$508,"<="&C4)/1000000 | F4: =IF(D4=0,0,E4/(D4*1000)*10000) | G4: =SUMIFS('Daily Data'!$D$4:$D$508,'Daily Data'!$A$4:$A$508,">="&B4,'Daily Data'!$A$4:$A$508,"<="&C4)/1000000000 | H4: =SUMIFS('Daily Data'!$F$4:$F$508,'Daily Data'!$A$4:$A$508,">="&B4,'Daily Data'!$A$4:$A$508,"<="&C4)/1000000 | I4: =IF(G4=0,0,H4/(G4*1000)*10000) | J4: =SUMIFS('Daily Data'!$C$4:$C$508,'Daily Data'!$A$4:$A$508,">="&B4,'Daily Data'!$A$4:$A$508,"<="&C4)/1000000000 | K4: =SUMIFS('Daily Data'!$I$4:$I$508,'Daily Data'!$A$4:$A$508,">="&B4,'Daily Data'!$A$4:$A$508,"<="&C4)/1000000 | L4: =IF(J4=0,0,K4/(J4*1000)*10000) | M4: =SUMIFS('Daily Model'!$P$4:$P$508,'Daily Model'!$A$4:$A$508,">="&B4,'Daily Model'!$A$4:$A$508,"<="&C4)/1000000 | N4: =IF((E4+H4+K4)=0,0,M4/(E4+H4+K4)) | O4: =SUMIFS('Daily Model'!$N$4:$N$508,'Daily Model'!$A$4:$A$508,">="&B4,'Daily Model'!$A$4:$A$508,"<="&C4)/1000000 | P4: =SUMIFS('Daily Data'!$G$4:$G$508,'Daily Data'!$A$4:$A$508,">="&B4,'Daily Data'!$A$4:$A$508,"<="&C4)/1000000 | Q4: =SUMIFS('Daily Model'!$O$4:$O$508,'Daily Model'!$A$4:$A$508,">="&B4,'Daily Model'!$A$4:$A$508,"<="&C4)/1000000 | R4: =E4+H4+K4 | S4: =SUMIFS('Daily Data'!$E$4:$E$508,'Daily Data'!$A$4:$A$508,">="&B4,'Daily Data'!$A$4:$A$508,"<="&C4)/1000000 | T4: =IF(R4=0,0,S4/R4) | U4: =R4-M4-O4-P4-S4 | V4: =SUMIFS('Daily Data'!$J$4:$J$508,'Daily Data'!$A$4:$A$508,">="&B4,'Daily Data'!$A$4:$A$508,"<="&C4)/1000000 | W4: =SUMIFS('Daily Data'!$K$4:$K$508,'Daily Data'!$A$4:$A$508,">="&B4,'Daily Data'!$A$4:$A$508,"<="&C4)/1000000 | X4: =S4 | Y4: =SUMIFS('Daily Data'!$L$4:$L$508,'Daily Data'!$A$4:$A$508,">="&B4,'Daily Data'!$A$4:$A$508,"<="&C4)/1000000 | Z4: =IF(Y4=0,"",SUMIFS('Daily Data'!$M$4:$M$508,'Daily Data'!$A$4:$A$508,">="&B4,'Daily Data'!$A$4:$A$508,"<="&C4)/1000000/Y4) | AA4: =SUMIFS('Daily Data'!$O$4:$O$508,'Daily Data'!$A$4:$A$508,">="&B4,'Daily Data'!$A$4:$A$508,"<="&C4)/1000000 | AB4: =SUMIFS('OTS Breakdown'!$G$4:$G$508,'OTS Breakdown'!$A$4:$A$508,">="&B4,'OTS Breakdown'!$A$4:$A$508,"<="&C4)/1000000 | AC4: =SUMIFS('Daily Data'!$P$4:$P$508,'Daily Data'!$A$4:$A$508,">="&B4,'Daily Data'!$A$4:$A$508,"<="&C4)/1000000 | AD4: =LOOKUP(2,1/(('OTS Breakdown'!$A$4:$A$508<=C4)*('OTS Breakdown'!$O$4:$O$508<>"")),'OTS Breakdown'!$O$4:$O$508)/1000000 | AE4: =LOOKUP(2,1/(('OTS Breakdown'!$A$4:$A$508<=C4)*('OTS Breakdown'!$AE$4:$AE$508<>"")),'OTS Breakdown'!$AE$4:$AE$508) | AF4: =LOOKUP(2,1/(('OTS Breakdown'!$A$4:$A$508<=C4)*('OTS Breakdown'!$AF$4:$AF$508<>"")),'OTS Breakdown'!$AF$4:$AF$508) | AG4: =AD4-AE4-AF4
A5: Q2 2025 | B5: 45748 | C5: 45838 | D5: =SUMIFS('Daily Data'!$B$4:$B$508,'Daily Data'!$A$4:$A$508,">="&B5,'Daily Data'!$A$4:$A$508,"<="&C5)/1000000000 | E5: =SUMIFS('Daily Model'!$L$4:$L$508,'Daily Model'!$A$4:$A$508,">="&B5,'Daily Model'!$A$4:$A$508,"<="&C5)/1000000 | F5: =IF(D5=0,0,E5/(D5*1000)*10000) | G5: =SUMIFS('Daily Data'!$D$4:$D$508,'Daily Data'!$A$4:$A$508,">="&B5,'Daily Data'!$A$4:$A$508,"<="&C5)/1000000000 | H5: =SUMIFS('Daily Data'!$F$4:$F$508,'Daily Data'!$A$4:$A$508,">="&B5,'Daily Data'!$A$4:$A$508,"<="&C5)/1000000 | I5: =IF(G5=0,0,H5/(G5*1000)*10000) | J5: =SUMIFS('Daily Data'!$C$4:$C$508,'Daily Data'!$A$4:$A$508,">="&B5,'Daily Data'!$A$4:$A$508,"<="&C5)/1000000000 | K5: =SUMIFS('Daily Data'!$I$4:$I$508,'Daily Data'!$A$4:$A$508,">="&B5,'Daily Data'!$A$4:$A$508,"<="&C5)/1000000 | L5: =IF(J5=0,0,K5/(J5*1000)*10000) | M5: =SUMIFS('Daily Model'!$P$4:$P$508,'Daily Model'!$A$4:$A$508,">="&B5,'Daily Model'!$A$4:$A$508,"<="&C5)/1000000 | N5: =IF((E5+H5+K5)=0,0,M5/(E5+H5+K5)) | O5: =SUMIFS('Daily Model'!$N$4:$N$508,'Daily Model'!$A$4:$A$508,">="&B5,'Daily Model'!$A$4:$A$508,"<="&C5)/1000000 | P5: =SUMIFS('Daily Data'!$G$4:$G$508,'Daily Data'!$A$4:$A$508,">="&B5,'Daily Data'!$A$4:$A$508,"<="&C5)/1000000 | Q5: =SUMIFS('Daily Model'!$O$4:$O$508,'Daily Model'!$A$4:$A$508,">="&B5,'Daily Model'!$A$4:$A$508,"<="&C5)/1000000 | R5: =E5+H5+K5 | S5: =SUMIFS('Daily Data'!$E$4:$E$508,'Daily Data'!$A$4:$A$508,">="&B5,'Daily Data'!$A$4:$A$508,"<="&C5)/1000000 | T5: =IF(R5=0,0,S5/R5) | U5: =R5-M5-O5-P5-S5 | V5: =SUMIFS('Daily Data'!$J$4:$J$508,'Daily Data'!$A$4:$A$508,">="&B5,'Daily Data'!$A$4:$A$508,"<="&C5)/1000000 | W5: =SUMIFS('Daily Data'!$K$4:$K$508,'Daily Data'!$A$4:$A$508,">="&B5,'Daily Data'!$A$4:$A$508,"<="&C5)/1000000 | X5: =S5 | Y5: =SUMIFS('Daily Data'!$L$4:$L$508,'Daily Data'!$A$4:$A$508,">="&B5,'Daily Data'!$A$4:$A$508,"<="&C5)/1000000 | Z5: =IF(Y5=0,"",SUMIFS('Daily Data'!$M$4:$M$508,'Daily Data'!$A$4:$A$508,">="&B5,'Daily Data'!$A$4:$A$508,"<="&C5)/1000000/Y5) | AA5: =SUMIFS('Daily Data'!$O$4:$O$508,'Daily Data'!$A$4:$A$508,">="&B5,'Daily Data'!$A$4:$A$508,"<="&C5)/1000000 | AB5: =SUMIFS('OTS Breakdown'!$G$4:$G$508,'OTS Breakdown'!$A$4:$A$508,">="&B5,'OTS Breakdown'!$A$4:$A$508,"<="&C5)/1000000 | AC5: =SUMIFS('Daily Data'!$P$4:$P$508,'Daily Data'!$A$4:$A$508,">="&B5,'Daily Data'!$A$4:$A$508,"<="&C5)/1000000 | AD5: =LOOKUP(2,1/(('OTS Breakdown'!$A$4:$A$508<=C5)*('OTS Breakdown'!$O$4:$O$508<>"")),'OTS Breakdown'!$O$4:$O$508)/1000000 | AE5: =LOOKUP(2,1/(('OTS Breakdown'!$A$4:$A$508<=C5)*('OTS Breakdown'!$AE$4:$AE$508<>"")),'OTS Breakdown'!$AE$4:$AE$508) | AF5: =LOOKUP(2,1/(('OTS Breakdown'!$A$4:$A$508<=C5)*('OTS Breakdown'!$AF$4:$AF$508<>"")),'OTS Breakdown'!$AF$4:$AF$508) | AG5: =AD5-AE5-AF5
A6: Q3 2025 | B6: 45839 | C6: 45930 | D6: =SUMIFS('Daily Data'!$B$4:$B$508,'Daily Data'!$A$4:$A$508,">="&B6,'Daily Data'!$A$4:$A$508,"<="&C6)/1000000000 | E6: =SUMIFS('Daily Model'!$L$4:$L$508,'Daily Model'!$A$4:$A$508,">="&B6,'Daily Model'!$A$4:$A$508,"<="&C6)/1000000 | F6: =IF(D6=0,0,E6/(D6*1000)*10000) | G6: =SUMIFS('Daily Data'!$D$4:$D$508,'Daily Data'!$A$4:$A$508,">="&B6,'Daily Data'!$A$4:$A$508,"<="&C6)/1000000000 | H6: =SUMIFS('Daily Data'!$F$4:$F$508,'Daily Data'!$A$4:$A$508,">="&B6,'Daily Data'!$A$4:$A$508,"<="&C6)/1000000 | I6: =IF(G6=0,0,H6/(G6*1000)*10000) | J6: =SUMIFS('Daily Data'!$C$4:$C$508,'Daily Data'!$A$4:$A$508,">="&B6,'Daily Data'!$A$4:$A$508,"<="&C6)/1000000000 | K6: =SUMIFS('Daily Data'!$I$4:$I$508,'Daily Data'!$A$4:$A$508,">="&B6,'Daily Data'!$A$4:$A$508,"<="&C6)/1000000 | L6: =IF(J6=0,0,K6/(J6*1000)*10000) | M6: =SUMIFS('Daily Model'!$P$4:$P$508,'Daily Model'!$A$4:$A$508,">="&B6,'Daily Model'!$A$4:$A$508,"<="&C6)/1000000 | N6: =IF((E6+H6+K6)=0,0,M6/(E6+H6+K6)) | O6: =SUMIFS('Daily Model'!$N$4:$N$508,'Daily Model'!$A$4:$A$508,">="&B6,'Daily Model'!$A$4:$A$508,"<="&C6)/1000000 | P6: =SUMIFS('Daily Data'!$G$4:$G$508,'Daily Data'!$A$4:$A$508,">="&B6,'Daily Data'!$A$4:$A$508,"<="&C6)/1000000 | Q6: =SUMIFS('Daily Model'!$O$4:$O$508,'Daily Model'!$A$4:$A$508,">="&B6,'Daily Model'!$A$4:$A$508,"<="&C6)/1000000 | R6: =E6+H6+K6 | S6: =SUMIFS('Daily Data'!$E$4:$E$508,'Daily Data'!$A$4:$A$508,">="&B6,'Daily Data'!$A$4:$A$508,"<="&C6)/1000000 | T6: =IF(R6=0,0,S6/R6) | U6: =R6-M6-O6-P6-S6 | V6: =SUMIFS('Daily Data'!$J$4:$J$508,'Daily Data'!$A$4:$A$508,">="&B6,'Daily Data'!$A$4:$A$508,"<="&C6)/1000000 | W6: =SUMIFS('Daily Data'!$K$4:$K$508,'Daily Data'!$A$4:$A$508,">="&B6,'Daily Data'!$A$4:$A$508,"<="&C6)/1000000 | X6: =S6 | Y6: =SUMIFS('Daily Data'!$L$4:$L$508,'Daily Data'!$A$4:$A$508,">="&B6,'Daily Data'!$A$4:$A$508,"<="&C6)/1000000 | Z6: =IF(Y6=0,"",SUMIFS('Daily Data'!$M$4:$M$508,'Daily Data'!$A$4:$A$508,">="&B6,'Daily Data'!$A$4:$A$508,"<="&C6)/1000000/Y6) | AA6: =SUMIFS('Daily Data'!$O$4:$O$508,'Daily Data'!$A$4:$A$508,">="&B6,'Daily Data'!$A$4:$A$508,"<="&C6)/1000000 | AB6: =SUMIFS('OTS Breakdown'!$G$4:$G$508,'OTS Breakdown'!$A$4:$A$508,">="&B6,'OTS Breakdown'!$A$4:$A$508,"<="&C6)/1000000 | AC6: =SUMIFS('Daily Data'!$P$4:$P$508,'Daily Data'!$A$4:$A$508,">="&B6,'Daily Data'!$A$4:$A$508,"<="&C6)/1000000 | AD6: =LOOKUP(2,1/(('OTS Breakdown'!$A$4:$A$508<=C6)*('OTS Breakdown'!$O$4:$O$508<>"")),'OTS Breakdown'!$O$4:$O$508)/1000000 | AE6: =LOOKUP(2,1/(('OTS Breakdown'!$A$4:$A$508<=C6)*('OTS Breakdown'!$AE$4:$AE$508<>"")),'OTS Breakdown'!$AE$4:$AE$508) | AF6: =LOOKUP(2,1/(('OTS Breakdown'!$A$4:$A$508<=C6)*('OTS Breakdown'!$AF$4:$AF$508<>"")),'OTS Breakdown'!$AF$4:$AF$508) | AG6: =AD6-AE6-AF6
A7: Q4 2025 | B7: 45931 | C7: 46022 | D7: =SUMIFS('Daily Data'!$B$4:$B$508,'Daily Data'!$A$4:$A$508,">="&B7,'Daily Data'!$A$4:$A$508,"<="&C7)/1000000000 | E7: =SUMIFS('Daily Model'!$L$4:$L$508,'Daily Model'!$A$4:$A$508,">="&B7,'Daily Model'!$A$4:$A$508,"<="&C7)/1000000 | F7: =IF(D7=0,0,E7/(D7*1000)*10000) | G7: =SUMIFS('Daily Data'!$D$4:$D$508,'Daily Data'!$A$4:$A$508,">="&B7,'Daily Data'!$A$4:$A$508,"<="&C7)/1000000000 | H7: =SUMIFS('Daily Data'!$F$4:$F$508,'Daily Data'!$A$4:$A$508,">="&B7,'Daily Data'!$A$4:$A$508,"<="&C7)/1000000 | I7: =IF(G7=0,0,H7/(G7*1000)*10000) | J7: =SUMIFS('Daily Data'!$C$4:$C$508,'Daily Data'!$A$4:$A$508,">="&B7,'Daily Data'!$A$4:$A$508,"<="&C7)/1000000000 | K7: =SUMIFS('Daily Data'!$I$4:$I$508,'Daily Data'!$A$4:$A$508,">="&B7,'Daily Data'!$A$4:$A$508,"<="&C7)/1000000 | L7: =IF(J7=0,0,K7/(J7*1000)*10000) | M7: =SUMIFS('Daily Model'!$P$4:$P$508,'Daily Model'!$A$4:$A$508,">="&B7,'Daily Model'!$A$4:$A$508,"<="&C7)/1000000 | N7: =IF((E7+H7+K7)=0,0,M7/(E7+H7+K7)) | O7: =SUMIFS('Daily Model'!$N$4:$N$508,'Daily Model'!$A$4:$A$508,">="&B7,'Daily Model'!$A$4:$A$508,"<="&C7)/1000000 | P7: =SUMIFS('Daily Data'!$G$4:$G$508,'Daily Data'!$A$4:$A$508,">="&B7,'Daily Data'!$A$4:$A$508,"<="&C7)/1000000 | Q7: =SUMIFS('Daily Model'!$O$4:$O$508,'Daily Model'!$A$4:$A$508,">="&B7,'Daily Model'!$A$4:$A$508,"<="&C7)/1000000 | R7: =E7+H7+K7 | S7: =SUMIFS('Daily Data'!$E$4:$E$508,'Daily Data'!$A$4:$A$508,">="&B7,'Daily Data'!$A$4:$A$508,"<="&C7)/1000000 | T7: =IF(R7=0,0,S7/R7) | U7: =R7-M7-O7-P7-S7 | V7: =SUMIFS('Daily Data'!$J$4:$J$508,'Daily Data'!$A$4:$A$508,">="&B7,'Daily Data'!$A$4:$A$508,"<="&C7)/1000000 | W7: =SUMIFS('Daily Data'!$K$4:$K$508,'Daily Data'!$A$4:$A$508,">="&B7,'Daily Data'!$A$4:$A$508,"<="&C7)/1000000 | X7: =S7 | Y7: =SUMIFS('Daily Data'!$L$4:$L$508,'Daily Data'!$A$4:$A$508,">="&B7,'Daily Data'!$A$4:$A$508,"<="&C7)/1000000 | Z7: =IF(Y7=0,"",SUMIFS('Daily Data'!$M$4:$M$508,'Daily Data'!$A$4:$A$508,">="&B7,'Daily Data'!$A$4:$A$508,"<="&C7)/1000000/Y7) | AA7: =SUMIFS('Daily Data'!$O$4:$O$508,'Daily Data'!$A$4:$A$508,">="&B7,'Daily Data'!$A$4:$A$508,"<="&C7)/1000000 | AB7: =SUMIFS('OTS Breakdown'!$G$4:$G$508,'OTS Breakdown'!$A$4:$A$508,">="&B7,'OTS Breakdown'!$A$4:$A$508,"<="&C7)/1000000 | AC7: =SUMIFS('Daily Data'!$P$4:$P$508,'Daily Data'!$A$4:$A$508,">="&B7,'Daily Data'!$A$4:$A$508,"<="&C7)/1000000 | AD7: =LOOKUP(2,1/(('OTS Breakdown'!$A$4:$A$508<=C7)*('OTS Breakdown'!$O$4:$O$508<>"")),'OTS Breakdown'!$O$4:$O$508)/1000000 | AE7: =LOOKUP(2,1/(('OTS Breakdown'!$A$4:$A$508<=C7)*('OTS Breakdown'!$AE$4:$AE$508<>"")),'OTS Breakdown'!$AE$4:$AE$508) | AF7: =LOOKUP(2,1/(('OTS Breakdown'!$A$4:$A$508<=C7)*('OTS Breakdown'!$AF$4:$AF$508<>"")),'OTS Breakdown'!$AF$4:$AF$508) | AG7: =AD7-AE7-AF7
A8: Q1 2026 | B8: 46023 | C8: 46112 | D8: =SUMIFS('Daily Data'!$B$4:$B$508,'Daily Data'!$A$4:$A$508,">="&B8,'Daily Data'!$A$4:$A$508,"<="&C8)/1000000000 | E8: =SUMIFS('Daily Model'!$L$4:$L$508,'Daily Model'!$A$4:$A$508,">="&B8,'Daily Model'!$A$4:$A$508,"<="&C8)/1000000 | F8: =IF(D8=0,0,E8/(D8*1000)*10000) | G8: =SUMIFS('Daily Data'!$D$4:$D$508,'Daily Data'!$A$4:$A$508,">="&B8,'Daily Data'!$A$4:$A$508,"<="&C8)/1000000000 | H8: =SUMIFS('Daily Data'!$F$4:$F$508,'Daily Data'!$A$4:$A$508,">="&B8,'Daily Data'!$A$4:$A$508,"<="&C8)/1000000 | I8: =IF(G8=0,0,H8/(G8*1000)*10000) | J8: =SUMIFS('Daily Data'!$C$4:$C$508,'Daily Data'!$A$4:$A$508,">="&B8,'Daily Data'!$A$4:$A$508,"<="&C8)/1000000000 | K8: =SUMIFS('Daily Data'!$I$4:$I$508,'Daily Data'!$A$4:$A$508,">="&B8,'Daily Data'!$A$4:$A$508,"<="&C8)/1000000 | L8: =IF(J8=0,0,K8/(J8*1000)*10000) | M8: =SUMIFS('Daily Model'!$P$4:$P$508,'Daily Model'!$A$4:$A$508,">="&B8,'Daily Model'!$A$4:$A$508,"<="&C8)/1000000 | N8: =IF((E8+H8+K8)=0,0,M8/(E8+H8+K8)) | O8: =SUMIFS('Daily Model'!$N$4:$N$508,'Daily Model'!$A$4:$A$508,">="&B8,'Daily Model'!$A$4:$A$508,"<="&C8)/1000000 | P8: =SUMIFS('Daily Data'!$G$4:$G$508,'Daily Data'!$A$4:$A$508,">="&B8,'Daily Data'!$A$4:$A$508,"<="&C8)/1000000 | Q8: =SUMIFS('Daily Model'!$O$4:$O$508,'Daily Model'!$A$4:$A$508,">="&B8,'Daily Model'!$A$4:$A$508,"<="&C8)/1000000 | R8: =E8+H8+K8 | S8: =SUMIFS('Daily Data'!$E$4:$E$508,'Daily Data'!$A$4:$A$508,">="&B8,'Daily Data'!$A$4:$A$508,"<="&C8)/1000000 | T8: =IF(R8=0,0,S8/R8) | U8: =R8-M8-O8-P8-S8 | V8: =SUMIFS('Daily Data'!$J$4:$J$508,'Daily Data'!$A$4:$A$508,">="&B8,'Daily Data'!$A$4:$A$508,"<="&C8)/1000000 | W8: =SUMIFS('Daily Data'!$K$4:$K$508,'Daily Data'!$A$4:$A$508,">="&B8,'Daily Data'!$A$4:$A$508,"<="&C8)/1000000 | X8: =S8 | Y8: =SUMIFS('Daily Data'!$L$4:$L$508,'Daily Data'!$A$4:$A$508,">="&B8,'Daily Data'!$A$4:$A$508,"<="&C8)/1000000 | Z8: =IF(Y8=0,"",SUMIFS('Daily Data'!$M$4:$M$508,'Daily Data'!$A$4:$A$508,">="&B8,'Daily Data'!$A$4:$A$508,"<="&C8)/1000000/Y8) | AA8: =SUMIFS('Daily Data'!$O$4:$O$508,'Daily Data'!$A$4:$A$508,">="&B8,'Daily Data'!$A$4:$A$508,"<="&C8)/1000000 | AB8: =SUMIFS('OTS Breakdown'!$G$4:$G$508,'OTS Breakdown'!$A$4:$A$508,">="&B8,'OTS Breakdown'!$A$4:$A$508,"<="&C8)/1000000 | AC8: =SUMIFS('Daily Data'!$P$4:$P$508,'Daily Data'!$A$4:$A$508,">="&B8,'Daily Data'!$A$4:$A$508,"<="&C8)/1000000 | AD8: =LOOKUP(2,1/(('OTS Breakdown'!$A$4:$A$508<=C8)*('OTS Breakdown'!$O$4:$O$508<>"")),'OTS Breakdown'!$O$4:$O$508)/1000000 | AE8: =LOOKUP(2,1/(('OTS Breakdown'!$A$4:$A$508<=C8)*('OTS Breakdown'!$AE$4:$AE$508<>"")),'OTS Breakdown'!$AE$4:$AE$508) | AF8: =LOOKUP(2,1/(('OTS Breakdown'!$A$4:$A$508<=C8)*('OTS Breakdown'!$AF$4:$AF$508<>"")),'OTS Breakdown'!$AF$4:$AF$508) | AG8: =AD8-AE8-AF8
A9: Q2 2026 (partial) | B9: 46113 | C9: 46162 | D9: =SUMIFS('Daily Data'!$B$4:$B$508,'Daily Data'!$A$4:$A$508,">="&B9,'Daily Data'!$A$4:$A$508,"<="&C9)/1000000000 | E9: =SUMIFS('Daily Model'!$L$4:$L$508,'Daily Model'!$A$4:$A$508,">="&B9,'Daily Model'!$A$4:$A$508,"<="&C9)/1000000 | F9: =IF(D9=0,0,E9/(D9*1000)*10000) | G9: =SUMIFS('Daily Data'!$D$4:$D$508,'Daily Data'!$A$4:$A$508,">="&B9,'Daily Data'!$A$4:$A$508,"<="&C9)/1000000000 | H9: =SUMIFS('Daily Data'!$F$4:$F$508,'Daily Data'!$A$4:$A$508,">="&B9,'Daily Data'!$A$4:$A$508,"<="&C9)/1000000 | I9: =IF(G9=0,0,H9/(G9*1000)*10000) | J9: =SUMIFS('Daily Data'!$C$4:$C$508,'Daily Data'!$A$4:$A$508,">="&B9,'Daily Data'!$A$4:$A$508,"<="&C9)/1000000000 | K9: =SUMIFS('Daily Data'!$I$4:$I$508,'Daily Data'!$A$4:$A$508,">="&B9,'Daily Data'!$A$4:$A$508,"<="&C9)/1000000 | L9: =IF(J9=0,0,K9/(J9*1000)*10000) | M9: =SUMIFS('Daily Model'!$P$4:$P$508,'Daily Model'!$A$4:$A$508,">="&B9,'Daily Model'!$A$4:$A$508,"<="&C9)/1000000 | N9: =IF((E9+H9+K9)=0,0,M9/(E9+H9+K9)) | O9: =SUMIFS('Daily Model'!$N$4:$N$508,'Daily Model'!$A$4:$A$508,">="&B9,'Daily Model'!$A$4:$A$508,"<="&C9)/1000000 | P9: =SUMIFS('Daily Data'!$G$4:$G$508,'Daily Data'!$A$4:$A$508,">="&B9,'Daily Data'!$A$4:$A$508,"<="&C9)/1000000 | Q9: =SUMIFS('Daily Model'!$O$4:$O$508,'Daily Model'!$A$4:$A$508,">="&B9,'Daily Model'!$A$4:$A$508,"<="&C9)/1000000 | R9: =E9+H9+K9 | S9: =SUMIFS('Daily Data'!$E$4:$E$508,'Daily Data'!$A$4:$A$508,">="&B9,'Daily Data'!$A$4:$A$508,"<="&C9)/1000000 | T9: =IF(R9=0,0,S9/R9) | U9: =R9-M9-O9-P9-S9 | V9: =SUMIFS('Daily Data'!$J$4:$J$508,'Daily Data'!$A$4:$A$508,">="&B9,'Daily Data'!$A$4:$A$508,"<="&C9)/1000000 | W9: =SUMIFS('Daily Data'!$K$4:$K$508,'Daily Data'!$A$4:$A$508,">="&B9,'Daily Data'!$A$4:$A$508,"<="&C9)/1000000 | X9: =S9 | Y9: =SUMIFS('Daily Data'!$L$4:$L$508,'Daily Data'!$A$4:$A$508,">="&B9,'Daily Data'!$A$4:$A$508,"<="&C9)/1000000 | Z9: =IF(Y9=0,"",SUMIFS('Daily Data'!$M$4:$M$508,'Daily Data'!$A$4:$A$508,">="&B9,'Daily Data'!$A$4:$A$508,"<="&C9)/1000000/Y9) | AA9: =SUMIFS('Daily Data'!$O$4:$O$508,'Daily Data'!$A$4:$A$508,">="&B9,'Daily Data'!$A$4:$A$508,"<="&C9)/1000000 | AB9: =SUMIFS('OTS Breakdown'!$G$4:$G$508,'OTS Breakdown'!$A$4:$A$508,">="&B9,'OTS Breakdown'!$A$4:$A$508,"<="&C9)/1000000 | AC9: =SUMIFS('Daily Data'!$P$4:$P$508,'Daily Data'!$A$4:$A$508,">="&B9,'Daily Data'!$A$4:$A$508,"<="&C9)/1000000 | AD9: =LOOKUP(2,1/(('OTS Breakdown'!$A$4:$A$508<=C9)*('OTS Breakdown'!$O$4:$O$508<>"")),'OTS Breakdown'!$O$4:$O$508)/1000000 | AE9: =LOOKUP(2,1/(('OTS Breakdown'!$A$4:$A$508<=C9)*('OTS Breakdown'!$AE$4:$AE$508<>"")),'OTS Breakdown'!$AE$4:$AE$508) | AF9: =LOOKUP(2,1/(('OTS Breakdown'!$A$4:$A$508<=C9)*('OTS Breakdown'!$AF$4:$AF$508<>"")),'OTS Breakdown'!$AF$4:$AF$508) | AG9: =AD9-AE9-AF9
A12: OTS CROSS-CHECK — reconciles our OTS definition to the public sources (PURR US Equity NAV per HYPE; CoinGecko circulating supply)
A13: Snapshot date | D13: 46141 | G13: Cross-check anchor (matches PURR US Equity public NAV statement of 29-Apr-2026 referenced by the user).
A14: ASXN-style OTS (Initial 1B − Future Emission Reserve − Hyper Foundation − AF − Community Grants − Cumulative Burns) | D14: =LOOKUP(2,1/(('OTS Breakdown'!$A$4:$A$508=DATE(2026,4,29))*('OTS Breakdown'!$O$4:$O$508<>"")),'OTS Breakdown'!$O$4:$O$508)/1000000 | G14: This model's OTS. The HYPE valuation base. ≈ 477.2M.
A15: Hyperscreener circulating supply (HYPE) | D15: =LOOKUP(2,1/(('Daily Data'!$A$4:$A$508=DATE(2026,4,29))*('Daily Data'!$R$4:$R$508<>"")),'Daily Data'!$R$4:$R$508)/1000000 | G15: Hyperscreener /buyback/daily-burn currentDaySupply minus reserves. ≈ 298.7M.
A16: CoinGecko-style circulating = Total Supply − Future Emission Reserve | D16: =(LOOKUP(2,1/(('Daily Data'!$A$4:$A$508=DATE(2026,4,29))*('Daily Data'!$S$4:$S$508<>"")),'Daily Data'!$S$4:$S$508)-(LOOKUP(2,1/(('OTS Breakdown'!$A$4:$A$508=DATE(2026,4,29))*('OTS Breakdown'!$J$4:$J$508<>"")),'OTS Breakdown'!$J$4:$J$508)))/1000000 | G16: CoinGecko methodology subtracts only the staking emission reserve from total supply (does not exclude HF / AF / Community Grants). ≈ 584.0M.
A17: PURR US Equity — implied HYPE outstanding (per public NAV statement, 29-Apr-2026) | G17: Enter the disclosed figure here (NOT auto-pulled — PURR is the OTC HYPE wrapper). Then compare to our ASXN-style OTS above. Difference is the methodology gap (PURR typically uses a fully-diluted-ex-future-emissions basis closer to ASXN).
A18: Reconciliation: ASXN OTS − Circulating (hyperscreener) | D18: =LOOKUP(2,1/(('OTS Breakdown'!$A$4:$A$508=DATE(2026,4,29))*('OTS Breakdown'!$O$4:$O$508<>"")),'OTS Breakdown'!$O$4:$O$508)/1000000-(LOOKUP(2,1/(('Daily Data'!$A$4:$A$508=DATE(2026,4,29))*('Daily Data'!$R$4:$R$508<>"")),'Daily Data'!$R$4:$R$508))/1000000 | G18: ≈178M HYPE gap = team / core-contributor locked allocation (~238M genesis less ~3.5M discretionary unlocks so far) + small Foundation budget movements. The three reserves explicitly carved out of OTS (HF 60 + AF 44 + CG 3 = 107M) are already subtracted from OTS, so the gap to hyperscreener circulating is the still-locked team bucket. CoinGecko's 584M sits above ASXN because CoinGecko subtracts only the staking emission reserve from total supply.
A20: Notes: (i) Core Perp Fees = HC core perp revenue grossed up by HLP (Daily Model col L). (ii) HIP-3 Fees = Loris gross fees; HIP-3 Deployer = Loris (zero before 2026-03-21). (iii) Spot Fees = DefiLlama dailyFees (TOTAL spot fees); the prior mismatch between Daily Model spot fees and Daily Data spot fees is now resolved — both equal DefiLlama actual. Unit/Spot deduction = DefiLlama dailyFees − dailyHoldersRevenue (the Unit/Hyperunit on-top fee, the balancing item). (iv) HLP cut is CALCULATED, not extracted — no public daily HLP-revenue feed exists. Formula: HLP cut = (Core Perp Fees + HIP-3 Gross + Spot Fees) × HLP rate; rate = 3% before 2025-08-30, 1% after (per DefiLlama hyperliquid-spot-orderbook methodology — "1% of the spot fees go to HLP vault" — and the same 1%/3% applies to perps and HIP-3 gross). Daily Model cols Q/R/S show the HLP split across the three segments; col P is their sum. Col N "HLP Eff. Rate" = HLP $ ÷ (Core + HIP-3 + Spot) — should print 1% post-2025-08-30, 3% before, or a blend mid-Aug-25 (Q3 ≈ 2.4%). Spot bridge: Spot Fees (DefiLlama) = Spot Rev (post-HLP, post-Unit) + Unit + HLP_spot → Unit = Spot Fees × (1 − HLP rate) − Spot Rev. (v) Builder/Core = hyperscreener actual builder code fees, top-20 builders (daily from 2025-09-13; blank-treated-as-0 before). These are EXTRA fees front-ends charge on top of protocol fees and pass 100% to themselves — they do NOT reduce HL's revenue, so they are excluded from the Total Fees → Revenue bridge. (vi) Revenue (R) ties exactly to hyperscreener daily HC Rev sum (the daily-totals match the user asked about); Recon Δ (T) ≈ 0 confirms the segment fees + deductions reconcile. (vii) Avg HYPE Price = USD buyback ÷ HYPE bought (volume-weighted realised price, not period-average mark). (viii) Team / Vesting = ACTUAL discretionary unlock claims (insights.unlocks.app / tokenomist) — not the theoretical ~9.92M/month schedule. (ix) Ending OTS uses LOOKUP into OTS Breakdown col O at quarter-end. (x) Q2 2026 is partial (through 2026-05-20 — the last day with full Loris/hyperscreener data).

Sheet Daily Model
A1: HYPERLIQUID — DAILY FEE → REVENUE DECOMPOSITION (HyperCore revenue split into core perp / HIP-3 / spot)
B2: VOLUME | E2: REVENUE DECOMPOSITION | K2: IMPLIED FEES | T2: TAKE-RATE CROSS-CHECK
A3: Date | B3: Core Perp Volume ($) | C3: HIP-3 Volume ($) | D3: Spot Volume ($) | E3: HyperCore Revenue — north star ($) | F3: HIP-3 Gross Fees ($) | G3: HIP-3 Deployer Fees ($) | H3: HIP-3 Protocol Revenue in HC (post-HLP, post-Dep) ($) | I3: Spot Revenue ($) — post-HLP, post-Unit | J3: Core Perp Revenue — plug, post-HLP ($) | K3: HLP Rate Applied | L3: Core Perp Protocol Fees ($) | M3: Spot Gross Fees ($) — DefiLlama | N3: Unit Protocol Fees ($) — Spot × (1−HLP) − Spot Rev | O3: Builder Code Fees ($) | P3: HLP Cut — TOTAL ($) | Q3: HLP — Core ($) | R3: HLP — HIP-3 ($) | S3: HLP — Spot ($) | T3: Core Perp Take Rate (bps) | U3: HIP-3 Take Rate (bps) | V3: Spot Take Rate (bps)
A4: 45658 | B4: ='Daily Data'!B4 | C4: ='Daily Data'!D4 | D4: ='Daily Data'!C4 | E4: =IF('Daily Data'!E4="","",'Daily Data'!E4) | F4: =IF($E4="","",'Daily Data'!F4) | G4: =IF($E4="","",'Daily Data'!G4) | H4: =IF($E4="","",(1-K4)*F4-G4) | I4: =IF($E4="","",'Daily Data'!H4) | J4: =IF($E4="","",E4-H4-I4) | K4: =IF($E4="","",IF(A4<HLP_ChangeDate,HLP_Legacy,HLP_Current)) | L4: =IF($E4="","",J4/(1-K4)) | M4: =IF($E4="","",'Daily Data'!I4) | N4: =IF($E4="","",M4*(1-K4)-I4) | P4: =IF($E4="","",(L4+F4+M4)*K4) | Q4: =IF($E4="","",L4*K4) | R4: =IF($E4="","",F4*K4) | S4: =IF($E4="","",M4*K4) | T4: =IF(OR($E4="",B4=0),"",L4/B4*10000) | U4: =IF(OR($E4="",C4=0),"",F4/C4*10000) | V4: =IF(OR($E4="",D4=0),"",M4/D4*10000)
A5: 45659 | B5: ='Daily Data'!B5 | C5: ='Daily Data'!D5 | D5: ='Daily Data'!C5 | E5: =IF('Daily Data'!E5="","",'Daily Data'!E5) | F5: =IF($E5="","",'Daily Data'!F5) | G5: =IF($E5="","",'Daily Data'!G5) | H5: =IF($E5="","",(1-K5)*F5-G5) | I5: =IF($E5="","",'Daily Data'!H5) | J5: =IF($E5="","",E5-H5-I5) | K5: =IF($E5="","",IF(A5<HLP_ChangeDate,HLP_Legacy,HLP_Current)) | L5: =IF($E5="","",J5/(1-K5)) | M5: =IF($E5="","",'Daily Data'!I5) | N5: =IF($E5="","",M5*(1-K5)-I5) | P5: =IF($E5="","",(L5+F5+M5)*K5) | Q5: =IF($E5="","",L5*K5) | R5: =IF($E5="","",F5*K5) | S5: =IF($E5="","",M5*K5) | T5: =IF(OR($E5="",B5=0),"",L5/B5*10000) | U5: =IF(OR($E5="",C5=0),"",F5/C5*10000) | V5: =IF(OR($E5="",D5=0),"",M5/D5*10000)
A6: 45660 | B6: ='Daily Data'!B6 | C6: ='Daily Data'!D6 | D6: ='Daily Data'!C6 | E6: =IF('Daily Data'!E6="","",'Daily Data'!E6) | F6: =IF($E6="","",'Daily Data'!F6) | G6: =IF($E6="","",'Daily Data'!G6) | H6: =IF($E6="","",(1-K6)*F6-G6) | I6: =IF($E6="","",'Daily Data'!H6) | J6: =IF($E6="","",E6-H6-I6) | K6: =IF($E6="","",IF(A6<HLP_ChangeDate,HLP_Legacy,HLP_Current)) | L6: =IF($E6="","",J6/(1-K6)) | M6: =IF($E6="","",'Daily Data'!I6) | N6: =IF($E6="","",M6*(1-K6)-I6) | P6: =IF($E6="","",(L6+F6+M6)*K6) | Q6: =IF($E6="","",L6*K6) | R6: =IF($E6="","",F6*K6) | S6: =IF($E6="","",M6*K6) | T6: =IF(OR($E6="",B6=0),"",L6/B6*10000) | U6: =IF(OR($E6="",C6=0),"",F6/C6*10000) | V6: =IF(OR($E6="",D6=0),"",M6/D6*10000)
A7: 45661 | B7: ='Daily Data'!B7 | C7: ='Daily Data'!D7 | D7: ='Daily Data'!C7 | E7: =IF('Daily Data'!E7="","",'Daily Data'!E7) | F7: =IF($E7="","",'Daily Data'!F7) | G7: =IF($E7="","",'Daily Data'!G7) | H7: =IF($E7="","",(1-K7)*F7-G7) | I7: =IF($E7="","",'Daily Data'!H7) | J7: =IF($E7="","",E7-H7-I7) | K7: =IF($E7="","",IF(A7<HLP_ChangeDate,HLP_Legacy,HLP_Current)) | L7: =IF($E7="","",J7/(1-K7)) | M7: =IF($E7="","",'Daily Data'!I7) | N7: =IF($E7="","",M7*(1-K7)-I7) | P7: =IF($E7="","",(L7+F7+M7)*K7) | Q7: =IF($E7="","",L7*K7) | R7: =IF($E7="","",F7*K7) | S7: =IF($E7="","",M7*K7) | T7: =IF(OR($E7="",B7=0),"",L7/B7*10000) | U7: =IF(OR($E7="",C7=0),"",F7/C7*10000) | V7: =IF(OR($E7="",D7=0),"",M7/D7*10000)
A8: 45662 | B8: ='Daily Data'!B8 | C8: ='Daily Data'!D8 | D8: ='Daily Data'!C8 | E8: =IF('Daily Data'!E8="","",'Daily Data'!E8) | F8: =IF($E8="","",'Daily Data'!F8) | G8: =IF($E8="","",'Daily Data'!G8) | H8: =IF($E8="","",(1-K8)*F8-G8) | I8: =IF($E8="","",'Daily Data'!H8) | J8: =IF($E8="","",E8-H8-I8) | K8: =IF($E8="","",IF(A8<HLP_ChangeDate,HLP_Legacy,HLP_Current)) | L8: =IF($E8="","",J8/(1-K8)) | M8: =IF($E8="","",'Daily Data'!I8) | N8: =IF($E8="","",M8*(1-K8)-I8) | P8: =IF($E8="","",(L8+F8+M8)*K8) | Q8: =IF($E8="","",L8*K8) | R8: =IF($E8="","",F8*K8) | S8: =IF($E8="","",M8*K8) | T8: =IF(OR($E8="",B8=0),"",L8/B8*10000) | U8: =IF(OR($E8="",C8=0),"",F8/C8*10000) | V8: =IF(OR($E8="",D8=0),"",M8/D8*10000)
A9: 45663 | B9: ='Daily Data'!B9 | C9: ='Daily Data'!D9 | D9: ='Daily Data'!C9 | E9: =IF('Daily Data'!E9="","",'Daily Data'!E9) | F9: =IF($E9="","",'Daily Data'!F9) | G9: =IF($E9="","",'Daily Data'!G9) | H9: =IF($E9="","",(1-K9)*F9-G9) | I9: =IF($E9="","",'Daily Data'!H9) | J9: =IF($E9="","",E9-H9-I9) | K9: =IF($E9="","",IF(A9<HLP_ChangeDate,HLP_Legacy,HLP_Current)) | L9: =IF($E9="","",J9/(1-K9)) | M9: =IF($E9="","",'Daily Data'!I9) | N9: =IF($E9="","",M9*(1-K9)-I9) | P9: =IF($E9="","",(L9+F9+M9)*K9) | Q9: =IF($E9="","",L9*K9) | R9: =IF($E9="","",F9*K9) | S9: =IF($E9="","",M9*K9) | T9: =IF(OR($E9="",B9=0),"",L9/B9*10000) | U9: =IF(OR($E9="",C9=0),"",F9/C9*10000) | V9: =IF(OR($E9="",D9=0),"",M9/D9*10000)
A10: 45664 | B10: ='Daily Data'!B10 | C10: ='Daily Data'!D10 | D10: ='Daily Data'!C10 | E10: =IF('Daily Data'!E10="","",'Daily Data'!E10) | F10: =IF($E10="","",'Daily Data'!F10) | G10: =IF($E10="","",'Daily Data'!G10) | H10: =IF($E10="","",(1-K10)*F10-G10) | I10: =IF($E10="","",'Daily Data'!H10) | J10: =IF($E10="","",E10-H10-I10) | K10: =IF($E10="","",IF(A10<HLP_ChangeDate,HLP_Legacy,HLP_Current)) | L10: =IF($E10="","",J10/(1-K10)) | M10: =IF($E10="","",'Daily Data'!I10) | N10: =IF($E10="","",M10*(1-K10)-I10) | P10: =IF($E10="","",(L10+F10+M10)*K10) | Q10: =IF($E10="","",L10*K10) | R10: =IF($E10="","",F10*K10) | S10: =IF($E10="","",M10*K10) | T10: =IF(OR($E10="",B10=0),"",L10/B10*10000) | U10: =IF(OR($E10="",C10=0),"",F10/C10*10000) | V10: =IF(OR($E10="",D10=0),"",M10/D10*10000)
A11: 45665 | B11: ='Daily Data'!B11 | C11: ='Daily Data'!D11 | D11: ='Daily Data'!C11 | E11: =IF('Daily Data'!E11="","",'Daily Data'!E11) | F11: =IF($E11="","",'Daily Data'!F11) | G11: =IF($E11="","",'Daily Data'!G11) | H11: =IF($E11="","",(1-K11)*F11-G11) | I11: =IF($E11="","",'Daily Data'!H11) | J11: =IF($E11="","",E11-H11-I11) | K11: =IF($E11="","",IF(A11<HLP_ChangeDate,HLP_Legacy,HLP_Current)) | L11: =IF($E11="","",J11/(1-K11)) | M11: =IF($E11="","",'Daily Data'!I11) | N11: =IF($E11="","",M11*(1-K11)-I11) | P11: =IF($E11="","",(L11+F11+M11)*K11) | Q11: =IF($E11="","",L11*K11) | R11: =IF($E11="","",F11*K11) | S11: =IF($E11="","",M11*K11) | T11: =IF(OR($E11="",B11=0),"",L11/B11*10000) | U11: =IF(OR($E11="",C11=0),"",F11/C11*10000) | V11: =IF(OR($E11="",D11=0),"",M11/D11*10000)
A12: 45666 | B12: ='Daily Data'!B12 | C12: ='Daily Data'!D12 | D12: ='Daily Data'!C12 | E12: =IF('Daily Data'!E12="","",'Daily Data'!E12) | F12: =IF($E12="","",'Daily Data'!F12) | G12: =IF($E12="","",'Daily Data'!G12) | H12: =IF($E12="","",(1-K12)*F12-G12) | I12: =IF($E12="","",'Daily Data'!H12) | J12: =IF($E12="","",E12-H12-I12) | K12: =IF($E12="","",IF(A12<HLP_ChangeDate,HLP_Legacy,HLP_Current)) | L12: =IF($E12="","",J12/(1-K12)) | M12: =IF($E12="","",'Daily Data'!I12) | N12: =IF($E12="","",M12*(1-K12)-I12) | P12: =IF($E12="","",(L12+F12+M12)*K12) | Q12: =IF($E12="","",L12*K12) | R12: =IF($E12="","",F12*K12) | S12: =IF($E12="","",M12*K12) | T12: =IF(OR($E12="",B12=0),"",L12/B12*10000) | U12: =IF(OR($E12="",C12=0),"",F12/C12*10000) | V12: =IF(OR($E12="",D12=0),"",M12/D12*10000)
A13: 45667 | B13: ='Daily Data'!B13 | C13: ='Daily Data'!D13 | D13: ='Daily Data'!C13 | E13: =IF('Daily Data'!E13="","",'Daily Data'!E13) | F13: =IF($E13="","",'Daily Data'!F13) | G13: =IF($E13="","",'Daily Data'!G13) | H13: =IF($E13="","",(1-K13)*F13-G13) | I13: =IF($E13="","",'Daily Data'!H13) | J13: =IF($E13="","",E13-H13-I13) | K13: =IF($E13="","",IF(A13<HLP_ChangeDate,HLP_Legacy,HLP_Current)) | L13: =IF($E13="","",J13/(1-K13)) | M13: =IF($E13="","",'Daily Data'!I13) | N13: =IF($E13="","",M13*(1-K13)-I13) | P13: =IF($E13="","",(L13+F13+M13)*K13) | Q13: =IF($E13="","",L13*K13) | R13: =IF($E13="","",F13*K13) | S13: =IF($E13="","",M13*K13) | T13: =IF(OR($E13="",B13=0),"",L13/B13*10000) | U13: =IF(OR($E13="",C13=0),"",F13/C13*10000) | V13: =IF(OR($E13="",D13=0),"",M13/D13*10000)
A14: 45668 | B14: ='Daily Data'!B14 | C14: ='Daily Data'!D14 | D14: ='Daily Data'!C14 | E14: =IF('Daily Data'!E14="","",'Daily Data'!E14) | F14: =IF($E14="","",'Daily Data'!F14) | G14: =IF($E14="","",'Daily Data'!G14) | H14: =IF($E14="","",(1-K14)*F14-G14) | I14: =IF($E14="","",'Daily Data'!H14) | J14: =IF($E14="","",E14-H14-I14) | K14: =IF($E14="","",IF(A14<HLP_ChangeDate,HLP_Legacy,HLP_Current)) | L14: =IF($E14="","",J14/(1-K14)) | M14: =IF($E14="","",'Daily Data'!I14) | N14: =IF($E14="","",M14*(1-K14)-I14) | P14: =IF($E14="","",(L14+F14+M14)*K14) | Q14: =IF($E14="","",L14*K14) | R14: =IF($E14="","",F14*K14) | S14: =IF($E14="","",M14*K14) | T14: =IF(OR($E14="",B14=0),"",L14/B14*10000) | U14: =IF(OR($E14="",C14=0),"",F14/C14*10000) | V14: =IF(OR($E14="",D14=0),"",M14/D14*10000)
A15: 45669 | B15: ='Daily Data'!B15 | C15: ='Daily Data'!D15 | D15: ='Daily Data'!C15 | E15: =IF('Daily Data'!E15="","",'Daily Data'!E15) | F15: =IF($E15="","",'Daily Data'!F15) | G15: =IF($E15="","",'Daily Data'!G15) | H15: =IF($E15="","",(1-K15)*F15-G15) | I15: =IF($E15="","",'Daily Data'!H15) | J15: =IF($E15="","",E15-H15-I15) | K15: =IF($E15="","",IF(A15<HLP_ChangeDate,HLP_Legacy,HLP_Current)) | L15: =IF($E15="","",J15/(1-K15)) | M15: =IF($E15="","",'Daily Data'!I15) | N15: =IF($E15="","",M15*(1-K15)-I15) | P15: =IF($E15="","",(L15+F15+M15)*K15) | Q15: =IF($E15="","",L15*K15) | R15: =IF($E15="","",F15*K15) | S15: =IF($E15="","",M15*K15) | T15: =IF(OR($E15="",B15=0),"",L15/B15*10000) | U15: =IF(OR($E15="",C15=0),"",F15/C15*10000) | V15: =IF(OR($E15="",D15=0),"",M15/D15*10000)
... A258: 45912 | B258: ='Daily Data'!B258 | C258: ='Daily Data'!D258 | D258: ='Daily Data'!C258 | E258: =IF('Daily Data'!E258="","",'Daily Data'!E258) | F258: =IF($E258="","",'Daily Data'!F258) | G258: =IF($E258="","",'Daily Data'!G258) | H258: =IF($E258="","",(1-K258)*F258-G258) | I258: =IF($E258="","",'Daily Data'!H258) | J258: =IF($E258="","",E258-H258-I258) | K258: =IF($E258="","",IF(A258<HLP_ChangeDate,HLP_Legacy,HLP_Current)) | L258: =IF($E258="","",J258/(1-K258)) | M258: =IF($E258="","",'Daily Data'!I258) | N258: =IF($E258="","",M258*(1-K258)-I258) | P258: =IF($E258="","",(L258+F258+M258)*K258) | Q258: =IF($E258="","",L258*K258) | R258: =IF($E258="","",F258*K258) | S258: =IF($E258="","",M258*K258) | T258: =IF(OR($E258="",B258=0),"",L258/B258*10000) | U258: =IF(OR($E258="",C258=0),"",F258/C258*10000) | V258: =IF(OR($E258="",D258=0),"",M258/D258*10000)
A259: 45913 | B259: ='Daily Data'!B259 | C259: ='Daily Data'!D259 | D259: ='Daily Data'!C259 | E259: =IF('Daily Data'!E259="","",'Daily Data'!E259) | F259: =IF($E259="","",'Daily Data'!F259) | G259: =IF($E259="","",'Daily Data'!G259) | H259: =IF($E259="","",(1-K259)*F259-G259) | I259: =IF($E259="","",'Daily Data'!H259) | J259: =IF($E259="","",E259-H259-I259) | K259: =IF($E259="","",IF(A259<HLP_ChangeDate,HLP_Legacy,HLP_Current)) | L259: =IF($E259="","",J259/(1-K259)) | M259: =IF($E259="","",'Daily Data'!I259) | N259: =IF($E259="","",M259*(1-K259)-I259) | O259: 335679 | P259: =IF($E259="","",(L259+F259+M259)*K259) | Q259: =IF($E259="","",L259*K259) | R259: =IF($E259="","",F259*K259) | S259: =IF($E259="","",M259*K259) | T259: =IF(OR($E259="",B259=0),"",L259/B259*10000) | U259: =IF(OR($E259="",C259=0),"",F259/C259*10000) | V259: =IF(OR($E259="",D259=0),"",M259/D259*10000)
A260: 45914 | B260: ='Daily Data'!B260 | C260: ='Daily Data'!D260 | D260: ='Daily Data'!C260 | E260: =IF('Daily Data'!E260="","",'Daily Data'!E260) | F260: =IF($E260="","",'Daily Data'!F260) | G260: =IF($E260="","",'Daily Data'!G260) | H260: =IF($E260="","",(1-K260)*F260-G260) | I260: =IF($E260="","",'Daily Data'!H260) | J260: =IF($E260="","",E260-H260-I260) | K260: =IF($E260="","",IF(A260<HLP_ChangeDate,HLP_Legacy,HLP_Current)) | L260: =IF($E260="","",J260/(1-K260)) | M260: =IF($E260="","",'Daily Data'!I260) | N260: =IF($E260="","",M260*(1-K260)-I260) | O260: 997056 | P260: =IF($E260="","",(L260+F260+M260)*K260) | Q260: =IF($E260="","",L260*K260) | R260: =IF($E260="","",F260*K260) | S260: =IF($E260="","",M260*K260) | T260: =IF(OR($E260="",B260=0),"",L260/B260*10000) | U260: =IF(OR($E260="",C260=0),"",F260/C260*10000) | V260: =IF(OR($E260="",D260=0),"",M260/D260*10000)
A261: 45915 | B261: ='Daily Data'!B261 | C261: ='Daily Data'!D261 | D261: ='Daily Data'!C261 | E261: =IF('Daily Data'!E261="","",'Daily Data'!E261) | F261: =IF($E261="","",'Daily Data'!F261) | G261: =IF($E261="","",'Daily Data'!G261) | H261: =IF($E261="","",(1-K261)*F261-G261) | I261: =IF($E261="","",'Daily Data'!H261) | J261: =IF($E261="","",E261-H261-I261) | K261: =IF($E261="","",IF(A261<HLP_ChangeDate,HLP_Legacy,HLP_Current)) | L261: =IF($E261="","",J261/(1-K261)) | M261: =IF($E261="","",'Daily Data'!I261) | N261: =IF($E261="","",M261*(1-K261)-I261) | O261: 507449 | P261: =IF($E261="","",(L261+F261+M261)*K261) | Q261: =IF($E261="","",L261*K261) | R261: =IF($E261="","",F261*K261) | S261: =IF($E261="","",M261*K261) | T261: =IF(OR($E261="",B261=0),"",L261/B261*10000) | U261: =IF(OR($E261="",C261=0),"",F261/C261*10000) | V261: =IF(OR($E261="",D261=0),"",M261/D261*10000)
A262: 45916 | B262: ='Daily Data'!B262 | C262: ='Daily Data'!D262 | D262: ='Daily Data'!C262 | E262: =IF('Daily Data'!E262="","",'Daily Data'!E262) | F262: =IF($E262="","",'Daily Data'!F262) | G262: =IF($E262="","",'Daily Data'!G262) | H262: =IF($E262="","",(1-K262)*F262-G262) | I262: =IF($E262="","",'Daily Data'!H262) | J262: =IF($E262="","",E262-H262-I262) | K262: =IF($E262="","",IF(A262<HLP_ChangeDate,HLP_Legacy,HLP_Current)) | L262: =IF($E262="","",J262/(1-K262)) | M262: =IF($E262="","",'Daily Data'!I262) | N262: =IF($E262="","",M262*(1-K262)-I262) | O262: 439663 | P262: =IF($E262="","",(L262+F262+M262)*K262) | Q262: =IF($E262="","",L262*K262) | R262: =IF($E262="","",F262*K262) | S262: =IF($E262="","",M262*K262) | T262: =IF(OR($E262="",B262=0),"",L262/B262*10000) | U262: =IF(OR($E262="",C262=0),"",F262/C262*10000) | V262: =IF(OR($E262="",D262=0),"",M262/D262*10000)
A263: 45917 | B263: ='Daily Data'!B263 | C263: ='Daily Data'!D263 | D263: ='Daily Data'!C263 | E263: =IF('Daily Data'!E263="","",'Daily Data'!E263) | F263: =IF($E263="","",'Daily Data'!F263) | G263: =IF($E263="","",'Daily Data'!G263) | H263: =IF($E263="","",(1-K263)*F263-G263) | I263: =IF($E263="","",'Daily Data'!H263) | J263: =IF($E263="","",E263-H263-I263) | K263: =IF($E263="","",IF(A263<HLP_ChangeDate,HLP_Legacy,HLP_Current)) | L263: =IF($E263="","",J263/(1-K263)) | M263: =IF($E263="","",'Daily Data'!I263) | N263: =IF($E263="","",M263*(1-K263)-I263) | O263: 649107 | P263: =IF($E263="","",(L263+F263+M263)*K263) | Q263: =IF($E263="","",L263*K263) | R263: =IF($E263="","",F263*K263) | S263: =IF($E263="","",M263*K263) | T263: =IF(OR($E263="",B263=0),"",L263/B263*10000) | U263: =IF(OR($E263="",C263=0),"",F263/C263*10000) | V263: =IF(OR($E263="",D263=0),"",M263/D263*10000)
A264: 45918 | B264: ='Daily Data'!B264 | C264: ='Daily Data'!D264 | D264: ='Daily Data'!C264 | E264: =IF('Daily Data'!E264="","",'Daily Data'!E264) | F264: =IF($E264="","",'Daily Data'!F264) | G264: =IF($E264="","",'Daily Data'!G264) | H264: =IF($E264="","",(1-K264)*F264-G264) | I264: =IF($E264="","",'Daily Data'!H264) | J264: =IF($E264="","",E264-H264-I264) | K264: =IF($E264="","",IF(A264<HLP_ChangeDate,HLP_Legacy,HLP_Current)) | L264: =IF($E264="","",J264/(1-K264)) | M264: =IF($E264="","",'Daily Data'!I264) | N264: =IF($E264="","",M264*(1-K264)-I264) | O264: 542586 | P264: =IF($E264="","",(L264+F264+M264)*K264) | Q264: =IF($E264="","",L264*K264) | R264: =IF($E264="","",F264*K264) | S264: =IF($E264="","",M264*K264) | T264: =IF(OR($E264="",B264=0),"",L264/B264*10000) | U264: =IF(OR($E264="",C264=0),"",F264/C264*10000) | V264: =IF(OR($E264="",D264=0),"",M264/D264*10000)
A265: 45919 | B265: ='Daily Data'!B265 | C265: ='Daily Data'!D265 | D265: ='Daily Data'!C265 | E265: =IF('Daily Data'!E265="","",'Daily Data'!E265) | F265: =IF($E265="","",'Daily Data'!F265) | G265: =IF($E265="","",'Daily Data'!G265) | H265: =IF($E265="","",(1-K265)*F265-G265) | I265: =IF($E265="","",'Daily Data'!H265) | J265: =IF($E265="","",E265-H265-I265) | K265: =IF($E265="","",IF(A265<HLP_ChangeDate,HLP_Legacy,HLP_Current)) | L265: =IF($E265="","",J265/(1-K265)) | M265: =IF($E265="","",'Daily Data'!I265) | N265: =IF($E265="","",M265*(1-K265)-I265) | O265: 366033 | P265: =IF($E265="","",(L265+F265+M265)*K265) | Q265: =IF($E265="","",L265*K265) | R265: =IF($E265="","",F265*K265) | S265: =IF($E265="","",M265*K265) | T265: =IF(OR($E265="",B265=0),"",L265/B265*10000) | U265: =IF(OR($E265="",C265=0),"",F265/C265*10000) | V265: =IF(OR($E265="",D265=0),"",M265/D265*10000)
A266: 45920 | B266: ='Daily Data'!B266 | C266: ='Daily Data'!D266 | D266: ='Daily Data'!C266 | E266: =IF('Daily Data'!E266="","",'Daily Data'!E266) | F266: =IF($E266="","",'Daily Data'!F266) | G266: =IF($E266="","",'Daily Data'!G266) | H266: =IF($E266="","",(1-K266)*F266-G266) | I266: =IF($E266="","",'Daily Data'!H266) | J266: =IF($E266="","",E266-H266-I266) | K266: =IF($E266="","",IF(A266<HLP_ChangeDate,HLP_Legacy,HLP_Current)) | L266: =IF($E266="","",J266/(1-K266)) | M266: =IF($E266="","",'Daily Data'!I266) | N266: =IF($E266="","",M266*(1-K266)-I266) | O266: 299433 | P266: =IF($E266="","",(L266+F266+M266)*K266) | Q266: =IF($E266="","",L266*K266) | R266: =IF($E266="","",F266*K266) | S266: =IF($E266="","",M266*K266) | T266: =IF(OR($E266="",B266=0),"",L266/B266*10000) | U266: =IF(OR($E266="",C266=0),"",F266/C266*10000) | V266: =IF(OR($E266="",D266=0),"",M266/D266*10000)
A267: 45921 | B267: ='Daily Data'!B267 | C267: ='Daily Data'!D267 | D267: ='Daily Data'!C267 | E267: =IF('Daily Data'!E267="","",'Daily Data'!E267) | F267: =IF($E267="","",'Daily Data'!F267) | G267: =IF($E267="","",'Daily Data'!G267) | H267: =IF($E267="","",(1-K267)*F267-G267) | I267: =IF($E267="","",'Daily Data'!H267) | J267: =IF($E267="","",E267-H267-I267) | K267: =IF($E267="","",IF(A267<HLP_ChangeDate,HLP_Legacy,HLP_Current)) | L267: =IF($E267="","",J267/(1-K267)) | M267: =IF($E267="","",'Daily Data'!I267) | N267: =IF($E267="","",M267*(1-K267)-I267) | O267: 230812 | P267: =IF($E267="","",(L267+F267+M267)*K267) | Q267: =IF($E267="","",L267*K267) | R267: =IF($E267="","",F267*K267) | S267: =IF($E267="","",M267*K267) | T267: =IF(OR($E267="",B267=0),"",L267/B267*10000) | U267: =IF(OR($E267="",C267=0),"",F267/C267*10000) | V267: =IF(OR($E267="",D267=0),"",M267/D267*10000)
A268: 45922 | B268: ='Daily Data'!B268 | C268: ='Daily Data'!D268 | D268: ='Daily Data'!C268 | E268: =IF('Daily Data'!E268="","",'Daily Data'!E268) | F268: =IF($E268="","",'Daily Data'!F268) | G268: =IF($E268="","",'Daily Data'!G268) | H268: =IF($E268="","",(1-K268)*F268-G268) | I268: =IF($E268="","",'Daily Data'!H268) | J268: =IF($E268="","",E268-H268-I268) | K268: =IF($E268="","",IF(A268<HLP_ChangeDate,HLP_Legacy,HLP_Current)) | L268: =IF($E268="","",J268/(1-K268)) | M268: =IF($E268="","",'Daily Data'!I268) | N268: =IF($E268="","",M268*(1-K268)-I268) | O268: 262234 | P268: =IF($E268="","",(L268+F268+M268)*K268) | Q268: =IF($E268="","",L268*K268) | R268: =IF($E268="","",F268*K268) | S268: =IF($E268="","",M268*K268) | T268: =IF(OR($E268="",B268=0),"",L268/B268*10000) | U268: =IF(OR($E268="",C268=0),"",F268/C268*10000) | V268: =IF(OR($E268="",D268=0),"",M268/D268*10000)
A269: 45923 | B269: ='Daily Data'!B269 | C269: ='Daily Data'!D269 | D269: ='Daily Data'!C269 | E269: =IF('Daily Data'!E269="","",'Daily Data'!E269) | F269: =IF($E269="","",'Daily Data'!F269) | G269: =IF($E269="","",'Daily Data'!G269) | H269: =IF($E269="","",(1-K269)*F269-G269) | I269: =IF($E269="","",'Daily Data'!H269) | J269: =IF($E269="","",E269-H269-I269) | K269: =IF($E269="","",IF(A269<HLP_ChangeDate,HLP_Legacy,HLP_Current)) | L269: =IF($E269="","",J269/(1-K269)) | M269: =IF($E269="","",'Daily Data'!I269) | N269: =IF($E269="","",M269*(1-K269)-I269) | O269: 208485 | P269: =IF($E269="","",(L269+F269+M269)*K269) | Q269: =IF($E269="","",L269*K269) | R269: =IF($E269="","",F269*K269) | S269: =IF($E269="","",M269*K269) | T269: =IF(OR($E269="",B269=0),"",L269/B269*10000) | U269: =IF(OR($E269="",C269=0),"",F269/C269*10000) | V269: =IF(OR($E269="",D269=0),"",M269/D269*10000)
A270: 45924 | B270: ='Daily Data'!B270 | C270: ='Daily Data'!D270 | D270: ='Daily Data'!C270 | E270: =IF('Daily Data'!E270="","",'Daily Data'!E270) | F270: =IF($E270="","",'Daily Data'!F270) | G270: =IF($E270="","",'Daily Data'!G270) | H270: =IF($E270="","",(1-K270)*F270-G270) | I270: =IF($E270="","",'Daily Data'!H270) | J270: =IF($E270="","",E270-H270-I270) | K270: =IF($E270="","",IF(A270<HLP_ChangeDate,HLP_Legacy,HLP_Current)) | L270: =IF($E270="","",J270/(1-K270)) | M270: =IF($E270="","",'Daily Data'!I270) | N270: =IF($E270="","",M270*(1-K270)-I270) | O270: 194550 | P270: =IF($E270="","",(L270+F270+M270)*K270) | Q270: =IF($E270="","",L270*K270) | R270: =IF($E270="","",F270*K270) | S270: =IF($E270="","",M270*K270) | T270: =IF(OR($E270="",B270=0),"",L270/B270*10000) | U270: =IF(OR($E270="",C270=0),"",F270/C270*10000) | V270: =IF(OR($E270="",D270=0),"",M270/D270*10000)
... A508: 46162 | B508: ='Daily Data'!B508 | C508: ='Daily Data'!D508 | D508: ='Daily Data'!C508 | E508: =IF('Daily Data'!E508="","",'Daily Data'!E508) | F508: =IF($E508="","",'Daily Data'!F508) | G508: =IF($E508="","",'Daily Data'!G508) | H508: =IF($E508="","",(1-K508)*F508-G508) | I508: =IF($E508="","",'Daily Data'!H508) | J508: =IF($E508="","",E508-H508-I508) | K508: =IF($E508="","",IF(A508<HLP_ChangeDate,HLP_Legacy,HLP_Current)) | L508: =IF($E508="","",J508/(1-K508)) | M508: =IF($E508="","",'Daily Data'!I508) | N508: =IF($E508="","",M508*(1-K508)-I508) | O508: 89113 | P508: =IF($E508="","",(L508+F508+M508)*K508) | Q508: =IF($E508="","",L508*K508) | R508: =IF($E508="","",F508*K508) | S508: =IF($E508="","",M508*K508) | T508: =IF(OR($E508="",B508=0),"",L508/B508*10000) | U508: =IF(OR($E508="",C508=0),"",F508/C508*10000) | V508: =IF(OR($E508="",D508=0),"",M508/D508*10000)

Sheet OTS Breakdown
A1: OTS BREAKDOWN — historical Outstanding Token Supply, daily 2025-01-01 → 2026-05-20. Cols B–P = the schedule itself; cols Q–Y = formula verification + burn decomposition (audit + projection). For PROJECTION: project Buyback (D) from HC Rev / HYPE price, project Daily Emission (E), project the three burn streams (W/X/Y); then S,Q,U give projected AF, FE, CumBurns, which feed OTS (O).
B2: SUPPLY FLOWS | I2: OUTSTANDING TOKEN SUPPLY (OTS = 1bn HYPE − the five buckets) | Q2: FORMULA VERIFICATION (running balances; should ≈ 0) | W2: BURN DECOMPOSITION (Daily Burn = EVM + Auction + AF) | Z2: STAKING (ASXN actuals + implied APR) | AE2: OTS COMPOSITION (OTS = Circulating + Core Contributors)
A3: Date | B3: Revenue → Buyback ($) | C3: HYPE Price ($) | D3: HYPE Bought Back (HYPE) | E3: Emissions / Staking Rewards (HYPE) | F3: Fees Burned (HYPE) | G3: Team Tokens Unlocked (HYPE) | H3: Cumulative Team Vested (HYPE) | I3: Initial Supply (HYPE) | J3: (−) Future Emissions Reserve (HYPE) | K3: (−) Hyper Foundation (HYPE) | L3: (−) Assistance Fund (HYPE) | M3: (−) Community Grants (HYPE) | N3: (−) Cumulative Fees Burnt (HYPE) | O3: =Outstanding Token Supply (HYPE) | P3: OTS Value ($) | Q3: FE — Formula (running) | R3: FE — Match (Data−Formula) | S3: AF — Pure Buyback Formula | T3: AF — Match (Data−Formula) | U3: CumBurns — Running Sum | V3: CumBurns — Match (Data−Formula) | W3: Burn: EVM gas (HYPE) | X3: Burn: HIP-1 auction (HYPE) | Y3: Burn: AF / other (HYPE) — residual | Z3: Active Stake (M HYPE) | AA3: Inactive Stake (M HYPE) | AB3: Total Stake (M HYPE) | AC3: Implied Staking APR | AD3: % of OTS Staked | AE3: Team Locked Remaining (M HYPE) | AF3: Circulating Supply (M HYPE)
A4: 45658 | B4: =IF('Daily Data'!E4="","",'Daily Data'!E4) | C4: 24 | D4: 48753.47 | E4: 24499.354 | F4: 941.1022 | H4: =SUM($G$4:G4) | I4: 1000000000 | J4: 4.2798028e+08 | K4: 60000000 | L4: 11719551 | M4: 3000000 | N4: 111035.77 | O4: =IF(OR(I4="",J4="",L4="",N4=""),"",I4-J4-K4-L4-M4-N4) | P4: =IF(OR(O4="",C4=""),"",O4*C4) | Q4: =J4 | R4: =IF(OR(J4="",Q4=""),"",J4-Q4) | S4: =L4 | T4: =IF(OR(L4="",S4=""),"",L4-S4) | U4: =N4 | V4: =IF(OR(N4="",U4=""),"",N4-U4) | W4: =IF(OR(C4="",C4=0,'Daily Data'!J4=""),"",'Daily Data'!J4/C4) | X4: =IF(OR(C4="",C4=0,'Daily Data'!K4=""),"",'Daily Data'!K4/C4) | Y4: =IF(OR(F4="",W4="",X4=""),"",F4-W4-X4) | Z4: 363.65 | AA4: 64.17 | AB4: =Z4+AA4 | AC4: =IF(OR(E4="",E4=0,AB4=""),"",E4*365/(AB4*1000000)) | AD4: =IF(OR(O4="",O4=0,AB4=""),"",(AB4*1000000)/O4) | AE4: =IF(H4="","",(Team_Genesis-H4)/1000000) | AF4: =IF(OR(O4="",AE4=""),"",(O4-AE4*1000000)/1000000)
A5: 45659 | B5: =IF('Daily Data'!E5="","",'Daily Data'!E5) | C5: 26.31 | D5: 37230.03 | E5: 24851.902 | F5: 920.9016 | H5: =SUM($G$4:G5) | I5: 1000000000 | J5: =J4-E5 | K5: 60000000 | L5: 11756781 | M5: 3000000 | N5: 111956.67 | O5: =IF(OR(I5="",J5="",L5="",N5=""),"",I5-J5-K5-L5-M5-N5) | P5: =IF(OR(O5="",C5=""),"",O5*C5) | Q5: =Q4-E5 | R5: =IF(OR(J5="",Q5=""),"",J5-Q5) | S5: =IF(D5="",S4,S4+D5) | T5: =IF(OR(L5="",S5=""),"",L5-S5) | U5: =IF(F5="",U4,U4+F5) | V5: =IF(OR(N5="",U5=""),"",N5-U5) | W5: =IF(OR(C5="",C5=0,'Daily Data'!J5=""),"",'Daily Data'!J5/C5) | X5: =IF(OR(C5="",C5=0,'Daily Data'!K5=""),"",'Daily Data'!K5/C5) | Y5: =IF(OR(F5="",W5="",X5=""),"",F5-W5-X5) | Z5: 363.65 | AA5: 64.17 | AB5: =Z5+AA5 | AC5: =IF(OR(E5="",E5=0,AB5=""),"",E5*365/(AB5*1000000)) | AD5: =IF(OR(O5="",O5=0,AB5=""),"",(AB5*1000000)/O5) | AE5: =IF(H5="","",(Team_Genesis-H5)/1000000) | AF5: =IF(OR(O5="",AE5=""),"",(O5-AE5*1000000)/1000000)
A6: 45660 | B6: =IF('Daily Data'!E6="","",'Daily Data'!E6) | C6: 23.15 | D6: 55732.01 | E6: 25219.868 | F6: 905.5316 | H6: =SUM($G$4:G6) | I6: 1000000000 | J6: =J5-E6 | K6: 60000000 | L6: 11812513 | M6: 3000000 | N6: 112862.2 | O6: =IF(OR(I6="",J6="",L6="",N6=""),"",I6-J6-K6-L6-M6-N6) | P6: =IF(OR(O6="",C6=""),"",O6*C6) | Q6: =Q5-E6 | R6: =IF(OR(J6="",Q6=""),"",J6-Q6) | S6: =IF(D6="",S5,S5+D6) | T6: =IF(OR(L6="",S6=""),"",L6-S6) | U6: =IF(F6="",U5,U5+F6) | V6: =IF(OR(N6="",U6=""),"",N6-U6) | W6: =IF(OR(C6="",C6=0,'Daily Data'!J6=""),"",'Daily Data'!J6/C6) | X6: =IF(OR(C6="",C6=0,'Daily Data'!K6=""),"",'Daily Data'!K6/C6) | Y6: =IF(OR(F6="",W6="",X6=""),"",F6-W6-X6) | Z6: 363.65 | AA6: 64.17 | AB6: =Z6+AA6 | AC6: =IF(OR(E6="",E6=0,AB6=""),"",E6*365/(AB6*1000000)) | AD6: =IF(OR(O6="",O6=0,AB6=""),"",(AB6*1000000)/O6) | AE6: =IF(H6="","",(Team_Genesis-H6)/1000000) | AF6: =IF(OR(O6="",AE6=""),"",(O6-AE6*1000000)/1000000)
A7: 45661 | B7: =IF('Daily Data'!E7="","",'Daily Data'!E7) | C7: 24.43 | D7: 34281.41 | E7: 25452.778 | F7: 1232.8801 | H7: =SUM($G$4:G7) | I7: 1000000000 | J7: =J6-E7 | K7: 60000000 | L7: 11846794 | M7: 3000000 | N7: 114095.08 | O7: =IF(OR(I7="",J7="",L7="",N7=""),"",I7-J7-K7-L7-M7-N7) | P7: =IF(OR(O7="",C7=""),"",O7*C7) | Q7: =Q6-E7 | R7: =IF(OR(J7="",Q7=""),"",J7-Q7) | S7: =IF(D7="",S6,S6+D7) | T7: =IF(OR(L7="",S7=""),"",L7-S7) | U7: =IF(F7="",U6,U6+F7) | V7: =IF(OR(N7="",U7=""),"",N7-U7) | W7: =IF(OR(C7="",C7=0,'Daily Data'!J7=""),"",'Daily Data'!J7/C7) | X7: =IF(OR(C7="",C7=0,'Daily Data'!K7=""),"",'Daily Data'!K7/C7) | Y7: =IF(OR(F7="",W7="",X7=""),"",F7-W7-X7) | Z7: 363.65 | AA7: 64.17 | AB7: =Z7+AA7 | AC7: =IF(OR(E7="",E7=0,AB7=""),"",E7*365/(AB7*1000000)) | AD7: =IF(OR(O7="",O7=0,AB7=""),"",(AB7*1000000)/O7) | AE7: =IF(H7="","",(Team_Genesis-H7)/1000000) | AF7: =IF(OR(O7="",AE7=""),"",(O7-AE7*1000000)/1000000)
A8: 45662 | B8: =IF('Daily Data'!E8="","",'Daily Data'!E8) | C8: 25.02 | D8: 42553.47 | E8: 25665.111 | F8: 617.3145 | H8: =SUM($G$4:G8) | I8: 1000000000 | J8: =J7-E8 | K8: 60000000 | L8: 11889348 | M8: 3000000 | N8: 114712.4 | O8: =IF(OR(I8="",J8="",L8="",N8=""),"",I8-J8-K8-L8-M8-N8) | P8: =IF(OR(O8="",C8=""),"",O8*C8) | Q8: =Q7-E8 | R8: =IF(OR(J8="",Q8=""),"",J8-Q8) | S8: =IF(D8="",S7,S7+D8) | T8: =IF(OR(L8="",S8=""),"",L8-S8) | U8: =IF(F8="",U7,U7+F8) | V8: =IF(OR(N8="",U8=""),"",N8-U8) | W8: =IF(OR(C8="",C8=0,'Daily Data'!J8=""),"",'Daily Data'!J8/C8) | X8: =IF(OR(C8="",C8=0,'Daily Data'!K8=""),"",'Daily Data'!K8/C8) | Y8: =IF(OR(F8="",W8="",X8=""),"",F8-W8-X8) | Z8: 363.65 | AA8: 64.17 | AB8: =Z8+AA8 | AC8: =IF(OR(E8="",E8=0,AB8=""),"",E8*365/(AB8*1000000)) | AD8: =IF(OR(O8="",O8=0,AB8=""),"",(AB8*1000000)/O8) | AE8: =IF(H8="","",(Team_Genesis-H8)/1000000) | AF8: =IF(OR(O8="",AE8=""),"",(O8-AE8*1000000)/1000000)
A9: 45663 | B9: =IF('Daily Data'!E9="","",'Daily Data'!E9) | C9: 24.4 | D9: 43787.34 | E9: 25789.885 | F9: 447.5855 | H9: =SUM($G$4:G9) | I9: 1000000000 | J9: =J8-E9 | K9: 60000000 | L9: 11933135 | M9: 3000000 | N9: 115159.98 | O9: =IF(OR(I9="",J9="",L9="",N9=""),"",I9-J9-K9-L9-M9-N9) | P9: =IF(OR(O9="",C9=""),"",O9*C9) | Q9: =Q8-E9 | R9: =IF(OR(J9="",Q9=""),"",J9-Q9) | S9: =IF(D9="",S8,S8+D9) | T9: =IF(OR(L9="",S9=""),"",L9-S9) | U9: =IF(F9="",U8,U8+F9) | V9: =IF(OR(N9="",U9=""),"",N9-U9) | W9: =IF(OR(C9="",C9=0,'Daily Data'!J9=""),"",'Daily Data'!J9/C9) | X9: =IF(OR(C9="",C9=0,'Daily Data'!K9=""),"",'Daily Data'!K9/C9) | Y9: =IF(OR(F9="",W9="",X9=""),"",F9-W9-X9) | Z9: 363.65 | AA9: 64.17 | AB9: =Z9+AA9 | AC9: =IF(OR(E9="",E9=0,AB9=""),"",E9*365/(AB9*1000000)) | AD9: =IF(OR(O9="",O9=0,AB9=""),"",(AB9*1000000)/O9) | AE9: =IF(H9="","",(Team_Genesis-H9)/1000000) | AF9: =IF(OR(O9="",AE9=""),"",(O9-AE9*1000000)/1000000)
A10: 45664 | B10: =IF('Daily Data'!E10="","",'Daily Data'!E10) | C10: 25.23 | D10: 58651.7 | E10: 25854.611 | F10: 718.7295 | H10: =SUM($G$4:G10) | I10: 1000000000 | J10: =J9-E10 | K10: 60000000 | L10: 11991787 | M10: 3000000 | N10: 115878.71 | O10: =IF(OR(I10="",J10="",L10="",N10=""),"",I10-J10-K10-L10-M10-N10) | P10: =IF(OR(O10="",C10=""),"",O10*C10) | Q10: =Q9-E10 | R10: =IF(OR(J10="",Q10=""),"",J10-Q10) | S10: =IF(D10="",S9,S9+D10) | T10: =IF(OR(L10="",S10=""),"",L10-S10) | U10: =IF(F10="",U9,U9+F10) | V10: =IF(OR(N10="",U10=""),"",N10-U10) | W10: =IF(OR(C10="",C10=0,'Daily Data'!J10=""),"",'Daily Data'!J10/C10) | X10: =IF(OR(C10="",C10=0,'Daily Data'!K10=""),"",'Daily Data'!K10/C10) | Y10: =IF(OR(F10="",W10="",X10=""),"",F10-W10-X10) | Z10: 363.65 | AA10: 64.17 | AB10: =Z10+AA10 | AC10: =IF(OR(E10="",E10=0,AB10=""),"",E10*365/(AB10*1000000)) | AD10: =IF(OR(O10="",O10=0,AB10=""),"",(AB10*1000000)/O10) | AE10: =IF(H10="","",(Team_Genesis-H10)/1000000) | AF10: =IF(OR(O10="",AE10=""),"",(O10-AE10*1000000)/1000000)
A11: 45665 | B11: =IF('Daily Data'!E11="","",'Daily Data'!E11) | C11: 23.5 | D11: 84543.47 | E11: 25924.42 | F11: 744.9065 | H11: =SUM($G$4:G11) | I11: 1000000000 | J11: =J10-E11 | K11: 60000000 | L11: 12076330 | M11: 3000000 | N11: 116623.62 | O11: =IF(OR(I11="",J11="",L11="",N11=""),"",I11-J11-K11-L11-M11-N11) | P11: =IF(OR(O11="",C11=""),"",O11*C11) | Q11: =Q10-E11 | R11: =IF(OR(J11="",Q11=""),"",J11-Q11) | S11: =IF(D11="",S10,S10+D11) | T11: =IF(OR(L11="",S11=""),"",L11-S11) | U11: =IF(F11="",U10,U10+F11) | V11: =IF(OR(N11="",U11=""),"",N11-U11) | W11: =IF(OR(C11="",C11=0,'Daily Data'!J11=""),"",'Daily Data'!J11/C11) | X11: =IF(OR(C11="",C11=0,'Daily Data'!K11=""),"",'Daily Data'!K11/C11) | Y11: =IF(OR(F11="",W11="",X11=""),"",F11-W11-X11) | Z11: 363.65 | AA11: 64.17 | AB11: =Z11+AA11 | AC11: =IF(OR(E11="",E11=0,AB11=""),"",E11*365/(AB11*1000000)) | AD11: =IF(OR(O11="",O11=0,AB11=""),"",(AB11*1000000)/O11) | AE11: =IF(H11="","",(Team_Genesis-H11)/1000000) | AF11: =IF(OR(O11="",AE11=""),"",(O11-AE11*1000000)/1000000)
A12: 45666 | B12: =IF('Daily Data'!E12="","",'Daily Data'!E12) | C12: 22.51 | D12: 80644.52 | E12: 25984.345 | F12: 1579.5356 | H12: =SUM($G$4:G12) | I12: 1000000000 | J12: =J11-E12 | K12: 60000000 | L12: 12156975 | M12: 3000000 | N12: 118203.15 | O12: =IF(OR(I12="",J12="",L12="",N12=""),"",I12-J12-K12-L12-M12-N12) | P12: =IF(OR(O12="",C12=""),"",O12*C12) | Q12: =Q11-E12 | R12: =IF(OR(J12="",Q12=""),"",J12-Q12) | S12: =IF(D12="",S11,S11+D12) | T12: =IF(OR(L12="",S12=""),"",L12-S12) | U12: =IF(F12="",U11,U11+F12) | V12: =IF(OR(N12="",U12=""),"",N12-U12) | W12: =IF(OR(C12="",C12=0,'Daily Data'!J12=""),"",'Daily Data'!J12/C12) | X12: =IF(OR(C12="",C12=0,'Daily Data'!K12=""),"",'Daily Data'!K12/C12) | Y12: =IF(OR(F12="",W12="",X12=""),"",F12-W12-X12) | Z12: 363.65 | AA12: 64.17 | AB12: =Z12+AA12 | AC12: =IF(OR(E12="",E12=0,AB12=""),"",E12*365/(AB12*1000000)) | AD12: =IF(OR(O12="",O12=0,AB12=""),"",(AB12*1000000)/O12) | AE12: =IF(H12="","",(Team_Genesis-H12)/1000000) | AF12: =IF(OR(O12="",AE12=""),"",(O12-AE12*1000000)/1000000)
A13: 45667 | B13: =IF('Daily Data'!E13="","",'Daily Data'!E13) | C13: 20.28 | D13: 84058.36 | E13: 26008.903 | F13: 1664.9046 | H13: =SUM($G$4:G13) | I13: 1000000000 | J13: =J12-E13 | K13: 60000000 | L13: 12241033 | M13: 3000000 | N13: 119868.06 | O13: =IF(OR(I13="",J13="",L13="",N13=""),"",I13-J13-K13-L13-M13-N13) | P13: =IF(OR(O13="",C13=""),"",O13*C13) | Q13: =Q12-E13 | R13: =IF(OR(J13="",Q13=""),"",J13-Q13) | S13: =IF(D13="",S12,S12+D13) | T13: =IF(OR(L13="",S13=""),"",L13-S13) | U13: =IF(F13="",U12,U12+F13) | V13: =IF(OR(N13="",U13=""),"",N13-U13) | W13: =IF(OR(C13="",C13=0,'Daily Data'!J13=""),"",'Daily Data'!J13/C13) | X13: =IF(OR(C13="",C13=0,'Daily Data'!K13=""),"",'Daily Data'!K13/C13) | Y13: =IF(OR(F13="",W13="",X13=""),"",F13-W13-X13) | Z13: 363.65 | AA13: 64.17 | AB13: =Z13+AA13 | AC13: =IF(OR(E13="",E13=0,AB13=""),"",E13*365/(AB13*1000000)) | AD13: =IF(OR(O13="",O13=0,AB13=""),"",(AB13*1000000)/O13) | AE13: =IF(H13="","",(Team_Genesis-H13)/1000000) | AF13: =IF(OR(O13="",AE13=""),"",(O13-AE13*1000000)/1000000)
A14: 45668 | B14: =IF('Daily Data'!E14="","",'Daily Data'!E14) | C14: 20.65 | D14: 64375.7 | E14: 26032.719 | F14: 984.8383 | H14: =SUM($G$4:G14) | I14: 1000000000 | J14: =J13-E14 | K14: 60000000 | L14: 12305409 | M14: 3000000 | N14: 120852.9 | O14: =IF(OR(I14="",J14="",L14="",N14=""),"",I14-J14-K14-L14-M14-N14) | P14: =IF(OR(O14="",C14=""),"",O14*C14) | Q14: =Q13-E14 | R14: =IF(OR(J14="",Q14=""),"",J14-Q14) | S14: =IF(D14="",S13,S13+D14) | T14: =IF(OR(L14="",S14=""),"",L14-S14) | U14: =IF(F14="",U13,U13+F14) | V14: =IF(OR(N14="",U14=""),"",N14-U14) | W14: =IF(OR(C14="",C14=0,'Daily Data'!J14=""),"",'Daily Data'!J14/C14) | X14: =IF(OR(C14="",C14=0,'Daily Data'!K14=""),"",'Daily Data'!K14/C14) | Y14: =IF(OR(F14="",W14="",X14=""),"",F14-W14-X14) | Z14: 363.65 | AA14: 64.17 | AB14: =Z14+AA14 | AC14: =IF(OR(E14="",E14=0,AB14=""),"",E14*365/(AB14*1000000)) | AD14: =IF(OR(O14="",O14=0,AB14=""),"",(AB14*1000000)/O14) | AE14: =IF(H14="","",(Team_Genesis-H14)/1000000) | AF14: =IF(OR(O14="",AE14=""),"",(O14-AE14*1000000)/1000000)
A15: 45669 | B15: =IF('Daily Data'!E15="","",'Daily Data'!E15) | C15: 20.88 | D15: 17684.15 | E15: 26062.989 | F15: 555.3528 | H15: =SUM($G$4:G15) | I15: 1000000000 | J15: =J14-E15 | K15: 60000000 | L15: 12323093 | M15: 3000000 | N15: 121408.25 | O15: =IF(OR(I15="",J15="",L15="",N15=""),"",I15-J15-K15-L15-M15-N15) | P15: =IF(OR(O15="",C15=""),"",O15*C15) | Q15: =Q14-E15 | R15: =IF(OR(J15="",Q15=""),"",J15-Q15) | S15: =IF(D15="",S14,S14+D15) | T15: =IF(OR(L15="",S15=""),"",L15-S15) | U15: =IF(F15="",U14,U14+F15) | V15: =IF(OR(N15="",U15=""),"",N15-U15) | W15: =IF(OR(C15="",C15=0,'Daily Data'!J15=""),"",'Daily Data'!J15/C15) | X15: =IF(OR(C15="",C15=0,'Daily Data'!K15=""),"",'Daily Data'!K15/C15) | Y15: =IF(OR(F15="",W15="",X15=""),"",F15-W15-X15) | Z15: 363.65 | AA15: 64.17 | AB15: =Z15+AA15 | AC15: =IF(OR(E15="",E15=0,AB15=""),"",E15*365/(AB15*1000000)) | AD15: =IF(OR(O15="",O15=0,AB15=""),"",(AB15*1000000)/O15) | AE15: =IF(H15="","",(Team_Genesis-H15)/1000000) | AF15: =IF(OR(O15="",AE15=""),"",(O15-AE15*1000000)/1000000)
A16: 45670 | B16: =IF('Daily Data'!E16="","",'Daily Data'!E16) | C16: 21.12 | D16: 43364.96 | E16: 26085.585 | F16: 490.8274 | H16: =SUM($G$4:G16) | I16: 1000000000 | J16: =J15-E16 | K16: 60000000 | L16: 12366458 | M16: 3000000 | N16: 121899.08 | O16: =IF(OR(I16="",J16="",L16="",N16=""),"",I16-J16-K16-L16-M16-N16) | P16: =IF(OR(O16="",C16=""),"",O16*C16) | Q16: =Q15-E16 | R16: =IF(OR(J16="",Q16=""),"",J16-Q16) | S16: =IF(D16="",S15,S15+D16) | T16: =IF(OR(L16="",S16=""),"",L16-S16) | U16: =IF(F16="",U15,U15+F16) | V16: =IF(OR(N16="",U16=""),"",N16-U16) | W16: =IF(OR(C16="",C16=0,'Daily Data'!J16=""),"",'Daily Data'!J16/C16) | X16: =IF(OR(C16="",C16=0,'Daily Data'!K16=""),"",'Daily Data'!K16/C16) | Y16: =IF(OR(F16="",W16="",X16=""),"",F16-W16-X16) | Z16: 363.65 | AA16: 64.17 | AB16: =Z16+AA16 | AC16: =IF(OR(E16="",E16=0,AB16=""),"",E16*365/(AB16*1000000)) | AD16: =IF(OR(O16="",O16=0,AB16=""),"",(AB16*1000000)/O16) | AE16: =IF(H16="","",(Team_Genesis-H16)/1000000) | AF16: =IF(OR(O16="",AE16=""),"",(O16-AE16*1000000)/1000000)
... A312: 45966 | B312: =IF('Daily Data'!E312="","",'Daily Data'!E312) | C312: 39.09 | D312: 76813.03 | E312: 25985.335 | F312: 2903.9061 | H312: =SUM($G$4:G312) | I312: 1000000000 | J312: =J311-E312 | K312: 60000000 | L312: 34598550 | M312: 3000000 | N312: 477509.05 | O312: =IF(OR(I312="",J312="",L312="",N312=""),"",I312-J312-K312-L312-M312-N312) | P312: =IF(OR(O312="",C312=""),"",O312*C312) | Q312: =Q311-E312 | R312: =IF(OR(J312="",Q312=""),"",J312-Q312) | S312: =IF(D312="",S311,S311+D312) | T312: =IF(OR(L312="",S312=""),"",L312-S312) | U312: =IF(F312="",U311,U311+F312) | V312: =IF(OR(N312="",U312=""),"",N312-U312) | W312: =IF(OR(C312="",C312=0,'Daily Data'!J312=""),"",'Daily Data'!J312/C312) | X312: =IF(OR(C312="",C312=0,'Daily Data'!K312=""),"",'Daily Data'!K312/C312) | Y312: =IF(OR(F312="",W312="",X312=""),"",F312-W312-X312) | Z312: 354.93 | AA312: 62.63 | AB312: =Z312+AA312 | AC312: =IF(OR(E312="",E312=0,AB312=""),"",E312*365/(AB312*1000000)) | AD312: =IF(OR(O312="",O312=0,AB312=""),"",(AB312*1000000)/O312) | AE312: =IF(H312="","",(Team_Genesis-H312)/1000000) | AF312: =IF(OR(O312="",AE312=""),"",(O312-AE312*1000000)/1000000)
A313: 45967 | B313: =IF('Daily Data'!E313="","",'Daily Data'!E313) | C313: 41.04 | D313: 71839.51 | E313: 25961.949 | F313: 1791.5839 | G313: 1745746 | H313: =SUM($G$4:G313) | I313: 1000000000 | J313: =J312-E313 | K313: 60000000 | L313: 34669690 | M313: 3000000 | N313: 479300.63 | O313: =IF(OR(I313="",J313="",L313="",N313=""),"",I313-J313-K313-L313-M313-N313) | P313: =IF(OR(O313="",C313=""),"",O313*C313) | Q313: =Q312-E313 | R313: =IF(OR(J313="",Q313=""),"",J313-Q313) | S313: =IF(D313="",S312,S312+D313) | T313: =IF(OR(L313="",S313=""),"",L313-S313) | U313: =IF(F313="",U312,U312+F313) | V313: =IF(OR(N313="",U313=""),"",N313-U313) | W313: =IF(OR(C313="",C313=0,'Daily Data'!J313=""),"",'Daily Data'!J313/C313) | X313: =IF(OR(C313="",C313=0,'Daily Data'!K313=""),"",'Daily Data'!K313/C313) | Y313: =IF(OR(F313="",W313="",X313=""),"",F313-W313-X313) | Z313: 354.93 | AA313: 62.63 | AB313: =Z313+AA313 | AC313: =IF(OR(E313="",E313=0,AB313=""),"",E313*365/(AB313*1000000)) | AD313: =IF(OR(O313="",O313=0,AB313=""),"",(AB313*1000000)/O313) | AE313: =IF(H313="","",(Team_Genesis-H313)/1000000) | AF313: =IF(OR(O313="",AE313=""),"",(O313-AE313*1000000)/1000000)
A314: 45968 | B314: =IF('Daily Data'!E314="","",'Daily Data'!E314) | C314: 38.44 | D314: 79550.84 | E314: 25933.036 | F314: 769.2206 | H314: =SUM($G$4:G314) | I314: 1000000000 | J314: =J313-E314 | K314: 60000000 | L314: 34749097 | M314: 3000000 | N314: 480069.85 | O314: =IF(OR(I314="",J314="",L314="",N314=""),"",I314-J314-K314-L314-M314-N314) | P314: =IF(OR(O314="",C314=""),"",O314*C314) | Q314: =Q313-E314 | R314: =IF(OR(J314="",Q314=""),"",J314-Q314) | S314: =IF(D314="",S313,S313+D314) | T314: =IF(OR(L314="",S314=""),"",L314-S314) | U314: =IF(F314="",U313,U313+F314) | V314: =IF(OR(N314="",U314=""),"",N314-U314) | W314: =IF(OR(C314="",C314=0,'Daily Data'!J314=""),"",'Daily Data'!J314/C314) | X314: =IF(OR(C314="",C314=0,'Daily Data'!K314=""),"",'Daily Data'!K314/C314) | Y314: =IF(OR(F314="",W314="",X314=""),"",F314-W314-X314) | Z314: 354.93 | AA314: 62.63 | AB314: =Z314+AA314 | AC314: =IF(OR(E314="",E314=0,AB314=""),"",E314*365/(AB314*1000000)) | AD314: =IF(OR(O314="",O314=0,AB314=""),"",(AB314*1000000)/O314) | AE314: =IF(H314="","",(Team_Genesis-H314)/1000000) | AF314: =IF(OR(O314="",AE314=""),"",(O314-AE314*1000000)/1000000)
A315: 45969 | B315: =IF('Daily Data'!E315="","",'Daily Data'!E315) | C315: 42.09 | D315: 39496.34 | E315: 25923.367 | F315: 2190.7271 | H315: =SUM($G$4:G315) | I315: 1000000000 | J315: =J314-E315 | K315: 60000000 | L315: 34788700 | M315: 3000000 | N315: 482260.58 | O315: =IF(OR(I315="",J315="",L315="",N315=""),"",I315-J315-K315-L315-M315-N315) | P315: =IF(OR(O315="",C315=""),"",O315*C315) | Q315: =Q314-E315 | R315: =IF(OR(J315="",Q315=""),"",J315-Q315) | S315: =IF(D315="",S314,S314+D315) | T315: =IF(OR(L315="",S315=""),"",L315-S315) | U315: =IF(F315="",U314,U314+F315) | V315: =IF(OR(N315="",U315=""),"",N315-U315) | W315: =IF(OR(C315="",C315=0,'Daily Data'!J315=""),"",'Daily Data'!J315/C315) | X315: =IF(OR(C315="",C315=0,'Daily Data'!K315=""),"",'Daily Data'!K315/C315) | Y315: =IF(OR(F315="",W315="",X315=""),"",F315-W315-X315) | Z315: 354.93 | AA315: 62.63 | AB315: =Z315+AA315 | AC315: =IF(OR(E315="",E315=0,AB315=""),"",E315*365/(AB315*1000000)) | AD315: =IF(OR(O315="",O315=0,AB315=""),"",(AB315*1000000)/O315) | AE315: =IF(H315="","",(Team_Genesis-H315)/1000000) | AF315: =IF(OR(O315="",AE315=""),"",(O315-AE315*1000000)/1000000)
A316: 45970 | B316: =IF('Daily Data'!E316="","",'Daily Data'!E316) | C316: 40.06 | D316: 42278.57 | E316: 25894.772 | F316: 972.6213 | H316: =SUM($G$4:G316) | I316: 1000000000 | J316: =J315-E316 | K316: 60000000 | L316: 34831433 | M316: 3000000 | N316: 483233.2 | O316: =IF(OR(I316="",J316="",L316="",N316=""),"",I316-J316-K316-L316-M316-N316) | P316: =IF(OR(O316="",C316=""),"",O316*C316) | Q316: =Q315-E316 | R316: =IF(OR(J316="",Q316=""),"",J316-Q316) | S316: =IF(D316="",S315,S315+D316) | T316: =IF(OR(L316="",S316=""),"",L316-S316) | U316: =IF(F316="",U315,U315+F316) | V316: =IF(OR(N316="",U316=""),"",N316-U316) | W316: =IF(OR(C316="",C316=0,'Daily Data'!J316=""),"",'Daily Data'!J316/C316) | X316: =IF(OR(C316="",C316=0,'Daily Data'!K316=""),"",'Daily Data'!K316/C316) | Y316: =IF(OR(F316="",W316="",X316=""),"",F316-W316-X316) | Z316: 354.93 | AA316: 62.63 | AB316: =Z316+AA316 | AC316: =IF(OR(E316="",E316=0,AB316=""),"",E316*365/(AB316*1000000)) | AD316: =IF(OR(O316="",O316=0,AB316=""),"",(AB316*1000000)/O316) | AE316: =IF(H316="","",(Team_Genesis-H316)/1000000) | AF316: =IF(OR(O316="",AE316=""),"",(O316-AE316*1000000)/1000000)
A317: 45971 | B317: =IF('Daily Data'!E317="","",'Daily Data'!E317) | C317: 41.98 | D317: 58760.44 | E317: 25893.859 | F317: 1115.504 | H317: =SUM($G$4:G317) | I317: 1000000000 | J317: =J316-E317 | K317: 60000000 | L317: 34889689 | M317: 3000000 | N317: 484348.7 | O317: =IF(OR(I317="",J317="",L317="",N317=""),"",I317-J317-K317-L317-M317-N317) | P317: =IF(OR(O317="",C317=""),"",O317*C317) | Q317: =Q316-E317 | R317: =IF(OR(J317="",Q317=""),"",J317-Q317) | S317: =IF(D317="",S316,S316+D317) | T317: =IF(OR(L317="",S317=""),"",L317-S317) | U317: =IF(F317="",U316,U316+F317) | V317: =IF(OR(N317="",U317=""),"",N317-U317) | W317: =IF(OR(C317="",C317=0,'Daily Data'!J317=""),"",'Daily Data'!J317/C317) | X317: =IF(OR(C317="",C317=0,'Daily Data'!K317=""),"",'Daily Data'!K317/C317) | Y317: =IF(OR(F317="",W317="",X317=""),"",F317-W317-X317) | Z317: 354.93 | AA317: 62.63 | AB317: =Z317+AA317 | AC317: =IF(OR(E317="",E317=0,AB317=""),"",E317*365/(AB317*1000000)) | AD317: =IF(OR(O317="",O317=0,AB317=""),"",(AB317*1000000)/O317) | AE317: =IF(H317="","",(Team_Genesis-H317)/1000000) | AF317: =IF(OR(O317="",AE317=""),"",(O317-AE317*1000000)/1000000)
A318: 45972 | B318: =IF('Daily Data'!E318="","",'Daily Data'!E318) | C318: 40.99 | D318: 65665.93 | E318: 25897.845 | F318: 1227.8531 | H318: =SUM($G$4:G318) | I318: 1000000000 | J318: =J317-E318 | K318: 60000000 | L318: 34955481 | M318: 3000000 | N318: 485576.56 | O318: =IF(OR(I318="",J318="",L318="",N318=""),"",I318-J318-K318-L318-M318-N318) | P318: =IF(OR(O318="",C318=""),"",O318*C318) | Q318: =Q317-E318 | R318: =IF(OR(J318="",Q318=""),"",J318-Q318) | S318: =IF(D318="",S317,S317+D318) | T318: =IF(OR(L318="",S318=""),"",L318-S318) | U318: =IF(F318="",U317,U317+F318) | V318: =IF(OR(N318="",U318=""),"",N318-U318) | W318: =IF(OR(C318="",C318=0,'Daily Data'!J318=""),"",'Daily Data'!J318/C318) | X318: =IF(OR(C318="",C318=0,'Daily Data'!K318=""),"",'Daily Data'!K318/C318) | Y318: =IF(OR(F318="",W318="",X318=""),"",F318-W318-X318) | Z318: 354.93 | AA318: 62.63 | AB318: =Z318+AA318 | AC318: =IF(OR(E318="",E318=0,AB318=""),"",E318*365/(AB318*1000000)) | AD318: =IF(OR(O318="",O318=0,AB318=""),"",(AB318*1000000)/O318) | AE318: =IF(H318="","",(Team_Genesis-H318)/1000000) | AF318: =IF(OR(O318="",AE318=""),"",(O318-AE318*1000000)/1000000)
A319: 45973 | B319: =IF('Daily Data'!E319="","",'Daily Data'!E319) | C319: 38.76 | D319: 57050.12 | E319: 25950.145 | F319: 1130.4074 | H319: =SUM($G$4:G319) | I319: 1000000000 | J319: =J318-E319 | K319: 60000000 | L319: 35011837 | M319: 3000000 | N319: 486706.96 | O319: =IF(OR(I319="",J319="",L319="",N319=""),"",I319-J319-K319-L319-M319-N319) | P319: =IF(OR(O319="",C319=""),"",O319*C319) | Q319: =Q318-E319 | R319: =IF(OR(J319="",Q319=""),"",J319-Q319) | S319: =IF(D319="",S318,S318+D319) | T319: =IF(OR(L319="",S319=""),"",L319-S319) | U319: =IF(F319="",U318,U318+F319) | V319: =IF(OR(N319="",U319=""),"",N319-U319) | W319: =IF(OR(C319="",C319=0,'Daily Data'!J319=""),"",'Daily Data'!J319/C319) | X319: =IF(OR(C319="",C319=0,'Daily Data'!K319=""),"",'Daily Data'!K319/C319) | Y319: =IF(OR(F319="",W319="",X319=""),"",F319-W319-X319) | Z319: 354.93 | AA319: 62.63 | AB319: =Z319+AA319 | AC319: =IF(OR(E319="",E319=0,AB319=""),"",E319*365/(AB319*1000000)) | AD319: =IF(OR(O319="",O319=0,AB319=""),"",(AB319*1000000)/O319) | AE319: =IF(H319="","",(Team_Genesis-H319)/1000000) | AF319: =IF(OR(O319="",AE319=""),"",(O319-AE319*1000000)/1000000)
A320: 45974 | B320: =IF('Daily Data'!E320="","",'Daily Data'!E320) | C320: 38.17 | D320: 95270.13 | E320: 25638.153 | F320: 1508.7648 | H320: =SUM($G$4:G320) | I320: 1000000000 | J320: =J319-E320 | K320: 60000000 | L320: 35109692 | M320: 3000000 | N320: 488215.73 | O320: =IF(OR(I320="",J320="",L320="",N320=""),"",I320-J320-K320-L320-M320-N320) | P320: =IF(OR(O320="",C320=""),"",O320*C320) | Q320: =Q319-E320 | R320: =IF(OR(J320="",Q320=""),"",J320-Q320) | S320: =IF(D320="",S319,S319+D320) | T320: =IF(OR(L320="",S320=""),"",L320-S320) | U320: =IF(F320="",U319,U319+F320) | V320: =IF(OR(N320="",U320=""),"",N320-U320) | W320: =IF(OR(C320="",C320=0,'Daily Data'!J320=""),"",'Daily Data'!J320/C320) | X320: =IF(OR(C320="",C320=0,'Daily Data'!K320=""),"",'Daily Data'!K320/C320) | Y320: =IF(OR(F320="",W320="",X320=""),"",F320-W320-X320) | Z320: 354.93 | AA320: 62.63 | AB320: =Z320+AA320 | AC320: =IF(OR(E320="",E320=0,AB320=""),"",E320*365/(AB320*1000000)) | AD320: =IF(OR(O320="",O320=0,AB320=""),"",(AB320*1000000)/O320) | AE320: =IF(H320="","",(Team_Genesis-H320)/1000000) | AF320: =IF(OR(O320="",AE320=""),"",(O320-AE320*1000000)/1000000)
A321: 45975 | B321: =IF('Daily Data'!E321="","",'Daily Data'!E321) | C321: 38.24 | D321: 101425.41 | E321: 25446.186 | F321: 705.1372 | H321: =SUM($G$4:G321) | I321: 1000000000 | J321: =J320-E321 | K321: 60000000 | L321: 35207988 | M321: 3000000 | N321: 488920.87 | O321: =IF(OR(I321="",J321="",L321="",N321=""),"",I321-J321-K321-L321-M321-N321) | P321: =IF(OR(O321="",C321=""),"",O321*C321) | Q321: =Q320-E321 | R321: =IF(OR(J321="",Q321=""),"",J321-Q321) | S321: =IF(D321="",S320,S320+D321) | T321: =IF(OR(L321="",S321=""),"",L321-S321) | U321: =IF(F321="",U320,U320+F321) | V321: =IF(OR(N321="",U321=""),"",N321-U321) | W321: =IF(OR(C321="",C321=0,'Daily Data'!J321=""),"",'Daily Data'!J321/C321) | X321: =IF(OR(C321="",C321=0,'Daily Data'!K321=""),"",'Daily Data'!K321/C321) | Y321: =IF(OR(F321="",W321="",X321=""),"",F321-W321-X321) | Z321: 354.93 | AA321: 62.63 | AB321: =Z321+AA321 | AC321: =IF(OR(E321="",E321=0,AB321=""),"",E321*365/(AB321*1000000)) | AD321: =IF(OR(O321="",O321=0,AB321=""),"",(AB321*1000000)/O321) | AE321: =IF(H321="","",(Team_Genesis-H321)/1000000) | AF321: =IF(OR(O321="",AE321=""),"",(O321-AE321*1000000)/1000000)
A322: 45976 | B322: =IF('Daily Data'!E322="","",'Daily Data'!E322) | C322: 37.67 | D322: 34839.66 | E322: 25324.602 | F322: 2028.2638 | H322: =SUM($G$4:G322) | I322: 1000000000 | J322: =J321-E322 | K322: 60000000 | L322: 35243906 | M322: 3000000 | N322: 490949.13 | O322: =IF(OR(I322="",J322="",L322="",N322=""),"",I322-J322-K322-L322-M322-N322) | P322: =IF(OR(O322="",C322=""),"",O322*C322) | Q322: =Q321-E322 | R322: =IF(OR(J322="",Q322=""),"",J322-Q322) | S322: =IF(D322="",S321,S321+D322) | T322: =IF(OR(L322="",S322=""),"",L322-S322) | U322: =IF(F322="",U321,U321+F322) | V322: =IF(OR(N322="",U322=""),"",N322-U322) | W322: =IF(OR(C322="",C322=0,'Daily Data'!J322=""),"",'Daily Data'!J322/C322) | X322: =IF(OR(C322="",C322=0,'Daily Data'!K322=""),"",'Daily Data'!K322/C322) | Y322: =IF(OR(F322="",W322="",X322=""),"",F322-W322-X322) | Z322: 354.93 | AA322: 62.63 | AB322: =Z322+AA322 | AC322: =IF(OR(E322="",E322=0,AB322=""),"",E322*365/(AB322*1000000)) | AD322: =IF(OR(O322="",O322=0,AB322=""),"",(AB322*1000000)/O322) | AE322: =IF(H322="","",(Team_Genesis-H322)/1000000) | AF322: =IF(OR(O322="",AE322=""),"",(O322-AE322*1000000)/1000000)
A323: 45977 | B323: =IF('Daily Data'!E323="","",'Daily Data'!E323) | C323: 38.39 | D323: 50364.81 | E323: 25348.006 | F323: 368.3821 | H323: =SUM($G$4:G323) | I323: 1000000000 | J323: =J322-E323 | K323: 60000000 | L323: 35296567 | M323: 3000000 | N323: 491317.51 | O323: =IF(OR(I323="",J323="",L323="",N323=""),"",I323-J323-K323-L323-M323-N323) | P323: =IF(OR(O323="",C323=""),"",O323*C323) | Q323: =Q322-E323 | R323: =IF(OR(J323="",Q323=""),"",J323-Q323) | S323: =IF(D323="",S322,S322+D323) | T323: =IF(OR(L323="",S323=""),"",L323-S323) | U323: =IF(F323="",U322,U322+F323) | V323: =IF(OR(N323="",U323=""),"",N323-U323) | W323: =IF(OR(C323="",C323=0,'Daily Data'!J323=""),"",'Daily Data'!J323/C323) | X323: =IF(OR(C323="",C323=0,'Daily Data'!K323=""),"",'Daily Data'!K323/C323) | Y323: =IF(OR(F323="",W323="",X323=""),"",F323-W323-X323) | Z323: 354.93 | AA323: 62.63 | AB323: =Z323+AA323 | AC323: =IF(OR(E323="",E323=0,AB323=""),"",E323*365/(AB323*1000000)) | AD323: =IF(OR(O323="",O323=0,AB323=""),"",(AB323*1000000)/O323) | AE323: =IF(H323="","",(Team_Genesis-H323)/1000000) | AF323: =IF(OR(O323="",AE323=""),"",(O323-AE323*1000000)/1000000)
A324: 45978 | B324: =IF('Daily Data'!E324="","",'Daily Data'!E324) | C324: 38.69 | D324: 73999.24 | E324: 25332.247 | F324: 1015.1872 | H324: =SUM($G$4:G324) | I324: 1000000000 | J324: =J323-E324 | K324: 60000000 | L324: 35367094 | M324: 3000000 | N324: 492332.7 | O324: =IF(OR(I324="",J324="",L324="",N324=""),"",I324-J324-K324-L324-M324-N324) | P324: =IF(OR(O324="",C324=""),"",O324*C324) | Q324: =Q323-E324 | R324: =IF(OR(J324="",Q324=""),"",J324-Q324) | S324: =IF(D324="",S323,S323+D324) | T324: =IF(OR(L324="",S324=""),"",L324-S324) | U324: =IF(F324="",U323,U323+F324) | V324: =IF(OR(N324="",U324=""),"",N324-U324) | W324: =IF(OR(C324="",C324=0,'Daily Data'!J324=""),"",'Daily Data'!J324/C324) | X324: =IF(OR(C324="",C324=0,'Daily Data'!K324=""),"",'Daily Data'!K324/C324) | Y324: =IF(OR(F324="",W324="",X324=""),"",F324-W324-X324) | Z324: 354.93 | AA324: 62.63 | AB324: =Z324+AA324 | AC324: =IF(OR(E324="",E324=0,AB324=""),"",E324*365/(AB324*1000000)) | AD324: =IF(OR(O324="",O324=0,AB324=""),"",(AB324*1000000)/O324) | AE324: =IF(H324="","",(Team_Genesis-H324)/1000000) | AF324: =IF(OR(O324="",AE324=""),"",(O324-AE324*1000000)/1000000)
A325: 45979 | B325: =IF('Daily Data'!E325="","",'Daily Data'!E325) | C325: 39.07 | D325: 73038.41 | E325: 25303.995 | F325: 689.8976 | H325: =SUM($G$4:G325) | I325: 1000000000 | J325: =J324-E325 | K325: 60000000 | L325: 35441467 | M325: 3000000 | N325: 493022.6 | O325: =IF(OR(I325="",J325="",L325="",N325=""),"",I325-J325-K325-L325-M325-N325) | P325: =IF(OR(O325="",C325=""),"",O325*C325) | Q325: =Q324-E325 | R325: =IF(OR(J325="",Q325=""),"",J325-Q325) | S325: =IF(D325="",S324,S324+D325) | T325: =IF(OR(L325="",S325=""),"",L325-S325) | U325: =IF(F325="",U324,U324+F325) | V325: =IF(OR(N325="",U325=""),"",N325-U325) | W325: =IF(OR(C325="",C325=0,'Daily Data'!J325=""),"",'Daily Data'!J325/C325) | X325: =IF(OR(C325="",C325=0,'Daily Data'!K325=""),"",'Daily Data'!K325/C325) | Y325: =IF(OR(F325="",W325="",X325=""),"",F325-W325-X325) | Z325: 354.93 | AA325: 62.63 | AB325: =Z325+AA325 | AC325: =IF(OR(E325="",E325=0,AB325=""),"",E325*365/(AB325*1000000)) | AD325: =IF(OR(O325="",O325=0,AB325=""),"",(AB325*1000000)/O325) | AE325: =IF(H325="","",(Team_Genesis-H325)/1000000) | AF325: =IF(OR(O325="",AE325=""),"",(O325-AE325*1000000)/1000000)
... A342: 45996 | B342: =IF('Daily Data'!E342="","",'Daily Data'!E342) | C342: 33.49 | D342: 63142.73 | E342: 26286.839 | F342: 1171.0211 | H342: =SUM($G$4:G342) | I342: 1000000000 | J342: =J341-E342 | K342: 60000000 | L342: 36495512 | M342: 3000000 | N342: 514153.9 | O342: =IF(OR(I342="",J342="",L342="",N342=""),"",I342-J342-K342-L342-M342-N342) | P342: =IF(OR(O342="",C342=""),"",O342*C342) | Q342: =Q341-E342 | R342: =IF(OR(J342="",Q342=""),"",J342-Q342) | S342: =IF(D342="",S341,S341+D342) | T342: =IF(OR(L342="",S342=""),"",L342-S342) | U342: =IF(F342="",U341,U341+F342) | V342: =IF(OR(N342="",U342=""),"",N342-U342) | W342: =IF(OR(C342="",C342=0,'Daily Data'!J342=""),"",'Daily Data'!J342/C342) | X342: =IF(OR(C342="",C342=0,'Daily Data'!K342=""),"",'Daily Data'!K342/C342) | Y342: =IF(OR(F342="",W342="",X342=""),"",F342-W342-X342) | Z342: 367.47 | AA342: 64.85 | AB342: =Z342+AA342 | AC342: =IF(OR(E342="",E342=0,AB342=""),"",E342*365/(AB342*1000000)) | AD342: =IF(OR(O342="",O342=0,AB342=""),"",(AB342*1000000)/O342) | AE342: =IF(H342="","",(Team_Genesis-H342)/1000000) | AF342: =IF(OR(O342="",AE342=""),"",(O342-AE342*1000000)/1000000)
A343: 45997 | B343: =IF('Daily Data'!E343="","",'Daily Data'!E343) | C343: 30.66 | D343: 21702.43 | E343: 26453.385 | F343: 1209.6382 | G343: 0 | H343: =SUM($G$4:G343) | I343: 1000000000 | J343: =J342-E343 | K343: 60000000 | L343: 36516646 | M343: 3000000 | N343: 515363.54 | O343: =IF(OR(I343="",J343="",L343="",N343=""),"",I343-J343-K343-L343-M343-N343) | P343: =IF(OR(O343="",C343=""),"",O343*C343) | Q343: =Q342-E343 | R343: =IF(OR(J343="",Q343=""),"",J343-Q343) | S343: =IF(D343="",S342,S342+D343) | T343: =IF(OR(L343="",S343=""),"",L343-S343) | U343: =IF(F343="",U342,U342+F343) | V343: =IF(OR(N343="",U343=""),"",N343-U343) | W343: =IF(OR(C343="",C343=0,'Daily Data'!J343=""),"",'Daily Data'!J343/C343) | X343: =IF(OR(C343="",C343=0,'Daily Data'!K343=""),"",'Daily Data'!K343/C343) | Y343: =IF(OR(F343="",W343="",X343=""),"",F343-W343-X343) | Z343: 367.47 | AA343: 64.85 | AB343: =Z343+AA343 | AC343: =IF(OR(E343="",E343=0,AB343=""),"",E343*365/(AB343*1000000)) | AD343: =IF(OR(O343="",O343=0,AB343=""),"",(AB343*1000000)/O343) | AE343: =IF(H343="","",(Team_Genesis-H343)/1000000) | AF343: =IF(OR(O343="",AE343=""),"",(O343-AE343*1000000)/1000000)
A344: 45998 | B344: =IF('Daily Data'!E344="","",'Daily Data'!E344) | C344: 31.12 | D344: 58504.27 | E344: 26424.927 | F344: 969.9399 | H344: =SUM($G$4:G344) | I344: 1000000000 | J344: =J343-E344 | K344: 60000000 | L344: 36575097 | M344: 3000000 | N344: 516333.48 | O344: =IF(OR(I344="",J344="",L344="",N344=""),"",I344-J344-K344-L344-M344-N344) | P344: =IF(OR(O344="",C344=""),"",O344*C344) | Q344: =Q343-E344 | R344: =IF(OR(J344="",Q344=""),"",J344-Q344) | S344: =IF(D344="",S343,S343+D344) | T344: =IF(OR(L344="",S344=""),"",L344-S344) | U344: =IF(F344="",U343,U343+F344) | V344: =IF(OR(N344="",U344=""),"",N344-U344) | W344: =IF(OR(C344="",C344=0,'Daily Data'!J344=""),"",'Daily Data'!J344/C344) | X344: =IF(OR(C344="",C344=0,'Daily Data'!K344=""),"",'Daily Data'!K344/C344) | Y344: =IF(OR(F344="",W344="",X344=""),"",F344-W344-X344) | Z344: 367.47 | AA344: 64.85 | AB344: =Z344+AA344 | AC344: =IF(OR(E344="",E344=0,AB344=""),"",E344*365/(AB344*1000000)) | AD344: =IF(OR(O344="",O344=0,AB344=""),"",(AB344*1000000)/O344) | AE344: =IF(H344="","",(Team_Genesis-H344)/1000000) | AF344: =IF(OR(O344="",AE344=""),"",(O344-AE344*1000000)/1000000)
A345: 45999 | B345: =IF('Daily Data'!E345="","",'Daily Data'!E345) | C345: 29.91 | D345: 58433.15 | E345: 0 | F345: -4131.1617 | H345: =SUM($G$4:G345) | I345: 1000000000 | J345: =J344-E345 | K345: 60000000 | L345: 36821105 | M345: 3000000 | N345: 517806.6 | O345: =IF(OR(I345="",J345="",L345="",N345=""),"",I345-J345-K345-L345-M345-N345) | P345: =IF(OR(O345="",C345=""),"",O345*C345) | Q345: =Q344-E345 | R345: =IF(OR(J345="",Q345=""),"",J345-Q345) | S345: =IF(D345="",S344,S344+D345) | T345: =IF(OR(L345="",S345=""),"",L345-S345) | U345: =IF(F345="",U344,U344+F345) | V345: =IF(OR(N345="",U345=""),"",N345-U345) | W345: =IF(OR(C345="",C345=0,'Daily Data'!J345=""),"",'Daily Data'!J345/C345) | X345: =IF(OR(C345="",C345=0,'Daily Data'!K345=""),"",'Daily Data'!K345/C345) | Y345: =IF(OR(F345="",W345="",X345=""),"",F345-W345-X345) | Z345: 367.47 | AA345: 64.85 | AB345: =Z345+AA345 | AC345: =IF(OR(E345="",E345=0,AB345=""),"",E345*365/(AB345*1000000)) | AD345: =IF(OR(O345="",O345=0,AB345=""),"",(AB345*1000000)/O345) | AE345: =IF(H345="","",(Team_Genesis-H345)/1000000) | AF345: =IF(OR(O345="",AE345=""),"",(O345-AE345*1000000)/1000000)
A346: 46000 | B346: =IF('Daily Data'!E346="","",'Daily Data'!E346) | C346: 27.95 | D346: 84868.58 | E346: 88711.846 | F346: 4131.1617 | H346: =SUM($G$4:G346) | I346: 1000000000 | J346: =J345-E346 | K346: 60000000 | L346: 36821105 | M346: 3000000 | N346: 521937.76 | O346: =IF(OR(I346="",J346="",L346="",N346=""),"",I346-J346-K346-L346-M346-N346) | P346: =IF(OR(O346="",C346=""),"",O346*C346) | Q346: =Q345-E346 | R346: =IF(OR(J346="",Q346=""),"",J346-Q346) | S346: =IF(D346="",S345,S345+D346) | T346: =IF(OR(L346="",S346=""),"",L346-S346) | U346: =IF(F346="",U345,U345+F346) | V346: =IF(OR(N346="",U346=""),"",N346-U346) | W346: =IF(OR(C346="",C346=0,'Daily Data'!J346=""),"",'Daily Data'!J346/C346) | X346: =IF(OR(C346="",C346=0,'Daily Data'!K346=""),"",'Daily Data'!K346/C346) | Y346: =IF(OR(F346="",W346="",X346=""),"",F346-W346-X346) | Z346: 367.47 | AA346: 64.85 | AB346: =Z346+AA346 | AC346: =IF(OR(E346="",E346=0,AB346=""),"",E346*365/(AB346*1000000)) | AD346: =IF(OR(O346="",O346=0,AB346=""),"",(AB346*1000000)/O346) | AE346: =IF(H346="","",(Team_Genesis-H346)/1000000) | AF346: =IF(OR(O346="",AE346=""),"",(O346-AE346*1000000)/1000000)
A347: 46001 | B347: =IF('Daily Data'!E347="","",'Daily Data'!E347) | C347: 27.9 | D347: 77372.82 | E347: 275.58 | F347: 0.5085 | H347: =SUM($G$4:G347) | I347: 1000000000 | J347: =J346-E347 | K347: 60000000 | L347: 36819850 | M347: 3000000 | N347: 521938.27 | O347: =IF(OR(I347="",J347="",L347="",N347=""),"",I347-J347-K347-L347-M347-N347) | P347: =IF(OR(O347="",C347=""),"",O347*C347) | Q347: =Q346-E347 | R347: =IF(OR(J347="",Q347=""),"",J347-Q347) | S347: =IF(D347="",S346,S346+D347) | T347: =IF(OR(L347="",S347=""),"",L347-S347) | U347: =IF(F347="",U346,U346+F347) | V347: =IF(OR(N347="",U347=""),"",N347-U347) | W347: =IF(OR(C347="",C347=0,'Daily Data'!J347=""),"",'Daily Data'!J347/C347) | X347: =IF(OR(C347="",C347=0,'Daily Data'!K347=""),"",'Daily Data'!K347/C347) | Y347: =IF(OR(F347="",W347="",X347=""),"",F347-W347-X347) | Z347: 367.47 | AA347: 64.85 | AB347: =Z347+AA347 | AC347: =IF(OR(E347="",E347=0,AB347=""),"",E347*365/(AB347*1000000)) | AD347: =IF(OR(O347="",O347=0,AB347=""),"",(AB347*1000000)/O347) | AE347: =IF(H347="","",(Team_Genesis-H347)/1000000) | AF347: =IF(OR(O347="",AE347=""),"",(O347-AE347*1000000)/1000000)
A348: 46002 | B348: =IF('Daily Data'!E348="","",'Daily Data'!E348) | C348: 28.03 | D348: 76238.06 | E348: 0 | F348: -4.9549 | H348: =SUM($G$4:G348) | I348: 1000000000 | J348: =J347-E348 | K348: 60000000 | L348: 36874341 | M348: 3000000 | N348: 521933.32 | O348: =IF(OR(I348="",J348="",L348="",N348=""),"",I348-J348-K348-L348-M348-N348) | P348: =IF(OR(O348="",C348=""),"",O348*C348) | Q348: =Q347-E348 | R348: =IF(OR(J348="",Q348=""),"",J348-Q348) | S348: =IF(D348="",S347,S347+D348) | T348: =IF(OR(L348="",S348=""),"",L348-S348) | U348: =IF(F348="",U347,U347+F348) | V348: =IF(OR(N348="",U348=""),"",N348-U348) | W348: =IF(OR(C348="",C348=0,'Daily Data'!J348=""),"",'Daily Data'!J348/C348) | X348: =IF(OR(C348="",C348=0,'Daily Data'!K348=""),"",'Daily Data'!K348/C348) | Y348: =IF(OR(F348="",W348="",X348=""),"",F348-W348-X348) | Z348: 367.47 | AA348: 64.85 | AB348: =Z348+AA348 | AC348: =IF(OR(E348="",E348=0,AB348=""),"",E348*365/(AB348*1000000)) | AD348: =IF(OR(O348="",O348=0,AB348=""),"",(AB348*1000000)/O348) | AE348: =IF(H348="","",(Team_Genesis-H348)/1000000) | AF348: =IF(OR(O348="",AE348=""),"",(O348-AE348*1000000)/1000000)
A349: 46003 | B349: =IF('Daily Data'!E349="","",'Daily Data'!E349) | C349: 29.13 | D349: 58888.81 | E349: 18059.735 | F349: 1445.5575 | H349: =SUM($G$4:G349) | I349: 1000000000 | J349: =J348-E349 | K349: 60000000 | L349: 36931526 | M349: 3000000 | N349: 523378.87 | O349: =IF(OR(I349="",J349="",L349="",N349=""),"",I349-J349-K349-L349-M349-N349) | P349: =IF(OR(O349="",C349=""),"",O349*C349) | Q349: =Q348-E349 | R349: =IF(OR(J349="",Q349=""),"",J349-Q349) | S349: =IF(D349="",S348,S348+D349) | T349: =IF(OR(L349="",S349=""),"",L349-S349) | U349: =IF(F349="",U348,U348+F349) | V349: =IF(OR(N349="",U349=""),"",N349-U349) | W349: =IF(OR(C349="",C349=0,'Daily Data'!J349=""),"",'Daily Data'!J349/C349) | X349: =IF(OR(C349="",C349=0,'Daily Data'!K349=""),"",'Daily Data'!K349/C349) | Y349: =IF(OR(F349="",W349="",X349=""),"",F349-W349-X349) | Z349: 367.47 | AA349: 64.85 | AB349: =Z349+AA349 | AC349: =IF(OR(E349="",E349=0,AB349=""),"",E349*365/(AB349*1000000)) | AD349: =IF(OR(O349="",O349=0,AB349=""),"",(AB349*1000000)/O349) | AE349: =IF(H349="","",(Team_Genesis-H349)/1000000) | AF349: =IF(OR(O349="",AE349=""),"",(O349-AE349*1000000)/1000000)
A350: 46004 | B350: =IF('Daily Data'!E350="","",'Daily Data'!E350) | C350: 28.74 | D350: 15306.92 | E350: 26452.147 | F350: 480.8023 | H350: =SUM($G$4:G350) | I350: 1000000000 | J350: =J349-E350 | K350: 60000000 | L350: 36946205 | M350: 3000000 | N350: 523859.68 | O350: =IF(OR(I350="",J350="",L350="",N350=""),"",I350-J350-K350-L350-M350-N350) | P350: =IF(OR(O350="",C350=""),"",O350*C350) | Q350: =Q349-E350 | R350: =IF(OR(J350="",Q350=""),"",J350-Q350) | S350: =IF(D350="",S349,S349+D350) | T350: =IF(OR(L350="",S350=""),"",L350-S350) | U350: =IF(F350="",U349,U349+F350) | V350: =IF(OR(N350="",U350=""),"",N350-U350) | W350: =IF(OR(C350="",C350=0,'Daily Data'!J350=""),"",'Daily Data'!J350/C350) | X350: =IF(OR(C350="",C350=0,'Daily Data'!K350=""),"",'Daily Data'!K350/C350) | Y350: =IF(OR(F350="",W350="",X350=""),"",F350-W350-X350) | Z350: 367.47 | AA350: 64.85 | AB350: =Z350+AA350 | AC350: =IF(OR(E350="",E350=0,AB350=""),"",E350*365/(AB350*1000000)) | AD350: =IF(OR(O350="",O350=0,AB350=""),"",(AB350*1000000)/O350) | AE350: =IF(H350="","",(Team_Genesis-H350)/1000000) | AF350: =IF(OR(O350="",AE350=""),"",(O350-AE350*1000000)/1000000)
A351: 46005 | B351: =IF('Daily Data'!E351="","",'Daily Data'!E351) | C351: 29.82 | D351: 32806.2 | E351: 26457.322 | F351: 1187.8446 | H351: =SUM($G$4:G351) | I351: 1000000000 | J351: =J350-E351 | K351: 60000000 | L351: 36980134 | M351: 3000000 | N351: 525047.52 | O351: =IF(OR(I351="",J351="",L351="",N351=""),"",I351-J351-K351-L351-M351-N351) | P351: =IF(OR(O351="",C351=""),"",O351*C351) | Q351: =Q350-E351 | R351: =IF(OR(J351="",Q351=""),"",J351-Q351) | S351: =IF(D351="",S350,S350+D351) | T351: =IF(OR(L351="",S351=""),"",L351-S351) | U351: =IF(F351="",U350,U350+F351) | V351: =IF(OR(N351="",U351=""),"",N351-U351) | W351: =IF(OR(C351="",C351=0,'Daily Data'!J351=""),"",'Daily Data'!J351/C351) | X351: =IF(OR(C351="",C351=0,'Daily Data'!K351=""),"",'Daily Data'!K351/C351) | Y351: =IF(OR(F351="",W351="",X351=""),"",F351-W351-X351) | Z351: 367.47 | AA351: 64.85 | AB351: =Z351+AA351 | AC351: =IF(OR(E351="",E351=0,AB351=""),"",E351*365/(AB351*1000000)) | AD351: =IF(OR(O351="",O351=0,AB351=""),"",(AB351*1000000)/O351) | AE351: =IF(H351="","",(Team_Genesis-H351)/1000000) | AF351: =IF(OR(O351="",AE351=""),"",(O351-AE351*1000000)/1000000)
A352: 46006 | B352: =IF('Daily Data'!E352="","",'Daily Data'!E352) | C352: 29.04 | D352: 73873.39 | E352: 26379.945 | F352: 1342.3667 | H352: =SUM($G$4:G352) | I352: 1000000000 | J352: =J351-E352 | K352: 60000000 | L352: 37054037 | M352: 3000000 | N352: 526389.89 | O352: =IF(OR(I352="",J352="",L352="",N352=""),"",I352-J352-K352-L352-M352-N352) | P352: =IF(OR(O352="",C352=""),"",O352*C352) | Q352: =Q351-E352 | R352: =IF(OR(J352="",Q352=""),"",J352-Q352) | S352: =IF(D352="",S351,S351+D352) | T352: =IF(OR(L352="",S352=""),"",L352-S352) | U352: =IF(F352="",U351,U351+F352) | V352: =IF(OR(N352="",U352=""),"",N352-U352) | W352: =IF(OR(C352="",C352=0,'Daily Data'!J352=""),"",'Daily Data'!J352/C352) | X352: =IF(OR(C352="",C352=0,'Daily Data'!K352=""),"",'Daily Data'!K352/C352) | Y352: =IF(OR(F352="",W352="",X352=""),"",F352-W352-X352) | Z352: 367.47 | AA352: 64.85 | AB352: =Z352+AA352 | AC352: =IF(OR(E352="",E352=0,AB352=""),"",E352*365/(AB352*1000000)) | AD352: =IF(OR(O352="",O352=0,AB352=""),"",(AB352*1000000)/O352) | AE352: =IF(H352="","",(Team_Genesis-H352)/1000000) | AF352: =IF(OR(O352="",AE352=""),"",(O352-AE352*1000000)/1000000)
A353: 46007 | B353: =IF('Daily Data'!E353="","",'Daily Data'!E353) | C353: 27.49 | D353: 56352.5 | E353: 26460.085 | F353: 1653.3904 | H353: =SUM($G$4:G353) | I353: 1000000000 | J353: =J352-E353 | K353: 60000000 | L353: 37110590 | M353: 3000000 | N353: 528043.28 | O353: =IF(OR(I353="",J353="",L353="",N353=""),"",I353-J353-K353-L353-M353-N353) | P353: =IF(OR(O353="",C353=""),"",O353*C353) | Q353: =Q352-E353 | R353: =IF(OR(J353="",Q353=""),"",J353-Q353) | S353: =IF(D353="",S352,S352+D353) | T353: =IF(OR(L353="",S353=""),"",L353-S353) | U353: =IF(F353="",U352,U352+F353) | V353: =IF(OR(N353="",U353=""),"",N353-U353) | W353: =IF(OR(C353="",C353=0,'Daily Data'!J353=""),"",'Daily Data'!J353/C353) | X353: =IF(OR(C353="",C353=0,'Daily Data'!K353=""),"",'Daily Data'!K353/C353) | Y353: =IF(OR(F353="",W353="",X353=""),"",F353-W353-X353) | Z353: 367.47 | AA353: 64.85 | AB353: =Z353+AA353 | AC353: =IF(OR(E353="",E353=0,AB353=""),"",E353*365/(AB353*1000000)) | AD353: =IF(OR(O353="",O353=0,AB353=""),"",(AB353*1000000)/O353) | AE353: =IF(H353="","",(Team_Genesis-H353)/1000000) | AF353: =IF(OR(O353="",AE353=""),"",(O353-AE353*1000000)/1000000)
A354: 46008 | B354: =IF('Daily Data'!E354="","",'Daily Data'!E354) | C354: 26.45 | D354: 84365.17 | E354: 26428.425 | F354: 1593.7829 | H354: =SUM($G$4:G354) | I354: 1000000000 | J354: =J353-E354 | K354: 60000000 | L354: 37194425 | M354: 3000000 | N354: 529637.06 | O354: =IF(OR(I354="",J354="",L354="",N354=""),"",I354-J354-K354-L354-M354-N354) | P354: =IF(OR(O354="",C354=""),"",O354*C354) | Q354: =Q353-E354 | R354: =IF(OR(J354="",Q354=""),"",J354-Q354) | S354: =IF(D354="",S353,S353+D354) | T354: =IF(OR(L354="",S354=""),"",L354-S354) | U354: =IF(F354="",U353,U353+F354) | V354: =IF(OR(N354="",U354=""),"",N354-U354) | W354: =IF(OR(C354="",C354=0,'Daily Data'!J354=""),"",'Daily Data'!J354/C354) | X354: =IF(OR(C354="",C354=0,'Daily Data'!K354=""),"",'Daily Data'!K354/C354) | Y354: =IF(OR(F354="",W354="",X354=""),"",F354-W354-X354) | Z354: 367.47 | AA354: 64.85 | AB354: =Z354+AA354 | AC354: =IF(OR(E354="",E354=0,AB354=""),"",E354*365/(AB354*1000000)) | AD354: =IF(OR(O354="",O354=0,AB354=""),"",(AB354*1000000)/O354) | AE354: =IF(H354="","",(Team_Genesis-H354)/1000000) | AF354: =IF(OR(O354="",AE354=""),"",(O354-AE354*1000000)/1000000)
A355: 46009 | B355: =IF('Daily Data'!E355="","",'Daily Data'!E355) | C355: 24.56 | D355: 100632.9 | E355: 26437.158 | F355: 2179.0652 | H355: =SUM($G$4:G355) | I355: 1000000000 | J355: =J354-E355 | K355: 60000000 | L355: 37295350 | M355: 3000000 | N355: 531816.13 | O355: =IF(OR(I355="",J355="",L355="",N355=""),"",I355-J355-K355-L355-M355-N355) | P355: =IF(OR(O355="",C355=""),"",O355*C355) | Q355: =Q354-E355 | R355: =IF(OR(J355="",Q355=""),"",J355-Q355) | S355: =IF(D355="",S354,S354+D355) | T355: =IF(OR(L355="",S355=""),"",L355-S355) | U355: =IF(F355="",U354,U354+F355) | V355: =IF(OR(N355="",U355=""),"",N355-U355) | W355: =IF(OR(C355="",C355=0,'Daily Data'!J355=""),"",'Daily Data'!J355/C355) | X355: =IF(OR(C355="",C355=0,'Daily Data'!K355=""),"",'Daily Data'!K355/C355) | Y355: =IF(OR(F355="",W355="",X355=""),"",F355-W355-X355) | Z355: 367.47 | AA355: 64.85 | AB355: =Z355+AA355 | AC355: =IF(OR(E355="",E355=0,AB355=""),"",E355*365/(AB355*1000000)) | AD355: =IF(OR(O355="",O355=0,AB355=""),"",(AB355*1000000)/O355) | AE355: =IF(H355="","",(Team_Genesis-H355)/1000000) | AF355: =IF(OR(O355="",AE355=""),"",(O355-AE355*1000000)/1000000)
... A373: 46027 | B373: =IF('Daily Data'!E373="","",'Daily Data'!E373) | C373: 26.58 | D373: 78485.08 | E373: 26387.372 | F373: 901.9737 | H373: =SUM($G$4:G373) | I373: 1000000000 | J373: =J372-E373 | K373: 60000000 | L373: 38120899 | M373: 3000000 | N373: 560686.68 | O373: =IF(OR(I373="",J373="",L373="",N373=""),"",I373-J373-K373-L373-M373-N373) | P373: =IF(OR(O373="",C373=""),"",O373*C373) | Q373: =Q372-E373 | R373: =IF(OR(J373="",Q373=""),"",J373-Q373) | S373: =IF(D373="",S372,S372+D373) | T373: =IF(OR(L373="",S373=""),"",L373-S373) | U373: =IF(F373="",U372,U372+F373) | V373: =IF(OR(N373="",U373=""),"",N373-U373) | W373: =IF(OR(C373="",C373=0,'Daily Data'!J373=""),"",'Daily Data'!J373/C373) | X373: =IF(OR(C373="",C373=0,'Daily Data'!K373=""),"",'Daily Data'!K373/C373) | Y373: =IF(OR(F373="",W373="",X373=""),"",F373-W373-X373) | Z373: 372.43 | AA373: 65.72 | AB373: =Z373+AA373 | AC373: =IF(OR(E373="",E373=0,AB373=""),"",E373*365/(AB373*1000000)) | AD373: =IF(OR(O373="",O373=0,AB373=""),"",(AB373*1000000)/O373) | AE373: =IF(H373="","",(Team_Genesis-H373)/1000000) | AF373: =IF(OR(O373="",AE373=""),"",(O373-AE373*1000000)/1000000)
A374: 46028 | B374: =IF('Daily Data'!E374="","",'Daily Data'!E374) | C374: 26.72 | D374: 88011.81 | E374: 26389.365 | F374: 2534.2663 | G374: 1125766 | H374: =SUM($G$4:G374) | I374: 1000000000 | J374: =J373-E374 | K374: 60000000 | L374: 38212023 | M374: 3000000 | N374: 563220.94 | O374: =IF(OR(I374="",J374="",L374="",N374=""),"",I374-J374-K374-L374-M374-N374) | P374: =IF(OR(O374="",C374=""),"",O374*C374) | Q374: =Q373-E374 | R374: =IF(OR(J374="",Q374=""),"",J374-Q374) | S374: =IF(D374="",S373,S373+D374) | T374: =IF(OR(L374="",S374=""),"",L374-S374) | U374: =IF(F374="",U373,U373+F374) | V374: =IF(OR(N374="",U374=""),"",N374-U374) | W374: =IF(OR(C374="",C374=0,'Daily Data'!J374=""),"",'Daily Data'!J374/C374) | X374: =IF(OR(C374="",C374=0,'Daily Data'!K374=""),"",'Daily Data'!K374/C374) | Y374: =IF(OR(F374="",W374="",X374=""),"",F374-W374-X374) | Z374: 372.43 | AA374: 65.72 | AB374: =Z374+AA374 | AC374: =IF(OR(E374="",E374=0,AB374=""),"",E374*365/(AB374*1000000)) | AD374: =IF(OR(O374="",O374=0,AB374=""),"",(AB374*1000000)/O374) | AE374: =IF(H374="","",(Team_Genesis-H374)/1000000) | AF374: =IF(OR(O374="",AE374=""),"",(O374-AE374*1000000)/1000000)
A375: 46029 | B375: =IF('Daily Data'!E375="","",'Daily Data'!E375) | C375: 28.01 | D375: 68872.57 | E375: 26373.048 | F375: 2947.2225 | H375: =SUM($G$4:G375) | I375: 1000000000 | J375: =J374-E375 | K375: 60000000 | L375: 38277974 | M375: 3000000 | N375: 566168.17 | O375: =IF(OR(I375="",J375="",L375="",N375=""),"",I375-J375-K375-L375-M375-N375) | P375: =IF(OR(O375="",C375=""),"",O375*C375) | Q375: =Q374-E375 | R375: =IF(OR(J375="",Q375=""),"",J375-Q375) | S375: =IF(D375="",S374,S374+D375) | T375: =IF(OR(L375="",S375=""),"",L375-S375) | U375: =IF(F375="",U374,U374+F375) | V375: =IF(OR(N375="",U375=""),"",N375-U375) | W375: =IF(OR(C375="",C375=0,'Daily Data'!J375=""),"",'Daily Data'!J375/C375) | X375: =IF(OR(C375="",C375=0,'Daily Data'!K375=""),"",'Daily Data'!K375/C375) | Y375: =IF(OR(F375="",W375="",X375=""),"",F375-W375-X375) | Z375: 372.43 | AA375: 65.72 | AB375: =Z375+AA375 | AC375: =IF(OR(E375="",E375=0,AB375=""),"",E375*365/(AB375*1000000)) | AD375: =IF(OR(O375="",O375=0,AB375=""),"",(AB375*1000000)/O375) | AE375: =IF(H375="","",(Team_Genesis-H375)/1000000) | AF375: =IF(OR(O375="",AE375=""),"",(O375-AE375*1000000)/1000000)
A376: 46030 | B376: =IF('Daily Data'!E376="","",'Daily Data'!E376) | C376: 26.79 | D376: 80019.35 | E376: 26374.641 | F376: 1968.7768 | H376: =SUM($G$4:G376) | I376: 1000000000 | J376: =J375-E376 | K376: 60000000 | L376: 38357236 | M376: 3000000 | N376: 568136.94 | O376: =IF(OR(I376="",J376="",L376="",N376=""),"",I376-J376-K376-L376-M376-N376) | P376: =IF(OR(O376="",C376=""),"",O376*C376) | Q376: =Q375-E376 | R376: =IF(OR(J376="",Q376=""),"",J376-Q376) | S376: =IF(D376="",S375,S375+D376) | T376: =IF(OR(L376="",S376=""),"",L376-S376) | U376: =IF(F376="",U375,U375+F376) | V376: =IF(OR(N376="",U376=""),"",N376-U376) | W376: =IF(OR(C376="",C376=0,'Daily Data'!J376=""),"",'Daily Data'!J376/C376) | X376: =IF(OR(C376="",C376=0,'Daily Data'!K376=""),"",'Daily Data'!K376/C376) | Y376: =IF(OR(F376="",W376="",X376=""),"",F376-W376-X376) | Z376: 372.43 | AA376: 65.72 | AB376: =Z376+AA376 | AC376: =IF(OR(E376="",E376=0,AB376=""),"",E376*365/(AB376*1000000)) | AD376: =IF(OR(O376="",O376=0,AB376=""),"",(AB376*1000000)/O376) | AE376: =IF(H376="","",(Team_Genesis-H376)/1000000) | AF376: =IF(OR(O376="",AE376=""),"",(O376-AE376*1000000)/1000000)
A377: 46031 | B377: =IF('Daily Data'!E377="","",'Daily Data'!E377) | C377: 25.53 | D377: 69974.7 | E377: 26370.882 | F377: 2704.8659 | H377: =SUM($G$4:G377) | I377: 1000000000 | J377: =J376-E377 | K377: 60000000 | L377: 38428013 | M377: 3000000 | N377: 570841.81 | O377: =IF(OR(I377="",J377="",L377="",N377=""),"",I377-J377-K377-L377-M377-N377) | P377: =IF(OR(O377="",C377=""),"",O377*C377) | Q377: =Q376-E377 | R377: =IF(OR(J377="",Q377=""),"",J377-Q377) | S377: =IF(D377="",S376,S376+D377) | T377: =IF(OR(L377="",S377=""),"",L377-S377) | U377: =IF(F377="",U376,U376+F377) | V377: =IF(OR(N377="",U377=""),"",N377-U377) | W377: =IF(OR(C377="",C377=0,'Daily Data'!J377=""),"",'Daily Data'!J377/C377) | X377: =IF(OR(C377="",C377=0,'Daily Data'!K377=""),"",'Daily Data'!K377/C377) | Y377: =IF(OR(F377="",W377="",X377=""),"",F377-W377-X377) | Z377: 372.43 | AA377: 65.72 | AB377: =Z377+AA377 | AC377: =IF(OR(E377="",E377=0,AB377=""),"",E377*365/(AB377*1000000)) | AD377: =IF(OR(O377="",O377=0,AB377=""),"",(AB377*1000000)/O377) | AE377: =IF(H377="","",(Team_Genesis-H377)/1000000) | AF377: =IF(OR(O377="",AE377=""),"",(O377-AE377*1000000)/1000000)
A378: 46032 | B378: =IF('Daily Data'!E378="","",'Daily Data'!E378) | C378: 24.91 | D378: 18968.35 | E378: 26361.092 | F378: 955.1403 | H378: =SUM($G$4:G378) | I378: 1000000000 | J378: =J377-E378 | K378: 60000000 | L378: 38446139 | M378: 3000000 | N378: 571796.95 | O378: =IF(OR(I378="",J378="",L378="",N378=""),"",I378-J378-K378-L378-M378-N378) | P378: =IF(OR(O378="",C378=""),"",O378*C378) | Q378: =Q377-E378 | R378: =IF(OR(J378="",Q378=""),"",J378-Q378) | S378: =IF(D378="",S377,S377+D378) | T378: =IF(OR(L378="",S378=""),"",L378-S378) | U378: =IF(F378="",U377,U377+F378) | V378: =IF(OR(N378="",U378=""),"",N378-U378) | W378: =IF(OR(C378="",C378=0,'Daily Data'!J378=""),"",'Daily Data'!J378/C378) | X378: =IF(OR(C378="",C378=0,'Daily Data'!K378=""),"",'Daily Data'!K378/C378) | Y378: =IF(OR(F378="",W378="",X378=""),"",F378-W378-X378) | Z378: 372.43 | AA378: 65.72 | AB378: =Z378+AA378 | AC378: =IF(OR(E378="",E378=0,AB378=""),"",E378*365/(AB378*1000000)) | AD378: =IF(OR(O378="",O378=0,AB378=""),"",(AB378*1000000)/O378) | AE378: =IF(H378="","",(Team_Genesis-H378)/1000000) | AF378: =IF(OR(O378="",AE378=""),"",(O378-AE378*1000000)/1000000)
A379: 46033 | B379: =IF('Daily Data'!E379="","",'Daily Data'!E379) | C379: 24.08 | D379: 33286.67 | E379: 26258.663 | F379: 2542.9764 | H379: =SUM($G$4:G379) | I379: 1000000000 | J379: =J378-E379 | K379: 60000000 | L379: 38480705 | M379: 3000000 | N379: 574339.93 | O379: =IF(OR(I379="",J379="",L379="",N379=""),"",I379-J379-K379-L379-M379-N379) | P379: =IF(OR(O379="",C379=""),"",O379*C379) | Q379: =Q378-E379 | R379: =IF(OR(J379="",Q379=""),"",J379-Q379) | S379: =IF(D379="",S378,S378+D379) | T379: =IF(OR(L379="",S379=""),"",L379-S379) | U379: =IF(F379="",U378,U378+F379) | V379: =IF(OR(N379="",U379=""),"",N379-U379) | W379: =IF(OR(C379="",C379=0,'Daily Data'!J379=""),"",'Daily Data'!J379/C379) | X379: =IF(OR(C379="",C379=0,'Daily Data'!K379=""),"",'Daily Data'!K379/C379) | Y379: =IF(OR(F379="",W379="",X379=""),"",F379-W379-X379) | Z379: 372.43 | AA379: 65.72 | AB379: =Z379+AA379 | AC379: =IF(OR(E379="",E379=0,AB379=""),"",E379*365/(AB379*1000000)) | AD379: =IF(OR(O379="",O379=0,AB379=""),"",(AB379*1000000)/O379) | AE379: =IF(H379="","",(Team_Genesis-H379)/1000000) | AF379: =IF(OR(O379="",AE379=""),"",(O379-AE379*1000000)/1000000)
A380: 46034 | B380: =IF('Daily Data'!E380="","",'Daily Data'!E380) | C380: 24.41 | D380: 79151.85 | E380: 26359.817 | F380: 1943.4075 | H380: =SUM($G$4:G380) | I380: 1000000000 | J380: =J379-E380 | K380: 60000000 | L380: 38558758 | M380: 3000000 | N380: 576283.33 | O380: =IF(OR(I380="",J380="",L380="",N380=""),"",I380-J380-K380-L380-M380-N380) | P380: =IF(OR(O380="",C380=""),"",O380*C380) | Q380: =Q379-E380 | R380: =IF(OR(J380="",Q380=""),"",J380-Q380) | S380: =IF(D380="",S379,S379+D380) | T380: =IF(OR(L380="",S380=""),"",L380-S380) | U380: =IF(F380="",U379,U379+F380) | V380: =IF(OR(N380="",U380=""),"",N380-U380) | W380: =IF(OR(C380="",C380=0,'Daily Data'!J380=""),"",'Daily Data'!J380/C380) | X380: =IF(OR(C380="",C380=0,'Daily Data'!K380=""),"",'Daily Data'!K380/C380) | Y380: =IF(OR(F380="",W380="",X380=""),"",F380-W380-X380) | Z380: 372.43 | AA380: 65.72 | AB380: =Z380+AA380 | AC380: =IF(OR(E380="",E380=0,AB380=""),"",E380*365/(AB380*1000000)) | AD380: =IF(OR(O380="",O380=0,AB380=""),"",(AB380*1000000)/O380) | AE380: =IF(H380="","",(Team_Genesis-H380)/1000000) | AF380: =IF(OR(O380="",AE380=""),"",(O380-AE380*1000000)/1000000)
A381: 46035 | B381: =IF('Daily Data'!E381="","",'Daily Data'!E381) | C381: 24.09 | D381: 92963.94 | E381: 26369.654 | F381: 2800.1185 | H381: =SUM($G$4:G381) | I381: 1000000000 | J381: =J380-E381 | K381: 60000000 | L381: 38651124 | M381: 3000000 | N381: 579083.45 | O381: =IF(OR(I381="",J381="",L381="",N381=""),"",I381-J381-K381-L381-M381-N381) | P381: =IF(OR(O381="",C381=""),"",O381*C381) | Q381: =Q380-E381 | R381: =IF(OR(J381="",Q381=""),"",J381-Q381) | S381: =IF(D381="",S380,S380+D381) | T381: =IF(OR(L381="",S381=""),"",L381-S381) | U381: =IF(F381="",U380,U380+F381) | V381: =IF(OR(N381="",U381=""),"",N381-U381) | W381: =IF(OR(C381="",C381=0,'Daily Data'!J381=""),"",'Daily Data'!J381/C381) | X381: =IF(OR(C381="",C381=0,'Daily Data'!K381=""),"",'Daily Data'!K381/C381) | Y381: =IF(OR(F381="",W381="",X381=""),"",F381-W381-X381) | Z381: 372.43 | AA381: 65.72 | AB381: =Z381+AA381 | AC381: =IF(OR(E381="",E381=0,AB381=""),"",E381*365/(AB381*1000000)) | AD381: =IF(OR(O381="",O381=0,AB381=""),"",(AB381*1000000)/O381) | AE381: =IF(H381="","",(Team_Genesis-H381)/1000000) | AF381: =IF(OR(O381="",AE381=""),"",(O381-AE381*1000000)/1000000)
A382: 46036 | B382: =IF('Daily Data'!E382="","",'Daily Data'!E382) | C382: 25.73 | D382: 88651.64 | E382: 26298.323 | F382: 1022.0645 | H382: =SUM($G$4:G382) | I382: 1000000000 | J382: =J381-E382 | K382: 60000000 | L382: 38741830 | M382: 3000000 | N382: 580105.52 | O382: =IF(OR(I382="",J382="",L382="",N382=""),"",I382-J382-K382-L382-M382-N382) | P382: =IF(OR(O382="",C382=""),"",O382*C382) | Q382: =Q381-E382 | R382: =IF(OR(J382="",Q382=""),"",J382-Q382) | S382: =IF(D382="",S381,S381+D382) | T382: =IF(OR(L382="",S382=""),"",L382-S382) | U382: =IF(F382="",U381,U381+F382) | V382: =IF(OR(N382="",U382=""),"",N382-U382) | W382: =IF(OR(C382="",C382=0,'Daily Data'!J382=""),"",'Daily Data'!J382/C382) | X382: =IF(OR(C382="",C382=0,'Daily Data'!K382=""),"",'Daily Data'!K382/C382) | Y382: =IF(OR(F382="",W382="",X382=""),"",F382-W382-X382) | Z382: 372.43 | AA382: 65.72 | AB382: =Z382+AA382 | AC382: =IF(OR(E382="",E382=0,AB382=""),"",E382*365/(AB382*1000000)) | AD382: =IF(OR(O382="",O382=0,AB382=""),"",(AB382*1000000)/O382) | AE382: =IF(H382="","",(Team_Genesis-H382)/1000000) | AF382: =IF(OR(O382="",AE382=""),"",(O382-AE382*1000000)/1000000)
A383: 46037 | B383: =IF('Daily Data'!E383="","",'Daily Data'!E383) | C383: 25.76 | D383: 74458.25 | E383: 26149.329 | F383: 3113.108 | H383: =SUM($G$4:G383) | I383: 1000000000 | J383: =J382-E383 | K383: 60000000 | L383: 38814234 | M383: 3000000 | N383: 583218.62 | O383: =IF(OR(I383="",J383="",L383="",N383=""),"",I383-J383-K383-L383-M383-N383) | P383: =IF(OR(O383="",C383=""),"",O383*C383) | Q383: =Q382-E383 | R383: =IF(OR(J383="",Q383=""),"",J383-Q383) | S383: =IF(D383="",S382,S382+D383) | T383: =IF(OR(L383="",S383=""),"",L383-S383) | U383: =IF(F383="",U382,U382+F383) | V383: =IF(OR(N383="",U383=""),"",N383-U383) | W383: =IF(OR(C383="",C383=0,'Daily Data'!J383=""),"",'Daily Data'!J383/C383) | X383: =IF(OR(C383="",C383=0,'Daily Data'!K383=""),"",'Daily Data'!K383/C383) | Y383: =IF(OR(F383="",W383="",X383=""),"",F383-W383-X383) | Z383: 372.43 | AA383: 65.72 | AB383: =Z383+AA383 | AC383: =IF(OR(E383="",E383=0,AB383=""),"",E383*365/(AB383*1000000)) | AD383: =IF(OR(O383="",O383=0,AB383=""),"",(AB383*1000000)/O383) | AE383: =IF(H383="","",(Team_Genesis-H383)/1000000) | AF383: =IF(OR(O383="",AE383=""),"",(O383-AE383*1000000)/1000000)
A384: 46038 | B384: =IF('Daily Data'!E384="","",'Daily Data'!E384) | C384: 24.81 | D384: 44909.63 | E384: 26275.894 | F384: 3062.658 | H384: =SUM($G$4:G384) | I384: 1000000000 | J384: =J383-E384 | K384: 60000000 | L384: 38859945 | M384: 3000000 | N384: 586281.28 | O384: =IF(OR(I384="",J384="",L384="",N384=""),"",I384-J384-K384-L384-M384-N384) | P384: =IF(OR(O384="",C384=""),"",O384*C384) | Q384: =Q383-E384 | R384: =IF(OR(J384="",Q384=""),"",J384-Q384) | S384: =IF(D384="",S383,S383+D384) | T384: =IF(OR(L384="",S384=""),"",L384-S384) | U384: =IF(F384="",U383,U383+F384) | V384: =IF(OR(N384="",U384=""),"",N384-U384) | W384: =IF(OR(C384="",C384=0,'Daily Data'!J384=""),"",'Daily Data'!J384/C384) | X384: =IF(OR(C384="",C384=0,'Daily Data'!K384=""),"",'Daily Data'!K384/C384) | Y384: =IF(OR(F384="",W384="",X384=""),"",F384-W384-X384) | Z384: 372.43 | AA384: 65.72 | AB384: =Z384+AA384 | AC384: =IF(OR(E384="",E384=0,AB384=""),"",E384*365/(AB384*1000000)) | AD384: =IF(OR(O384="",O384=0,AB384=""),"",(AB384*1000000)/O384) | AE384: =IF(H384="","",(Team_Genesis-H384)/1000000) | AF384: =IF(OR(O384="",AE384=""),"",(O384-AE384*1000000)/1000000)
A385: 46039 | B385: =IF('Daily Data'!E385="","",'Daily Data'!E385) | C385: 24.98 | D385: 20400.66 | E385: 26449.255 | F385: 3640.35 | H385: =SUM($G$4:G385) | I385: 1000000000 | J385: =J384-E385 | K385: 60000000 | L385: 38879910 | M385: 3000000 | N385: 589921.63 | O385: =IF(OR(I385="",J385="",L385="",N385=""),"",I385-J385-K385-L385-M385-N385) | P385: =IF(OR(O385="",C385=""),"",O385*C385) | Q385: =Q384-E385 | R385: =IF(OR(J385="",Q385=""),"",J385-Q385) | S385: =IF(D385="",S384,S384+D385) | T385: =IF(OR(L385="",S385=""),"",L385-S385) | U385: =IF(F385="",U384,U384+F385) | V385: =IF(OR(N385="",U385=""),"",N385-U385) | W385: =IF(OR(C385="",C385=0,'Daily Data'!J385=""),"",'Daily Data'!J385/C385) | X385: =IF(OR(C385="",C385=0,'Daily Data'!K385=""),"",'Daily Data'!K385/C385) | Y385: =IF(OR(F385="",W385="",X385=""),"",F385-W385-X385) | Z385: 372.43 | AA385: 65.72 | AB385: =Z385+AA385 | AC385: =IF(OR(E385="",E385=0,AB385=""),"",E385*365/(AB385*1000000)) | AD385: =IF(OR(O385="",O385=0,AB385=""),"",(AB385*1000000)/O385) | AE385: =IF(H385="","",(Team_Genesis-H385)/1000000) | AF385: =IF(OR(O385="",AE385=""),"",(O385-AE385*1000000)/1000000)
A386: 46040 | B386: =IF('Daily Data'!E386="","",'Daily Data'!E386) | C386: 25.51 | D386: 32107.65 | E386: 26383.416 | F386: 205.2242 | H386: =SUM($G$4:G386) | I386: 1000000000 | J386: =J385-E386 | K386: 60000000 | L386: 38931975 | M386: 3000000 | N386: 590126.86 | O386: =IF(OR(I386="",J386="",L386="",N386=""),"",I386-J386-K386-L386-M386-N386) | P386: =IF(OR(O386="",C386=""),"",O386*C386) | Q386: =Q385-E386 | R386: =IF(OR(J386="",Q386=""),"",J386-Q386) | S386: =IF(D386="",S385,S385+D386) | T386: =IF(OR(L386="",S386=""),"",L386-S386) | U386: =IF(F386="",U385,U385+F386) | V386: =IF(OR(N386="",U386=""),"",N386-U386) | W386: =IF(OR(C386="",C386=0,'Daily Data'!J386=""),"",'Daily Data'!J386/C386) | X386: =IF(OR(C386="",C386=0,'Daily Data'!K386=""),"",'Daily Data'!K386/C386) | Y386: =IF(OR(F386="",W386="",X386=""),"",F386-W386-X386) | Z386: 372.43 | AA386: 65.72 | AB386: =Z386+AA386 | AC386: =IF(OR(E386="",E386=0,AB386=""),"",E386*365/(AB386*1000000)) | AD386: =IF(OR(O386="",O386=0,AB386=""),"",(AB386*1000000)/O386) | AE386: =IF(H386="","",(Team_Genesis-H386)/1000000) | AF386: =IF(OR(O386="",AE386=""),"",(O386-AE386*1000000)/1000000)
... A404: 46058 | B404: =IF('Daily Data'!E404="","",'Daily Data'!E404) | C404: 35.26 | D404: 160754.65 | E404: 26510.671 | F404: 1549.8525 | H404: =SUM($G$4:G404) | I404: 1000000000 | J404: =J403-E404 | K404: 60000000 | L404: 40448356 | M404: 3000000 | N404: 677805.3 | O404: =IF(OR(I404="",J404="",L404="",N404=""),"",I404-J404-K404-L404-M404-N404) | P404: =IF(OR(O404="",C404=""),"",O404*C404) | Q404: =Q403-E404 | R404: =IF(OR(J404="",Q404=""),"",J404-Q404) | S404: =IF(D404="",S403,S403+D404) | T404: =IF(OR(L404="",S404=""),"",L404-S404) | U404: =IF(F404="",U403,U403+F404) | V404: =IF(OR(N404="",U404=""),"",N404-U404) | W404: =IF(OR(C404="",C404=0,'Daily Data'!J404=""),"",'Daily Data'!J404/C404) | X404: =IF(OR(C404="",C404=0,'Daily Data'!K404=""),"",'Daily Data'!K404/C404) | Y404: =IF(OR(F404="",W404="",X404=""),"",F404-W404-X404) | Z404: 369.61 | AA404: 65.23 | AB404: =Z404+AA404 | AC404: =IF(OR(E404="",E404=0,AB404=""),"",E404*365/(AB404*1000000)) | AD404: =IF(OR(O404="",O404=0,AB404=""),"",(AB404*1000000)/O404) | AE404: =IF(H404="","",(Team_Genesis-H404)/1000000) | AF404: =IF(OR(O404="",AE404=""),"",(O404-AE404*1000000)/1000000)
A405: 46059 | B405: =IF('Daily Data'!E405="","",'Daily Data'!E405) | C405: 32.69 | D405: 112041.27 | E405: 26548.211 | F405: 3523.7199 | G405: 140333 | H405: =SUM($G$4:G405) | I405: 1000000000 | J405: =J404-E405 | K405: 60000000 | L405: 40549551 | M405: 3000000 | N405: 681329.02 | O405: =IF(OR(I405="",J405="",L405="",N405=""),"",I405-J405-K405-L405-M405-N405) | P405: =IF(OR(O405="",C405=""),"",O405*C405) | Q405: =Q404-E405 | R405: =IF(OR(J405="",Q405=""),"",J405-Q405) | S405: =IF(D405="",S404,S404+D405) | T405: =IF(OR(L405="",S405=""),"",L405-S405) | U405: =IF(F405="",U404,U404+F405) | V405: =IF(OR(N405="",U405=""),"",N405-U405) | W405: =IF(OR(C405="",C405=0,'Daily Data'!J405=""),"",'Daily Data'!J405/C405) | X405: =IF(OR(C405="",C405=0,'Daily Data'!K405=""),"",'Daily Data'!K405/C405) | Y405: =IF(OR(F405="",W405="",X405=""),"",F405-W405-X405) | Z405: 369.61 | AA405: 65.23 | AB405: =Z405+AA405 | AC405: =IF(OR(E405="",E405=0,AB405=""),"",E405*365/(AB405*1000000)) | AD405: =IF(OR(O405="",O405=0,AB405=""),"",(AB405*1000000)/O405) | AE405: =IF(H405="","",(Team_Genesis-H405)/1000000) | AF405: =IF(OR(O405="",AE405=""),"",(O405-AE405*1000000)/1000000)
A406: 46060 | B406: =IF('Daily Data'!E406="","",'Daily Data'!E406) | C406: 32.16 | D406: 50422.63 | E406: 26532.97 | F406: 3341.9098 | H406: =SUM($G$4:G406) | I406: 1000000000 | J406: =J405-E406 | K406: 60000000 | L406: 40599246 | M406: 3000000 | N406: 684670.93 | O406: =IF(OR(I406="",J406="",L406="",N406=""),"",I406-J406-K406-L406-M406-N406) | P406: =IF(OR(O406="",C406=""),"",O406*C406) | Q406: =Q405-E406 | R406: =IF(OR(J406="",Q406=""),"",J406-Q406) | S406: =IF(D406="",S405,S405+D406) | T406: =IF(OR(L406="",S406=""),"",L406-S406) | U406: =IF(F406="",U405,U405+F406) | V406: =IF(OR(N406="",U406=""),"",N406-U406) | W406: =IF(OR(C406="",C406=0,'Daily Data'!J406=""),"",'Daily Data'!J406/C406) | X406: =IF(OR(C406="",C406=0,'Daily Data'!K406=""),"",'Daily Data'!K406/C406) | Y406: =IF(OR(F406="",W406="",X406=""),"",F406-W406-X406) | Z406: 369.61 | AA406: 65.23 | AB406: =Z406+AA406 | AC406: =IF(OR(E406="",E406=0,AB406=""),"",E406*365/(AB406*1000000)) | AD406: =IF(OR(O406="",O406=0,AB406=""),"",(AB406*1000000)/O406) | AE406: =IF(H406="","",(Team_Genesis-H406)/1000000) | AF406: =IF(OR(O406="",AE406=""),"",(O406-AE406*1000000)/1000000)
A407: 46061 | B407: =IF('Daily Data'!E407="","",'Daily Data'!E407) | C407: 31.24 | D407: 34080.59 | E407: 26560.877 | F407: 360.2197 | H407: =SUM($G$4:G407) | I407: 1000000000 | J407: =J406-E407 | K407: 60000000 | L407: 40632890 | M407: 3000000 | N407: 685031.15 | O407: =IF(OR(I407="",J407="",L407="",N407=""),"",I407-J407-K407-L407-M407-N407) | P407: =IF(OR(O407="",C407=""),"",O407*C407) | Q407: =Q406-E407 | R407: =IF(OR(J407="",Q407=""),"",J407-Q407) | S407: =IF(D407="",S406,S406+D407) | T407: =IF(OR(L407="",S407=""),"",L407-S407) | U407: =IF(F407="",U406,U406+F407) | V407: =IF(OR(N407="",U407=""),"",N407-U407) | W407: =IF(OR(C407="",C407=0,'Daily Data'!J407=""),"",'Daily Data'!J407/C407) | X407: =IF(OR(C407="",C407=0,'Daily Data'!K407=""),"",'Daily Data'!K407/C407) | Y407: =IF(OR(F407="",W407="",X407=""),"",F407-W407-X407) | Z407: 369.61 | AA407: 65.23 | AB407: =Z407+AA407 | AC407: =IF(OR(E407="",E407=0,AB407=""),"",E407*365/(AB407*1000000)) | AD407: =IF(OR(O407="",O407=0,AB407=""),"",(AB407*1000000)/O407) | AE407: =IF(H407="","",(Team_Genesis-H407)/1000000) | AF407: =IF(OR(O407="",AE407=""),"",(O407-AE407*1000000)/1000000)
A408: 46062 | B408: =IF('Daily Data'!E408="","",'Daily Data'!E408) | C408: 32.46 | D408: 48777.95 | E408: 26556.769 | F408: 2523.6788 | H408: =SUM($G$4:G408) | I408: 1000000000 | J408: =J407-E408 | K408: 60000000 | L408: 40681693 | M408: 3000000 | N408: 687554.83 | O408: =IF(OR(I408="",J408="",L408="",N408=""),"",I408-J408-K408-L408-M408-N408) | P408: =IF(OR(O408="",C408=""),"",O408*C408) | Q408: =Q407-E408 | R408: =IF(OR(J408="",Q408=""),"",J408-Q408) | S408: =IF(D408="",S407,S407+D408) | T408: =IF(OR(L408="",S408=""),"",L408-S408) | U408: =IF(F408="",U407,U407+F408) | V408: =IF(OR(N408="",U408=""),"",N408-U408) | W408: =IF(OR(C408="",C408=0,'Daily Data'!J408=""),"",'Daily Data'!J408/C408) | X408: =IF(OR(C408="",C408=0,'Daily Data'!K408=""),"",'Daily Data'!K408/C408) | Y408: =IF(OR(F408="",W408="",X408=""),"",F408-W408-X408) | Z408: 369.61 | AA408: 65.23 | AB408: =Z408+AA408 | AC408: =IF(OR(E408="",E408=0,AB408=""),"",E408*365/(AB408*1000000)) | AD408: =IF(OR(O408="",O408=0,AB408=""),"",(AB408*1000000)/O408) | AE408: =IF(H408="","",(Team_Genesis-H408)/1000000) | AF408: =IF(OR(O408="",AE408=""),"",(O408-AE408*1000000)/1000000)
A409: 46063 | B409: =IF('Daily Data'!E409="","",'Daily Data'!E409) | C409: 31.04 | D409: 45261.62 | E409: 26556.042 | F409: 3101.5672 | H409: =SUM($G$4:G409) | I409: 1000000000 | J409: =J408-E409 | K409: 60000000 | L409: 40726662 | M409: 3000000 | N409: 690656.4 | O409: =IF(OR(I409="",J409="",L409="",N409=""),"",I409-J409-K409-L409-M409-N409) | P409: =IF(OR(O409="",C409=""),"",O409*C409) | Q409: =Q408-E409 | R409: =IF(OR(J409="",Q409=""),"",J409-Q409) | S409: =IF(D409="",S408,S408+D409) | T409: =IF(OR(L409="",S409=""),"",L409-S409) | U409: =IF(F409="",U408,U408+F409) | V409: =IF(OR(N409="",U409=""),"",N409-U409) | W409: =IF(OR(C409="",C409=0,'Daily Data'!J409=""),"",'Daily Data'!J409/C409) | X409: =IF(OR(C409="",C409=0,'Daily Data'!K409=""),"",'Daily Data'!K409/C409) | Y409: =IF(OR(F409="",W409="",X409=""),"",F409-W409-X409) | Z409: 369.61 | AA409: 65.23 | AB409: =Z409+AA409 | AC409: =IF(OR(E409="",E409=0,AB409=""),"",E409*365/(AB409*1000000)) | AD409: =IF(OR(O409="",O409=0,AB409=""),"",(AB409*1000000)/O409) | AE409: =IF(H409="","",(Team_Genesis-H409)/1000000) | AF409: =IF(OR(O409="",AE409=""),"",(O409-AE409*1000000)/1000000)
A410: 46064 | B410: =IF('Daily Data'!E410="","",'Daily Data'!E410) | C410: 29.07 | D410: 59026.79 | E410: 26553.469 | F410: 1030.2548 | H410: =SUM($G$4:G410) | I410: 1000000000 | J410: =J409-E410 | K410: 60000000 | L410: 40785343 | M410: 3000000 | N410: 691686.66 | O410: =IF(OR(I410="",J410="",L410="",N410=""),"",I410-J410-K410-L410-M410-N410) | P410: =IF(OR(O410="",C410=""),"",O410*C410) | Q410: =Q409-E410 | R410: =IF(OR(J410="",Q410=""),"",J410-Q410) | S410: =IF(D410="",S409,S409+D410) | T410: =IF(OR(L410="",S410=""),"",L410-S410) | U410: =IF(F410="",U409,U409+F410) | V410: =IF(OR(N410="",U410=""),"",N410-U410) | W410: =IF(OR(C410="",C410=0,'Daily Data'!J410=""),"",'Daily Data'!J410/C410) | X410: =IF(OR(C410="",C410=0,'Daily Data'!K410=""),"",'Daily Data'!K410/C410) | Y410: =IF(OR(F410="",W410="",X410=""),"",F410-W410-X410) | Z410: 369.61 | AA410: 65.23 | AB410: =Z410+AA410 | AC410: =IF(OR(E410="",E410=0,AB410=""),"",E410*365/(AB410*1000000)) | AD410: =IF(OR(O410="",O410=0,AB410=""),"",(AB410*1000000)/O410) | AE410: =IF(H410="","",(Team_Genesis-H410)/1000000) | AF410: =IF(OR(O410="",AE410=""),"",(O410-AE410*1000000)/1000000)
A411: 46065 | B411: =IF('Daily Data'!E411="","",'Daily Data'!E411) | C411: 29.72 | D411: 44632.74 | E411: 26549.682 | F411: 1199.9727 | H411: =SUM($G$4:G411) | I411: 1000000000 | J411: =J410-E411 | K411: 60000000 | L411: 40833357 | M411: 3000000 | N411: 692886.63 | O411: =IF(OR(I411="",J411="",L411="",N411=""),"",I411-J411-K411-L411-M411-N411) | P411: =IF(OR(O411="",C411=""),"",O411*C411) | Q411: =Q410-E411 | R411: =IF(OR(J411="",Q411=""),"",J411-Q411) | S411: =IF(D411="",S410,S410+D411) | T411: =IF(OR(L411="",S411=""),"",L411-S411) | U411: =IF(F411="",U410,U410+F411) | V411: =IF(OR(N411="",U411=""),"",N411-U411) | W411: =IF(OR(C411="",C411=0,'Daily Data'!J411=""),"",'Daily Data'!J411/C411) | X411: =IF(OR(C411="",C411=0,'Daily Data'!K411=""),"",'Daily Data'!K411/C411) | Y411: =IF(OR(F411="",W411="",X411=""),"",F411-W411-X411) | Z411: 369.61 | AA411: 65.23 | AB411: =Z411+AA411 | AC411: =IF(OR(E411="",E411=0,AB411=""),"",E411*365/(AB411*1000000)) | AD411: =IF(OR(O411="",O411=0,AB411=""),"",(AB411*1000000)/O411) | AE411: =IF(H411="","",(Team_Genesis-H411)/1000000) | AF411: =IF(OR(O411="",AE411=""),"",(O411-AE411*1000000)/1000000)
A412: 46066 | B412: =IF('Daily Data'!E412="","",'Daily Data'!E412) | C412: 30.79 | D412: 41194.1 | E412: 26553.766 | F412: 1215.4388 | H412: =SUM($G$4:G412) | I412: 1000000000 | J412: =J411-E412 | K412: 60000000 | L412: 40871803 | M412: 3000000 | N412: 694102.07 | O412: =IF(OR(I412="",J412="",L412="",N412=""),"",I412-J412-K412-L412-M412-N412) | P412: =IF(OR(O412="",C412=""),"",O412*C412) | Q412: =Q411-E412 | R412: =IF(OR(J412="",Q412=""),"",J412-Q412) | S412: =IF(D412="",S411,S411+D412) | T412: =IF(OR(L412="",S412=""),"",L412-S412) | U412: =IF(F412="",U411,U411+F412) | V412: =IF(OR(N412="",U412=""),"",N412-U412) | W412: =IF(OR(C412="",C412=0,'Daily Data'!J412=""),"",'Daily Data'!J412/C412) | X412: =IF(OR(C412="",C412=0,'Daily Data'!K412=""),"",'Daily Data'!K412/C412) | Y412: =IF(OR(F412="",W412="",X412=""),"",F412-W412-X412) | Z412: 369.61 | AA412: 65.23 | AB412: =Z412+AA412 | AC412: =IF(OR(E412="",E412=0,AB412=""),"",E412*365/(AB412*1000000)) | AD412: =IF(OR(O412="",O412=0,AB412=""),"",(AB412*1000000)/O412) | AE412: =IF(H412="","",(Team_Genesis-H412)/1000000) | AF412: =IF(OR(O412="",AE412=""),"",(O412-AE412*1000000)/1000000)
A413: 46067 | B413: =IF('Daily Data'!E413="","",'Daily Data'!E413) | C413: 31.53 | D413: 23679.76 | E413: 26554.776 | F413: 888.9465 | H413: =SUM($G$4:G413) | I413: 1000000000 | J413: =J412-E413 | K413: 60000000 | L413: 40895558 | M413: 3000000 | N413: 694991.01 | O413: =IF(OR(I413="",J413="",L413="",N413=""),"",I413-J413-K413-L413-M413-N413) | P413: =IF(OR(O413="",C413=""),"",O413*C413) | Q413: =Q412-E413 | R413: =IF(OR(J413="",Q413=""),"",J413-Q413) | S413: =IF(D413="",S412,S412+D413) | T413: =IF(OR(L413="",S413=""),"",L413-S413) | U413: =IF(F413="",U412,U412+F413) | V413: =IF(OR(N413="",U413=""),"",N413-U413) | W413: =IF(OR(C413="",C413=0,'Daily Data'!J413=""),"",'Daily Data'!J413/C413) | X413: =IF(OR(C413="",C413=0,'Daily Data'!K413=""),"",'Daily Data'!K413/C413) | Y413: =IF(OR(F413="",W413="",X413=""),"",F413-W413-X413) | Z413: 369.61 | AA413: 65.23 | AB413: =Z413+AA413 | AC413: =IF(OR(E413="",E413=0,AB413=""),"",E413*365/(AB413*1000000)) | AD413: =IF(OR(O413="",O413=0,AB413=""),"",(AB413*1000000)/O413) | AE413: =IF(H413="","",(Team_Genesis-H413)/1000000) | AF413: =IF(OR(O413="",AE413=""),"",(O413-AE413*1000000)/1000000)
A414: 46068 | B414: =IF('Daily Data'!E414="","",'Daily Data'!E414) | C414: 31.73 | D414: 31482 | E414: 26531.321 | F414: 194.0083 | H414: =SUM($G$4:G414) | I414: 1000000000 | J414: =J413-E414 | K414: 60000000 | L414: 40926983 | M414: 3000000 | N414: 695185.02 | O414: =IF(OR(I414="",J414="",L414="",N414=""),"",I414-J414-K414-L414-M414-N414) | P414: =IF(OR(O414="",C414=""),"",O414*C414) | Q414: =Q413-E414 | R414: =IF(OR(J414="",Q414=""),"",J414-Q414) | S414: =IF(D414="",S413,S413+D414) | T414: =IF(OR(L414="",S414=""),"",L414-S414) | U414: =IF(F414="",U413,U413+F414) | V414: =IF(OR(N414="",U414=""),"",N414-U414) | W414: =IF(OR(C414="",C414=0,'Daily Data'!J414=""),"",'Daily Data'!J414/C414) | X414: =IF(OR(C414="",C414=0,'Daily Data'!K414=""),"",'Daily Data'!K414/C414) | Y414: =IF(OR(F414="",W414="",X414=""),"",F414-W414-X414) | Z414: 369.61 | AA414: 65.23 | AB414: =Z414+AA414 | AC414: =IF(OR(E414="",E414=0,AB414=""),"",E414*365/(AB414*1000000)) | AD414: =IF(OR(O414="",O414=0,AB414=""),"",(AB414*1000000)/O414) | AE414: =IF(H414="","",(Team_Genesis-H414)/1000000) | AF414: =IF(OR(O414="",AE414=""),"",(O414-AE414*1000000)/1000000)
A415: 46069 | B415: =IF('Daily Data'!E415="","",'Daily Data'!E415) | C415: 30.67 | D415: 28342.14 | E415: 26531.732 | F415: 1310.5528 | H415: =SUM($G$4:G415) | I415: 1000000000 | J415: =J414-E415 | K415: 60000000 | L415: 40954673 | M415: 3000000 | N415: 696495.57 | O415: =IF(OR(I415="",J415="",L415="",N415=""),"",I415-J415-K415-L415-M415-N415) | P415: =IF(OR(O415="",C415=""),"",O415*C415) | Q415: =Q414-E415 | R415: =IF(OR(J415="",Q415=""),"",J415-Q415) | S415: =IF(D415="",S414,S414+D415) | T415: =IF(OR(L415="",S415=""),"",L415-S415) | U415: =IF(F415="",U414,U414+F415) | V415: =IF(OR(N415="",U415=""),"",N415-U415) | W415: =IF(OR(C415="",C415=0,'Daily Data'!J415=""),"",'Daily Data'!J415/C415) | X415: =IF(OR(C415="",C415=0,'Daily Data'!K415=""),"",'Daily Data'!K415/C415) | Y415: =IF(OR(F415="",W415="",X415=""),"",F415-W415-X415) | Z415: 369.61 | AA415: 65.23 | AB415: =Z415+AA415 | AC415: =IF(OR(E415="",E415=0,AB415=""),"",E415*365/(AB415*1000000)) | AD415: =IF(OR(O415="",O415=0,AB415=""),"",(AB415*1000000)/O415) | AE415: =IF(H415="","",(Team_Genesis-H415)/1000000) | AF415: =IF(OR(O415="",AE415=""),"",(O415-AE415*1000000)/1000000)
A416: 46070 | B416: =IF('Daily Data'!E416="","",'Daily Data'!E416) | C416: 31.23 | D416: 44826.66 | E416: 26528.882 | F416: 248.4681 | H416: =SUM($G$4:G416) | I416: 1000000000 | J416: =J415-E416 | K416: 60000000 | L416: 41000109 | M416: 3000000 | N416: 696744.04 | O416: =IF(OR(I416="",J416="",L416="",N416=""),"",I416-J416-K416-L416-M416-N416) | P416: =IF(OR(O416="",C416=""),"",O416*C416) | Q416: =Q415-E416 | R416: =IF(OR(J416="",Q416=""),"",J416-Q416) | S416: =IF(D416="",S415,S415+D416) | T416: =IF(OR(L416="",S416=""),"",L416-S416) | U416: =IF(F416="",U415,U415+F416) | V416: =IF(OR(N416="",U416=""),"",N416-U416) | W416: =IF(OR(C416="",C416=0,'Daily Data'!J416=""),"",'Daily Data'!J416/C416) | X416: =IF(OR(C416="",C416=0,'Daily Data'!K416=""),"",'Daily Data'!K416/C416) | Y416: =IF(OR(F416="",W416="",X416=""),"",F416-W416-X416) | Z416: 369.61 | AA416: 65.23 | AB416: =Z416+AA416 | AC416: =IF(OR(E416="",E416=0,AB416=""),"",E416*365/(AB416*1000000)) | AD416: =IF(OR(O416="",O416=0,AB416=""),"",(AB416*1000000)/O416) | AE416: =IF(H416="","",(Team_Genesis-H416)/1000000) | AF416: =IF(OR(O416="",AE416=""),"",(O416-AE416*1000000)/1000000)
A417: 46071 | B417: =IF('Daily Data'!E417="","",'Daily Data'!E417) | C417: 29.33 | D417: 40585.19 | E417: 26542.981 | F417: 812.8349 | H417: =SUM($G$4:G417) | I417: 1000000000 | J417: =J416-E417 | K417: 60000000 | L417: 41040715 | M417: 3000000 | N417: 697556.88 | O417: =IF(OR(I417="",J417="",L417="",N417=""),"",I417-J417-K417-L417-M417-N417) | P417: =IF(OR(O417="",C417=""),"",O417*C417) | Q417: =Q416-E417 | R417: =IF(OR(J417="",Q417=""),"",J417-Q417) | S417: =IF(D417="",S416,S416+D417) | T417: =IF(OR(L417="",S417=""),"",L417-S417) | U417: =IF(F417="",U416,U416+F417) | V417: =IF(OR(N417="",U417=""),"",N417-U417) | W417: =IF(OR(C417="",C417=0,'Daily Data'!J417=""),"",'Daily Data'!J417/C417) | X417: =IF(OR(C417="",C417=0,'Daily Data'!K417=""),"",'Daily Data'!K417/C417) | Y417: =IF(OR(F417="",W417="",X417=""),"",F417-W417-X417) | Z417: 369.61 | AA417: 65.23 | AB417: =Z417+AA417 | AC417: =IF(OR(E417="",E417=0,AB417=""),"",E417*365/(AB417*1000000)) | AD417: =IF(OR(O417="",O417=0,AB417=""),"",(AB417*1000000)/O417) | AE417: =IF(H417="","",(Team_Genesis-H417)/1000000) | AF417: =IF(OR(O417="",AE417=""),"",(O417-AE417*1000000)/1000000)
... A432: 46086 | B432: =IF('Daily Data'!E432="","",'Daily Data'!E432) | C432: 32.08 | D432: 53765.04 | E432: 26504.571 | F432: 1153.7756 | H432: =SUM($G$4:G432) | I432: 1000000000 | J432: =J431-E432 | K432: 60000000 | L432: 41804261 | M432: 3000000 | N432: 710561.71 | O432: =IF(OR(I432="",J432="",L432="",N432=""),"",I432-J432-K432-L432-M432-N432) | P432: =IF(OR(O432="",C432=""),"",O432*C432) | Q432: =Q431-E432 | R432: =IF(OR(J432="",Q432=""),"",J432-Q432) | S432: =IF(D432="",S431,S431+D432) | T432: =IF(OR(L432="",S432=""),"",L432-S432) | U432: =IF(F432="",U431,U431+F432) | V432: =IF(OR(N432="",U432=""),"",N432-U432) | W432: =IF(OR(C432="",C432=0,'Daily Data'!J432=""),"",'Daily Data'!J432/C432) | X432: =IF(OR(C432="",C432=0,'Daily Data'!K432=""),"",'Daily Data'!K432/C432) | Y432: =IF(OR(F432="",W432="",X432=""),"",F432-W432-X432) | Z432: 369.48 | AA432: 65.2 | AB432: =Z432+AA432 | AC432: =IF(OR(E432="",E432=0,AB432=""),"",E432*365/(AB432*1000000)) | AD432: =IF(OR(O432="",O432=0,AB432=""),"",(AB432*1000000)/O432) | AE432: =IF(H432="","",(Team_Genesis-H432)/1000000) | AF432: =IF(OR(O432="",AE432=""),"",(O432-AE432*1000000)/1000000)
A433: 46087 | B433: =IF('Daily Data'!E433="","",'Daily Data'!E433) | C433: 30.54 | D433: 60658.81 | E433: 26356.934 | F433: 1343.8283 | G433: 173217 | H433: =SUM($G$4:G433) | I433: 1000000000 | J433: =J432-E433 | K433: 60000000 | L433: 41865293 | M433: 3000000 | N433: 711905.54 | O433: =IF(OR(I433="",J433="",L433="",N433=""),"",I433-J433-K433-L433-M433-N433) | P433: =IF(OR(O433="",C433=""),"",O433*C433) | Q433: =Q432-E433 | R433: =IF(OR(J433="",Q433=""),"",J433-Q433) | S433: =IF(D433="",S432,S432+D433) | T433: =IF(OR(L433="",S433=""),"",L433-S433) | U433: =IF(F433="",U432,U432+F433) | V433: =IF(OR(N433="",U433=""),"",N433-U433) | W433: =IF(OR(C433="",C433=0,'Daily Data'!J433=""),"",'Daily Data'!J433/C433) | X433: =IF(OR(C433="",C433=0,'Daily Data'!K433=""),"",'Daily Data'!K433/C433) | Y433: =IF(OR(F433="",W433="",X433=""),"",F433-W433-X433) | Z433: 369.48 | AA433: 65.2 | AB433: =Z433+AA433 | AC433: =IF(OR(E433="",E433=0,AB433=""),"",E433*365/(AB433*1000000)) | AD433: =IF(OR(O433="",O433=0,AB433=""),"",(AB433*1000000)/O433) | AE433: =IF(H433="","",(Team_Genesis-H433)/1000000) | AF433: =IF(OR(O433="",AE433=""),"",(O433-AE433*1000000)/1000000)
A434: 46088 | B434: =IF('Daily Data'!E434="","",'Daily Data'!E434) | C434: 30.93 | D434: 23407.54 | E434: 26487.197 | F434: 340.9178 | H434: =SUM($G$4:G434) | I434: 1000000000 | J434: =J433-E434 | K434: 60000000 | L434: 41889416 | M434: 3000000 | N434: 712246.45 | O434: =IF(OR(I434="",J434="",L434="",N434=""),"",I434-J434-K434-L434-M434-N434) | P434: =IF(OR(O434="",C434=""),"",O434*C434) | Q434: =Q433-E434 | R434: =IF(OR(J434="",Q434=""),"",J434-Q434) | S434: =IF(D434="",S433,S433+D434) | T434: =IF(OR(L434="",S434=""),"",L434-S434) | U434: =IF(F434="",U433,U433+F434) | V434: =IF(OR(N434="",U434=""),"",N434-U434) | W434: =IF(OR(C434="",C434=0,'Daily Data'!J434=""),"",'Daily Data'!J434/C434) | X434: =IF(OR(C434="",C434=0,'Daily Data'!K434=""),"",'Daily Data'!K434/C434) | Y434: =IF(OR(F434="",W434="",X434=""),"",F434-W434-X434) | Z434: 369.48 | AA434: 65.2 | AB434: =Z434+AA434 | AC434: =IF(OR(E434="",E434=0,AB434=""),"",E434*365/(AB434*1000000)) | AD434: =IF(OR(O434="",O434=0,AB434=""),"",(AB434*1000000)/O434) | AE434: =IF(H434="","",(Team_Genesis-H434)/1000000) | AF434: =IF(OR(O434="",AE434=""),"",(O434-AE434*1000000)/1000000)
A435: 46089 | B435: =IF('Daily Data'!E435="","",'Daily Data'!E435) | C435: 30.14 | D435: 38591.87 | E435: 26503.372 | F435: 231.1789 | H435: =SUM($G$4:G435) | I435: 1000000000 | J435: =J434-E435 | K435: 60000000 | L435: 41927546 | M435: 3000000 | N435: 712477.63 | O435: =IF(OR(I435="",J435="",L435="",N435=""),"",I435-J435-K435-L435-M435-N435) | P435: =IF(OR(O435="",C435=""),"",O435*C435) | Q435: =Q434-E435 | R435: =IF(OR(J435="",Q435=""),"",J435-Q435) | S435: =IF(D435="",S434,S434+D435) | T435: =IF(OR(L435="",S435=""),"",L435-S435) | U435: =IF(F435="",U434,U434+F435) | V435: =IF(OR(N435="",U435=""),"",N435-U435) | W435: =IF(OR(C435="",C435=0,'Daily Data'!J435=""),"",'Daily Data'!J435/C435) | X435: =IF(OR(C435="",C435=0,'Daily Data'!K435=""),"",'Daily Data'!K435/C435) | Y435: =IF(OR(F435="",W435="",X435=""),"",F435-W435-X435) | Z435: 369.48 | AA435: 65.2 | AB435: =Z435+AA435 | AC435: =IF(OR(E435="",E435=0,AB435=""),"",E435*365/(AB435*1000000)) | AD435: =IF(OR(O435="",O435=0,AB435=""),"",(AB435*1000000)/O435) | AE435: =IF(H435="","",(Team_Genesis-H435)/1000000) | AF435: =IF(OR(O435="",AE435=""),"",(O435-AE435*1000000)/1000000)
A436: 46090 | B436: =IF('Daily Data'!E436="","",'Daily Data'!E436) | C436: 30.97 | D436: 59871.67 | E436: 26508.149 | F436: 697.6186 | H436: =SUM($G$4:G436) | I436: 1000000000 | J436: =J435-E436 | K436: 60000000 | L436: 41987627 | M436: 3000000 | N436: 713175.25 | O436: =IF(OR(I436="",J436="",L436="",N436=""),"",I436-J436-K436-L436-M436-N436) | P436: =IF(OR(O436="",C436=""),"",O436*C436) | Q436: =Q435-E436 | R436: =IF(OR(J436="",Q436=""),"",J436-Q436) | S436: =IF(D436="",S435,S435+D436) | T436: =IF(OR(L436="",S436=""),"",L436-S436) | U436: =IF(F436="",U435,U435+F436) | V436: =IF(OR(N436="",U436=""),"",N436-U436) | W436: =IF(OR(C436="",C436=0,'Daily Data'!J436=""),"",'Daily Data'!J436/C436) | X436: =IF(OR(C436="",C436=0,'Daily Data'!K436=""),"",'Daily Data'!K436/C436) | Y436: =IF(OR(F436="",W436="",X436=""),"",F436-W436-X436) | Z436: 369.48 | AA436: 65.2 | AB436: =Z436+AA436 | AC436: =IF(OR(E436="",E436=0,AB436=""),"",E436*365/(AB436*1000000)) | AD436: =IF(OR(O436="",O436=0,AB436=""),"",(AB436*1000000)/O436) | AE436: =IF(H436="","",(Team_Genesis-H436)/1000000) | AF436: =IF(OR(O436="",AE436=""),"",(O436-AE436*1000000)/1000000)
A437: 46091 | B437: =IF('Daily Data'!E437="","",'Daily Data'!E437) | C437: 34.2 | D437: 47849.84 | E437: 26499.942 | F437: 1303.5364 | H437: =SUM($G$4:G437) | I437: 1000000000 | J437: =J436-E437 | K437: 60000000 | L437: 42035734 | M437: 3000000 | N437: 714478.79 | O437: =IF(OR(I437="",J437="",L437="",N437=""),"",I437-J437-K437-L437-M437-N437) | P437: =IF(OR(O437="",C437=""),"",O437*C437) | Q437: =Q436-E437 | R437: =IF(OR(J437="",Q437=""),"",J437-Q437) | S437: =IF(D437="",S436,S436+D437) | T437: =IF(OR(L437="",S437=""),"",L437-S437) | U437: =IF(F437="",U436,U436+F437) | V437: =IF(OR(N437="",U437=""),"",N437-U437) | W437: =IF(OR(C437="",C437=0,'Daily Data'!J437=""),"",'Daily Data'!J437/C437) | X437: =IF(OR(C437="",C437=0,'Daily Data'!K437=""),"",'Daily Data'!K437/C437) | Y437: =IF(OR(F437="",W437="",X437=""),"",F437-W437-X437) | Z437: 369.48 | AA437: 65.2 | AB437: =Z437+AA437 | AC437: =IF(OR(E437="",E437=0,AB437=""),"",E437*365/(AB437*1000000)) | AD437: =IF(OR(O437="",O437=0,AB437=""),"",(AB437*1000000)/O437) | AE437: =IF(H437="","",(Team_Genesis-H437)/1000000) | AF437: =IF(OR(O437="",AE437=""),"",(O437-AE437*1000000)/1000000)
A438: 46092 | B438: =IF('Daily Data'!E438="","",'Daily Data'!E438) | C438: 34.3 | D438: 38974.26 | E438: 26523.22 | F438: 1078.4004 | H438: =SUM($G$4:G438) | I438: 1000000000 | J438: =J437-E438 | K438: 60000000 | L438: 42073713 | M438: 3000000 | N438: 715557.19 | O438: =IF(OR(I438="",J438="",L438="",N438=""),"",I438-J438-K438-L438-M438-N438) | P438: =IF(OR(O438="",C438=""),"",O438*C438) | Q438: =Q437-E438 | R438: =IF(OR(J438="",Q438=""),"",J438-Q438) | S438: =IF(D438="",S437,S437+D438) | T438: =IF(OR(L438="",S438=""),"",L438-S438) | U438: =IF(F438="",U437,U437+F438) | V438: =IF(OR(N438="",U438=""),"",N438-U438) | W438: =IF(OR(C438="",C438=0,'Daily Data'!J438=""),"",'Daily Data'!J438/C438) | X438: =IF(OR(C438="",C438=0,'Daily Data'!K438=""),"",'Daily Data'!K438/C438) | Y438: =IF(OR(F438="",W438="",X438=""),"",F438-W438-X438) | Z438: 369.48 | AA438: 65.2 | AB438: =Z438+AA438 | AC438: =IF(OR(E438="",E438=0,AB438=""),"",E438*365/(AB438*1000000)) | AD438: =IF(OR(O438="",O438=0,AB438=""),"",(AB438*1000000)/O438) | AE438: =IF(H438="","",(Team_Genesis-H438)/1000000) | AF438: =IF(OR(O438="",AE438=""),"",(O438-AE438*1000000)/1000000)
A439: 46093 | B439: =IF('Daily Data'!E439="","",'Daily Data'!E439) | C439: 36.38 | D439: 36803.51 | E439: 26526.823 | F439: 608.4577 | H439: =SUM($G$4:G439) | I439: 1000000000 | J439: =J438-E439 | K439: 60000000 | L439: 42110130 | M439: 3000000 | N439: 716165.65 | O439: =IF(OR(I439="",J439="",L439="",N439=""),"",I439-J439-K439-L439-M439-N439) | P439: =IF(OR(O439="",C439=""),"",O439*C439) | Q439: =Q438-E439 | R439: =IF(OR(J439="",Q439=""),"",J439-Q439) | S439: =IF(D439="",S438,S438+D439) | T439: =IF(OR(L439="",S439=""),"",L439-S439) | U439: =IF(F439="",U438,U438+F439) | V439: =IF(OR(N439="",U439=""),"",N439-U439) | W439: =IF(OR(C439="",C439=0,'Daily Data'!J439=""),"",'Daily Data'!J439/C439) | X439: =IF(OR(C439="",C439=0,'Daily Data'!K439=""),"",'Daily Data'!K439/C439) | Y439: =IF(OR(F439="",W439="",X439=""),"",F439-W439-X439) | Z439: 369.48 | AA439: 65.2 | AB439: =Z439+AA439 | AC439: =IF(OR(E439="",E439=0,AB439=""),"",E439*365/(AB439*1000000)) | AD439: =IF(OR(O439="",O439=0,AB439=""),"",(AB439*1000000)/O439) | AE439: =IF(H439="","",(Team_Genesis-H439)/1000000) | AF439: =IF(OR(O439="",AE439=""),"",(O439-AE439*1000000)/1000000)
A440: 46094 | B440: =IF('Daily Data'!E440="","",'Daily Data'!E440) | C440: 37.81 | D440: 49323.48 | E440: 26531.676 | F440: 1118.0109 | H440: =SUM($G$4:G440) | I440: 1000000000 | J440: =J439-E440 | K440: 60000000 | L440: 42160887 | M440: 3000000 | N440: 717283.66 | O440: =IF(OR(I440="",J440="",L440="",N440=""),"",I440-J440-K440-L440-M440-N440) | P440: =IF(OR(O440="",C440=""),"",O440*C440) | Q440: =Q439-E440 | R440: =IF(OR(J440="",Q440=""),"",J440-Q440) | S440: =IF(D440="",S439,S439+D440) | T440: =IF(OR(L440="",S440=""),"",L440-S440) | U440: =IF(F440="",U439,U439+F440) | V440: =IF(OR(N440="",U440=""),"",N440-U440) | W440: =IF(OR(C440="",C440=0,'Daily Data'!J440=""),"",'Daily Data'!J440/C440) | X440: =IF(OR(C440="",C440=0,'Daily Data'!K440=""),"",'Daily Data'!K440/C440) | Y440: =IF(OR(F440="",W440="",X440=""),"",F440-W440-X440) | Z440: 369.48 | AA440: 65.2 | AB440: =Z440+AA440 | AC440: =IF(OR(E440="",E440=0,AB440=""),"",E440*365/(AB440*1000000)) | AD440: =IF(OR(O440="",O440=0,AB440=""),"",(AB440*1000000)/O440) | AE440: =IF(H440="","",(Team_Genesis-H440)/1000000) | AF440: =IF(OR(O440="",AE440=""),"",(O440-AE440*1000000)/1000000)
A441: 46095 | B441: =IF('Daily Data'!E441="","",'Daily Data'!E441) | C441: 36.59 | D441: 16809.89 | E441: 26522.557 | F441: 1169.2845 | H441: =SUM($G$4:G441) | I441: 1000000000 | J441: =J440-E441 | K441: 60000000 | L441: 42176729 | M441: 3000000 | N441: 718452.94 | O441: =IF(OR(I441="",J441="",L441="",N441=""),"",I441-J441-K441-L441-M441-N441) | P441: =IF(OR(O441="",C441=""),"",O441*C441) | Q441: =Q440-E441 | R441: =IF(OR(J441="",Q441=""),"",J441-Q441) | S441: =IF(D441="",S440,S440+D441) | T441: =IF(OR(L441="",S441=""),"",L441-S441) | U441: =IF(F441="",U440,U440+F441) | V441: =IF(OR(N441="",U441=""),"",N441-U441) | W441: =IF(OR(C441="",C441=0,'Daily Data'!J441=""),"",'Daily Data'!J441/C441) | X441: =IF(OR(C441="",C441=0,'Daily Data'!K441=""),"",'Daily Data'!K441/C441) | Y441: =IF(OR(F441="",W441="",X441=""),"",F441-W441-X441) | Z441: 369.48 | AA441: 65.2 | AB441: =Z441+AA441 | AC441: =IF(OR(E441="",E441=0,AB441=""),"",E441*365/(AB441*1000000)) | AD441: =IF(OR(O441="",O441=0,AB441=""),"",(AB441*1000000)/O441) | AE441: =IF(H441="","",(Team_Genesis-H441)/1000000) | AF441: =IF(OR(O441="",AE441=""),"",(O441-AE441*1000000)/1000000)
A442: 46096 | B442: =IF('Daily Data'!E442="","",'Daily Data'!E442) | C442: 37.67 | D442: 24882.62 | E442: 26513.68 | F442: 280.2648 | H442: =SUM($G$4:G442) | I442: 1000000000 | J442: =J441-E442 | K442: 60000000 | L442: 42202160 | M442: 3000000 | N442: 718733.21 | O442: =IF(OR(I442="",J442="",L442="",N442=""),"",I442-J442-K442-L442-M442-N442) | P442: =IF(OR(O442="",C442=""),"",O442*C442) | Q442: =Q441-E442 | R442: =IF(OR(J442="",Q442=""),"",J442-Q442) | S442: =IF(D442="",S441,S441+D442) | T442: =IF(OR(L442="",S442=""),"",L442-S442) | U442: =IF(F442="",U441,U441+F442) | V442: =IF(OR(N442="",U442=""),"",N442-U442) | W442: =IF(OR(C442="",C442=0,'Daily Data'!J442=""),"",'Daily Data'!J442/C442) | X442: =IF(OR(C442="",C442=0,'Daily Data'!K442=""),"",'Daily Data'!K442/C442) | Y442: =IF(OR(F442="",W442="",X442=""),"",F442-W442-X442) | Z442: 369.48 | AA442: 65.2 | AB442: =Z442+AA442 | AC442: =IF(OR(E442="",E442=0,AB442=""),"",E442*365/(AB442*1000000)) | AD442: =IF(OR(O442="",O442=0,AB442=""),"",(AB442*1000000)/O442) | AE442: =IF(H442="","",(Team_Genesis-H442)/1000000) | AF442: =IF(OR(O442="",AE442=""),"",(O442-AE442*1000000)/1000000)
A443: 46097 | B443: =IF('Daily Data'!E443="","",'Daily Data'!E443) | C443: 37.38 | D443: 52403.88 | E443: 26158.165 | F443: 690.6835 | H443: =SUM($G$4:G443) | I443: 1000000000 | J443: =J442-E443 | K443: 60000000 | L443: 42256896 | M443: 3000000 | N443: 719423.89 | O443: =IF(OR(I443="",J443="",L443="",N443=""),"",I443-J443-K443-L443-M443-N443) | P443: =IF(OR(O443="",C443=""),"",O443*C443) | Q443: =Q442-E443 | R443: =IF(OR(J443="",Q443=""),"",J443-Q443) | S443: =IF(D443="",S442,S442+D443) | T443: =IF(OR(L443="",S443=""),"",L443-S443) | U443: =IF(F443="",U442,U442+F443) | V443: =IF(OR(N443="",U443=""),"",N443-U443) | W443: =IF(OR(C443="",C443=0,'Daily Data'!J443=""),"",'Daily Data'!J443/C443) | X443: =IF(OR(C443="",C443=0,'Daily Data'!K443=""),"",'Daily Data'!K443/C443) | Y443: =IF(OR(F443="",W443="",X443=""),"",F443-W443-X443) | Z443: 369.48 | AA443: 65.2 | AB443: =Z443+AA443 | AC443: =IF(OR(E443="",E443=0,AB443=""),"",E443*365/(AB443*1000000)) | AD443: =IF(OR(O443="",O443=0,AB443=""),"",(AB443*1000000)/O443) | AE443: =IF(H443="","",(Team_Genesis-H443)/1000000) | AF443: =IF(OR(O443="",AE443=""),"",(O443-AE443*1000000)/1000000)
A444: 46098 | B444: =IF('Daily Data'!E444="","",'Daily Data'!E444) | C444: 40.63 | D444: 42168.48 | E444: 25920.25 | F444: 688.104 | H444: =SUM($G$4:G444) | I444: 1000000000 | J444: =J443-E444 | K444: 60000000 | L444: 42296552 | M444: 3000000 | N444: 720111.99 | O444: =IF(OR(I444="",J444="",L444="",N444=""),"",I444-J444-K444-L444-M444-N444) | P444: =IF(OR(O444="",C444=""),"",O444*C444) | Q444: =Q443-E444 | R444: =IF(OR(J444="",Q444=""),"",J444-Q444) | S444: =IF(D444="",S443,S443+D444) | T444: =IF(OR(L444="",S444=""),"",L444-S444) | U444: =IF(F444="",U443,U443+F444) | V444: =IF(OR(N444="",U444=""),"",N444-U444) | W444: =IF(OR(C444="",C444=0,'Daily Data'!J444=""),"",'Daily Data'!J444/C444) | X444: =IF(OR(C444="",C444=0,'Daily Data'!K444=""),"",'Daily Data'!K444/C444) | Y444: =IF(OR(F444="",W444="",X444=""),"",F444-W444-X444) | Z444: 369.48 | AA444: 65.2 | AB444: =Z444+AA444 | AC444: =IF(OR(E444="",E444=0,AB444=""),"",E444*365/(AB444*1000000)) | AD444: =IF(OR(O444="",O444=0,AB444=""),"",(AB444*1000000)/O444) | AE444: =IF(H444="","",(Team_Genesis-H444)/1000000) | AF444: =IF(OR(O444="",AE444=""),"",(O444-AE444*1000000)/1000000)
A445: 46099 | B445: =IF('Daily Data'!E445="","",'Daily Data'!E445) | C445: 40.73 | D445: 46408.79 | E445: 26481.171 | F445: 1001.0048 | H445: =SUM($G$4:G445) | I445: 1000000000 | J445: =J444-E445 | K445: 60000000 | L445: 42343472 | M445: 3000000 | N445: 721113 | O445: =IF(OR(I445="",J445="",L445="",N445=""),"",I445-J445-K445-L445-M445-N445) | P445: =IF(OR(O445="",C445=""),"",O445*C445) | Q445: =Q444-E445 | R445: =IF(OR(J445="",Q445=""),"",J445-Q445) | S445: =IF(D445="",S444,S444+D445) | T445: =IF(OR(L445="",S445=""),"",L445-S445) | U445: =IF(F445="",U444,U444+F445) | V445: =IF(OR(N445="",U445=""),"",N445-U445) | W445: =IF(OR(C445="",C445=0,'Daily Data'!J445=""),"",'Daily Data'!J445/C445) | X445: =IF(OR(C445="",C445=0,'Daily Data'!K445=""),"",'Daily Data'!K445/C445) | Y445: =IF(OR(F445="",W445="",X445=""),"",F445-W445-X445) | Z445: 369.48 | AA445: 65.2 | AB445: =Z445+AA445 | AC445: =IF(OR(E445="",E445=0,AB445=""),"",E445*365/(AB445*1000000)) | AD445: =IF(OR(O445="",O445=0,AB445=""),"",(AB445*1000000)/O445) | AE445: =IF(H445="","",(Team_Genesis-H445)/1000000) | AF445: =IF(OR(O445="",AE445=""),"",(O445-AE445*1000000)/1000000)
... A463: 46117 | B463: =IF('Daily Data'!E463="","",'Daily Data'!E463) | C463: 36.23 | D463: 16362.22 | E463: 26393.445 | F463: 125.9566 | H463: =SUM($G$4:G463) | I463: 1000000000 | J463: =J462-E463 | K463: 60000000 | L463: 42945223 | M463: 3000000 | N463: 735090.19 | O463: =IF(OR(I463="",J463="",L463="",N463=""),"",I463-J463-K463-L463-M463-N463) | P463: =IF(OR(O463="",C463=""),"",O463*C463) | Q463: =Q462-E463 | R463: =IF(OR(J463="",Q463=""),"",J463-Q463) | S463: =IF(D463="",S462,S462+D463) | T463: =IF(OR(L463="",S463=""),"",L463-S463) | U463: =IF(F463="",U462,U462+F463) | V463: =IF(OR(N463="",U463=""),"",N463-U463) | W463: =IF(OR(C463="",C463=0,'Daily Data'!J463=""),"",'Daily Data'!J463/C463) | X463: =IF(OR(C463="",C463=0,'Daily Data'!K463=""),"",'Daily Data'!K463/C463) | Y463: =IF(OR(F463="",W463="",X463=""),"",F463-W463-X463) | Z463: 367.87 | AA463: 64.92 | AB463: =Z463+AA463 | AC463: =IF(OR(E463="",E463=0,AB463=""),"",E463*365/(AB463*1000000)) | AD463: =IF(OR(O463="",O463=0,AB463=""),"",(AB463*1000000)/O463) | AE463: =IF(H463="","",(Team_Genesis-H463)/1000000) | AF463: =IF(OR(O463="",AE463=""),"",(O463-AE463*1000000)/1000000)
A464: 46118 | B464: =IF('Daily Data'!E464="","",'Daily Data'!E464) | C464: 36.67 | D464: 46080.62 | E464: 26398.453 | F464: 170.212 | G464: 330000 | H464: =SUM($G$4:G464) | I464: 1000000000 | J464: =J463-E464 | K464: 60000000 | L464: 42982589 | M464: 3000000 | N464: 735260.41 | O464: =IF(OR(I464="",J464="",L464="",N464=""),"",I464-J464-K464-L464-M464-N464) | P464: =IF(OR(O464="",C464=""),"",O464*C464) | Q464: =Q463-E464 | R464: =IF(OR(J464="",Q464=""),"",J464-Q464) | S464: =IF(D464="",S463,S463+D464) | T464: =IF(OR(L464="",S464=""),"",L464-S464) | U464: =IF(F464="",U463,U463+F464) | V464: =IF(OR(N464="",U464=""),"",N464-U464) | W464: =IF(OR(C464="",C464=0,'Daily Data'!J464=""),"",'Daily Data'!J464/C464) | X464: =IF(OR(C464="",C464=0,'Daily Data'!K464=""),"",'Daily Data'!K464/C464) | Y464: =IF(OR(F464="",W464="",X464=""),"",F464-W464-X464) | Z464: 367.87 | AA464: 64.92 | AB464: =Z464+AA464 | AC464: =IF(OR(E464="",E464=0,AB464=""),"",E464*365/(AB464*1000000)) | AD464: =IF(OR(O464="",O464=0,AB464=""),"",(AB464*1000000)/O464) | AE464: =IF(H464="","",(Team_Genesis-H464)/1000000) | AF464: =IF(OR(O464="",AE464=""),"",(O464-AE464*1000000)/1000000)
A465: 46119 | B465: =IF('Daily Data'!E465="","",'Daily Data'!E465) | C465: 36.47 | D465: 35674.93 | E465: 26394.375 | F465: 1310.5848 | H465: =SUM($G$4:G465) | I465: 1000000000 | J465: =J464-E465 | K465: 60000000 | L465: 43028188 | M465: 3000000 | N465: 736570.99 | O465: =IF(OR(I465="",J465="",L465="",N465=""),"",I465-J465-K465-L465-M465-N465) | P465: =IF(OR(O465="",C465=""),"",O465*C465) | Q465: =Q464-E465 | R465: =IF(OR(J465="",Q465=""),"",J465-Q465) | S465: =IF(D465="",S464,S464+D465) | T465: =IF(OR(L465="",S465=""),"",L465-S465) | U465: =IF(F465="",U464,U464+F465) | V465: =IF(OR(N465="",U465=""),"",N465-U465) | W465: =IF(OR(C465="",C465=0,'Daily Data'!J465=""),"",'Daily Data'!J465/C465) | X465: =IF(OR(C465="",C465=0,'Daily Data'!K465=""),"",'Daily Data'!K465/C465) | Y465: =IF(OR(F465="",W465="",X465=""),"",F465-W465-X465) | Z465: 367.87 | AA465: 64.92 | AB465: =Z465+AA465 | AC465: =IF(OR(E465="",E465=0,AB465=""),"",E465*365/(AB465*1000000)) | AD465: =IF(OR(O465="",O465=0,AB465=""),"",(AB465*1000000)/O465) | AE465: =IF(H465="","",(Team_Genesis-H465)/1000000) | AF465: =IF(OR(O465="",AE465=""),"",(O465-AE465*1000000)/1000000)
A466: 46120 | B466: =IF('Daily Data'!E466="","",'Daily Data'!E466) | C466: 38.59 | D466: 65114.98 | E466: 26391.427 | F466: 961.1906 | H466: =SUM($G$4:G466) | I466: 1000000000 | J466: =J465-E466 | K466: 60000000 | L466: 43083756 | M466: 3000000 | N466: 737532.18 | O466: =IF(OR(I466="",J466="",L466="",N466=""),"",I466-J466-K466-L466-M466-N466) | P466: =IF(OR(O466="",C466=""),"",O466*C466) | Q466: =Q465-E466 | R466: =IF(OR(J466="",Q466=""),"",J466-Q466) | S466: =IF(D466="",S465,S465+D466) | T466: =IF(OR(L466="",S466=""),"",L466-S466) | U466: =IF(F466="",U465,U465+F466) | V466: =IF(OR(N466="",U466=""),"",N466-U466) | W466: =IF(OR(C466="",C466=0,'Daily Data'!J466=""),"",'Daily Data'!J466/C466) | X466: =IF(OR(C466="",C466=0,'Daily Data'!K466=""),"",'Daily Data'!K466/C466) | Y466: =IF(OR(F466="",W466="",X466=""),"",F466-W466-X466) | Z466: 367.87 | AA466: 64.92 | AB466: =Z466+AA466 | AC466: =IF(OR(E466="",E466=0,AB466=""),"",E466*365/(AB466*1000000)) | AD466: =IF(OR(O466="",O466=0,AB466=""),"",(AB466*1000000)/O466) | AE466: =IF(H466="","",(Team_Genesis-H466)/1000000) | AF466: =IF(OR(O466="",AE466=""),"",(O466-AE466*1000000)/1000000)
A467: 46121 | B467: =IF('Daily Data'!E467="","",'Daily Data'!E467) | C467: 38.35 | D467: 42446.07 | E467: 26388.957 | F467: 1181.5189 | H467: =SUM($G$4:G467) | I467: 1000000000 | J467: =J466-E467 | K467: 60000000 | L467: 43125925 | M467: 3000000 | N467: 738713.7 | O467: =IF(OR(I467="",J467="",L467="",N467=""),"",I467-J467-K467-L467-M467-N467) | P467: =IF(OR(O467="",C467=""),"",O467*C467) | Q467: =Q466-E467 | R467: =IF(OR(J467="",Q467=""),"",J467-Q467) | S467: =IF(D467="",S466,S466+D467) | T467: =IF(OR(L467="",S467=""),"",L467-S467) | U467: =IF(F467="",U466,U466+F467) | V467: =IF(OR(N467="",U467=""),"",N467-U467) | W467: =IF(OR(C467="",C467=0,'Daily Data'!J467=""),"",'Daily Data'!J467/C467) | X467: =IF(OR(C467="",C467=0,'Daily Data'!K467=""),"",'Daily Data'!K467/C467) | Y467: =IF(OR(F467="",W467="",X467=""),"",F467-W467-X467) | Z467: 367.87 | AA467: 64.92 | AB467: =Z467+AA467 | AC467: =IF(OR(E467="",E467=0,AB467=""),"",E467*365/(AB467*1000000)) | AD467: =IF(OR(O467="",O467=0,AB467=""),"",(AB467*1000000)/O467) | AE467: =IF(H467="","",(Team_Genesis-H467)/1000000) | AF467: =IF(OR(O467="",AE467=""),"",(O467-AE467*1000000)/1000000)
A468: 46122 | B468: =IF('Daily Data'!E468="","",'Daily Data'!E468) | C468: 39.95 | D468: 31405.46 | E468: 26243.215 | F468: 841.2268 | H468: =SUM($G$4:G468) | I468: 1000000000 | J468: =J467-E468 | K468: 60000000 | L468: 43157464 | M468: 3000000 | N468: 739554.93 | O468: =IF(OR(I468="",J468="",L468="",N468=""),"",I468-J468-K468-L468-M468-N468) | P468: =IF(OR(O468="",C468=""),"",O468*C468) | Q468: =Q467-E468 | R468: =IF(OR(J468="",Q468=""),"",J468-Q468) | S468: =IF(D468="",S467,S467+D468) | T468: =IF(OR(L468="",S468=""),"",L468-S468) | U468: =IF(F468="",U467,U467+F468) | V468: =IF(OR(N468="",U468=""),"",N468-U468) | W468: =IF(OR(C468="",C468=0,'Daily Data'!J468=""),"",'Daily Data'!J468/C468) | X468: =IF(OR(C468="",C468=0,'Daily Data'!K468=""),"",'Daily Data'!K468/C468) | Y468: =IF(OR(F468="",W468="",X468=""),"",F468-W468-X468) | Z468: 367.87 | AA468: 64.92 | AB468: =Z468+AA468 | AC468: =IF(OR(E468="",E468=0,AB468=""),"",E468*365/(AB468*1000000)) | AD468: =IF(OR(O468="",O468=0,AB468=""),"",(AB468*1000000)/O468) | AE468: =IF(H468="","",(Team_Genesis-H468)/1000000) | AF468: =IF(OR(O468="",AE468=""),"",(O468-AE468*1000000)/1000000)
A469: 46123 | B469: =IF('Daily Data'!E469="","",'Daily Data'!E469) | C469: 41.59 | D469: 17727.89 | E469: 26333.501 | F469: 435.9036 | H469: =SUM($G$4:G469) | I469: 1000000000 | J469: =J468-E469 | K469: 60000000 | L469: 43175392 | M469: 3000000 | N469: 739990.83 | O469: =IF(OR(I469="",J469="",L469="",N469=""),"",I469-J469-K469-L469-M469-N469) | P469: =IF(OR(O469="",C469=""),"",O469*C469) | Q469: =Q468-E469 | R469: =IF(OR(J469="",Q469=""),"",J469-Q469) | S469: =IF(D469="",S468,S468+D469) | T469: =IF(OR(L469="",S469=""),"",L469-S469) | U469: =IF(F469="",U468,U468+F469) | V469: =IF(OR(N469="",U469=""),"",N469-U469) | W469: =IF(OR(C469="",C469=0,'Daily Data'!J469=""),"",'Daily Data'!J469/C469) | X469: =IF(OR(C469="",C469=0,'Daily Data'!K469=""),"",'Daily Data'!K469/C469) | Y469: =IF(OR(F469="",W469="",X469=""),"",F469-W469-X469) | Z469: 367.87 | AA469: 64.92 | AB469: =Z469+AA469 | AC469: =IF(OR(E469="",E469=0,AB469=""),"",E469*365/(AB469*1000000)) | AD469: =IF(OR(O469="",O469=0,AB469=""),"",(AB469*1000000)/O469) | AE469: =IF(H469="","",(Team_Genesis-H469)/1000000) | AF469: =IF(OR(O469="",AE469=""),"",(O469-AE469*1000000)/1000000)
A470: 46124 | B470: =IF('Daily Data'!E470="","",'Daily Data'!E470) | C470: 42.54 | D470: 27717.87 | E470: 26419.813 | F470: 718.5359 | H470: =SUM($G$4:G470) | I470: 1000000000 | J470: =J469-E470 | K470: 60000000 | L470: 43202404 | M470: 3000000 | N470: 740709.37 | O470: =IF(OR(I470="",J470="",L470="",N470=""),"",I470-J470-K470-L470-M470-N470) | P470: =IF(OR(O470="",C470=""),"",O470*C470) | Q470: =Q469-E470 | R470: =IF(OR(J470="",Q470=""),"",J470-Q470) | S470: =IF(D470="",S469,S469+D470) | T470: =IF(OR(L470="",S470=""),"",L470-S470) | U470: =IF(F470="",U469,U469+F470) | V470: =IF(OR(N470="",U470=""),"",N470-U470) | W470: =IF(OR(C470="",C470=0,'Daily Data'!J470=""),"",'Daily Data'!J470/C470) | X470: =IF(OR(C470="",C470=0,'Daily Data'!K470=""),"",'Daily Data'!K470/C470) | Y470: =IF(OR(F470="",W470="",X470=""),"",F470-W470-X470) | Z470: 367.87 | AA470: 64.92 | AB470: =Z470+AA470 | AC470: =IF(OR(E470="",E470=0,AB470=""),"",E470*365/(AB470*1000000)) | AD470: =IF(OR(O470="",O470=0,AB470=""),"",(AB470*1000000)/O470) | AE470: =IF(H470="","",(Team_Genesis-H470)/1000000) | AF470: =IF(OR(O470="",AE470=""),"",(O470-AE470*1000000)/1000000)
A471: 46125 | B471: =IF('Daily Data'!E471="","",'Daily Data'!E471) | C471: 41.05 | D471: 39230.22 | E471: 26416.9 | F471: 228.6712 | H471: =SUM($G$4:G471) | I471: 1000000000 | J471: =J470-E471 | K471: 60000000 | L471: 43242558 | M471: 3000000 | N471: 740938.04 | O471: =IF(OR(I471="",J471="",L471="",N471=""),"",I471-J471-K471-L471-M471-N471) | P471: =IF(OR(O471="",C471=""),"",O471*C471) | Q471: =Q470-E471 | R471: =IF(OR(J471="",Q471=""),"",J471-Q471) | S471: =IF(D471="",S470,S470+D471) | T471: =IF(OR(L471="",S471=""),"",L471-S471) | U471: =IF(F471="",U470,U470+F471) | V471: =IF(OR(N471="",U471=""),"",N471-U471) | W471: =IF(OR(C471="",C471=0,'Daily Data'!J471=""),"",'Daily Data'!J471/C471) | X471: =IF(OR(C471="",C471=0,'Daily Data'!K471=""),"",'Daily Data'!K471/C471) | Y471: =IF(OR(F471="",W471="",X471=""),"",F471-W471-X471) | Z471: 367.87 | AA471: 64.92 | AB471: =Z471+AA471 | AC471: =IF(OR(E471="",E471=0,AB471=""),"",E471*365/(AB471*1000000)) | AD471: =IF(OR(O471="",O471=0,AB471=""),"",(AB471*1000000)/O471) | AE471: =IF(H471="","",(Team_Genesis-H471)/1000000) | AF471: =IF(OR(O471="",AE471=""),"",(O471-AE471*1000000)/1000000)
A472: 46126 | B472: =IF('Daily Data'!E472="","",'Daily Data'!E472) | C472: 44.77 | D472: 42938.42 | E472: 26453.286 | F472: 997.557 | H472: =SUM($G$4:G472) | I472: 1000000000 | J472: =J471-E472 | K472: 60000000 | L472: 43285638 | M472: 3000000 | N472: 741935.59 | O472: =IF(OR(I472="",J472="",L472="",N472=""),"",I472-J472-K472-L472-M472-N472) | P472: =IF(OR(O472="",C472=""),"",O472*C472) | Q472: =Q471-E472 | R472: =IF(OR(J472="",Q472=""),"",J472-Q472) | S472: =IF(D472="",S471,S471+D472) | T472: =IF(OR(L472="",S472=""),"",L472-S472) | U472: =IF(F472="",U471,U471+F472) | V472: =IF(OR(N472="",U472=""),"",N472-U472) | W472: =IF(OR(C472="",C472=0,'Daily Data'!J472=""),"",'Daily Data'!J472/C472) | X472: =IF(OR(C472="",C472=0,'Daily Data'!K472=""),"",'Daily Data'!K472/C472) | Y472: =IF(OR(F472="",W472="",X472=""),"",F472-W472-X472) | Z472: 367.87 | AA472: 64.92 | AB472: =Z472+AA472 | AC472: =IF(OR(E472="",E472=0,AB472=""),"",E472*365/(AB472*1000000)) | AD472: =IF(OR(O472="",O472=0,AB472=""),"",(AB472*1000000)/O472) | AE472: =IF(H472="","",(Team_Genesis-H472)/1000000) | AF472: =IF(OR(O472="",AE472=""),"",(O472-AE472*1000000)/1000000)
A473: 46127 | B473: =IF('Daily Data'!E473="","",'Daily Data'!E473) | C473: 43.8 | D473: 29919.89 | E473: 26464.657 | F473: 421.2748 | H473: =SUM($G$4:G473) | I473: 1000000000 | J473: =J472-E473 | K473: 60000000 | L473: 43315330 | M473: 3000000 | N473: 742356.87 | O473: =IF(OR(I473="",J473="",L473="",N473=""),"",I473-J473-K473-L473-M473-N473) | P473: =IF(OR(O473="",C473=""),"",O473*C473) | Q473: =Q472-E473 | R473: =IF(OR(J473="",Q473=""),"",J473-Q473) | S473: =IF(D473="",S472,S472+D473) | T473: =IF(OR(L473="",S473=""),"",L473-S473) | U473: =IF(F473="",U472,U472+F473) | V473: =IF(OR(N473="",U473=""),"",N473-U473) | W473: =IF(OR(C473="",C473=0,'Daily Data'!J473=""),"",'Daily Data'!J473/C473) | X473: =IF(OR(C473="",C473=0,'Daily Data'!K473=""),"",'Daily Data'!K473/C473) | Y473: =IF(OR(F473="",W473="",X473=""),"",F473-W473-X473) | Z473: 367.87 | AA473: 64.92 | AB473: =Z473+AA473 | AC473: =IF(OR(E473="",E473=0,AB473=""),"",E473*365/(AB473*1000000)) | AD473: =IF(OR(O473="",O473=0,AB473=""),"",(AB473*1000000)/O473) | AE473: =IF(H473="","",(Team_Genesis-H473)/1000000) | AF473: =IF(OR(O473="",AE473=""),"",(O473-AE473*1000000)/1000000)
A474: 46128 | B474: =IF('Daily Data'!E474="","",'Daily Data'!E474) | C474: 44.53 | D474: 37404.67 | E474: 26464.585 | F474: 1297.7344 | H474: =SUM($G$4:G474) | I474: 1000000000 | J474: =J473-E474 | K474: 60000000 | L474: 43352297 | M474: 3000000 | N474: 743654.6 | O474: =IF(OR(I474="",J474="",L474="",N474=""),"",I474-J474-K474-L474-M474-N474) | P474: =IF(OR(O474="",C474=""),"",O474*C474) | Q474: =Q473-E474 | R474: =IF(OR(J474="",Q474=""),"",J474-Q474) | S474: =IF(D474="",S473,S473+D474) | T474: =IF(OR(L474="",S474=""),"",L474-S474) | U474: =IF(F474="",U473,U473+F474) | V474: =IF(OR(N474="",U474=""),"",N474-U474) | W474: =IF(OR(C474="",C474=0,'Daily Data'!J474=""),"",'Daily Data'!J474/C474) | X474: =IF(OR(C474="",C474=0,'Daily Data'!K474=""),"",'Daily Data'!K474/C474) | Y474: =IF(OR(F474="",W474="",X474=""),"",F474-W474-X474) | Z474: 367.87 | AA474: 64.92 | AB474: =Z474+AA474 | AC474: =IF(OR(E474="",E474=0,AB474=""),"",E474*365/(AB474*1000000)) | AD474: =IF(OR(O474="",O474=0,AB474=""),"",(AB474*1000000)/O474) | AE474: =IF(H474="","",(Team_Genesis-H474)/1000000) | AF474: =IF(OR(O474="",AE474=""),"",(O474-AE474*1000000)/1000000)
A475: 46129 | B475: =IF('Daily Data'!E475="","",'Daily Data'!E475) | C475: 44.09 | D475: 43321.04 | E475: 26437.098 | F475: 555.5301 | H475: =SUM($G$4:G475) | I475: 1000000000 | J475: =J474-E475 | K475: 60000000 | L475: 43395449 | M475: 3000000 | N475: 744210.13 | O475: =IF(OR(I475="",J475="",L475="",N475=""),"",I475-J475-K475-L475-M475-N475) | P475: =IF(OR(O475="",C475=""),"",O475*C475) | Q475: =Q474-E475 | R475: =IF(OR(J475="",Q475=""),"",J475-Q475) | S475: =IF(D475="",S474,S474+D475) | T475: =IF(OR(L475="",S475=""),"",L475-S475) | U475: =IF(F475="",U474,U474+F475) | V475: =IF(OR(N475="",U475=""),"",N475-U475) | W475: =IF(OR(C475="",C475=0,'Daily Data'!J475=""),"",'Daily Data'!J475/C475) | X475: =IF(OR(C475="",C475=0,'Daily Data'!K475=""),"",'Daily Data'!K475/C475) | Y475: =IF(OR(F475="",W475="",X475=""),"",F475-W475-X475) | Z475: 367.87 | AA475: 64.92 | AB475: =Z475+AA475 | AC475: =IF(OR(E475="",E475=0,AB475=""),"",E475*365/(AB475*1000000)) | AD475: =IF(OR(O475="",O475=0,AB475=""),"",(AB475*1000000)/O475) | AE475: =IF(H475="","",(Team_Genesis-H475)/1000000) | AF475: =IF(OR(O475="",AE475=""),"",(O475-AE475*1000000)/1000000)
A476: 46130 | B476: =IF('Daily Data'!E476="","",'Daily Data'!E476) | C476: 44.77 | D476: 19741.81 | E476: 26451.373 | F476: 1425.6598 | H476: =SUM($G$4:G476) | I476: 1000000000 | J476: =J475-E476 | K476: 60000000 | L476: 43415763 | M476: 3000000 | N476: 745635.79 | O476: =IF(OR(I476="",J476="",L476="",N476=""),"",I476-J476-K476-L476-M476-N476) | P476: =IF(OR(O476="",C476=""),"",O476*C476) | Q476: =Q475-E476 | R476: =IF(OR(J476="",Q476=""),"",J476-Q476) | S476: =IF(D476="",S475,S475+D476) | T476: =IF(OR(L476="",S476=""),"",L476-S476) | U476: =IF(F476="",U475,U475+F476) | V476: =IF(OR(N476="",U476=""),"",N476-U476) | W476: =IF(OR(C476="",C476=0,'Daily Data'!J476=""),"",'Daily Data'!J476/C476) | X476: =IF(OR(C476="",C476=0,'Daily Data'!K476=""),"",'Daily Data'!K476/C476) | Y476: =IF(OR(F476="",W476="",X476=""),"",F476-W476-X476) | Z476: 367.87 | AA476: 64.92 | AB476: =Z476+AA476 | AC476: =IF(OR(E476="",E476=0,AB476=""),"",E476*365/(AB476*1000000)) | AD476: =IF(OR(O476="",O476=0,AB476=""),"",(AB476*1000000)/O476) | AE476: =IF(H476="","",(Team_Genesis-H476)/1000000) | AF476: =IF(OR(O476="",AE476=""),"",(O476-AE476*1000000)/1000000)
...

Sheet Daily Data
A1: DAILY DATA — raw inputs by source. hyperscreener.asxn.xyz · Loris (loris.tools) · DefiLlama
B2: hyperscreener | C2: hyperscreener | D2: Loris | E2: hyperscreener / DefiLlama | F2: Loris | G2: Loris | H2: DefiLlama | I2: DefiLlama | J2: hyperscreener | K2: hyperscreener | L2: hyperscreener | M2: hyperscreener | N2: hyperscreener | O2: hyperscreener | P2: hyperscreener | Q2: hyperscreener | R2: hyperscreener | S2: hyperscreener | T2: Calc | U2: Calc | V2: Calc | W2: Calc
A3: Date | B3: Core Perp Volume ($) | C3: Spot Volume ($) | D3: HIP-3 Volume ($) | E3: HyperCore Revenue ($) | F3: HIP-3 Gross Fees ($) | G3: HIP-3 Deployer Fees ($) | H3: Spot Revenue ($) | I3: Spot Fees ($) | J3: HyperEVM Burn ($) | K3: Auction Burn ($) | L3: Buyback HYPE | M3: Buyback USD ($) | N3: AF Holdings (HYPE) | O3: Daily Emission (HYPE) | P3: Daily Burn (HYPE) | Q3: Daily Burn ($) | R3: Circulating Supply (HYPE) | S3: Total Supply (HYPE) | T3: Δ Circ Supply (HYPE) | U3: Δ Total Supply (HYPE) | V3: Total Supply Check ≈0 | W3: Circ Residual / Other (HYPE)
A4: 45658 | B4: 2.1572568e+09 | D4: 0 | E4: 498037 | F4: 0 | G4: 0 | H4: 29237 | I4: 30141 | N4: 11719551 | O4: 24499.354 | P4: 941.1022 | Q4: 22586.45 | R4: 3.3384913e+08 | S4: 9.9988896e+08
A5: 45659 | B5: 3.6458162e+09 | D5: 0 | E5: 1270220 | F5: 0 | G5: 0 | H5: 40416 | I5: 41666 | N5: 11756781 | O5: 24851.902 | P5: 920.9016 | Q5: 24230.76 | R5: 3.3385788e+08 | S5: 9.9988804e+08 | T5: =IF(OR(R5="",R4=""),"",R5-R4) | U5: =IF(OR(S5="",S4=""),"",S5-S4) | V5: =IF(OR(U5="",P5=""),"",U5+P5) | W5: =IF(OR(T5="",O5="",P5=""),"",T5-O5+P5)
A6: 45660 | B6: 3.5731603e+09 | D6: 0 | E6: 1369500 | F6: 0 | G6: 0 | H6: 35895 | I6: 37005 | N6: 11812513 | O6: 25219.868 | P6: 905.5316 | Q6: 20963.06 | R6: 3.3386719e+08 | S6: 9.9988714e+08 | T6: =IF(OR(R6="",R5=""),"",R6-R5) | U6: =IF(OR(S6="",S5=""),"",S6-S5) | V6: =IF(OR(U6="",P6=""),"",U6+P6) | W6: =IF(OR(T6="",O6="",P6=""),"",T6-O6+P6)
A7: 45661 | B7: 2.5062676e+09 | D7: 0 | E7: 1042972 | F7: 0 | G7: 0 | H7: 24616 | I7: 25377 | N7: 11846794 | O7: 25452.778 | P7: 1232.8801 | Q7: 30121.73 | R7: 3.3387648e+08 | S7: 9.998859e+08 | T7: =IF(OR(R7="",R6=""),"",R7-R6) | U7: =IF(OR(S7="",S6=""),"",S7-S6) | V7: =IF(OR(U7="",P7=""),"",U7+P7) | W7: =IF(OR(T7="",O7="",P7=""),"",T7-O7+P7)
A8: 45662 | B8: 2.149149e+09 | D8: 0 | E8: 985187 | F8: 0 | G8: 0 | H8: 18684 | I8: 19262 | N8: 11889348 | O8: 25665.111 | P8: 617.3145 | Q8: 15443.36 | R8: 3.3388674e+08 | S8: 9.9988529e+08 | T8: =IF(OR(R8="",R7=""),"",R8-R7) | U8: =IF(OR(S8="",S7=""),"",S8-S7) | V8: =IF(OR(U8="",P8=""),"",U8+P8) | W8: =IF(OR(T8="",O8="",P8=""),"",T8-O8+P8)
A9: 45663 | B9: 4.4049187e+09 | D9: 0 | E9: 1036760 | F9: 0 | G9: 0 | H9: 22750 | I9: 23453 | N9: 11933135 | O9: 25789.885 | P9: 447.5855 | Q9: 10920.86 | R9: 3.3389734e+08 | S9: 9.9988484e+08 | T9: =IF(OR(R9="",R8=""),"",R9-R8) | U9: =IF(OR(S9="",S8=""),"",S9-S8) | V9: =IF(OR(U9="",P9=""),"",U9+P9) | W9: =IF(OR(T9="",O9="",P9=""),"",T9-O9+P9)
A10: 45664 | B10: 7.0045455e+09 | D10: 0 | E10: 2114140 | F10: 0 | G10: 0 | H10: 29308 | I10: 30214 | N10: 11991787 | O10: 25854.611 | P10: 718.7295 | Q10: 18132.11 | R10: 3.3390778e+08 | S10: 9.9988412e+08 | T10: =IF(OR(R10="",R9=""),"",R10-R9) | U10: =IF(OR(S10="",S9=""),"",S10-S9) | V10: =IF(OR(U10="",P10=""),"",U10+P10) | W10: =IF(OR(T10="",O10="",P10=""),"",T10-O10+P10)
A11: 45665 | B11: 6.0197847e+09 | D11: 0 | E11: 1758819 | F11: 0 | G11: 0 | H11: 43915 | I11: 45273 | N11: 12076330 | O11: 25924.42 | P11: 744.9065 | Q11: 17501.58 | R11: 3.3391828e+08 | S11: 9.9988338e+08 | T11: =IF(OR(R11="",R10=""),"",R11-R10) | U11: =IF(OR(S11="",S10=""),"",S11-S10) | V11: =IF(OR(U11="",P11=""),"",U11+P11) | W11: =IF(OR(T11="",O11="",P11=""),"",T11-O11+P11)
A12: 45666 | B12: 7.1233273e+09 | D12: 0 | E12: 1921239 | F12: 0 | G12: 0 | H12: 45969 | I12: 47391 | N12: 12156975 | O12: 25984.345 | P12: 1579.5356 | Q12: 35552.19 | R12: 3.3392805e+08 | S12: 9.998818e+08 | T12: =IF(OR(R12="",R11=""),"",R12-R11) | U12: =IF(OR(S12="",S11=""),"",S12-S11) | V12: =IF(OR(U12="",P12=""),"",U12+P12) | W12: =IF(OR(T12="",O12="",P12=""),"",T12-O12+P12)
A13: 45667 | B13: 5.1100061e+09 | D13: 0 | E13: 1475032 | F13: 0 | G13: 0 | H13: 26938 | I13: 27771 | N13: 12241033 | O13: 26008.903 | P13: 1664.9046 | Q13: 33764.27 | R13: 3.3393775e+08 | S13: 9.9988013e+08 | T13: =IF(OR(R13="",R12=""),"",R13-R12) | U13: =IF(OR(S13="",S12=""),"",S13-S12) | V13: =IF(OR(U13="",P13=""),"",U13+P13) | W13: =IF(OR(T13="",O13="",P13=""),"",T13-O13+P13)
A14: 45668 | B14: 1.9752201e+09 | D14: 0 | E14: 458402 | F14: 0 | G14: 0 | H14: 14512 | I14: 14961 | N14: 12305409 | O14: 26032.719 | P14: 984.8383 | Q14: 20333.96 | R14: 3.3394818e+08 | S14: 9.9987915e+08 | T14: =IF(OR(R14="",R13=""),"",R14-R13) | U14: =IF(OR(S14="",S13=""),"",S14-S13) | V14: =IF(OR(U14="",P14=""),"",U14+P14) | W14: =IF(OR(T14="",O14="",P14=""),"",T14-O14+P14)
A15: 45669 | B15: 1.8688233e+09 | D15: 0 | F15: 0 | G15: 0 | N15: 12323093 | O15: 26062.989 | P15: 555.3528 | Q15: 11594.93 | R15: 3.3395908e+08 | S15: 9.9987859e+08 | T15: =IF(OR(R15="",R14=""),"",R15-R14) | U15: =IF(OR(S15="",S14=""),"",S15-S14) | V15: =IF(OR(U15="",P15=""),"",U15+P15) | W15: =IF(OR(T15="",O15="",P15=""),"",T15-O15+P15)
A16: 45670 | B16: 7.6148894e+09 | D16: 0 | F16: 0 | G16: 0 | N16: 12366458 | O16: 26085.585 | P16: 490.8274 | Q16: 10364.31 | R16: 3.339701e+08 | S16: 9.998781e+08 | T16: =IF(OR(R16="",R15=""),"",R16-R15) | U16: =IF(OR(S16="",S15=""),"",S16-S15) | V16: =IF(OR(U16="",P16=""),"",U16+P16) | W16: =IF(OR(T16="",O16="",P16=""),"",T16-O16+P16)
A17: 45671 | B17: 4.1645346e+09 | D17: 0 | E17: 1230157 | F17: 0 | G17: 0 | H17: 23594 | I17: 24324 | N17: 12467821 | O17: 26275.62 | P17: 1292.8946 | Q17: 27962.08 | R17: 3.3398062e+08 | S17: 9.9987681e+08 | T17: =IF(OR(R17="",R16=""),"",R17-R16) | U17: =IF(OR(S17="",S16=""),"",S17-S16) | V17: =IF(OR(U17="",P17=""),"",U17+P17) | W17: =IF(OR(T17="",O17="",P17=""),"",T17-O17+P17)
A18: 45672 | B18: 5.3154076e+09 | D18: 0 | E18: 1231497 | F18: 0 | G18: 0 | H18: 23198 | I18: 23915 | N18: 12522774 | O18: 26404.186 | P18: 1035.8599 | Q18: 23826.33 | R18: 3.3399159e+08 | S18: 9.9987577e+08 | T18: =IF(OR(R18="",R17=""),"",R18-R17) | U18: =IF(OR(S18="",S17=""),"",S18-S17) | V18: =IF(OR(U18="",P18=""),"",U18+P18) | W18: =IF(OR(T18="",O18="",P18=""),"",T18-O18+P18)
A19: 45673 | B19: 5.7136112e+09 | D19: 0 | E19: 1644992 | F19: 0 | G19: 0 | H19: 18044 | I19: 18602 | N19: 12591917 | O19: 26508.232 | P19: 883.4029 | Q19: 21532.95 | R19: 3.3400284e+08 | S19: 9.9987489e+08 | T19: =IF(OR(R19="",R18=""),"",R19-R18) | U19: =IF(OR(S19="",S18=""),"",S19-S18) | V19: =IF(OR(U19="",P19=""),"",U19+P19) | W19: =IF(OR(T19="",O19="",P19=""),"",T19-O19+P19)
A20: 45674 | B20: 5.4612772e+09 | D20: 0 | E20: 1647338 | F20: 0 | G20: 0 | H20: 19870 | I20: 20485 | N20: 12657482 | O20: 26562.754 | P20: 560.1256 | Q20: 13148.11 | R20: 3.3401451e+08 | S20: 9.9987433e+08 | T20: =IF(OR(R20="",R19=""),"",R20-R19) | U20: =IF(OR(S20="",S19=""),"",S20-S19) | V20: =IF(OR(U20="",P20=""),"",U20+P20) | W20: =IF(OR(T20="",O20="",P20=""),"",T20-O20+P20)
A21: 45675 | B21: 9.6789601e+09 | D21: 0 | E21: 2754660 | F21: 0 | G21: 0 | H21: 50841 | I21: 52413 | N21: 12746262 | O21: 26584.013 | P21: 614.0791 | Q21: 14179.39 | R21: 3.3402616e+08 | S21: 9.9987371e+08 | T21: =IF(OR(R21="",R20=""),"",R21-R20) | U21: =IF(OR(S21="",S20=""),"",S21-S20) | V21: =IF(OR(U21="",P21=""),"",U21+P21) | W21: =IF(OR(T21="",O21="",P21=""),"",T21-O21+P21)
A22: 45676 | B22: 1.775022e+10 | D22: 0 | E22: 4182537 | F22: 0 | G22: 0 | H22: 59675 | I22: 61521 | N22: 12889603 | O22: 26576.453 | P22: 1549.2138 | Q22: 33984.33 | R22: 3.3403684e+08 | S22: 9.9987217e+08 | T22: =IF(OR(R22="",R21=""),"",R22-R21) | U22: =IF(OR(S22="",S21=""),"",S22-S21) | V22: =IF(OR(U22="",P22=""),"",U22+P22) | W22: =IF(OR(T22="",O22="",P22=""),"",T22-O22+P22)
A23: 45677 | B23: 1.6339005e+10 | D23: 0 | E23: 3956440 | F23: 0 | G23: 0 | H23: 33251 | I23: 34279 | N23: 13118130 | O23: 26541.273 | P23: 2127.3129 | Q23: 42947.26 | R23: 3.3404689e+08 | S23: 9.9987004e+08 | T23: =IF(OR(R23="",R22=""),"",R23-R22) | U23: =IF(OR(S23="",S22=""),"",S23-S22) | V23: =IF(OR(U23="",P23=""),"",U23+P23) | W23: =IF(OR(T23="",O23="",P23=""),"",T23-O23+P23)
A24: 45678 | B24: 8.3419449e+09 | D24: 0 | E24: 2003967 | F24: 0 | G24: 0 | H24: 33047 | I24: 34069 | N24: 13251259 | O24: 26530.748 | P24: 1392.5278 | Q24: 28622.71 | R24: 3.3405768e+08 | S24: 9.9986865e+08 | T24: =IF(OR(R24="",R23=""),"",R24-R23) | U24: =IF(OR(S24="",S23=""),"",S24-S23) | V24: =IF(OR(U24="",P24=""),"",U24+P24) | W24: =IF(OR(T24="",O24="",P24=""),"",T24-O24+P24)
A25: 45679 | B25: 5.2815512e+09 | D25: 0 | E25: 1392360 | F25: 0 | G25: 0 | H25: 29505 | I25: 30418 | N25: 13322389 | O25: 26567.346 | P25: 1404.8497 | Q25: 32564.41 | R25: 3.3406849e+08 | S25: 9.9986724e+08 | T25: =IF(OR(R25="",R24=""),"",R25-R24) | U25: =IF(OR(S25="",S24=""),"",S25-S24) | V25: =IF(OR(U25="",P25=""),"",U25+P25) | W25: =IF(OR(T25="",O25="",P25=""),"",T25-O25+P25)
A26: 45680 | B26: 1.1321581e+10 | D26: 0 | E26: 2736794 | F26: 0 | G26: 0 | H26: 37014 | I26: 38159 | N26: 13384449 | O26: 26581.533 | P26: 923.5959 | Q26: 22448.92 | R26: 3.3407981e+08 | S26: 9.9986632e+08 | T26: =IF(OR(R26="",R25=""),"",R26-R25) | U26: =IF(OR(S26="",S25=""),"",S26-S25) | V26: =IF(OR(U26="",P26=""),"",U26+P26) | W26: =IF(OR(T26="",O26="",P26=""),"",T26-O26+P26)
A27: 45681 | B27: 5.7847318e+09 | D27: 0 | E27: 1268918 | F27: 0 | G27: 0 | H27: 23279 | I27: 23999 | N27: 13500446 | O27: 26552.402 | P27: 1425.0715 | Q27: 31310.24 | R27: 3.3409059e+08 | S27: 9.9986489e+08 | T27: =IF(OR(R27="",R26=""),"",R27-R26) | U27: =IF(OR(S27="",S26=""),"",S27-S26) | V27: =IF(OR(U27="",P27=""),"",U27+P27) | W27: =IF(OR(T27="",O27="",P27=""),"",T27-O27+P27)
A28: 45682 | B28: 3.5167284e+09 | D28: 0 | E28: 1043099 | F28: 0 | G28: 0 | H28: 13888 | I28: 14317 | N28: 13559681 | O28: 26530.811 | P28: 909.6107 | Q28: 20977.9 | R28: 3.3410184e+08 | S28: 9.9986398e+08 | T28: =IF(OR(R28="",R27=""),"",R28-R27) | U28: =IF(OR(S28="",S27=""),"",S28-S27) | V28: =IF(OR(U28="",P28=""),"",U28+P28) | W28: =IF(OR(T28="",O28="",P28=""),"",T28-O28+P28)
... A81: 45735 | B81: 5.9364707e+09 | D81: 0 | E81: 1367967 | F81: 0 | G81: 0 | H81: 17924 | I81: 18478 | N81: 17658356 | O81: 26377.289 | P81: 408.8611 | Q81: 5793.56 | R81: 3.3470475e+08 | S81: 9.9981459e+08 | T81: =IF(OR(R81="",R80=""),"",R81-R80) | U81: =IF(OR(S81="",S80=""),"",S81-S80) | V81: =IF(OR(U81="",P81=""),"",U81+P81) | W81: =IF(OR(T81="",O81="",P81=""),"",T81-O81+P81)
A82: 45736 | B82: 4.7983491e+09 | D82: 0 | E82: 1360250.1 | F82: 0 | G82: 0 | H82: 13612 | I82: 14033 | J82: 222.65073 | K82: 35438.86 | L82: 93242.48 | M82: 1360250.1 | N82: 17751598 | O82: 26389.385 | P82: 1047.6243 | Q82: 16362.32 | R82: 3.347156e+08 | S82: 9.9981354e+08 | T82: =IF(OR(R82="",R81=""),"",R82-R81) | U82: =IF(OR(S82="",S81=""),"",S82-S81) | V82: =IF(OR(U82="",P82=""),"",U82+P82) | W82: =IF(OR(T82="",O82="",P82=""),"",T82-O82+P82)
A83: 45737 | B83: 3.5352826e+09 | D83: 0 | E83: 1031164.9 | F83: 0 | G83: 0 | H83: 11995 | I83: 12366 | J83: 2823.9089 | K83: 45038.24 | L83: 70431.98 | M83: 1031164.9 | N83: 17822030 | O83: 26422.9 | P83: 592.8651 | Q83: 8389.63 | R83: 3.3472695e+08 | S83: 9.9981295e+08 | T83: =IF(OR(R83="",R82=""),"",R83-R82) | U83: =IF(OR(S83="",S82=""),"",S83-S82) | V83: =IF(OR(U83="",P83=""),"",U83+P83) | W83: =IF(OR(T83="",O83="",P83=""),"",T83-O83+P83)
A84: 45738 | B84: 2.0454278e+09 | D84: 0 | E84: 847303.18 | F84: 0 | G84: 0 | H84: 8184 | I84: 8437 | J84: 212.65569 | K84: 57676.12 | L84: 53131.87 | M84: 847303.18 | N84: 17875162 | O84: 26439.06 | P84: 633.9893 | Q84: 10097.86 | R84: 3.3473829e+08 | S84: 9.9981231e+08 | T84: =IF(OR(R84="",R83=""),"",R84-R83) | U84: =IF(OR(S84="",S83=""),"",S84-S83) | V84: =IF(OR(U84="",P84=""),"",U84+P84) | W84: =IF(OR(T84="",O84="",P84=""),"",T84-O84+P84)
A85: 45739 | B85: 2.4627913e+09 | D85: 0 | E85: 450708.74 | F85: 0 | G85: 0 | H85: 6361 | I85: 6558 | J85: 313.52069 | K85: 0 | L85: 28455.13 | M85: 450708.74 | N85: 17903617 | O85: 26250.617 | P85: 393.117 | Q85: 6122.6 | R85: 3.3474968e+08 | S85: 9.9981192e+08 | T85: =IF(OR(R85="",R84=""),"",R85-R84) | U85: =IF(OR(S85="",S84=""),"",S85-S84) | V85: =IF(OR(U85="",P85=""),"",U85+P85) | W85: =IF(OR(T85="",O85="",P85=""),"",T85-O85+P85)
A86: 45740 | B86: 5.1058256e+09 | D86: 0 | E86: 829053.81 | F86: 0 | G86: 0 | H86: 18609 | I86: 19185 | J86: 377.73303 | K86: 49980 | L86: 49430.03 | M86: 829053.81 | N86: 17953047 | O86: 26407.972 | P86: 282.117 | Q86: 4596.11 | R86: 3.3476131e+08 | S86: 9.9981164e+08 | T86: =IF(OR(R86="",R85=""),"",R86-R85) | U86: =IF(OR(S86="",S85=""),"",S86-S85) | V86: =IF(OR(U86="",P86=""),"",U86+P86) | W86: =IF(OR(T86="",O86="",P86=""),"",T86-O86+P86)
A87: 45741 | B87: 3.9320302e+09 | D87: 0 | E87: 1041581.3 | F87: 0 | G87: 0 | H87: 11179 | I87: 11525 | J87: 325.86711 | K87: 63542.04 | L87: 63584.4 | M87: 1041581.3 | N87: 18016632 | O87: 26408.12 | P87: 874.4752 | Q87: 14662.32 | R87: 3.3477236e+08 | S87: 9.9981076e+08 | T87: =IF(OR(R87="",R86=""),"",R87-R86) | U87: =IF(OR(S87="",S86=""),"",S87-S86) | V87: =IF(OR(U87="",P87=""),"",U87+P87) | W87: =IF(OR(T87="",O87="",P87=""),"",T87-O87+P87)
A88: 45742 | B88: 4.5464593e+09 | D88: 0 | E88: 829339.39 | F88: 0 | G88: 0 | H88: 60200 | I88: 62061 | J88: 520.88851 | K88: 0 | L88: 57631.29 | M88: 829339.39 | N88: 18074263 | O88: 26422.374 | P88: 418.2386 | Q88: 6705.62 | R88: 3.3478388e+08 | S88: 9.9981034e+08 | T88: =IF(OR(R88="",R87=""),"",R88-R87) | U88: =IF(OR(S88="",S87=""),"",S88-S87) | V88: =IF(OR(U88="",P88=""),"",U88+P88) | W88: =IF(OR(T88="",O88="",P88=""),"",T88-O88+P88)
A89: 45743 | B89: 2.9680178e+09 | D89: 0 | E89: 1118366.5 | F89: 0 | G89: 0 | H89: 11862 | I89: 12229 | J89: 170.72506 | K89: 145034.84 | L89: 77117.5 | M89: 1118366.5 | N89: 18151380 | O89: 26404.382 | P89: 3348.6945 | Q89: 47070.92 | R89: 3.3479246e+08 | S89: 9.99807e+08 | T89: =IF(OR(R89="",R88=""),"",R89-R88) | U89: =IF(OR(S89="",S88=""),"",S89-S88) | V89: =IF(OR(U89="",P89=""),"",U89+P89) | W89: =IF(OR(T89="",O89="",P89=""),"",T89-O89+P89)
A90: 45744 | B90: 4.6960274e+09 | D90: 0 | E90: 828868.5 | F90: 0 | G90: 0 | H90: 17635 | I90: 18181 | J90: 148.90207 | K90: 0 | L90: 62740.01 | M90: 828868.5 | N90: 18214121 | O90: 26355.458 | P90: 572.3714 | Q90: 8353.19 | R90: 3.3480375e+08 | S90: 9.9980642e+08 | T90: =IF(OR(R90="",R89=""),"",R90-R89) | U90: =IF(OR(S90="",S89=""),"",S90-S89) | V90: =IF(OR(U90="",P90=""),"",U90+P90) | W90: =IF(OR(T90="",O90="",P90=""),"",T90-O90+P90)
A91: 45745 | B91: 3.3004373e+09 | D91: 0 | E91: 901117.23 | F91: 0 | G91: 0 | H91: 12226 | I91: 12604 | J91: 123.14806 | K91: 53370.55 | L91: 70357.02 | M91: 901117.23 | N91: 18284478 | O91: 26368.156 | P91: 574.8896 | Q91: 7698.63 | R91: 3.3481505e+08 | S91: 9.9980585e+08 | T91: =IF(OR(R91="",R90=""),"",R91-R90) | U91: =IF(OR(S91="",S90=""),"",S91-S90) | V91: =IF(OR(U91="",P91=""),"",U91+P91) | W91: =IF(OR(T91="",O91="",P91=""),"",T91-O91+P91)
A92: 45746 | B92: 2.7740623e+09 | D92: 0 | E92: 696924.24 | F92: 0 | G92: 0 | H92: 7203 | I92: 7425 | J92: 101.87837 | K92: 45820.11 | L92: 55468.07 | M92: 696924.24 | N92: 18339946 | O92: 26361.194 | P92: 564.418 | Q92: 7222.57 | R92: 3.3482634e+08 | S92: 9.9980528e+08 | T92: =IF(OR(R92="",R91=""),"",R92-R91) | U92: =IF(OR(S92="",S91=""),"",S92-S91) | V92: =IF(OR(U92="",P92=""),"",U92+P92) | W92: =IF(OR(T92="",O92="",P92=""),"",T92-O92+P92)
A93: 45747 | B93: 5.7868158e+09 | D93: 0 | E93: 895707.82 | F93: 0 | G93: 0 | H93: 12269 | I93: 12648 | J93: 396.57366 | K93: 0 | L93: 68018.01 | M93: 895707.82 | N93: 18407964 | O93: 26329.338 | P93: 300.1917 | Q93: 3746.69 | R93: 3.3483785e+08 | S93: 9.9980498e+08 | T93: =IF(OR(R93="",R92=""),"",R93-R92) | U93: =IF(OR(S93="",S92=""),"",S93-S92) | V93: =IF(OR(U93="",P93=""),"",U93+P93) | W93: =IF(OR(T93="",O93="",P93=""),"",T93-O93+P93)
... A161: 45815 | B161: 3.033733e+09 | D161: 0 | E161: 1547600.8 | F161: 0 | G161: 0 | H161: 30046 | I161: 30975 | J161: 10596.986 | K161: 19606.25 | L161: 45268.08 | M161: 1547600.8 | N161: 24203501 | O161: 26173.826 | P161: 1731.8133 | Q161: 57205.26 | R161: 3.355408e+08 | S161: 9.997273e+08 | T161: =IF(OR(R161="",R160=""),"",R161-R160) | U161: =IF(OR(S161="",S160=""),"",S161-S160) | V161: =IF(OR(U161="",P161=""),"",U161+P161) | W161: =IF(OR(T161="",O161="",P161=""),"",T161-O161+P161)
A162: 45816 | B162: 3.1217007e+09 | D162: 0 | E162: 795945.09 | F162: 0 | G162: 0 | J162: 12374.019 | K162: 24700.19 | L162: 22402.6 | M162: 795945.09 | N162: 24225904 | O162: 26210.631 | P162: 1145.1683 | Q162: 39757.38 | R162: 3.3555121e+08 | S162: 9.9972615e+08 | T162: =IF(OR(R162="",R161=""),"",R162-R161) | U162: =IF(OR(S162="",S161=""),"",S162-S161) | V162: =IF(OR(U162="",P162=""),"",U162+P162) | W162: =IF(OR(T162="",O162="",P162=""),"",T162-O162+P162)
A163: 45817 | B163: 7.9469529e+09 | D163: 0 | E163: 1033782.9 | F163: 0 | G163: 0 | J163: 21782.409 | K163: 0 | L163: 27813.55 | M163: 1033782.9 | N163: 24253717 | O163: 25299.785 | P163: 1303.6525 | Q163: 45368.41 | R163: 3.3556093e+08 | S163: 9.9972485e+08 | T163: =IF(OR(R163="",R162=""),"",R163-R162) | U163: =IF(OR(S163="",S162=""),"",S163-S162) | V163: =IF(OR(U163="",P163=""),"",U163+P163) | W163: =IF(OR(T163="",O163="",P163=""),"",T163-O163+P163)
A164: 45818 | B164: 8.8680623e+09 | D164: 0 | E164: 2966717.5 | F164: 0 | G164: 0 | H164: 112003 | I164: 115467 | J164: 36602.413 | K164: 19343.05 | L164: 72585.42 | M164: 2966717.5 | N164: 24326303 | O164: 26201.094 | P164: 1301.1221 | Q164: 50109.47 | R164: 3.3557117e+08 | S164: 9.9972355e+08 | T164: =IF(OR(R164="",R163=""),"",R164-R163) | U164: =IF(OR(S164="",S163=""),"",S164-S163) | V164: =IF(OR(U164="",P164=""),"",U164+P164) | W164: =IF(OR(T164="",O164="",P164=""),"",T164-O164+P164)
A165: 45819 | B165: 8.8808494e+09 | D165: 0 | E165: 2670016.4 | F165: 0 | G165: 0 | H165: 102743 | I165: 105920 | J165: 23763.465 | K165: 0 | L165: 62825.88 | M165: 2670016.4 | N165: 24389129 | O165: 26194.285 | P165: 2420.7992 | Q165: 102175.88 | R165: 3.3558029e+08 | S165: 9.9972113e+08 | T165: =IF(OR(R165="",R164=""),"",R165-R164) | U165: =IF(OR(S165="",S164=""),"",S165-S164) | V165: =IF(OR(U165="",P165=""),"",U165+P165) | W165: =IF(OR(T165="",O165="",P165=""),"",T165-O165+P165)
A166: 45820 | B166: 9.8599768e+09 | D166: 0 | E166: 2787983.2 | F166: 0 | G166: 0 | H166: 92615 | I166: 95479 | J166: 21543.04 | K166: 0 | L166: 66551.07 | M166: 2787983.2 | N166: 24455680 | O166: 26172.677 | P166: 1573.8715 | Q166: 65059.91 | R166: 3.355902e+08 | S166: 9.9971955e+08 | T166: =IF(OR(R166="",R165=""),"",R166-R165) | U166: =IF(OR(S166="",S165=""),"",S166-S165) | V166: =IF(OR(U166="",P166=""),"",U166+P166) | W166: =IF(OR(T166="",O166="",P166=""),"",T166-O166+P166)
A167: 45821 | B167: 1.3286057e+10 | D167: 0 | E167: 4333047.9 | F167: 0 | G167: 0 | H167: 144260 | I167: 148721 | J167: 25139.009 | K167: 20519.17 | L167: 106831.07 | M167: 4333047.9 | N167: 24562511 | O167: 26192 | P167: 1328.325 | Q167: 52391.79 | R167: 3.356004e+08 | S167: 9.9971822e+08 | T167: =IF(OR(R167="",R166=""),"",R167-R166) | U167: =IF(OR(S167="",S166=""),"",S167-S166) | V167: =IF(OR(U167="",P167=""),"",U167+P167) | W167: =IF(OR(T167="",O167="",P167=""),"",T167-O167+P167)
A168: 45822 | B168: 4.4904691e+09 | D168: 0 | E168: 2185535.2 | F168: 0 | G168: 0 | H168: 51552 | I168: 53146 | J168: 8906.4284 | K168: 34608.23 | L168: 53683.83 | M168: 2185535.2 | N168: 24616195 | O168: 26263.484 | P168: 2718.0225 | Q168: 114351.28 | R168: 3.3560933e+08 | S168: 9.9971551e+08 | T168: =IF(OR(R168="",R167=""),"",R168-R167) | U168: =IF(OR(S168="",S167=""),"",S168-S167) | V168: =IF(OR(U168="",P168=""),"",U168+P168) | W168: =IF(OR(T168="",O168="",P168=""),"",T168-O168+P168)
A169: 45823 | B169: 4.1205593e+09 | D169: 0 | E169: 1164654 | F169: 0 | G169: 0 | H169: 38458 | I169: 39647 | J169: 6346.0583 | K169: 0 | L169: 28628.23 | M169: 1164654 | N169: 24644823 | O169: 26057.089 | P169: 1523.9619 | Q169: 61283.08 | R169: 3.3561929e+08 | S169: 9.9971398e+08 | T169: =IF(OR(R169="",R168=""),"",R169-R168) | U169: =IF(OR(S169="",S168=""),"",S169-S168) | V169: =IF(OR(U169="",P169=""),"",U169+P169) | W169: =IF(OR(T169="",O169="",P169=""),"",T169-O169+P169)
A170: 45824 | B170: 9.9104451e+09 | D170: 0 | E170: 1387388.4 | F170: 0 | G170: 0 | H170: 100767 | I170: 103884 | J170: 13337.004 | K170: 43700.71 | L170: 31692.79 | M170: 1387388.4 | N170: 24676516 | O170: 26275.498 | P170: 535.3125 | Q170: 21937.11 | R170: 3.3563042e+08 | S170: 9.9971345e+08 | T170: =IF(OR(R170="",R169=""),"",R170-R169) | U170: =IF(OR(S170="",S169=""),"",S170-S169) | V170: =IF(OR(U170="",P170=""),"",U170+P170) | W170: =IF(OR(T170="",O170="",P170=""),"",T170-O170+P170)
A171: 45825 | B171: 1.1324626e+10 | D171: 0 | E171: 3414074.1 | F171: 0 | G171: 0 | H171: 115542 | I171: 119116 | J171: 20062.713 | K171: 0 | L171: 84832.16 | M171: 3414074.1 | N171: 24761348 | O171: 26285.578 | P171: 2288.4006 | Q171: 94658.55 | R171: 3.3563982e+08 | S171: 9.9971116e+08 | T171: =IF(OR(R171="",R170=""),"",R171-R170) | U171: =IF(OR(S171="",S170=""),"",S171-S170) | V171: =IF(OR(U171="",P171=""),"",U171+P171) | W171: =IF(OR(T171="",O171="",P171=""),"",T171-O171+P171)
A172: 45826 | B172: 7.99953e+09 | D172: 0 | E172: 2621754.3 | F172: 0 | G172: 0 | H172: 86220 | I172: 88887 | J172: 15089.279 | K172: 28795.88 | L172: 68011.24 | M172: 2621754.3 | N172: 24829359 | O172: 26255.057 | P172: 1751.8615 | Q172: 69725.84 | R172: 3.3564968e+08 | S172: 9.9970941e+08 | T172: =IF(OR(R172="",R171=""),"",R172-R171) | U172: =IF(OR(S172="",S171=""),"",S172-S171) | V172: =IF(OR(U172="",P172=""),"",U172+P172) | W172: =IF(OR(T172="",O172="",P172=""),"",T172-O172+P172)
A173: 45827 | B173: 5.3097062e+09 | D173: 0 | E173: 2072394.7 | F173: 0 | G173: 0 | H173: 71693 | I173: 73911 | J173: 18252.615 | K173: 24354.76 | L173: 55708.49 | M173: 2072394.7 | N173: 24885068 | O173: 26211.471 | P173: 1998.2373 | Q173: 78520.73 | R173: 3.3565923e+08 | S173: 9.9970741e+08 | T173: =IF(OR(R173="",R172=""),"",R173-R172) | U173: =IF(OR(S173="",S172=""),"",S173-S172) | V173: =IF(OR(U173="",P173=""),"",U173+P173) | W173: =IF(OR(T173="",O173="",P173=""),"",T173-O173+P173)
A174: 45828 | B174: 8.9847656e+09 | D174: 0 | E174: 1572540.3 | F174: 0 | G174: 0 | H174: 90730 | I174: 93536 | J174: 19860.2 | K174: 25525.19 | L174: 46185.19 | M174: 1572540.3 | N174: 24931253 | O174: 26182.716 | P174: 1736.6411 | Q174: 64135.02 | R174: 3.3566905e+08 | S174: 9.9970567e+08 | T174: =IF(OR(R174="",R173=""),"",R174-R173) | U174: =IF(OR(S174="",S173=""),"",S174-S173) | V174: =IF(OR(U174="",P174=""),"",U174+P174) | W174: =IF(OR(T174="",O174="",P174=""),"",T174-O174+P174)
A175: 45829 | B175: 5.8535617e+09 | D175: 0 | E175: 2062339.9 | F175: 0 | G175: 0 | H175: 67039 | I175: 69112 | J175: 10510.707 | K175: 26551.55 | L175: 62400.26 | M175: 2062339.9 | N175: 24993653 | O175: 26223.75 | P175: 1975.2883 | Q175: 65201.3 | R175: 3.3567865e+08 | S175: 9.997037e+08 | T175: =IF(OR(R175="",R174=""),"",R175-R174) | U175: =IF(OR(S175="",S174=""),"",S175-S174) | V175: =IF(OR(U175="",P175=""),"",U175+P175) | W175: =IF(OR(T175="",O175="",P175=""),"",T175-O175+P175)
... A199: 45853 | B199: 1.7479663e+10 | D199: 0 | E199: 3961622.5 | F199: 0 | G199: 0 | H199: 122632 | I199: 126425 | J199: 28006.94 | K199: 0 | L199: 83530.85 | M199: 3961622.5 | N199: 26291595 | O199: 25934.958 | P199: 1590.787 | Q199: 75311.83 | R199: 3.3592849e+08 | S199: 9.9967608e+08 | T199: =IF(OR(R199="",R198=""),"",R199-R198) | U199: =IF(OR(S199="",S198=""),"",S199-S198) | V199: =IF(OR(U199="",P199=""),"",U199+P199) | W199: =IF(OR(T199="",O199="",P199=""),"",T199-O199+P199)
A200: 45854 | B200: 1.4838265e+10 | C200: 4.8312223e+08 | D200: 0 | E200: 4321512.6 | F200: 0 | G200: 0 | H200: 106735 | I200: 110036 | J200: 25631.071 | K200: 37909.3 | L200: 90398.68 | M200: 4321512.6 | N200: 26381994 | O200: 26049.467 | P200: 762.501 | Q200: 36536.76 | R200: 3.3593911e+08 | S200: 9.9967531e+08 | T200: =IF(OR(R200="",R199=""),"",R200-R199) | U200: =IF(OR(S200="",S199=""),"",S200-S199) | V200: =IF(OR(U200="",P200=""),"",U200+P200) | W200: =IF(OR(T200="",O200="",P200=""),"",T200-O200+P200)
A201: 45855 | B201: 1.6730827e+10 | C201: 6.0552013e+08 | D201: 0 | E201: 4475766 | F201: 0 | G201: 0 | H201: 137344 | I201: 141592 | J201: 30615.533 | K201: 40435.14 | L201: 96658.21 | M201: 4475766 | N201: 26478652 | O201: 26170.392 | P201: 1597.9602 | Q201: 75397.35 | R201: 3.3594908e+08 | S201: 9.9967371e+08 | T201: =IF(OR(R201="",R200=""),"",R201-R200) | U201: =IF(OR(S201="",S200=""),"",S201-S200) | V201: =IF(OR(U201="",P201=""),"",U201+P201) | W201: =IF(OR(T201="",O201="",P201=""),"",T201-O201+P201)
A202: 45856 | B202: 1.7860069e+10 | C202: 5.347588e+08 | D202: 0 | E202: 5353743.7 | F202: 0 | G202: 0 | H202: 119533 | I202: 123230 | J202: 27402.363 | K202: 38945.15 | L202: 117990.63 | M202: 5353743.7 | N202: 26596643 | O202: 26160.434 | P202: 1707.7749 | Q202: 77293.89 | R202: 3.3595904e+08 | S202: 9.9967201e+08 | T202: =IF(OR(R202="",R201=""),"",R202-R201) | U202: =IF(OR(S202="",S201=""),"",S202-S201) | V202: =IF(OR(U202="",P202=""),"",U202+P202) | W202: =IF(OR(T202="",O202="",P202=""),"",T202-O202+P202)
A203: 45857 | B203: 5.9404657e+09 | C203: 2.4200522e+08 | D203: 0 | E203: 3622903.1 | F203: 0 | G203: 0 | H203: 54170 | I203: 55845 | J203: 10314.04 | K203: 0 | L203: 81070.97 | M203: 3622903.1 | N203: 26677713 | O203: 26235.162 | P203: 1734.6771 | Q203: 77534.86 | R203: 3.3596897e+08 | S203: 9.9967027e+08 | T203: =IF(OR(R203="",R202=""),"",R203-R202) | U203: =IF(OR(S203="",S202=""),"",S203-S202) | V203: =IF(OR(U203="",P203=""),"",U203+P203) | W203: =IF(OR(T203="",O203="",P203=""),"",T203-O203+P203)
A204: 45858 | B204: 1.1223165e+10 | C204: 3.3320353e+08 | D204: 0 | E204: 1637416.7 | F204: 0 | G204: 0 | H204: 65594 | I204: 67623 | J204: 14768.492 | K204: 23021.35 | L204: 35661.34 | M204: 1637416.7 | N204: 26713375 | O204: 25437.461 | P204: 387.0758 | Q204: 17124.81 | R204: 3.3597988e+08 | S204: 9.9966989e+08 | T204: =IF(OR(R204="",R203=""),"",R204-R203) | U204: =IF(OR(S204="",S203=""),"",S204-S203) | V204: =IF(OR(U204="",P204=""),"",U204+P204) | W204: =IF(OR(T204="",O204="",P204=""),"",T204-O204+P204)
A205: 45859 | B205: 1.5217203e+10 | C205: 4.2399045e+08 | D205: 0 | E205: 4157067.3 | F205: 0 | G205: 0 | H205: 94711 | I205: 97640 | J205: 30281.515 | K205: 30274.37 | L205: 89986.02 | M205: 4157067.3 | N205: 26790541 | O205: 26253.086 | P205: 1064.9001 | Q205: 48440.71 | R205: 3.3599052e+08 | S205: 9.9966882e+08 | T205: =IF(OR(R205="",R204=""),"",R205-R204) | U205: =IF(OR(S205="",S204=""),"",S205-S204) | V205: =IF(OR(U205="",P205=""),"",U205+P205) | W205: =IF(OR(T205="",O205="",P205=""),"",T205-O205+P205)
A206: 45860 | B206: 1.7573227e+10 | C206: 4.9980959e+08 | D206: 0 | E206: 4309374.4 | F206: 0 | G206: 0 | H206: 102780 | I206: 105959 | J206: 29834.466 | K206: 31944.03 | L206: 97303.92 | M206: 4309374.4 | N206: 26894758 | O206: 26270.238 | P206: 1351.9293 | Q206: 60089.2 | R206: 3.3600087e+08 | S206: 9.9966747e+08 | T206: =IF(OR(R206="",R205=""),"",R206-R205) | U206: =IF(OR(S206="",S205=""),"",S206-S205) | V206: =IF(OR(U206="",P206=""),"",U206+P206) | W206: =IF(OR(T206="",O206="",P206=""),"",T206-O206+P206)
A207: 45861 | B207: 1.392002e+10 | C207: 4.6567537e+08 | D207: 0 | E207: 4231130.1 | F207: 0 | G207: 0 | H207: 96945 | I207: 99943 | J207: 22305.81 | K207: 38232.91 | L207: 96327.11 | M207: 4231130.1 | N207: 26980394 | O207: 26260.008 | P207: 1567.0252 | Q207: 71576.23 | R207: 3.36011e+08 | S207: 9.996659e+08 | T207: =IF(OR(R207="",R206=""),"",R207-R206) | U207: =IF(OR(S207="",S206=""),"",S207-S206) | V207: =IF(OR(U207="",P207=""),"",U207+P207) | W207: =IF(OR(T207="",O207="",P207=""),"",T207-O207+P207)
A208: 45862 | B208: 1.3225484e+10 | C208: 3.9775922e+08 | D208: 0 | E208: 3649361.1 | F208: 0 | G208: 0 | H208: 88469 | I208: 91205 | J208: 15704.905 | K208: 61157.71 | L208: 85212.58 | M208: 3649361.1 | N208: 27094232 | O208: 26273.1 | P208: 1495.0699 | Q208: 65208.97 | R208: 3.3602123e+08 | S208: 9.9966441e+08 | T208: =IF(OR(R208="",R207=""),"",R208-R207) | U208: =IF(OR(S208="",S207=""),"",S208-S207) | V208: =IF(OR(U208="",P208=""),"",U208+P208) | W208: =IF(OR(T208="",O208="",P208=""),"",T208-O208+P208)
A209: 45863 | B209: 1.5953353e+10 | C209: 4.1314328e+08 | D209: 0 | E209: 3875969.7 | F209: 0 | G209: 0 | H209: 87695 | I209: 90407 | J209: 17068.723 | K209: 0 | L209: 91651.09 | M209: 3875969.7 | N209: 27194424 | O209: 26270.683 | P209: 2080.4413 | Q209: 87022.78 | R209: 3.3603085e+08 | S209: 9.9966233e+08 | T209: =IF(OR(R209="",R208=""),"",R209-R208) | U209: =IF(OR(S209="",S208=""),"",S209-S208) | V209: =IF(OR(U209="",P209=""),"",U209+P209) | W209: =IF(OR(T209="",O209="",P209=""),"",T209-O209+P209)
A210: 45864 | B210: 5.6986335e+09 | C210: 2.3513833e+08 | D210: 0 | E210: 2008190.5 | F210: 0 | G210: 0 | H210: 49934 | I210: 51478 | J210: 9624.4893 | K210: 29566.6 | L210: 45480.69 | M210: 2008190.5 | N210: 27257118 | O210: 26267.594 | P210: 620.5895 | Q210: 27269.63 | R210: 3.3604193e+08 | S210: 9.9966171e+08 | T210: =IF(OR(R210="",R209=""),"",R210-R209) | U210: =IF(OR(S210="",S209=""),"",S210-S209) | V210: =IF(OR(U210="",P210=""),"",U210+P210) | W210: =IF(OR(T210="",O210="",P210=""),"",T210-O210+P210)
A211: 45865 | B211: 7.4132509e+09 | C211: 2.7716232e+08 | D211: 0 | E211: 2122051.8 | F211: 0 | G211: 0 | H211: 61525 | I211: 63428 | J211: 9811.1807 | K211: 0 | L211: 48885.03 | M211: 2122051.8 | N211: 27288585 | O211: 26273.955 | P211: 1027.789 | Q211: 44634.3 | R211: 3.3605263e+08 | S211: 9.9966068e+08 | T211: =IF(OR(R211="",R210=""),"",R211-R210) | U211: =IF(OR(S211="",S210=""),"",S211-S210) | V211: =IF(OR(U211="",P211=""),"",U211+P211) | W211: =IF(OR(T211="",O211="",P211=""),"",T211-O211+P211)
... A240: 45894 | B240: 2.0948854e+10 | C240: 3.4426446e+09 | D240: 0 | E240: 5591022.7 | F240: 0 | G240: 0 | H240: 314829 | I240: 543705 | J240: 57416.931 | K240: 0 | L240: 124431.35 | M240: 5591022.7 | N240: 29699945 | O240: 26363.933 | P240: 2861.0986 | Q240: 132424.52 | R240: 3.3636031e+08 | S240: 9.9962658e+08 | T240: =IF(OR(R240="",R239=""),"",R240-R239) | U240: =IF(OR(S240="",S239=""),"",S240-S239) | V240: =IF(OR(U240="",P240=""),"",U240+P240) | W240: =IF(OR(T240="",O240="",P240=""),"",T240-O240+P240)
A241: 45895 | B241: 1.5388541e+10 | D241: 0 | E241: 5812626 | F241: 0 | G241: 0 | H241: 459589 | I241: 782342 | J241: 43508.115 | K241: 49798.91 | L241: 124468.22 | M241: 5812626 | N241: 29824454 | O241: 26366.01 | P241: 1538.1765 | Q241: 65850.87 | R241: 3.3637066e+08 | S241: 9.9962505e+08 | T241: =IF(OR(R241="",R240=""),"",R241-R240) | U241: =IF(OR(S241="",S240=""),"",S241-S240) | V241: =IF(OR(U241="",P241=""),"",U241+P241) | W241: =IF(OR(T241="",O241="",P241=""),"",T241-O241+P241)
A242: 45896 | B242: 1.3058401e+10 | D242: 0 | E242: 3645666.4 | F242: 0 | G242: 0 | H242: 177611 | I242: 217368 | J242: 52325.088 | K242: 68838.23 | L242: 73824.09 | M242: 3645666.4 | N242: 29897947 | O242: 26403.572 | P242: 2522.4986 | Q242: 122551.81 | R242: 3.3638005e+08 | S242: 9.9962252e+08 | T242: =IF(OR(R242="",R241=""),"",R242-R241) | U242: =IF(OR(S242="",S241=""),"",S242-S241) | V242: =IF(OR(U242="",P242=""),"",U242+P242) | W242: =IF(OR(T242="",O242="",P242=""),"",T242-O242+P242)
A243: 45897 | B243: 1.0282719e+10 | D243: 0 | E243: 2852918.4 | F243: 0 | G243: 0 | H243: 133062 | I243: 176810 | J243: 26936.355 | K243: 0 | L243: 59964.64 | M243: 2852918.4 | N243: 29957492 | O243: 26384 | P243: 2596.5887 | Q243: 122355.15 | R243: 3.3638942e+08 | S243: 9.9961993e+08 | T243: =IF(OR(R243="",R242=""),"",R243-R242) | U243: =IF(OR(S243="",S242=""),"",S243-S242) | V243: =IF(OR(U243="",P243=""),"",U243+P243) | W243: =IF(OR(T243="",O243="",P243=""),"",T243-O243+P243)
A244: 45898 | B244: 1.6727207e+10 | D244: 0 | E244: 4517739.1 | F244: 0 | G244: 0 | H244: 353666 | I244: 598611 | J244: 28057.991 | K244: 34731.2 | L244: 101222.13 | M244: 4517739.1 | N244: 30059184 | O244: 26324.201 | P244: 775.6297 | Q244: 35347.77 | R244: 3.3640054e+08 | S244: 9.9961915e+08 | T244: =IF(OR(R244="",R243=""),"",R244-R243) | U244: =IF(OR(S244="",S243=""),"",S244-S243) | V244: =IF(OR(U244="",P244=""),"",U244+P244) | W244: =IF(OR(T244="",O244="",P244=""),"",T244-O244+P244)
A245: 45899 | B245: 6.7994197e+09 | D245: 0 | E245: 1903289.3 | F245: 0 | G245: 0 | H245: 187625 | I245: 323882 | J245: 7760.1102 | K245: 34702.17 | L245: 43251.17 | M245: 1903289.3 | N245: 30102385 | O245: 26261.878 | P245: 1515.4212 | Q245: 67293.04 | R245: 3.3641097e+08 | S245: 9.9961764e+08 | T245: =IF(OR(R245="",R244=""),"",R245-R244) | U245: =IF(OR(S245="",S244=""),"",S245-S244) | V245: =IF(OR(U245="",P245=""),"",U245+P245) | W245: =IF(OR(T245="",O245="",P245=""),"",T245-O245+P245)
A246: 45900 | B246: 5.7665084e+09 | D246: 0 | E246: 1781642.5 | F246: 0 | G246: 0 | H246: 258222 | I246: 473026 | J246: 6506.9381 | K246: 28404.45 | L246: 39932.11 | M246: 1781642.5 | N246: 30142543 | O246: 26548.256 | P246: 1051.6584 | Q246: 46374.45 | R246: 3.3642206e+08 | S246: 9.9961658e+08 | T246: =IF(OR(R246="",R245=""),"",R246-R245) | U246: =IF(OR(S246="",S245=""),"",S246-S245) | V246: =IF(OR(U246="",P246=""),"",U246+P246) | W246: =IF(OR(T246="",O246="",P246=""),"",T246-O246+P246)
A247: 45901 | B247: 1.1587933e+10 | D247: 0 | E247: 3002689.8 | F247: 0 | G247: 0 | H247: 186943 | I247: 297309 | J247: 18424.969 | K247: 0 | L247: 68021.86 | M247: 3002689.8 | N247: 30210339 | O247: 26680.479 | P247: 996.2214 | Q247: 44034.98 | R247: 3.3643328e+08 | S247: 9.9961559e+08 | T247: =IF(OR(R247="",R246=""),"",R247-R246) | U247: =IF(OR(S247="",S246=""),"",S247-S246) | V247: =IF(OR(U247="",P247=""),"",U247+P247) | W247: =IF(OR(T247="",O247="",P247=""),"",T247-O247+P247)
A248: 45902 | B248: 1.1422881e+10 | D248: 0 | E248: 3058785.6 | F248: 0 | G248: 0 | H248: 97355 | I248: 138213 | J248: 17147.428 | K248: 58325.55 | L248: 69292.78 | M248: 3058785.6 | N248: 30279632 | O248: 26649.846 | P248: 470.2765 | Q248: 20214.84 | R248: 3.3644493e+08 | S248: 9.9961512e+08 | T248: =IF(OR(R248="",R247=""),"",R248-R247) | U248: =IF(OR(S248="",S247=""),"",S248-S247) | V248: =IF(OR(U248="",P248=""),"",U248+P248) | W248: =IF(OR(T248="",O248="",P248=""),"",T248-O248+P248)
A249: 45903 | B249: 8.200161e+09 | D249: 0 | E249: 2259297.5 | F249: 0 | G249: 0 | H249: 90595 | I249: 121295 | J249: 22000.403 | K249: 0 | L249: 49663.71 | M249: 2259297.5 | N249: 30329295 | O249: 26600.414 | P249: 1849.0277 | Q249: 83187.76 | R249: 3.3645517e+08 | S249: 9.9961327e+08 | T249: =IF(OR(R249="",R248=""),"",R249-R248) | U249: =IF(OR(S249="",S248=""),"",S249-S248) | V249: =IF(OR(U249="",P249=""),"",U249+P249) | W249: =IF(OR(T249="",O249="",P249=""),"",T249-O249+P249)
A250: 45904 | B250: 9.3533345e+09 | D250: 0 | E250: 2588476.6 | F250: 0 | G250: 0 | H250: 108106 | I250: 141848 | J250: 20973.833 | K250: 23483.66 | L250: 56982.19 | M250: 2588476.6 | N250: 30386454 | O250: 26579.881 | P250: 500.6941 | Q250: 22924.03 | R250: 3.3646672e+08 | S250: 9.9961277e+08 | T250: =IF(OR(R250="",R249=""),"",R250-R249) | U250: =IF(OR(S250="",S249=""),"",S250-S249) | V250: =IF(OR(U250="",P250=""),"",U250+P250) | W250: =IF(OR(T250="",O250="",P250=""),"",T250-O250+P250)
A251: 45905 | B251: 1.3297496e+10 | D251: 0 | E251: 3390576.3 | F251: 0 | G251: 0 | H251: 152198 | I251: 202138 | J251: 33820.502 | K251: 0 | L251: 72961.84 | M251: 3390576.3 | N251: 30459239 | O251: 26477.556 | P251: 922.0321 | Q251: 41829.37 | R251: 3.3647774e+08 | S251: 9.9961185e+08 | T251: =IF(OR(R251="",R250=""),"",R251-R250) | U251: =IF(OR(S251="",S250=""),"",S251-S250) | V251: =IF(OR(U251="",P251=""),"",U251+P251) | W251: =IF(OR(T251="",O251="",P251=""),"",T251-O251+P251)
A252: 45906 | B252: 3.3317977e+09 | D252: 0 | E252: 996786 | F252: 0 | G252: 0 | H252: 86566 | I252: 113097 | J252: 9924.9661 | K252: 26595.36 | L252: 21417.47 | M252: 996786 | N252: 30480657 | O252: 26466.128 | P252: 660.0802 | Q252: 31311.23 | R252: 3.3648901e+08 | S252: 9.9961119e+08 | T252: =IF(OR(R252="",R251=""),"",R252-R251) | U252: =IF(OR(S252="",S251=""),"",S252-S251) | V252: =IF(OR(U252="",P252=""),"",U252+P252) | W252: =IF(OR(T252="",O252="",P252=""),"",T252-O252+P252)
A253: 45907 | B253: 3.8444059e+09 | C253: 2.284416e+08 | D253: 0 | E253: 1076047.9 | F253: 0 | G253: 0 | H253: 107118 | I253: 140516 | J253: 10078.663 | K253: 0 | L253: 22861.04 | M253: 1076047.9 | N253: 30503518 | O253: 26495.024 | P253: 869.383 | Q253: 40168.54 | R253: 3.365001e+08 | S253: 9.9961032e+08 | T253: =IF(OR(R253="",R252=""),"",R253-R252) | U253: =IF(OR(S253="",S252=""),"",S253-S252) | V253: =IF(OR(U253="",P253=""),"",U253+P253) | W253: =IF(OR(T253="",O253="",P253=""),"",T253-O253+P253)
A254: 45908 | B254: 9.2436385e+09 | C254: 5.6013087e+08 | D254: 0 | E254: 2646828.6 | F254: 0 | G254: 0 | H254: 217527 | I254: 273056 | J254: 30522.433 | K254: 23586.38 | L254: 52527.18 | M254: 2646828.6 | N254: 30556045 | O254: 26585.838 | P254: 393.8362 | Q254: 18541.02 | R254: 3.3651174e+08 | S254: 9.9960992e+08 | T254: =IF(OR(R254="",R253=""),"",R254-R253) | U254: =IF(OR(S254="",S253=""),"",S254-S253) | V254: =IF(OR(U254="",P254=""),"",U254+P254) | W254: =IF(OR(T254="",O254="",P254=""),"",T254-O254+P254)
A255: 45909 | B255: 1.0021382e+10 | C255: 6.9924394e+08 | D255: 0 | E255: 2868805.1 | F255: 0 | G255: 0 | H255: 342654 | I255: 413034 | J255: 44114.145 | K255: 32581.41 | L255: 53818.18 | M255: 2868805.1 | N255: 30609863 | O255: 26573.784 | P255: 1758.4763 | Q255: 89376.32 | R255: 3.3652202e+08 | S255: 9.9960816e+08 | T255: =IF(OR(R255="",R254=""),"",R255-R254) | U255: =IF(OR(S255="",S254=""),"",S255-S254) | V255: =IF(OR(U255="",P255=""),"",U255+P255) | W255: =IF(OR(T255="",O255="",P255=""),"",T255-O255+P255)
