Workbook

Sheet Summary
A1: Retail Trading TAM (ex Sports & Crypto): Traditional vs Prediction Markets
A2: GLOBAL = United States + non-US (Europe, UK, APAC, India, China, MENA, LatAm)
A4: WHAT THIS WORKBOOK DOES
A5: Builds the global retail TAM for trading on traditional financial instruments instrument-by-instrument, then compares against prediction-market volumes that are mapped to similar exposures. Every figure is in a blue (editable) cell; every total or ratio is a formula in black. Yellow cells = subtotals and key outputs. All sources have clickable URLs on the Sources tab.
A10: INSTRUMENTS INCLUDED IN THE RETAIL TAM (explicit list)
A11: 1. Retail CFDs (global, ex-US) | B11: FX pairs, indices (DAX, FTSE, SPX, NIFTY), commodities (gold, oil, silver), single stocks, rates. Mostly Europe / APAC / MENA.
A12: 2. US cash equities — retail share | B12: Stocks + ETFs traded by individuals via Robinhood, Schwab, Fidelity, IBKR. Retail = 30–37% of US equity volume.
A13: 3. US listed options — retail share | B13: Single-stock options, index options, 0DTE SPY/QQQ. Retail = ~46% of customer flow; >50% of short-dated.
A14: 4. US listed futures — retail share | B14: CME micros (MES, MNQ, MCL, MGC), Treasury, Eurodollar/SOFR. Retail is a smaller share but growing.
A15: 5. China cash equities — retail share | B15: Shanghai + Shenzhen. Individuals = 60–90% of daily volume per WEF.
A16: 6. India equity F&O — retail share | B16: NSE / BSE options + futures. Even post-SEBI crackdown, retail still dominates.
A17: 7. Other APAC + EU cash equity retail | B17: Japan, Korea, Taiwan, Australia, UK, Germany, France retail flow.
A18: — EXCLUDED | B18: Crypto spot & derivatives (excluded per user); sports betting (excluded per user); institutional-only flow (FX swaps for hedging, OTC IR swaps, repo).
A20: COLOR KEY
A21: Blue = hardcoded input you can change
A22: Black = formula / calculation
A23: Yellow fill = subtotal / key output

Sheet Retail_TAM_Traditional
A1: GLOBAL RETAIL TRADING TAM — Traditional Instruments (excl. sports & crypto), 2025
A2: For each instrument: Global Volume (2025) × Retail % share = Retail TAM. All values in $ Billions per year unless noted. Edit any blue cell.
A4: # | B4: Instrument | C4: Global Volume 2025 ($B/yr) | D4: Source — Global Volume | E4: Retail % Share | F4: Source — Retail Share | G4: Retail Volume ($B/yr) | H4: Geography | I4: Notes
A5: 1 | B5: Retail CFDs (FX + indices + commodities + single stocks + rates) | C5: 444000 | D5: S3 — CoinLaw | E5: 1 | F5: S3 — by definition retail | G5: =C5*E5 -> 444000 | H5: Global ex-US | I5: CFD = retail by definition. $37T/month × 12. Covers FX, indices (DAX, FTSE, SPX, NIFTY), commodities, single stocks, rates. Mostly Europe / APAC / MENA. Note this overlaps with FX market.
A6: 2 | B6: US cash equities (stocks + ETFs) | C6: 80000 | D6: S5 — MEMX | E6: 0.32 | F6: S5 — MEMX | G6: =C6*E6 -> 25600 | H6: United States | I6: Annual NYSE+Nasdaq+CBOE+IEX value traded ~$80T. Retail = 30–37%; midpoint used.
A7: 3 | B7: US listed options (single stock + index) | C7: 90000 | D7: S5 — MEMX | E7: 0.46 | F7: S5 — MEMX | G7: =C7*E7 -> 41400 | H7: United States | I7: Notional. Customer = 46% of OCC volume; >50% of <=10-contract trades. SPY 0DTE retail share ~40%+.
A8: 4 | B8: US listed futures (CME / ICE — incl. micros) | C8: 60000 | D8: S15 — CME / FIA | E8: 0.08 | F8: S15 — FIA / CME micro disclosures | G8: =C8*E8 -> 4800 | H8: United States | I8: CME group annual notional ~$1.5 quadrillion in contracts; using cash-flow proxy. Retail share ~8% (micros, retail FCMs).
A9: 5 | B9: China cash equities (Shanghai + Shenzhen) | C9: 60000 | D9: S16 — WFE FY2024 | E9: 0.75 | F9: S7 — WEF | G9: =C9*E9 -> 45000 | H9: China | I9: WFE 2024: Shanghai $20T+, Shenzhen $25T+; growing 17–19% YoY into 2025. Individuals = 60–90% of daily volume.
A10: 6 | B10: India equity F&O (NSE + BSE) | C10: 15000 | D10: S17 — FIA / NSE | E10: 0.4 | F10: S7 — WEF | G10: =C10*E10 -> 6000 | H10: India | I10: Even after SEBI crackdown (-75% in options 2024→2025), retail = ~40%+ of daily F&O volume. Cash equity adds more.
A11: 7 | B11: Other global cash equity — retail (EU, UK, Japan, Korea, Aus, Taiwan) | C11: 15000 | D11: S16 — WFE FY2024 | E11: 0.25 | F11: S7 — WEF | G11: =C11*E11 -> 3750 | H11: EU + UK + APAC ex-China/India | I11: Rough share-weighted. UK/Korea retail ~20-35%, Japan/EU lower. Conservative midpoint.
B12: SUBTOTAL — Retail volume (gross, with FX/index/commodity overlap) | G12: =SUM(G5:G11) -> 570550
B13: Less: estimated double-count (FX/index/commodity exposure in both CFDs and futures) | E13: 0.1 | G13: =-G12*E13 -> -57055 | I13: Editable overlap adjustment. Set to 0 if you want gross figure.
B14: NET RETAIL TAM — Traditional Instruments, 2025 ($B/yr) | G14: =G12+G13 -> 513495
B15: NET RETAIL TAM ($B/month) | G15: =G14/12 -> 42791.25

Sheet PredMarkets_TAM
A1: PREDICTION MARKETS TAM — Traditional Instrument-Equivalent Slice, 2025
A2: Total Kalshi + Polymarket 2025 volume × share of each category × whether it maps to a traditional instrument. The "Trad-Equivalent?" column flags which categories count toward the comparable TAM.
A4: PLATFORM-LEVEL VOLUMES (2025)
A5: Platform | B5: Annual Volume 2025 ($B) | C5: Source | D5: Note
A6: Kalshi | B6: 238 | C6: S10 — KuCoin | D6: CFTC-regulated; ~80%+ of volume is sports. Mostly US users.
A7: Polymarket (International) | B7: 220 | C7: S10 — KuCoin | D7: Crypto-native, USDC-settled. More diversified mix; politics + crypto + sports.
A8: All other prediction markets (Manifold, Limitless, etc.) | B8: 12.5 | C8: S10 — KuCoin | D8: Combined ~2.5% of category.
A9: TOTAL global prediction-market volume 2025 | B9: =SUM(B6:B8) -> 470.5
A11: CATEGORY BREAKDOWN (blended Kalshi + Polymarket)
A12: Category | B12: Share of Total Volume (blended) | C12: Trad-Instrument Equivalent? | D12: Volume 2025 ($B) | E12: Source | F12: Notes
A13: Sports | B13: 0.55 | C13: No | D13: =B13*$B$9 -> 258.775 | E13: S9 — Pew | F13: EXCLUDED per request. Kalshi 80% / Polymarket 39% weighted.
A14: Crypto | B14: 0.14 | C14: No | D14: =B14*$B$9 -> 65.87 | E14: S9 — Pew | F14: EXCLUDED per request. Kalshi 7% / Polymarket 20%.
A15: Politics / Elections / Geopolitics | B15: 0.18 | C15: No | D15: =B15*$B$9 -> 84.69 | E15: S9 — Pew | F15: Not a financial instrument. Kalshi 4% / Polymarket 32%.
A16: Economy / Finance / Fed / CPI / Jobs / Rates | B16: 0.02 | C16: YES | D16: =B16*$B$9 -> 9.41 | E16: S11 — DeFi Rate | F16: INCLUDED. FOMC decisions, CPI prints, NFP, GDP, rate-hike contracts. Polymarket Finance/Fed = 0.6%; Economy ~1%.
A17: Weather / Climate | B17: 0.003 | C17: YES (weak) | D17: =B17*$B$9 -> 1.4115 | E17: S11 — DeFi Rate | F17: INCLUDED as loose commodities proxy. Polymarket Weather = 0.1%.
A18: Commodities (oil, gold, etc. — explicit) | B18: 0.005 | C18: YES | D18: =B18*$B$9 -> 2.3525 | E18: S11 — DeFi Rate | F18: INCLUDED. Few markets exist; oil price contracts, gold above $X.
A19: Mention markets / Tech / Culture / Entertainment / Other | B19: 0.102 | C19: No | D19: =B19*$B$9 -> 47.991 | E19: S12 — DeFi Rate weekly | F19: Speech-mention contracts, Elon tweet count, Trump mention, etc. Not financial.
A20: SUM CHECK (must = 100%) | B20: =SUM(B13:B19) -> 1 | D20: =SUM(D13:D19) -> 470.5
A22: TRADITIONAL-INSTRUMENT-EQUIVALENT VOLUME (Economy + Weather + Commodities) | D22: =SUMIF(C13:C19,"YES*",D13:D19) -> 13.174 | E22: $B per year
A23: Monthly equivalent ($B/month) | D23: =D22/12 -> 1.0978333

Sheet Penetration
A1: Penetration: Prediction Markets vs Retail Traditional (2025)
A2: All numbers pulled by formula from the two TAM sheets. Change inputs there and these will recalc.
A4: KEY OUTPUTS
A5: Metric | B5: Value ($B/year) | C5: Source | D5: Formula | E5: Notes
A6: Retail Traditional TAM — annual | B6: =Retail_TAM_Traditional!G14 -> 513495 | C6: Retail_TAM_Traditional!G14 | D6: Sum of instrument-level retail volumes minus overlap | E6: See Retail_TAM_Traditional tab for the build
A7: Prediction Markets — trad-equivalent slice — annual | B7: =PredMarkets_TAM!D22 -> 13.174 | C7: PredMarkets_TAM!D22 | D7: Total times (Economy + Weather + Commodities shares) | E7: See PredMarkets_TAM tab for the build
A8: Prediction Markets — TOTAL annual (incl. sports + crypto) | B8: =PredMarkets_TAM!B9 -> 470.5 | C8: PredMarkets_TAM!B9 | D8: Sum of Kalshi + Polymarket + others | E8: For context — full category
A9: Retail Traditional TAM — monthly | B9: =Retail_TAM_Traditional!G15 -> 42791.25 | C9: Retail_TAM_Traditional!G15 | D9: annual divided by 12
A10: Prediction Markets trad-equivalent — monthly | B10: =PredMarkets_TAM!D23 -> 1.0978333 | C10: PredMarkets_TAM!D23 | D10: annual divided by 12
A13: PENETRATION RATIOS
A14: Ratio | B14: Value | C14: Formula | D14: Interpretation
A15: Trad-equivalent prediction markets vs Retail Traditional TAM (annual) | B15: =B7/B6 -> 2.5655557e-05 | C15: PM_trad divided by Retail_TAM | D15: Headline penetration. PM activity on rates/macro/commodities as % of all retail trading.
A16: Trad-equivalent prediction markets vs Retail Traditional TAM (monthly) | B16: =B10/B9 -> 2.5655557e-05 | C16: PM_trad_mo divided by Retail_TAM_mo | D16: Same thing on monthly basis — should match annual ratio.
A17: All prediction-market volume vs Retail Traditional TAM | B17: =B8/B6 -> 0.00091626988 | C17: PM_total divided by Retail_TAM | D17: Even counting ALL PM volume (incl. sports & crypto), still a small share.
A20: GEOGRAPHIC ASYMMETRY
A21: Retail Traditional | B21: Roughly 70-75% non-US: Europe (CFD hub, 43% of CFDs), APAC (India F&O, China A-shares, Japan / Korea), MENA, LatAm. US is a major slice via cash equities + options, but NOT the majority globally.
A22: Prediction Markets | B22: Effectively US-only. Kalshi is CFTC-regulated US product. Polymarket Intl serves non-US in principle but actual user base is largely US (VPN). Economy/Fed/CPI markets are 100% US-data-driven.
A23: Implication | B23: True global penetration is even smaller than the raw ratio — prediction markets have ~zero retail footprint in the EU, India, China, MENA where most of the retail TAM actually sits.

Sheet Sources
A1: Sources — all clickable
A2: Every number in the TAM and Prediction-Market sheets traces back here. Click any URL.
A4: Ref | B4: Publisher | C4: Title / What it gives us | D4: Date | E4: URL (click to open)
A5: S1 | B5: Finance Magnates / Modulus / Arxum | C5: Active retail FX traders globally (~9-10M) | D5: 2026 | E5: https://arxum.com/forex-trading-statistics/
A6: S2 | B6: Finance Magnates Intelligence | C6: Q1 2026 retail FX/CFD active accounts (7.4M); Retail Intensity Ratio | D6: May 2026 | E6: https://www.financemagnates.com/forex/analysis/volume-outpaces-account-growth-in-retail-fxcfd-as-per-trader-activity-hits-record/
A7: S3 | B7: CoinLaw | C7: Global retail CFD monthly notional volume ($37T/month, 2026) | D7: March 2026 | E7: https://coinlaw.io/foreign-exchange-industry-statistics/
A8: S4 | B8: Bank for International Settlements (BIS) | C8: Triennial Central Bank Survey 2025 — FX $9.6T/day, OTC rates $7.9T/day (April 2025) | D8: September 2025 | E8: https://www.bis.org/press/p250930.htm
A9: S5 | B9: MEMX | C9: Retail Trading Insights — US retail = 30-37% equity, 46% options, 40%+ SPY 0DTE | D9: September 2025 | E9: https://memx.com/insights/retail-trading-insights
A10: S6 | B10: RSM US / CoinLaw | C10: $302B retail net inflow into US equities, 2025 | D10: January 2026 | E10: https://coinlaw.io/retail-investing-statistics/
A11: S7 | B11: World Economic Forum | C11: Country-level retail share of equity volume — China 60-90%, India 40%, UK/KR/US 20-35% | D11: August 2025 | E11: https://www.weforum.org/stories/2025/08/how-will-24-7-trading-impact-retail-investors-and-the-economy/
A12: S8 | B12: Market Reports World | C12: CFD Broker Market — 19M active CFD traders globally; Europe 43% of CFDs; APAC 5M traders | D12: August 2025 | E12: https://www.marketreportsworld.com/market-reports/cfd-broker-market-14721086
A13: S9 | B13: Pew Research / The Block | C13: Kalshi + Polymarket category breakdown — sports 80% Kalshi / 39% Polymarket, etc. | D13: May 2026 | E13: https://www.pewresearch.org/short-reads/2026/05/27/trading-volume-on-prediction-markets-has-soared-in-recent-months/
A14: S10 | B14: KuCoin News / industry data | C14: Kalshi 2025 = $238B, Polymarket 2025 = $220B, others $12.5B (97.5% combined share) | D14: May 2026 | E14: https://www.kucoin.com/news/flash/kalshi-and-polymarket-dominate-97-5-of-prediction-market-share-in-2025
A15: S11 | B15: DeFi Rate — Polymarket page | C15: Polymarket category shares — Finance/Fed 0.6%, Weather 0.1%, Economy ~1% | D15: June 2026 | E15: https://defirate.com/prediction-markets/volume/polymarket/
... A21: S17 | B21: FIA MarketVoice | C21: India options crackdown — 75% drop in 5 months; global ETD impact | D21: May 2025 | E21: https://www.fia.org/marketvoice/articles/indias-options-crackdown-weighs-global-etd-trading-volume
